Workbook
Name 财务年度: IF('[1]图表输出-各种增长率对比图表'!$G$3=1,'[1]图表输出-各种增长率对比图表'!$B$2:$F$2,'[1]图表输出-各种增长率对比图表'!$D$2:$F$2)
Name 指标2: IF('[1]图表输出-各种增长率对比图表'!$G$3=1,'[1]图表输出-各种增长率对比图表'!$M$7:$Q$7,'[1]图表输出-各种增长率对比图表'!$O$7:$Q$7)
Name 指标3: IF('[1]图表输出-各种增长率对比图表'!$G$3=1,'[1]图表输出-各种增长率对比图表'!$M$8:$Q$8,'[1]图表输出-各种增长率对比图表'!$O$8:$Q$8)
Name 指标4: IF('[1]图表输出-各种增长率对比图表'!$G$3=1,'[1]图表输出-各种增长率对比图表'!$M$44:$Q$44,'[1]图表输出-各种增长率对比图表'!$O$44:$Q$44)
Name 指标5: IF('[1]图表输出-各种增长率对比图表'!$G$3=1,'[1]图表输出-各种增长率对比图表'!$M$45:$Q$45,'[1]图表输出-各种增长率对比图表'!$O$45:$Q$45)
Name 指标6: IF('[1]图表输出-各种增长率对比图表'!$G$3=1,'[1]图表输出-各种增长率对比图表'!$M$46:$Q$46,'[1]图表输出-各种增长率对比图表'!$O$46:$Q$46)
Name 指标7: IF('[1]图表输出-各种增长率对比图表'!$G$3=1,'[1]图表输出-各种增长率对比图表'!$M$82:$Q$82,'[1]图表输出-各种增长率对比图表'!$O$82:$Q$82)
Name 指标8: IF('[1]图表输出-各种增长率对比图表'!$G$3=1,'[1]图表输出-各种增长率对比图表'!$M$83:$Q$83,'[1]图表输出-各种增长率对比图表'!$O$83:$Q$83)
Name 指标9: IF('[1]图表输出-各种增长率对比图表'!$G$3=1,'[1]图表输出-各种增长率对比图表'!$M$84:$Q$84,'[1]图表输出-各种增长率对比图表'!$O$84:$Q$84)

Sheet 目录
D2: 百万股 | E2: 股票名称 | F2: XXXX
D3: 3 | E3: 最新报告期 | F3: XXXX-XX-XX
D4: 3 | E4: 最新年报报告期 | F4: XXXX-XX-XX
D5: 百万元 | E5: 估值日期 | F5: XXXX-XX-XX
B6: 版权所有： 上海携宁计算机科技股份有限公司 | D6: 1e-06 | E6: 最新收盘价(港元） | F6: XXXX
B7: 联系电话： 18101638931(工作日)，18117554345(值班) | D7: =LEFT(D5,LEN(D5)-1) -> 百万 | E7: 最新总股本（百万） | F7: XXXX
B8: E-mail ： modelsupport@sinitek.com | E8: 货币单位 | F8: XXXX
B9: WebSite： www.sinitek.com | E9: 最新行情日 | F9: XXXX-XX-XX | G9: 收盘价默认货币单位为港币，若与模型货币单位不一致，请在F10填写汇率。
B10: 下载地址： https://cloudmodel.sinitek.com | E10: 汇率 | G10: 如：模型货币单位为CNY，1HKD=0.92CNY,则在此填写0.92
B12: 使用步骤： | E12: 重要提示：
B13: 1.使用本模型前请确保已下载并安装估值模型插件(携宁科技云估值)； | E13: 1.修改股票代码或重新选择历史数据年数后，需重新点击“提取历史数据”按钮来更新数据；
B14: 2.点击“提取历史数据”，在股票代码框中输入代码或名称，支持模糊搜索； | E14: 2.不能修改单元格内的公式，否则可能导致报表不平；
B15: 选择历史数据年数、货币单位等选项，可以设置更新范围； | E15: 3.不能增加/删除已有sheet及已有Sheet中的行或列；
B16: 3.点击“预测数据设置”按钮可实现两张预测sheet的参数设置； | E16: 4.不能删除模型中原有Sheet；
B17: 4.点击“添加输出表”可进行输出表更新； | E17: 5.如有需要，可以自由增加Sheet，但不能修改已有sheet名；
B18: 5.点击“导入历史模型”可实现历史预测数据迁移，支持v2/v3版本导入。 | E18: 6.若资产负债表不平，请打开空模型并通过"导入历史模型"功能将未配平模型导入。
B20: 销售预测 | C20: 用户填写相关假设，自动生成数据 | E20: 黄色底纹需手工填写数据 | F20: 金色边框可自由修改参数
B21: 资产预测 | C21: 用户填写相关假设，自动生成数据 | E21: 黄色底纹需手工填写数据 | F21: 金色边框可自由修改参数 | G21: 蓝色底纹可以手工填写数据
B22: 主要财务摘要 | C22: 自动生成的财务指标计算结果 | G22: 蓝色底纹可以手工填写数据
B23: 报表摘要 | C23: 自动生成的财务指标计算结果
B24: 资产负债表 | C24: 用户填写相关假设，自动生成数据 | E24: 黄色底纹需手工填写数据
B25: 利润表 | C25: 用户填写相关假设，自动生成数据 | E25: 黄色底纹需手工填写数据
B26: 现金流量表 | C26: 用户填写相关假设，自动生成数据 | E26: 黄色底纹需手工填写数据
B27: 估值 | C27: 用户填写相关假设，自动生成数据 | E27: 黄色底纹需手工填写数据 | F27: 金色边框可自由修改参数
B28: 财务基础数据 | C28: 自动生成的财务基础数据

Sheet 销售预测
A1: 收入成本预测
A2: =主要财务摘要!H2 -> 单位：港币(百万) | G2: 注意：预测前三年可按照季度数据进行预测（如当前三季报已出，可直接在蓝色单元格填写第四季度数据），也可直接在黄色单元格填写年度预测数据 | AJ2: 此页季度数据为单季度数据，增长率为环比口径；请注意：若利润表季度数据缺失可能导致单季度数据显示为负数！
A3: 项 目 | G3: =利润表!O4 -> 2019 | H3: =利润表!S4 -> 2020 | I3: =利润表!W4 -> 2021 | J3: =利润表!AA4 -> 2022E | K3: =利润表!AB4 -> 2023 | L3: =利润表!AC4 -> 2024 | M3: =利润表!AD4 -> 2025 | N3: =利润表!AE4 -> 2026 | O3: =利润表!AF4 -> 2027 | P3: =利润表!AG4 -> 2028 | Q3: =利润表!AH4 -> 2029 | ... S3: =利润表!AJ4 -> 2031 | U3: ="1Q"&RIGHT(利润表!L4,2) -> 1Q19 | V3: ="2Q"&RIGHT(利润表!M4,2) -> 2Q19 | W3: ="3Q"&RIGHT(利润表!N4,2) -> 3Q19 | X3: ="4Q"&RIGHT(利润表!O4,2) -> 4Q19 | Y3: ="1Q"&RIGHT(利润表!P4,2) -> 1Q20 | Z3: ="2Q"&RIGHT(利润表!Q4,2) -> 2Q20 | AA3: ="3Q"&RIGHT(利润表!R4,2) -> 3Q20 | AB3: ="4Q"&RIGHT(利润表!S4,2) -> 4Q20 | AC3: ="1Q"&RIGHT(利润表!T4,2) -> 1Q21 | AD3: ="2Q"&RIGHT(利润表!U4,2) -> 2Q21 | AE3: ="3Q"&RIGHT(利润表!V4,2) -> 3Q21 | AF3: ="4Q"&RIGHT(利润表!W4,2) -> 4Q21 | AG3: ="1Q"&RIGHT(利润表!X4,2) -> 1Q22 | AH3: ="2Q"&RIGHT(利润表!Y4,2) -> 2Q22 | AI3: ="3Q"&RIGHT(利润表!Z4,2) -> 3Q22 | AJ3: ="1Q"&LEFT(利润表!$AA$4,4) -> 1Q2022 | AK3: ="2Q"&LEFT(利润表!$AA$4,4) -> 2Q2022 | AL3: ="3Q"&LEFT(利润表!$AA$4,4) -> 3Q2022 | AM3: ="4Q"&LEFT(利润表!$AA$4,4) -> 4Q2022 | AN3: ="1Q"&LEFT(利润表!$AB$4,4) -> 1Q2023 | AO3: ="2Q"&LEFT(利润表!$AB$4,4) -> 2Q2023 | AP3: ="3Q"&LEFT(利润表!$AB$4,4) -> 3Q2023 | AQ3: ="4Q"&LEFT(利润表!$AB$4,4) -> 4Q2023 | AR3: ="1Q"&LEFT(利润表!$AC$4,4) -> 1Q2024 | AS3: ="2Q"&LEFT(利润表!$AC$4,4) -> 2Q2024 | AT3: ="3Q"&LEFT(利润表!$AC$4,4) -> 3Q2024 | AU3: ="4Q"&LEFT(利润表!$AC$4,4) -> 4Q2024
A4: 营业收入小计 | G4: =利润表!O6 -> 0 | H4: =利润表!S6 -> 0 | I4: =利润表!W6 -> 0 | J4: =IF(COUNT(AJ4:AM4)=4,SUM(AJ4:AM4),0) -> 0 | K4: =IF(COUNT(AN4:AQ4)=4,SUM(AN4:AQ4),0) -> 0 | L4: =IF(COUNT(AR4:AU4)=4,SUM(AR4:AU4),0) -> 0 | U4: =利润表!L6 -> 0 | V4: =利润表!M6-利润表!L6 -> 0 | W4: =利润表!N6-利润表!M6 -> 0 | X4: =利润表!O6-利润表!N6 -> 0 | Y4: =利润表!P6 -> 0 | Z4: =利润表!Q6-利润表!P6 -> 0 | AA4: =利润表!R6-利润表!Q6 -> 0 | AB4: =利润表!S6-利润表!R6 -> 0 | AC4: =利润表!T6 -> 0 | AD4: =利润表!U6-利润表!T6 -> 0 | AE4: =利润表!V6-利润表!U6 -> 0 | AF4: =利润表!W6-利润表!V6 -> 0 | AG4: =IF(财务基础数据!$W$2=0,0,利润表!X6) -> 0 | AH4: =IF(财务基础数据!$W$2<=1,0,利润表!Y6-利润表!X6) -> 0 | AI4: =IF(财务基础数据!$W$2<=2,0,利润表!Z6-利润表!Y6) -> 0 | AJ4: =IF(财务基础数据!$W$2=0," ",AG4) | AK4: =IF(财务基础数据!$W$2<=1," ",AH4) | AL4: =IF(财务基础数据!$W$2<=2," ",AI4)
A5: 增长率% | G5: =IF(ISERROR((G4-利润表!K6)/ABS(利润表!K6)),"—",(G4-利润表!K6)/ABS(利润表!K6)) -> — | H5: =IF(ISERROR((H4-G4)/ABS(G4)),"—",(H4-G4)/ABS(G4)) -> — | I5: =IF(ISERROR((I4-H4)/ABS(H4)),"—",(I4-H4)/ABS(H4)) -> — | J5: =IF(ISERROR((J4-I4)/ABS(I4)),"—",(J4-I4)/ABS(I4)) -> — | K5: =IF(ISERROR((K4-J4)/ABS(J4)),"—",(K4-J4)/ABS(J4)) -> — | L5: =IF(ISERROR((L4-K4)/ABS(K4)),"—",(L4-K4)/ABS(K4)) -> — | M5: =IF(ISERROR((M4-L4)/ABS(L4)),"—",(M4-L4)/ABS(L4)) -> — | N5: =IF(ISERROR((N4-M4)/ABS(M4)),"—",(N4-M4)/ABS(M4)) -> — | O5: =IF(ISERROR((O4-N4)/ABS(N4)),"—",(O4-N4)/ABS(N4)) -> — | ... S5: =IF(ISERROR((S4-R4)/ABS(R4)),"—",(S4-R4)/ABS(R4)) -> — | V5: =IF(ISERROR((V4-U4)/ABS(U4)),"—",(V4-U4)/ABS(U4)) -> — | W5: =IF(ISERROR((W4-V4)/ABS(V4)),"—",(W4-V4)/ABS(V4)) -> — | X5: =IF(ISERROR((X4-W4)/ABS(W4)),"—",(X4-W4)/ABS(W4)) -> — | Y5: =IF(ISERROR((Y4-X4)/ABS(X4)),"—",(Y4-X4)/ABS(X4)) -> — | Z5: =IF(ISERROR((Z4-Y4)/ABS(Y4)),"—",(Z4-Y4)/ABS(Y4)) -> — | AA5: =IF(ISERROR((AA4-Z4)/ABS(Z4)),"—",(AA4-Z4)/ABS(Z4)) -> — | AB5: =IF(ISERROR((AB4-AA4)/ABS(AA4)),"—",(AB4-AA4)/ABS(AA4)) -> — | AC5: =IF(ISERROR((AC4-AB4)/ABS(AB4)),"—",(AC4-AB4)/ABS(AB4)) -> — | ... AI5: =IF(ISERROR((AI4-AH4)/ABS(AH4)),"—",(AI4-AH4)/ABS(AH4)) -> — | AJ5: =IF(ISERROR((AJ4-AF4)/ABS(AF4)),"—",(AJ4-AF4)/ABS(AF4)) -> — | AK5: =IF(ISERROR((AK4-AJ4)/ABS(AJ4)),"—",(AK4-AJ4)/ABS(AJ4)) -> — | AL5: =IF(ISERROR((AL4-AK4)/ABS(AK4)),"—",(AL4-AK4)/ABS(AK4)) -> — | AM5: =IF(ISERROR((AM4-AL4)/ABS(AL4)),"—",(AM4-AL4)/ABS(AL4)) -> — | AN5: =IF(ISERROR((AN4-AM4)/ABS(AM4)),"—",(AN4-AM4)/ABS(AM4)) -> — | AO5: =IF(ISERROR((AO4-AN4)/ABS(AN4)),"—",(AO4-AN4)/ABS(AN4)) -> — | AP5: =IF(ISERROR((AP4-AO4)/ABS(AO4)),"—",(AP4-AO4)/ABS(AO4)) -> — | AQ5: =IF(ISERROR((AQ4-AP4)/ABS(AP4)),"—",(AQ4-AP4)/ABS(AP4)) -> — | AR5: =IF(ISERROR((AR4-AQ4)/ABS(AQ4)),"—",(AR4-AQ4)/ABS(AQ4)) -> — | ... AU5: =IF(ISERROR((AU4-AT4)/ABS(AT4)),"—",(AU4-AT4)/ABS(AT4)) -> —
A6: 其他收入小计 | G6: =利润表!O7 -> 0 | H6: =利润表!S7 -> 0 | I6: =利润表!W7 -> 0 | J6: =IF(COUNT(AJ6:AM6)=4,SUM(AJ6:AM6),0) -> 0 | K6: =IF(COUNT(AN6:AQ6)=4,SUM(AN6:AQ6),0) -> 0 | L6: =IF(COUNT(AR6:AU6)=4,SUM(AR6:AU6),0) -> 0 | U6: =利润表!L7 -> 0 | V6: =利润表!M7-利润表!L7 -> 0 | W6: =利润表!N7-利润表!M7 -> 0 | X6: =利润表!O7-利润表!N7 -> 0 | Y6: =利润表!P7 -> 0 | Z6: =利润表!Q7-利润表!P7 -> 0 | AA6: =利润表!R7-利润表!Q7 -> 0 | AB6: =利润表!S7-利润表!R7 -> 0 | AC6: =利润表!T7 -> 0 | AD6: =利润表!U7-利润表!T7 -> 0 | AE6: =利润表!V7-利润表!U7 -> 0 | AF6: =利润表!W7-利润表!V7 -> 0 | AG6: =IF(财务基础数据!$W$2=0,0,利润表!X7) -> 0 | AH6: =IF(财务基础数据!$W$2<=1,0,利润表!Y7-利润表!X7) -> 0 | AI6: =IF(财务基础数据!$W$2<=2,0,利润表!Z7-利润表!Y7) -> 0 | AJ6: =IF(财务基础数据!$W$2=0,"",AG6) | AK6: =IF(财务基础数据!$W$2<=1,"",AH6) | AL6: =IF(财务基础数据!$W$2<=2,"",AI6)
A7: 营业成本小计 | G7: =利润表!O9 -> 0 | H7: =利润表!S9 -> 0 | I7: =利润表!W9 -> 0 | J7: =IF(COUNT(AJ7:AM7)=4,SUM(AJ7:AM7),0) -> 0 | K7: =IF(COUNT(AN7:AQ7)=4,SUM(AN7:AQ7),0) -> 0 | L7: =IF(COUNT(AR7:AU7)=4,SUM(AR7:AU7),0) -> 0 | U7: =利润表!L9 -> 0 | V7: =利润表!M9-利润表!L9 -> 0 | W7: =利润表!N9-利润表!M9 -> 0 | X7: =利润表!O9-利润表!N9 -> 0 | Y7: =利润表!P9 -> 0 | Z7: =利润表!Q9-利润表!P9 -> 0 | AA7: =利润表!R9-利润表!Q9 -> 0 | AB7: =利润表!S9-利润表!R9 -> 0 | AC7: =利润表!T9 -> 0 | AD7: =利润表!U9-利润表!T9 -> 0 | AE7: =利润表!V9-利润表!U9 -> 0 | AF7: =利润表!W9-利润表!V9 -> 0 | AG7: =IF(财务基础数据!$W$2=0,0,利润表!X9) -> 0 | AH7: =IF(财务基础数据!$W$2<=1,0,利润表!Y9-利润表!X9) -> 0 | AI7: =IF(财务基础数据!$W$2<=2,0,利润表!Z9-利润表!Y9) -> 0 | AJ7: =IF(财务基础数据!$W$2=0,"",AG7) | AK7: =IF(财务基础数据!$W$2<=2,"",AH7) | AL7: =IF(财务基础数据!$W$2<=2,"",AI7)
A8: 增长率% | G8: =IF(ISERROR((G7-利润表!K9)/ABS(利润表!K9)),"—",(G7-利润表!K9)/ABS(利润表!K9)) -> — | H8: =IF(ISERROR((H7-G7)/ABS(G7)),"—",(H7-G7)/ABS(G7)) -> — | I8: =IF(ISERROR((I7-H7)/ABS(H7)),"—",(I7-H7)/ABS(H7)) -> — | J8: =IF(ISERROR((J7-I7)/ABS(I7)),"—",(J7-I7)/ABS(I7)) -> — | K8: =IF(ISERROR((K7-J7)/ABS(J7)),"—",(K7-J7)/ABS(J7)) -> — | L8: =IF(ISERROR((L7-K7)/ABS(K7)),"—",(L7-K7)/ABS(K7)) -> — | M8: =IF(ISERROR((M7-L7)/ABS(L7)),"—",(M7-L7)/ABS(L7)) -> — | N8: =IF(ISERROR((N7-M7)/ABS(M7)),"—",(N7-M7)/ABS(M7)) -> — | O8: =IF(ISERROR((O7-N7)/ABS(N7)),"—",(O7-N7)/ABS(N7)) -> — | ... S8: =IF(ISERROR((S7-R7)/ABS(R7)),"—",(S7-R7)/ABS(R7)) -> — | V8: =IF(ISERROR((V7-U7)/ABS(U7)),"—",(V7-U7)/ABS(U7)) -> — | W8: =IF(ISERROR((W7-V7)/ABS(V7)),"—",(W7-V7)/ABS(V7)) -> — | X8: =IF(ISERROR((X7-W7)/ABS(W7)),"—",(X7-W7)/ABS(W7)) -> — | Y8: =IF(ISERROR((Y7-X7)/ABS(X7)),"—",(Y7-X7)/ABS(X7)) -> — | Z8: =IF(ISERROR((Z7-Y7)/ABS(Y7)),"—",(Z7-Y7)/ABS(Y7)) -> — | AA8: =IF(ISERROR((AA7-Z7)/ABS(Z7)),"—",(AA7-Z7)/ABS(Z7)) -> — | AB8: =IF(ISERROR((AB7-AA7)/ABS(AA7)),"—",(AB7-AA7)/ABS(AA7)) -> — | AC8: =IF(ISERROR((AC7-AB7)/ABS(AB7)),"—",(AC7-AB7)/ABS(AB7)) -> — | ... AI8: =IF(ISERROR((AI7-AH7)/ABS(AH7)),"—",(AI7-AH7)/ABS(AH7)) -> — | AJ8: =IF(ISERROR((AJ7-AF7)/ABS(AF7)),"—",(AJ7-AF7)/ABS(AF7)) -> — | AK8: =IF(ISERROR((AK7-AJ7)/ABS(AJ7)),"—",(AK7-AJ7)/ABS(AJ7)) -> — | AL8: =IF(ISERROR((AL7-AK7)/ABS(AK7)),"—",(AL7-AK7)/ABS(AK7)) -> — | AM8: =IF(ISERROR((AM7-AL7)/ABS(AL7)),"—",(AM7-AL7)/ABS(AL7)) -> — | AN8: =IF(ISERROR((AN7-AM7)/ABS(AM7)),"—",(AN7-AM7)/ABS(AM7)) -> — | AO8: =IF(ISERROR((AO7-AN7)/ABS(AN7)),"—",(AO7-AN7)/ABS(AN7)) -> — | AP8: =IF(ISERROR((AP7-AO7)/ABS(AO7)),"—",(AP7-AO7)/ABS(AO7)) -> — | AQ8: =IF(ISERROR((AQ7-AP7)/ABS(AP7)),"—",(AQ7-AP7)/ABS(AP7)) -> — | AR8: =IF(ISERROR((AR7-AQ7)/ABS(AQ7)),"—",(AR7-AQ7)/ABS(AQ7)) -> — | ... AU8: =IF(ISERROR((AU7-AT7)/ABS(AT7)),"—",(AU7-AT7)/ABS(AT7)) -> —
A9: 毛利 | G9: =利润表!O16 -> 0 | H9: =利润表!S16 -> 0 | I9: =利润表!W16 -> 0 | J9: =J4-J7 -> 0 | K9: =K4-K7 -> 0 | L9: =L4-L7 -> 0 | M9: =M4-M7 -> 0 | N9: =N4-N7 -> 0 | O9: =O4-O7 -> 0 | P9: =P4-P7 -> 0 | Q9: =Q4-Q7 -> 0 | ... S9: =S4-S7 -> 0 | U9: =利润表!L16 -> 0 | V9: =利润表!M16-利润表!L16 -> 0 | W9: =利润表!N16-利润表!M16 -> 0 | X9: =利润表!O16-利润表!N16 -> 0 | Y9: =利润表!P16 -> 0 | Z9: =利润表!Q16-利润表!P16 -> 0 | AA9: =利润表!R16-利润表!Q16 -> 0 | AB9: =利润表!S16-利润表!R16 -> 0 | AC9: =利润表!T16 -> 0 | AD9: =利润表!U16-利润表!T16 -> 0 | AE9: =利润表!V16-利润表!U16 -> 0 | AF9: =利润表!W16-利润表!V16 -> 0 | AG9: =IF(财务基础数据!$W$2=0,0,利润表!X16) -> 0 | AH9: =IF(财务基础数据!$W$2<=1,0,利润表!Y16-利润表!X16) -> 0 | AI9: =IF(财务基础数据!$W$2<=2,0,利润表!Z16-利润表!Y16) -> 0 | AJ9: =IF(ISERROR(AJ4-AJ7),"—",AJ4-AJ7) -> — | AK9: =IF(ISERROR(AK4-AK7),"—",AK4-AK7) -> — | AL9: =IF(ISERROR(AL4-AL7),"—",AL4-AL7) -> — | AM9: =IF(ISERROR(AM4-AM7),"—",AM4-AM7) -> 0 | AN9: =IF(ISERROR(AN4-AN7),"—",AN4-AN7) -> 0 | AO9: =IF(ISERROR(AO4-AO7),"—",AO4-AO7) -> 0 | AP9: =IF(ISERROR(AP4-AP7),"—",AP4-AP7) -> 0 | AQ9: =IF(ISERROR(AQ4-AQ7),"—",AQ4-AQ7) -> 0 | ... AU9: =IF(ISERROR(AU4-AU7),"—",AU4-AU7) -> 0
A10: 毛利率 | G10: =IF(ISERROR(G9/G4),"—",G9/G4) -> — | H10: =IF(ISERROR(H9/H4),"—",H9/H4) -> — | I10: =IF(ISERROR(I9/I4),"—",I9/I4) -> — | J10: =IF(ISERROR(J9/J4),"—",J9/J4) -> — | K10: =IF(ISERROR(K9/K4),"—",K9/K4) -> — | L10: =IF(ISERROR(L9/L4),"—",L9/L4) -> — | M10: =IF(ISERROR(M9/M4),"—",M9/M4) -> — | N10: =IF(ISERROR(N9/N4),"—",N9/N4) -> — | ... S10: =IF(ISERROR(S9/S4),"—",S9/S4) -> — | U10: =IF(ISERROR(U9/U4),"—",U9/U4) -> — | V10: =IF(ISERROR(V9/V4),"—",V9/V4) -> — | W10: =IF(ISERROR(W9/W4),"—",W9/W4) -> — | X10: =IF(ISERROR(X9/X4),"—",X9/X4) -> — | Y10: =IF(ISERROR(Y9/Y4),"—",Y9/Y4) -> — | Z10: =IF(ISERROR(Z9/Z4),"—",Z9/Z4) -> — | AA10: =IF(ISERROR(AA9/AA4),"—",AA9/AA4) -> — | AB10: =IF(ISERROR(AB9/AB4),"—",AB9/AB4) -> — | ... AU10: =IF(ISERROR(AU9/AU4),"—",AU9/AU4) -> —
A12: 经营收益的其他假设 | G12: 说明：季度数据预测和年度数据预测不可同时生效，只可选择其中一种预测方式
A13: 项 目 | G13: =G3 -> 2019 | H13: =H3 -> 2020 | I13: =I3 -> 2021 | J13: =J3 -> 2022E | K13: =K3 -> 2023 | L13: =L3 -> 2024 | M13: =M3 -> 2025 | N13: =N3 -> 2026 | ... S13: =S3 -> 2031 | U13: =U3 -> 1Q19 | V13: =V3 -> 2Q19 | W13: =W3 -> 3Q19 | X13: =X3 -> 4Q19 | Y13: =Y3 -> 1Q20 | Z13: =Z3 -> 2Q20 | AA13: =AA3 -> 3Q20 | AB13: =AB3 -> 4Q20 | ... AU13: =AU3 -> 4Q2024
A15: 营销费用 | G15: =利润表!O12 -> 0 | H15: =利润表!S12 -> 0 | I15: =利润表!W12 -> 0 | J15: =IF(COUNT(AJ16:AM16)=4,SUM(AJ15:AM15),J4*J16) -> 0 | K15: =IF(COUNT(AN16:AQ16)=4,SUM(AN15:AQ15),K4*K16) -> 0 | L15: =IF(COUNT(AR16:AU16)=4,SUM(AR15:AU15),L4*L16) -> 0 | M15: =IF(ISERROR(M4*M16),"—",M4*M16) -> 0 | N15: =IF(ISERROR(N4*N16),"—",N4*N16) -> 0 | O15: =IF(ISERROR(O4*O16),"—",O4*O16) -> 0 | P15: =IF(ISERROR(P4*P16),"—",P4*P16) -> 0 | Q15: =IF(ISERROR(Q4*Q16),"—",Q4*Q16) -> 0 | R15: =IF(ISERROR(R4*R16),"—",R4*R16) -> 0 | S15: =IF(ISERROR(S4*S16),"—",S4*S16) -> 0 | U15: =利润表!L12 -> 0 | V15: =利润表!M12-利润表!L12 -> 0 | W15: =利润表!N12-利润表!M12 -> 0 | X15: =利润表!O12-利润表!N12 -> 0 | Y15: =利润表!P12 -> 0 | Z15: =利润表!Q12-利润表!P12 -> 0 | AA15: =利润表!R12-利润表!Q12 -> 0 | AB15: =利润表!S12-利润表!R12 -> 0 | AC15: =利润表!T12 -> 0 | AD15: =利润表!U12-利润表!T12 -> 0 | AE15: =利润表!V12-利润表!U12 -> 0 | AF15: =利润表!W12-利润表!V12 -> 0 | AG15: =IF(财务基础数据!$W$2=0,0,利润表!X12) -> 0 | AH15: =IF(财务基础数据!$W$2<=1,0,利润表!Y12-利润表!X12) -> 0 | AI15: =IF(财务基础数据!$W$2<=2,0,利润表!Z12-利润表!Y12) -> 0 | AJ15: =IF(ISERROR(AJ16*AJ4),"—",AJ16*AJ4) -> — | AK15: =IF(ISERROR(AK16*AK4),"—",AK16*AK4) -> — | AL15: =IF(ISERROR(AL16*AL4),"—",AL16*AL4) -> — | AM15: =IF(ISERROR(AM16*AM4),"—",AM16*AM4) -> 0 | AN15: =IF(ISERROR(AN16*AN4),"—",AN16*AN4) -> 0 | AO15: =IF(ISERROR(AO16*AO4),"—",AO16*AO4) -> 0 | AP15: =IF(ISERROR(AP16*AP4),"—",AP16*AP4) -> 0 | AQ15: =IF(ISERROR(AQ16*AQ4),"—",AQ16*AQ4) -> 0 | ... AU15: =IF(ISERROR(AU16*AU4),"—",AU16*AU4) -> 0
A16: 占销售收入% | G16: =IF(ISERROR(G15/G4),"—",G15/G4) -> — | H16: =IF(ISERROR(H15/H4),"—",H15/H4) -> — | I16: =IF(ISERROR(I15/I4),"—",I15/I4) -> — | U16: =IF(ISERROR(U15/U4),"—",U15/U4) -> — | V16: =IF(ISERROR(V15/V4),"—",V15/V4) -> — | W16: =IF(ISERROR(W15/W4),"—",W15/W4) -> — | X16: =IF(ISERROR(X15/X4),"—",X15/X4) -> — | Y16: =IF(ISERROR(Y15/Y4),"—",Y15/Y4) -> — | Z16: =IF(ISERROR(Z15/Z4),"—",Z15/Z4) -> — | AA16: =IF(ISERROR(AA15/AA4),"—",AA15/AA4) -> — | AB16: =IF(ISERROR(AB15/AB4),"—",AB15/AB4) -> — | ... AI16: =IF(ISERROR(AI15/AI4),"—",AI15/AI4) -> — | AJ16: =IF(财务基础数据!$W$2=0," ",AG16) | AK16: =IF(财务基础数据!$W$2<=1," ",AH16) | AL16: =IF(财务基础数据!$W$2<=2," ",AI16)
A18: 管理费用 | G18: =利润表!O13 -> 0 | H18: =利润表!S13 -> 0 | I18: =利润表!W13 -> 0 | J18: =IF(COUNT(AJ19:AM19)=4,SUM(AJ18:AM18),J4*J19) -> 0 | K18: =IF(COUNT(AN19:AQ19)=4,SUM(AN18:AQ18),K4*K19) -> 0 | L18: =IF(COUNT(AR19:AU19)=4,SUM(AR18:AU18),L4*L19) -> 0 | M18: =IF(ISERROR(M4*M19),"—",M4*M19) -> 0 | N18: =IF(ISERROR(N4*N19),"—",N4*N19) -> 0 | O18: =IF(ISERROR(O4*O19),"—",O4*O19) -> 0 | P18: =IF(ISERROR(P4*P19),"—",P4*P19) -> 0 | Q18: =IF(ISERROR(Q4*Q19),"—",Q4*Q19) -> 0 | R18: =IF(ISERROR(R4*R19),"—",R4*R19) -> 0 | S18: =IF(ISERROR(S4*S19),"—",S4*S19) -> 0 | U18: =利润表!L13 -> 0 | V18: =利润表!M13-利润表!L13 -> 0 | W18: =利润表!N13-利润表!M13 -> 0 | X18: =利润表!O13-利润表!N13 -> 0 | Y18: =利润表!P13 -> 0 | Z18: =利润表!Q13-利润表!P13 -> 0 | AA18: =利润表!R13-利润表!Q13 -> 0 | AB18: =利润表!S13-利润表!R13 -> 0 | AC18: =利润表!T13 -> 0 | AD18: =利润表!U13-利润表!T13 -> 0 | AE18: =利润表!V13-利润表!U13 -> 0 | AF18: =利润表!W13-利润表!V13 -> 0 | AG18: =IF(财务基础数据!$W$2=0,0,利润表!X13) -> 0 | AH18: =IF(财务基础数据!$W$2<=1,0,利润表!Y13-利润表!X12) -> 0 | AI18: =IF(财务基础数据!$W$2<=2,0,利润表!Z13-利润表!Y12) -> 0 | AJ18: =IF(ISERROR(AJ19*AJ4),"—",AJ19*AJ4) -> — | AK18: =IF(ISERROR(AK19*AK4),"—",AK19*AK4) -> — | AL18: =IF(ISERROR(AL19*AL4),"—",AL19*AL4) -> — | AM18: =IF(ISERROR(AM19*AM4),"—",AM19*AM4) -> 0 | AN18: =IF(ISERROR(AN19*AN4),"—",AN19*AN4) -> 0 | AO18: =IF(ISERROR(AO19*AO4),"—",AO19*AO4) -> 0 | AP18: =IF(ISERROR(AP19*AP4),"—",AP19*AP4) -> 0 | AQ18: =IF(ISERROR(AQ19*AQ4),"—",AQ19*AQ4) -> 0 | ... AU18: =IF(ISERROR(AU19*AU4),"—",AU19*AU4) -> 0
A19: 占销售收入% | G19: =IF(ISERROR(G18/G4),"—",G18/G4) -> — | H19: =IF(ISERROR(H18/H4),"—",H18/H4) -> — | I19: =IF(ISERROR(I18/I4),"—",I18/I4) -> — | U19: =IF(ISERROR(U18/U4),"—",U18/U4) -> — | V19: =IF(ISERROR(V18/V4),"—",V18/V4) -> — | W19: =IF(ISERROR(W18/W4),"—",W18/W4) -> — | X19: =IF(ISERROR(X18/X4),"—",X18/X4) -> — | Y19: =IF(ISERROR(Y18/Y4),"—",Y18/Y4) -> — | Z19: =IF(ISERROR(Z18/Z4),"—",Z18/Z4) -> — | AA19: =IF(ISERROR(AA18/AA4),"—",AA18/AA4) -> — | AB19: =IF(ISERROR(AB18/AB4),"—",AB18/AB4) -> — | ... AI19: =IF(ISERROR(AI18/AI4),"—",AI18/AI4) -> — | AJ19: =IF(财务基础数据!$W$2=0," ",AG19) | AK19: =IF(财务基础数据!$W$2<=1," ",AH19) | AL19: =IF(财务基础数据!$W$2<=2," ",AI19)
A21: 研发费用 | G21: =利润表!O14 -> 0 | H21: =利润表!S14 -> 0 | I21: =利润表!W14 -> 0 | J21: =IF(COUNT(AJ22:AM22)=4,SUM(AJ21:AM21),J4*J22) -> 0 | K21: =IF(COUNT(AN22:AQ22)=4,SUM(AN21:AQ21),K4*K22) -> 0 | L21: =IF(COUNT(AR22:AU22)=4,SUM(AR21:AU21),L4*L22) -> 0 | M21: =IF(ISERROR(M4*M22),"—",M4*M22) -> 0 | N21: =IF(ISERROR(N4*N22),"—",N4*N22) -> 0 | O21: =IF(ISERROR(O4*O22),"—",O4*O22) -> 0 | P21: =IF(ISERROR(P4*P22),"—",P4*P22) -> 0 | Q21: =IF(ISERROR(Q4*Q22),"—",Q4*Q22) -> 0 | R21: =IF(ISERROR(R4*R22),"—",R4*R22) -> 0 | S21: =IF(ISERROR(S4*S22),"—",S4*S22) -> 0 | U21: =利润表!L14 -> 0 | V21: =利润表!M14-利润表!L14 -> 0 | W21: =利润表!N14-利润表!M14 -> 0 | X21: =利润表!O14-利润表!N14 -> 0 | Y21: =利润表!P14 -> 0 | Z21: =利润表!Q14-利润表!P14 -> 0 | AA21: =利润表!R14-利润表!Q14 -> 0 | AB21: =利润表!S14-利润表!R14 -> 0 | AC21: =利润表!T14 -> 0 | AD21: =利润表!U14-利润表!T14 -> 0 | AE21: =利润表!V14-利润表!U14 -> 0 | AF21: =利润表!W14-利润表!V14 -> 0 | AG21: =IF(财务基础数据!$W$2=0,0,利润表!X14) -> 0 | AH21: =IF(财务基础数据!$W$2<=1,0,利润表!Y14-利润表!X14) -> 0 | AI21: =IF(财务基础数据!$W$2<=2,0,利润表!Z14-利润表!Y14) -> 0 | AJ21: =IF(ISERROR(AJ22*AJ4),"—",AJ22*AJ4) -> — | AK21: =IF(ISERROR(AK22*AK4),"—",AK22*AK4) -> — | AL21: =IF(ISERROR(AL22*AL4),"—",AL22*AL4) -> — | AM21: =IF(ISERROR(AM22*AM4),"—",AM22*AM4) -> 0 | AN21: =IF(ISERROR(AN22*AN4),"—",AN22*AN4) -> 0 | AO21: =IF(ISERROR(AO22*AO4),"—",AO22*AO4) -> 0 | AP21: =IF(ISERROR(AP22*AP4),"—",AP22*AP4) -> 0 | AQ21: =IF(ISERROR(AQ22*AQ4),"—",AQ22*AQ4) -> 0 | ... AU21: =IF(ISERROR(AU22*AU4),"—",AU22*AU4) -> 0
A22: 占销售收入% | G22: =IF(ISERROR(G21/G4),"—",G21/G4) -> — | H22: =IF(ISERROR(H21/H4),"—",H21/H4) -> — | I22: =IF(ISERROR(I21/I4),"—",I21/I4) -> — | U22: =IF(ISERROR(U21/U4),"—",U21/U4) -> — | V22: =IF(ISERROR(V21/V4),"—",V21/V4) -> — | W22: =IF(ISERROR(W21/W4),"—",W21/W4) -> — | X22: =IF(ISERROR(X21/X4),"—",X21/X4) -> — | Y22: =IF(ISERROR(Y21/Y4),"—",Y21/Y4) -> — | Z22: =IF(ISERROR(Z21/Z4),"—",Z21/Z4) -> — | AA22: =IF(ISERROR(AA21/AA4),"—",AA21/AA4) -> — | AB22: =IF(ISERROR(AB21/AB4),"—",AB21/AB4) -> — | ... AI22: =IF(ISERROR(AI21/AI4),"—",AI21/AI4) -> — | AJ22: =IF(财务基础数据!$W$2=0," ",AG22) | AK22: =IF(财务基础数据!$W$2<=1," ",AH22) | AL22: =IF(财务基础数据!$W$2<=2," ",AI22)
A24: 其他费用 | G24: =利润表!O15 -> 0 | H24: =利润表!S15 -> 0 | I24: =利润表!W15 -> 0 | J24: =IF(COUNT(AJ25:AM25)=4,SUM(AJ24:AM24),J4*J25) -> 0 | K24: =IF(COUNT(AN25:AQ25)=4,SUM(AN24:AQ24),K4*K25) -> 0 | L24: =IF(COUNT(AR25:AU25)=4,SUM(AR24:AU24),L4*L25) -> 0 | M24: =IF(ISERROR(M4*M25),"—",M4*M25) -> 0 | N24: =IF(ISERROR(N4*N25),"—",N4*N25) -> 0 | O24: =IF(ISERROR(O4*O25),"—",O4*O25) -> 0 | P24: =IF(ISERROR(P4*P25),"—",P4*P25) -> 0 | Q24: =IF(ISERROR(Q4*Q25),"—",Q4*Q25) -> 0 | R24: =IF(ISERROR(R4*R25),"—",R4*R25) -> 0 | S24: =IF(ISERROR(S4*S25),"—",S4*S25) -> 0 | U24: =利润表!L15 -> 0 | V24: =利润表!M15-利润表!L15 -> 0 | W24: =利润表!N15-利润表!M15 -> 0 | X24: =利润表!O15-利润表!N15 -> 0 | Y24: =利润表!P15 -> 0 | Z24: =利润表!Q15-利润表!P15 -> 0 | AA24: =利润表!R15-利润表!Q15 -> 0 | AB24: =利润表!S15-利润表!R15 -> 0 | AC24: =利润表!T15 -> 0 | AD24: =利润表!U15-利润表!T15 -> 0 | AE24: =利润表!V15-利润表!U15 -> 0 | AF24: =利润表!W15-利润表!V15 -> 0 | AG24: =IF(财务基础数据!$W$2=0,0,利润表!X15) -> 0 | AH24: =IF(财务基础数据!$W$2<=1,0,利润表!Y15-利润表!X15) -> 0 | AI24: =IF(财务基础数据!$W$2<=2,0,利润表!Z15-利润表!Y15) -> 0 | AJ24: =IF(ISERROR(AJ25*AJ4),"—",AJ25*AJ4) -> — | AK24: =IF(ISERROR(AK25*AK4),"—",AK25*AK4) -> — | AL24: =IF(ISERROR(AL25*AL4),"—",AL25*AL4) -> — | AM24: =IF(ISERROR(AM25*AM4),"—",AM25*AM4) -> 0 | AN24: =IF(ISERROR(AN25*AN4),"—",AN25*AN4) -> 0 | AO24: =IF(ISERROR(AO25*AO4),"—",AO25*AO4) -> 0 | AP24: =IF(ISERROR(AP25*AP4),"—",AP25*AP4) -> 0 | AQ24: =IF(ISERROR(AQ25*AQ4),"—",AQ25*AQ4) -> 0 | ... AU24: =IF(ISERROR(AU25*AU4),"—",AU25*AU4) -> 0
A25: 占销售收入% | G25: =IF(ISERROR(G24/G4),"—",G24/G4) -> — | H25: =IF(ISERROR(H24/H4),"—",H24/H4) -> — | I25: =IF(ISERROR(I24/I4),"—",I24/I4) -> — | U25: =IF(ISERROR(U24/U4),"—",U24/U4) -> — | V25: =IF(ISERROR(V24/V4),"—",V24/V4) -> — | W25: =IF(ISERROR(W24/W4),"—",W24/W4) -> — | X25: =IF(ISERROR(X24/X4),"—",X24/X4) -> — | Y25: =IF(ISERROR(Y24/Y4),"—",Y24/Y4) -> — | Z25: =IF(ISERROR(Z24/Z4),"—",Z24/Z4) -> — | AA25: =IF(ISERROR(AA24/AA4),"—",AA24/AA4) -> — | AB25: =IF(ISERROR(AB24/AB4),"—",AB24/AB4) -> — | ... AI25: =IF(ISERROR(AI24/AI4),"—",AI24/AI4) -> — | AJ25: =IF(财务基础数据!$W$2=0," ",AG25) | AK25: =IF(财务基础数据!$W$2<=1," ",AH25) | AL25: =IF(财务基础数据!$W$2<=2," ",AI25)
A27: 权益性投资损益 | G27: =利润表!O20 -> 0 | H27: =利润表!S20 -> 0 | I27: =利润表!W20 -> 0 | J27: =IF(COUNT(AJ28:AM28)=4,SUM(AJ27:AM27),资产负债表!AA16*J28) -> 0 | K27: =IF(COUNT(AN28:AQ28)=4,SUM(AN27:AQ27),资产负债表!AB16*K28) -> 0 | L27: =IF(COUNT(AR28:AU28)=4,SUM(AR27:AU27),资产负债表!AC16*L28) -> 0 | M27: =IF(ISERROR(资产负债表!AD16*M28),"—",资产负债表!AD16*M28) -> 0 | N27: =IF(ISERROR(资产负债表!AE16*N28),"—",资产负债表!AE16*N28) -> 0 | O27: =IF(ISERROR(资产负债表!AF16*O28),"—",资产负债表!AF16*O28) -> 0 | P27: =IF(ISERROR(资产负债表!AG16*P28),"—",资产负债表!AG16*P28) -> 0 | Q27: =IF(ISERROR(资产负债表!AH16*Q28),"—",资产负债表!AH16*Q28) -> 0 | R27: =IF(ISERROR(资产负债表!AI16*R28),"—",资产负债表!AI16*R28) -> 0 | S27: =IF(ISERROR(资产负债表!AJ16*S28),"—",资产负债表!AJ16*S28) -> 0 | U27: =利润表!L20 -> 0 | V27: =利润表!M20-利润表!L20 -> 0 | W27: =利润表!N20-利润表!M20 -> 0 | X27: =利润表!O20-利润表!N20 -> 0 | Y27: =利润表!P20 -> 0 | Z27: =利润表!Q20-利润表!P20 -> 0 | AA27: =利润表!R20-利润表!Q20 -> 0 | AB27: =利润表!S20-利润表!R20 -> 0 | AC27: =利润表!T20 -> 0 | AD27: =利润表!U20-利润表!T20 -> 0 | AE27: =利润表!V20-利润表!U20 -> 0 | AF27: =利润表!W20-利润表!V20 -> 0 | AG27: =IF(财务基础数据!$W$2=0,0,利润表!X20) -> 0 | AH27: =IF(财务基础数据!$W$2<=1,0,利润表!Y20-利润表!X20) -> 0 | AI27: =IF(财务基础数据!$W$2<=2,0,利润表!Z20-利润表!Y20) -> 0 | AJ27: =IF(ISERROR(AJ28*资产负债表!$AA$16),"—",AJ28*资产负债表!$AA$16) -> — | AK27: =IF(ISERROR(AK28*资产负债表!$AA$16),"—",AK28*资产负债表!$AA$16) -> — | AL27: =IF(ISERROR(AL28*资产负债表!$AA$16),"—",AL28*资产负债表!$AA$16) -> — | AM27: =IF(ISERROR(AM28*资产负债表!$AA$16),"—",AM28*资产负债表!$AA$16) -> 0 | AN27: =IF(ISERROR(AN28*资产负债表!$AB$16),"—",AN28*资产负债表!$AB$16) -> 0 | AO27: =IF(ISERROR(AO28*资产负债表!$AB$16),"—",AO28*资产负债表!$AB$16) -> 0 | AP27: =IF(ISERROR(AP28*资产负债表!$AB$16),"—",AP28*资产负债表!$AB$16) -> 0 | AQ27: =IF(ISERROR(AQ28*资产负债表!$AB$16),"—",AQ28*资产负债表!$AB$16) -> 0 | AR27: =IF(ISERROR(AR28*资产负债表!$AC$16),"—",AR28*资产负债表!$AC$16) -> 0 | AS27: =IF(ISERROR(AS28*资产负债表!$AC$16),"—",AS28*资产负债表!$AC$16) -> 0 | AT27: =IF(ISERROR(AT28*资产负债表!$AC$16),"—",AT28*资产负债表!$AC$16) -> 0 | AU27: =IF(ISERROR(AU28*资产负债表!$AC$16),"—",AU28*资产负债表!$AC$16) -> 0
A28: 占权益性投资% | G28: =IF(ISERROR(G27/资产负债表!O16),0,G27/资产负债表!O16) -> 0 | H28: =IF(ISERROR(H27/资产负债表!S16),0,H27/资产负债表!S16) -> 0 | I28: =IF(ISERROR(I27/资产负债表!W16),0,I27/资产负债表!W16) -> 0 | U28: =IF(ISERROR(U27/资产负债表!$O$16),"—",U27/资产负债表!$O$16) -> — | V28: =IF(ISERROR(V27/资产负债表!$O$16),"—",V27/资产负债表!$O$16) -> — | W28: =IF(ISERROR(W27/资产负债表!$O$16),"—",W27/资产负债表!$O$16) -> — | X28: =IF(ISERROR(X27/资产负债表!$O$16),"—",X27/资产负债表!$O$16) -> — | Y28: =IF(ISERROR(Y27/资产负债表!$S$16),"—",Y27/资产负债表!$S$16) -> — | Z28: =IF(ISERROR(Z27/资产负债表!$S$16),"—",Z27/资产负债表!$S$16) -> — | AA28: =IF(ISERROR(AA27/资产负债表!$S$16),"—",AA27/资产负债表!$S$16) -> — | AB28: =IF(ISERROR(AB27/资产负债表!$S$16),"—",AB27/资产负债表!$S$16) -> — | AC28: =IF(ISERROR(AC27/资产负债表!$W$16),"—",AC27/资产负债表!$W$16) -> — | AD28: =IF(ISERROR(AD27/资产负债表!$W$16),"—",AD27/资产负债表!$W$16) -> — | AE28: =IF(ISERROR(AE27/资产负债表!$W$16),"—",AE27/资产负债表!$W$16) -> — | AF28: =IF(ISERROR(AF27/资产负债表!$W$16),"—",AF27/资产负债表!$W$16) -> — | AG28: =IF(ISERROR(AG27/资产负债表!$AA$16),"—",AG27/资产负债表!$AA$16) -> — | AH28: =IF(ISERROR(AH27/资产负债表!$AA$16),"—",AH27/资产负债表!$AA$16) -> — | AI28: =IF(ISERROR(AI27/资产负债表!$AA$16),"—",AI27/资产负债表!$AA$16) -> — | AJ28: =IF(财务基础数据!$W$2=0," ",AG28) | AK28: =IF(财务基础数据!$W$2<=1," ",AH28) | AL28: =IF(财务基础数据!$W$2<=2," ",AI28)
A30: 其他非经营性损益 | G30: =利润表!O21 -> 0 | H30: =利润表!S21 -> 0 | I30: =利润表!W21 -> 0 | J30: =IF(COUNT(AJ31:AM31)=4,SUM(AJ30:AM30),J4*J31) -> 0 | K30: =IF(COUNT(AN31:AQ31)=4,SUM(AN30:AQ30),K4*K31) -> 0 | L30: =IF(COUNT(AR31:AU31)=4,SUM(AR30:AU30),L4*L31) -> 0 | M30: =IF(ISERROR(M4*M31),"—",M4*M31) -> 0 | N30: =IF(ISERROR(N4*N31),"—",N4*N31) -> 0 | O30: =IF(ISERROR(O4*O31),"—",O4*O31) -> 0 | P30: =IF(ISERROR(P4*P31),"—",P4*P31) -> 0 | Q30: =IF(ISERROR(Q4*Q31),"—",Q4*Q31) -> 0 | R30: =IF(ISERROR(R4*R31),"—",R4*R31) -> 0 | S30: =IF(ISERROR(S4*S31),"—",S4*S31) -> 0 | U30: =利润表!L21 -> 0 | V30: =利润表!M21-利润表!L21 -> 0 | W30: =利润表!N21-利润表!M21 -> 0 | X30: =利润表!O21-利润表!N21 -> 0 | Y30: =利润表!P21 -> 0 | Z30: =利润表!Q21-利润表!P21 -> 0 | AA30: =利润表!R21-利润表!Q21 -> 0 | AB30: =利润表!S21-利润表!R21 -> 0 | AC30: =利润表!T21 -> 0 | AD30: =利润表!U21-利润表!T21 -> 0 | AE30: =利润表!V21-利润表!U21 -> 0 | AF30: =利润表!W21-利润表!V21 -> 0 | AG30: =IF(财务基础数据!$W$2=0,0,利润表!X21) -> 0 | AH30: =IF(财务基础数据!$W$2<=1,0,利润表!Y21-利润表!X21) -> 0 | AI30: =IF(财务基础数据!$W$2<=2,0,利润表!Z21-利润表!Y21) -> 0 | AJ30: =IF(ISERROR(AJ31*AJ4),"—",AJ31*AJ4) -> — | AK30: =IF(ISERROR(AK31*AK4),"—",AK31*AK4) -> — | AL30: =IF(ISERROR(AL31*AL4),"—",AL31*AL4) -> — | AM30: =IF(ISERROR(AM31*AM4),"—",AM31*AM4) -> 0 | AN30: =IF(ISERROR(AN31*AN4),"—",AN31*AN4) -> 0 | AO30: =IF(ISERROR(AO31*AO4),"—",AO31*AO4) -> 0 | AP30: =IF(ISERROR(AP31*AP4),"—",AP31*AP4) -> 0 | AQ30: =IF(ISERROR(AQ31*AQ4),"—",AQ31*AQ4) -> 0 | ... AU30: =IF(ISERROR(AU31*AU4),"—",AU31*AU4) -> 0
A31: 占销售收入% | G31: =IF(ISERROR(G30/G4),"—",G30/G4) -> — | H31: =IF(ISERROR(H30/H4),"—",H30/H4) -> — | I31: =IF(ISERROR(I30/I4),"—",I30/I4) -> — | U31: =IF(ISERROR(U30/U4),"—",U30/U4) -> — | V31: =IF(ISERROR(V30/V4),"—",V30/V4) -> — | W31: =IF(ISERROR(W30/W4),"—",W30/W4) -> — | X31: =IF(ISERROR(X30/X4),"—",X30/X4) -> — | Y31: =IF(ISERROR(Y30/Y4),"—",Y30/Y4) -> — | Z31: =IF(ISERROR(Z30/Z4),"—",Z30/Z4) -> — | AA31: =IF(ISERROR(AA30/AA4),"—",AA30/AA4) -> — | AB31: =IF(ISERROR(AB30/AB4),"—",AB30/AB4) -> — | ... AI31: =IF(ISERROR(AI30/AI4),"—",AI30/AI4) -> — | AJ31: =IF(财务基础数据!$W$2=0," ",AG31) | AK31: =IF(财务基础数据!$W$2<=1," ",AH31) | AL31: =IF(财务基础数据!$W$2<=2," ",AI31)
A33: 所得税支出 | G33: =利润表!O25 -> 0 | H33: =利润表!S25 -> 0 | I33: =利润表!W25 -> 0 | J33: =IF(COUNT(AJ33:AM33)=4,SUM(AJ33:AM33),J34*利润表!AA24) -> 0 | K33: =IF(COUNT(AN33:AQ33)=4,SUM(AN33:AQ33),K34*利润表!AB24) -> 0 | L33: =IF(COUNT(AR33:AU33)=4,SUM(AR33:AU33),L34*利润表!AC24) -> 0 | M33: =IF(ISERROR(M34*利润表!AD24),"0",M34*利润表!AD24) -> 0 | N33: =IF(ISERROR(N34*利润表!AE24),"0",N34*利润表!AE24) -> 0 | O33: =IF(ISERROR(O34*利润表!AF24),"0",O34*利润表!AF24) -> 0 | P33: =IF(ISERROR(P34*利润表!AG24),"0",P34*利润表!AG24) -> 0 | Q33: =IF(ISERROR(Q34*利润表!AH24),"0",Q34*利润表!AH24) -> 0 | R33: =IF(ISERROR(R34*利润表!AI24),"0",R34*利润表!AI24) -> 0 | S33: =IF(ISERROR(S34*利润表!AJ24),"0",S34*利润表!AJ24) -> 0 | U33: =利润表!L25 -> 0 | V33: =利润表!M25-利润表!L25 -> 0 | W33: =利润表!N25-利润表!M25 -> 0 | X33: =利润表!O25-利润表!N25 -> 0 | Y33: =利润表!P25 -> 0 | Z33: =利润表!Q25-利润表!P25 -> 0 | AA33: =利润表!R25-利润表!Q25 -> 0 | AB33: =利润表!S25-利润表!R25 -> 0 | AC33: =利润表!T25 -> 0 | AD33: =利润表!U25-利润表!T25 -> 0 | AE33: =利润表!V25-利润表!U25 -> 0 | AF33: =利润表!W25-利润表!V25 -> 0 | AG33: =IF(财务基础数据!$W$2=0,0,利润表!X25) -> 0 | AH33: =IF(财务基础数据!$W$2<=1,0,利润表!Y25-利润表!X25) -> 0 | AI33: =IF(财务基础数据!$W$2<=2,0,利润表!Z25-利润表!Y25) -> 0 | AJ33: =IF(财务基础数据!$W$2=0,"",AG33) | AK33: =IF(财务基础数据!$W$2<=1,"",AH33) | AL33: =IF(财务基础数据!$W$2<=2,"",AI33)
A34: 所得税税率 | G34: =IF(ISERROR(G33/利润表!O24),"—",G33/利润表!O24) -> — | H34: =IF(ISERROR(H33/利润表!S24),"—",H33/利润表!S24) -> — | I34: =IF(ISERROR(I33/利润表!W24),"—",I33/利润表!W24) -> —
A36: 少数股东损益 | G36: =利润表!O27 -> 0 | H36: =利润表!S27 -> 0 | I36: =利润表!W27 -> 0 | J36: =IF(COUNT(AJ36:AM36)=4,SUM(AJ36:AM36),J37*(利润表!AA26)) -> 0 | K36: =IF(COUNT(AN36:AQ36)=4,SUM(AN36:AQ36),K37*(利润表!AB26)) -> 0 | L36: =IF(COUNT(AR36:AU36)=4,SUM(AR36:AU36),L37*(利润表!AC26)) -> 0 | M36: =IF(ISERROR(M37*(利润表!AD26)),"—",M37*(利润表!AD26)) -> 0 | N36: =IF(ISERROR(N37*(利润表!AE26)),"—",N37*(利润表!AE26)) -> 0 | O36: =IF(ISERROR(O37*(利润表!AF26)),"—",O37*(利润表!AF26)) -> 0 | P36: =IF(ISERROR(P37*(利润表!AG26)),"—",P37*(利润表!AG26)) -> 0 | Q36: =IF(ISERROR(Q37*(利润表!AH26)),"—",Q37*(利润表!AH26)) -> 0 | R36: =IF(ISERROR(R37*(利润表!AI26)),"—",R37*(利润表!AI26)) -> 0 | S36: =IF(ISERROR(S37*(利润表!AJ26)),"—",S37*(利润表!AJ26)) -> 0 | U36: =利润表!L27 -> 0 | V36: =利润表!M27-利润表!L27 -> 0 | W36: =利润表!N27-利润表!M27 -> 0 | X36: =利润表!O27-利润表!N27 -> 0 | Y36: =利润表!P27 -> 0 | Z36: =利润表!Q27-利润表!P27 -> 0 | AA36: =利润表!R27-利润表!Q27 -> 0 | AB36: =利润表!S27-利润表!R27 -> 0 | AC36: =利润表!T27 -> 0 | AD36: =利润表!U27-利润表!T27 -> 0 | AE36: =利润表!V27-利润表!U27 -> 0 | AF36: =利润表!W27-利润表!V27 -> 0 | AG36: =IF(财务基础数据!$W$2=0,0,利润表!X27) -> 0 | AH36: =IF(财务基础数据!$W$2<=1,0,利润表!Y27-利润表!X27) -> 0 | AI36: =IF(财务基础数据!$W$2<=2,0,利润表!Z27-利润表!Y27) -> 0 | AJ36: =IF(财务基础数据!$W$2=0,"",AG36) | AK36: =IF(财务基础数据!$W$2<=1,"",AH36) | AL36: =IF(财务基础数据!$W$2<=2,"",AI36)
A37: 少数股东损益/净利润 | G37: =IF(ISERROR(G36/(利润表!O26)),"—",G36/(利润表!O26)) -> — | H37: =IF(ISERROR(H36/(利润表!S26)),"—",H36/(利润表!S26)) -> — | I37: =IF(ISERROR(I36/(利润表!W26)),"—",I36/(利润表!W26)) -> —

Sheet 资产预测
A2: 营运资金
A3: =主要财务摘要!H2 -> 单位：港币(百万)
A4: 会计年度： | D4: =资产负债表!O4 -> 2019 | E4: =资产负债表!S4 -> 2020 | F4: =资产负债表!W4 -> 2021 | G4: =资产负债表!X4 -> 1Q22 | H4: =资产负债表!Y4 -> 1H22 | I4: =资产负债表!Z4 -> 3Q22 | J4: =资产负债表!AA4 -> 2022E | K4: =资产负债表!AB4 -> 2023 | L4: =资产负债表!AC4 -> 2024 | M4: =资产负债表!AD4 -> 2025 | ... S4: =资产负债表!AJ4 -> 2031
A5: 营业收入 | D5: =利润表!O6 -> 0 | E5: =利润表!S6 -> 0 | F5: =利润表!W6 -> 0 | G5: =利润表!X6 -> 0 | H5: =利润表!Y6 -> 0 | I5: =利润表!Z6 -> 0 | J5: =利润表!AA6 -> 0 | K5: =利润表!AB6 -> 0 | L5: =利润表!AC6 -> 0 | M5: =利润表!AD6 -> 0 | ... S5: =利润表!AJ6 -> 0
A6: 营业成本 | D6: =利润表!O9 -> 0 | E6: =利润表!S9 -> 0 | F6: =利润表!W9 -> 0 | G6: =利润表!X9 -> 0 | H6: =利润表!Y9 -> 0 | I6: =利润表!Z9 -> 0 | J6: =利润表!AA9 -> 0 | K6: =利润表!AB9 -> 0 | L6: =利润表!AC9 -> 0 | M6: =利润表!AD9 -> 0 | ... S6: =利润表!AJ9 -> 0
A8: （一）流动资产
A9: 应收账款及票据 | D9: =资产负债表!O9 -> 0 | E9: =资产负债表!S9 -> 0 | F9: =资产负债表!W9 -> 0 | G9: =资产负债表!X9 -> 0 | H9: =资产负债表!Y9 -> 0 | I9: =资产负债表!Z9 -> 0 | J9: =IF(ISERROR(J5/(360/J10)),0,J5/(360/J10)) -> 0 | K9: =IF(ISERROR(K5/(360/K10)),0,K5/(360/K10)) -> 0 | L9: =IF(ISERROR(L5/(360/L10)),0,L5/(360/L10)) -> 0 | M9: =IF(ISERROR(M5/(360/M10)),0,M5/(360/M10)) -> 0 | N9: =IF(ISERROR(N5/(360/N10)),0,N5/(360/N10)) -> 0 | O9: =IF(ISERROR(O5/(360/O10)),0,O5/(360/O10)) -> 0 | P9: =IF(ISERROR(P5/(360/P10)),0,P5/(360/P10)) -> 0 | Q9: =IF(ISERROR(Q5/(360/Q10)),0,Q5/(360/Q10)) -> 0 | ... S9: =IF(ISERROR(S5/(360/S10)),0,S5/(360/S10)) -> 0
A10: 周转天数（相对于销售收入） | D10: =IF(ISERROR(360/(D5/D9)),"—",360/(D5/D9)) -> — | E10: =IF(ISERROR(360/(E5/E9)),"—",360/(E5/E9)) -> — | F10: =IF(ISERROR(360/(F5/F9)),"—",360/(F5/F9)) -> — | G10: =IF(ISERROR(360/(G5/G9)),"—",360/(G5/G9)) -> — | H10: =IF(ISERROR(360/(H5/H9)),"—",360/(H5/H9)) -> — | I10: =IF(ISERROR(360/(I5/I9)),"—",360/(I5/I9)) -> — | T10: 说明：此处周转天数按照期末值计算
A11: 应收帐款/销售收入（%） | D11: =IF(ISERROR(D9/D5),"—",D9/D5) -> — | E11: =IF(ISERROR(E9/E5),"—",E9/E5) -> — | F11: =IF(ISERROR(F9/F5),"—",F9/F5) -> — | G11: =IF(ISERROR(G9/G5),"—",G9/G5) -> — | H11: =IF(ISERROR(H9/H5),"—",H9/H5) -> — | I11: =IF(ISERROR(I9/I5),"—",I9/I5) -> — | J11: =IF(ISERROR(J9/J5),"—",J9/J5) -> — | K11: =IF(ISERROR(K9/K5),"—",K9/K5) -> — | ... S11: =IF(ISERROR(S9/S5),"—",S9/S5) -> —
A13: 存货 | D13: =资产负债表!O11 -> 0 | E13: =资产负债表!S11 -> 0 | F13: =资产负债表!W11 -> 0 | G13: =资产负债表!X11 -> 0 | H13: =资产负债表!Y11 -> 0 | I13: =资产负债表!Z11 -> 0 | J13: =IF(ISERROR(J6/(360/J14)),0,J6/(360/J14)) -> 0 | K13: =IF(ISERROR(K6/(360/K14)),0,K6/(360/K14)) -> 0 | L13: =IF(ISERROR(L6/(360/L14)),0,L6/(360/L14)) -> 0 | M13: =IF(ISERROR(M6/(360/M14)),0,M6/(360/M14)) -> 0 | N13: =IF(ISERROR(N6/(360/N14)),0,N6/(360/N14)) -> 0 | O13: =IF(ISERROR(O6/(360/O14)),0,O6/(360/O14)) -> 0 | P13: =IF(ISERROR(P6/(360/P14)),0,P6/(360/P14)) -> 0 | Q13: =IF(ISERROR(Q6/(360/Q14)),0,Q6/(360/Q14)) -> 0 | ... S13: =IF(ISERROR(S6/(360/S14)),0,S6/(360/S14)) -> 0
A14: 周转天数（相对于销售成本） | D14: =IF(ISERROR(360/(D6/D13)),"—",360/(D6/D13)) -> — | E14: =IF(ISERROR(360/(E6/E13)),"—",360/(E6/E13)) -> — | F14: =IF(ISERROR(360/(F6/F13)),"—",360/(F6/F13)) -> — | G14: =IF(ISERROR(360/(G6/G13)),"—",360/(G6/G13)) -> — | H14: =IF(ISERROR(360/(H6/H13)),"—",360/(H6/H13)) -> — | I14: =IF(ISERROR(360/(I6/I13)),"—",360/(I6/I13)) -> — | T14: 说明：此处周转天数按照期末值计算
A15: 存货/销售成本（%） | D15: =IF(ISERROR(D13/D6),"—",D13/D6) -> — | E15: =IF(ISERROR(E13/E6),"—",E13/E6) -> — | F15: =IF(ISERROR(F13/F6),"—",F13/F6) -> — | G15: =IF(ISERROR(G13/G6),"—",G13/G6) -> — | H15: =IF(ISERROR(H13/H6),"—",H13/H6) -> — | I15: =IF(ISERROR(I13/I6),"—",I13/I6) -> — | J15: =IF(ISERROR(J13/J6),"—",J13/J6) -> — | K15: =IF(ISERROR(K13/K6),"—",K13/K6) -> — | ... S15: =IF(ISERROR(S13/S6),"—",S13/S6) -> —
A17: 其他应收款 | D17: =资产负债表!O10 -> 0 | E17: =资产负债表!S10 -> 0 | F17: =资产负债表!W10 -> 0 | G17: =资产负债表!X10 -> 0 | H17: =资产负债表!Y10 -> 0 | I17: =资产负债表!Z10 -> 0 | J17: =IF(ISERROR(J18*J5),0,J18*J5) -> 0 | K17: =IF(ISERROR(K18*K5),0,K18*K5) -> 0 | L17: =IF(ISERROR(L18*L5),0,L18*L5) -> 0 | M17: =IF(ISERROR(M18*M5),0,M18*M5) -> 0 | N17: =IF(ISERROR(N18*N5),0,N18*N5) -> 0 | O17: =IF(ISERROR(O18*O5),0,O18*O5) -> 0 | P17: =IF(ISERROR(P18*P5),0,P18*P5) -> 0 | Q17: =IF(ISERROR(Q18*Q5),0,Q18*Q5) -> 0 | ... S17: =IF(ISERROR(S18*S5),0,S18*S5) -> 0
A18: 比销售收入（%） | D18: =IF(ISERROR(D17/D5),"—",D17/D5) -> — | E18: =IF(ISERROR(E17/E5),"—",E17/E5) -> — | F18: =IF(ISERROR(F17/F5),"—",F17/F5) -> — | G18: =IF(ISERROR(G17/G5),"—",G17/G5) -> — | H18: =IF(ISERROR(H17/H5),"—",H17/H5) -> — | I18: =IF(ISERROR(I17/I5),"—",I17/I5) -> —
A20: 其他流动资产 | D20: =资产负债表!O12 -> 0 | E20: =资产负债表!S12 -> 0 | F20: =资产负债表!W12 -> 0 | G20: =资产负债表!X12 -> 0 | H20: =资产负债表!Y12 -> 0 | I20: =资产负债表!Z12 -> 0 | J20: =IF(ISERROR(J21*J5),0,J21*J5) -> 0 | K20: =IF(ISERROR(K21*K5),0,K21*K5) -> 0 | L20: =IF(ISERROR(L21*L5),0,L21*L5) -> 0 | M20: =IF(ISERROR(M21*M5),0,M21*M5) -> 0 | N20: =IF(ISERROR(N21*N5),0,N21*N5) -> 0 | O20: =IF(ISERROR(O21*O5),0,O21*O5) -> 0 | P20: =IF(ISERROR(P21*P5),0,P21*P5) -> 0 | Q20: =IF(ISERROR(Q21*Q5),0,Q21*Q5) -> 0 | ... S20: =IF(ISERROR(S21*S5),0,S21*S5) -> 0
A21: 比销售收入（%） | D21: =IF(ISERROR(D20/D5),"—",D20/D5) -> — | E21: =IF(ISERROR(E20/E5),"—",E20/E5) -> — | F21: =IF(ISERROR(F20/F5),"—",F20/F5) -> — | G21: =IF(ISERROR(G20/G5),"—",G20/G5) -> — | H21: =IF(ISERROR(H20/H5),"—",H20/H5) -> — | I21: =IF(ISERROR(I20/I5),"—",I20/I5) -> —
A23: （二）流动负债
A24: 应付账款及票据 | D24: =资产负债表!O28 -> 0 | E24: =资产负债表!S28 -> 0 | F24: =资产负债表!W28 -> 0 | G24: =资产负债表!X28 -> 0 | H24: =资产负债表!Y28 -> 0 | I24: =资产负债表!Z28 -> 0 | J24: =IF(ISERROR(J6/(360/J25)),0,J6/(360/J25)) -> 0 | K24: =IF(ISERROR(K6/(360/K25)),0,K6/(360/K25)) -> 0 | L24: =IF(ISERROR(L6/(360/L25)),0,L6/(360/L25)) -> 0 | M24: =IF(ISERROR(M6/(360/M25)),0,M6/(360/M25)) -> 0 | N24: =IF(ISERROR(N6/(360/N25)),0,N6/(360/N25)) -> 0 | O24: =IF(ISERROR(O6/(360/O25)),0,O6/(360/O25)) -> 0 | P24: =IF(ISERROR(P6/(360/P25)),0,P6/(360/P25)) -> 0 | Q24: =IF(ISERROR(Q6/(360/Q25)),0,Q6/(360/Q25)) -> 0 | ... S24: =IF(ISERROR(S6/(360/S25)),0,S6/(360/S25)) -> 0
A25: 周转天数（相对于销售成本） | D25: =IF(ISERROR(360/(D6/D24)),"—",360/(D6/D24)) -> — | E25: =IF(ISERROR(360/(E6/E24)),"—",360/(E6/E24)) -> — | F25: =IF(ISERROR(360/(F6/F24)),"—",360/(F6/F24)) -> — | G25: =IF(ISERROR(360/(G6/G24)),"—",360/(G6/G24)) -> — | H25: =IF(ISERROR(360/(H6/H24)),"—",360/(H6/H24)) -> — | I25: =IF(ISERROR(360/(I6/I24)),"—",360/(I6/I24)) -> — | T25: 说明：此处周转天数按照期末值计算
A26: 应付帐款/销售成本（%） | D26: =IF(ISERROR(D24/D6),"—",D24/D6) -> — | E26: =IF(ISERROR(E24/E6),"—",E24/E6) -> — | F26: =IF(ISERROR(F24/F6),"—",F24/F6) -> — | G26: =IF(ISERROR(G24/G6),"—",G24/G6) -> — | H26: =IF(ISERROR(H24/H6),"—",H24/H6) -> — | I26: =IF(ISERROR(I24/I6),"—",I24/I6) -> — | J26: =IF(ISERROR(J24/J6),"—",J24/J6) -> — | K26: =IF(ISERROR(K24/K6),"—",K24/K6) -> — | ... S26: =IF(ISERROR(S24/S6),"—",S24/S6) -> —
A28: 其他流动负债 | D28: =资产负债表!O32 -> 0 | E28: =资产负债表!S32 -> 0 | F28: =资产负债表!W32 -> 0 | G28: =资产负债表!X32 -> 0 | H28: =资产负债表!Y32 -> 0 | I28: =资产负债表!Z32 -> 0 | J28: =IF(ISERROR(J29*J5),0,J29*J5) -> 0 | K28: =IF(ISERROR(K29*K5),0,K29*K5) -> 0 | L28: =IF(ISERROR(L29*L5),0,L29*L5) -> 0 | M28: =IF(ISERROR(M29*M5),0,M29*M5) -> 0 | N28: =IF(ISERROR(N29*N5),0,N29*N5) -> 0 | O28: =IF(ISERROR(O29*O5),0,O29*O5) -> 0 | P28: =IF(ISERROR(P29*P5),0,P29*P5) -> 0 | Q28: =IF(ISERROR(Q29*Q5),0,Q29*Q5) -> 0 | ... S28: =IF(ISERROR(S29*S5),0,S29*S5) -> 0
A29: 比销售收入（%） | D29: =IF(ISERROR(D28/D5),"—",D28/D5) -> — | E29: =IF(ISERROR(E28/E5),"—",E28/E5) -> — | F29: =IF(ISERROR(F28/F5),"—",F28/F5) -> — | G29: =IF(ISERROR(G28/G5),"—",G28/G5) -> — | H29: =IF(ISERROR(H28/H5),"—",H28/H5) -> — | I29: =IF(ISERROR(I28/I5),"—",I28/I5) -> —
A31: 应交税金 | D31: =资产负债表!O29 -> 0 | E31: =资产负债表!S29 -> 0 | F31: =资产负债表!W29 -> 0 | G31: =资产负债表!X29 -> 0 | H31: =资产负债表!Y29 -> 0 | I31: =资产负债表!Z29 -> 0 | J31: =IF(ISERROR(J32*J5),0,J32*J5) -> 0 | K31: =IF(ISERROR(K32*K5),0,K32*K5) -> 0 | L31: =IF(ISERROR(L32*L5),0,L32*L5) -> 0 | M31: =IF(ISERROR(M32*M5),0,M32*M5) -> 0 | N31: =IF(ISERROR(N32*N5),0,N32*N5) -> 0 | O31: =IF(ISERROR(O32*O5),0,O32*O5) -> 0 | P31: =IF(ISERROR(P32*P5),0,P32*P5) -> 0 | Q31: =IF(ISERROR(Q32*Q5),0,Q32*Q5) -> 0 | ... S31: =IF(ISERROR(S32*S5),0,S32*S5) -> 0
A32: 比销售收入（%） | D32: =IF(ISERROR(D31/D5),"—",D31/D5) -> — | E32: =IF(ISERROR(E31/E5),"—",E31/E5) -> — | F32: =IF(ISERROR(F31/F5),"—",F31/F5) -> — | G32: =IF(ISERROR(G31/G5),"—",G31/G5) -> — | H32: =IF(ISERROR(H31/H5),"—",H31/H5) -> — | I32: =IF(ISERROR(I31/I5),"—",I31/I5) -> —
A35: 投资预测
A36: =A3 -> 单位：港币(百万)
A37: 会计年度截止日：12/31 | D37: =D4 -> 2019 | E37: =E4 -> 2020 | F37: =F4 -> 2021 | G37: =G4 -> 1Q22 | H37: =H4 -> 1H22 | I37: =I4 -> 3Q22 | J37: =J4 -> 2022E | K37: =K4 -> 2023 | ... S37: =S4 -> 2031
A39: （一）短期投资
A40: 交易性金融资产 | D40: =资产负债表!O7 -> 0 | E40: =资产负债表!S7 -> 0 | F40: =资产负债表!W7 -> 0 | G40: =资产负债表!X7 -> 0 | H40: =资产负债表!Y7 -> 0 | I40: =资产负债表!Z7 -> 0 | J40: =IF(ISERROR(F40+J41),"—",F40+J41) -> 0 | K40: =IF(ISERROR(J40+K41),"—",J40+K41) -> 0 | L40: =IF(ISERROR(K40+L41),"—",K40+L41) -> 0 | M40: =IF(ISERROR(L40+M41),"—",L40+M41) -> 0 | N40: =IF(ISERROR(M40+N41),"—",M40+N41) -> 0 | O40: =IF(ISERROR(N40+O41),"—",N40+O41) -> 0 | P40: =IF(ISERROR(O40+P41),"—",O40+P41) -> 0 | Q40: =IF(ISERROR(P40+Q41),"—",P40+Q41) -> 0 | R40: =IF(ISERROR(Q40+R41),"—",Q40+R41) -> 0 | S40: =IF(ISERROR(R40+S41),"—",R40+S41) -> 0
A41: 当期增减 | D41: =D40-资产负债表!K7 -> 0 | E41: =E40-D40 -> 0 | F41: =F40-E40 -> 0 | G41: =IF(财务基础数据!$W$2=0,0,G40-F40) -> 0 | H41: =IF(财务基础数据!$W$2<=1,0,H40-G40) -> 0 | I41: =IF(财务基础数据!$W$2<=2,0,I40-H40) -> 0
A43: 其他短期投资 | D43: =资产负债表!O8 -> 0 | E43: =资产负债表!S8 -> 0 | F43: =资产负债表!W8 -> 0 | G43: =资产负债表!X8 -> 0 | H43: =资产负债表!Y8 -> 0 | I43: =资产负债表!Z8 -> 0 | J43: =IF(ISERROR(F43+J44),"—",F43+J44) -> 0 | K43: =IF(ISERROR(J43+K44),"—",J43+K44) -> 0 | L43: =IF(ISERROR(K43+L44),"—",K43+L44) -> 0 | M43: =IF(ISERROR(L43+M44),"—",L43+M44) -> 0 | N43: =IF(ISERROR(M43+N44),"—",M43+N44) -> 0 | O43: =IF(ISERROR(N43+O44),"—",N43+O44) -> 0 | P43: =IF(ISERROR(O43+P44),"—",O43+P44) -> 0 | Q43: =IF(ISERROR(P43+Q44),"—",P43+Q44) -> 0 | R43: =IF(ISERROR(Q43+R44),"—",Q43+R44) -> 0 | S43: =IF(ISERROR(R43+S44),"—",R43+S44) -> 0
A44: 当期增减 | D44: =D43-资产负债表!K8 -> 0 | E44: =E43-D43 -> 0 | F44: =F43-E43 -> 0 | G44: =IF(财务基础数据!$W$2=0,0,G43-F43) -> 0 | H44: =IF(财务基础数据!$W$2<=1,0,H43-G43) -> 0 | I44: =IF(财务基础数据!$W$2<=2,0,I43-H43) -> 0
A46: 交易性金融负债 | D46: =资产负债表!O30 -> 0 | E46: =资产负债表!S30 -> 0 | F46: =资产负债表!W30 -> 0 | G46: =资产负债表!X30 -> 0 | H46: =资产负债表!Y30 -> 0 | I46: =资产负债表!Z30 -> 0 | J46: =IF(ISERROR(F46+J47),"—",F46+J47) -> 0 | K46: =IF(ISERROR(J46+K47),"—",J46+K47) -> 0 | L46: =IF(ISERROR(K46+L47),"—",K46+L47) -> 0 | M46: =IF(ISERROR(L46+M47),"—",L46+M47) -> 0 | N46: =IF(ISERROR(M46+N47),"—",M46+N47) -> 0 | O46: =IF(ISERROR(N46+O47),"—",N46+O47) -> 0 | P46: =IF(ISERROR(O46+P47),"—",O46+P47) -> 0 | Q46: =IF(ISERROR(P46+Q47),"—",P46+Q47) -> 0 | R46: =IF(ISERROR(Q46+R47),"—",Q46+R47) -> 0 | S46: =IF(ISERROR(R46+S47),"—",R46+S47) -> 0
A47: 当期增减 | D47: =D46-资产负债表!K30 -> 0 | E47: =E46-D46 -> 0 | F47: =F46-E46 -> 0 | G47: =IF(财务基础数据!$W$2=0,0,G46-F46) -> 0 | H47: =IF(财务基础数据!$W$2<=1,0,H46-G46) -> 0 | I47: =IF(财务基础数据!$W$2<=2,0,I46-H46) -> 0
A50: （二）长期投资
A51: 权益性投资 | D51: =资产负债表!O16 -> 0 | E51: =资产负债表!S16 -> 0 | F51: =资产负债表!W16 -> 0 | G51: =资产负债表!X16 -> 0 | H51: =资产负债表!Y16 -> 0 | I51: =资产负债表!Z16 -> 0 | J51: =IF(ISERROR(F51+J52),"—",F51+J52) -> 0 | K51: =IF(ISERROR(J51+K52),"—",J51+K52) -> 0 | L51: =IF(ISERROR(K51+L52),"—",K51+L52) -> 0 | M51: =IF(ISERROR(L51+M52),"—",L51+M52) -> 0 | N51: =IF(ISERROR(M51+N52),"—",M51+N52) -> 0 | O51: =IF(ISERROR(N51+O52),"—",N51+O52) -> 0 | P51: =IF(ISERROR(O51+P52),"—",O51+P52) -> 0 | Q51: =IF(ISERROR(P51+Q52),"—",P51+Q52) -> 0 | R51: =IF(ISERROR(Q51+R52),"—",Q51+R52) -> 0 | S51: =IF(ISERROR(R51+S52),"—",R51+S52) -> 0
A52: 当期增减 | D52: =D51-资产负债表!K16 -> 0 | E52: =E51-D51 -> 0 | F52: =F51-E51 -> 0 | G52: =IF(财务基础数据!$W$2=0,0,G51-F51) -> 0 | H52: =IF(财务基础数据!$W$2<=1,0,H51-G51) -> 0 | I52: =IF(财务基础数据!$W$2<=2,0,I51-H51) -> 0
A54: 债务工具 | D54: =资产负债表!O17 -> 0 | E54: =资产负债表!S17 -> 0 | F54: =资产负债表!W17 -> 0 | G54: =资产负债表!X17 -> 0 | H54: =资产负债表!Y17 -> 0 | I54: =资产负债表!Z17 -> 0 | J54: =IF(ISERROR(F54+J55),"—",F54+J55) -> 0 | K54: =IF(ISERROR(J54+K55),"—",J54+K55) -> 0 | L54: =IF(ISERROR(K54+L55),"—",K54+L55) -> 0 | M54: =IF(ISERROR(L54+M55),"—",L54+M55) -> 0 | N54: =IF(ISERROR(M54+N55),"—",M54+N55) -> 0 | O54: =IF(ISERROR(N54+O55),"—",N54+O55) -> 0 | P54: =IF(ISERROR(O54+P55),"—",O54+P55) -> 0 | Q54: =IF(ISERROR(P54+Q55),"—",P54+Q55) -> 0 | R54: =IF(ISERROR(Q54+R55),"—",Q54+R55) -> 0 | S54: =IF(ISERROR(R54+S55),"—",R54+S55) -> 0
A55: 当期增减 | D55: =D54-资产负债表!K17 -> 0 | E55: =E54-D54 -> 0 | F55: =F54-E54 -> 0 | G55: =IF(财务基础数据!$W$2=0,0,G54-F54) -> 0 | H55: =IF(财务基础数据!$W$2<=1,0,H54-G54) -> 0 | I55: =IF(财务基础数据!$W$2<=2,0,I54-H54) -> 0
A57: 可供出售投资 | D57: =资产负债表!O18 -> 0 | E57: =资产负债表!S18 -> 0 | F57: =资产负债表!W18 -> 0 | G57: =资产负债表!X18 -> 0 | H57: =资产负债表!Y18 -> 0 | I57: =资产负债表!Z18 -> 0 | J57: =IF(ISERROR(F57+J58),"—",F57+J58) -> 0 | K57: =IF(ISERROR(J57+K58),"—",J57+K58) -> 0 | L57: =IF(ISERROR(K57+L58),"—",K57+L58) -> 0 | M57: =IF(ISERROR(L57+M58),"—",L57+M58) -> 0 | N57: =IF(ISERROR(M57+N58),"—",M57+N58) -> 0 | O57: =IF(ISERROR(N57+O58),"—",N57+O58) -> 0 | P57: =IF(ISERROR(O57+P58),"—",O57+P58) -> 0 | Q57: =IF(ISERROR(P57+Q58),"—",P57+Q58) -> 0 | R57: =IF(ISERROR(Q57+R58),"—",Q57+R58) -> 0 | S57: =IF(ISERROR(R57+S58),"—",R57+S58) -> 0
A58: 当期增减 | D58: =D57-资产负债表!K18 -> 0 | E58: =E57-D57 -> 0 | F58: =F57-E57 -> 0 | G58: =IF(财务基础数据!$W$2=0,0,G57-F57) -> 0 | H58: =IF(财务基础数据!$W$2<=1,0,H57-G57) -> 0 | I58: =IF(财务基础数据!$W$2<=2,0,I57-H57) -> 0
A60: （三）资本性投资
A61: 固定资产初值 | D61: =资产负债表!K15 -> 0 | E61: =D64 -> 0 | F61: =E64 -> 0 | G61: =F64 -> 0 | H61: =G64 -> 0 | I61: =H64 -> 0 | J61: =F64 -> 0 | K61: =J64 -> 0 | L61: =K64 -> 0 | M61: =L64 -> 0 | N61: =M64 -> 0 | O61: =N64 -> 0 | P61: =O64 -> 0 | Q61: =P64 -> 0 | R61: =Q64 -> 0 | S61: =R64 -> 0
A62: 当期增减 | D62: =D64-D61 -> 0 | E62: =E64-E61 -> 0 | F62: =F64-F61 -> 0 | G62: =IF(财务基础数据!$W$2=0,0,G64-F64) -> 0 | H62: =IF(财务基础数据!$W$2<=1,0,H64-G64) -> 0 | I62: =IF(财务基础数据!$W$2<=2,0,I64-H64) -> 0
A63: 折旧 | B63: 0 | J63: =J61*$B$63+J62/2*$B$63 -> 0 | K63: =K61*$B$63+K62/2*$B$63 -> 0 | L63: =L61*$B$63+L62/2*$B$63 -> 0 | M63: =M61*$B$63+M62/2*$B$63 -> 0 | N63: =N61*$B$63+N62/2*$B$63 -> 0 | O63: =O61*$B$63+O62/2*$B$63 -> 0 | P63: =P61*$B$63+P62/2*$B$63 -> 0 | Q63: =Q61*$B$63+Q62/2*$B$63 -> 0 | ... S63: =S61*$B$63+S62/2*$B$63 -> 0
A64: 固定资产终值 | D64: =资产负债表!O15 -> 0 | E64: =资产负债表!S15 -> 0 | F64: =资产负债表!W15 -> 0 | G64: =资产负债表!X15 -> 0 | H64: =资产负债表!Y15 -> 0 | I64: =资产负债表!Z15 -> 0 | J64: =IF(ISERROR(J61+J62-J63),"—",J61+J62-J63) -> 0 | K64: =IF(ISERROR(K61+K62-K63),"—",K61+K62-K63) -> 0 | L64: =IF(ISERROR(L61+L62-L63),"—",L61+L62-L63) -> 0 | M64: =IF(ISERROR(M61+M62-M63),"—",M61+M62-M63) -> 0 | N64: =IF(ISERROR(N61+N62-N63),"—",N61+N62-N63) -> 0 | O64: =IF(ISERROR(O61+O62-O63),"—",O61+O62-O63) -> 0 | P64: =IF(ISERROR(P61+P62-P63),"—",P61+P62-P63) -> 0 | Q64: =IF(ISERROR(Q61+Q62-Q63),"—",Q61+Q62-Q63) -> 0 | ... S64: =IF(ISERROR(S61+S62-S63),"—",S61+S62-S63) -> 0
A66: 商誉及无形资产初值 | D66: =资产负债表!K20 -> 0 | E66: =D69 -> 0 | F66: =E69 -> 0 | G66: =F69 -> 0 | H66: =G69 -> 0 | I66: =H69 -> 0 | J66: =F69 -> 0 | K66: =J69 -> 0 | L66: =K69 -> 0 | M66: =L69 -> 0 | N66: =M69 -> 0 | O66: =N69 -> 0 | P66: =O69 -> 0 | Q66: =P69 -> 0 | R66: =Q69 -> 0 | S66: =R69 -> 0
A67: 本期增减 | D67: =D69-D66 -> 0 | E67: =E69-E66 -> 0 | F67: =F69-F66 -> 0 | G67: =IF(财务基础数据!$W$2=0,0,G69-F69) -> 0 | H67: =IF(财务基础数据!$W$2<=1,0,H69-G69) -> 0 | I67: =IF(财务基础数据!$W$2<=2,0,I69-H69) -> 0
A68: 摊销 | B68: 0 | J68: =J66*$B$68+J67/2*$B$68 -> 0 | K68: =K66*$B$68+K67/2*$B$68 -> 0 | L68: =L66*$B$68+L67/2*$B$68 -> 0 | M68: =M66*$B$68+M67/2*$B$68 -> 0 | N68: =N66*$B$68+N67/2*$B$68 -> 0 | O68: =O66*$B$68+O67/2*$B$68 -> 0 | P68: =P66*$B$68+P67/2*$B$68 -> 0 | Q68: =Q66*$B$68+Q67/2*$B$68 -> 0 | ... S68: =S66*$B$68+S67/2*$B$68 -> 0
A69: 商誉及无形资产终值 | D69: =资产负债表!O20 -> 0 | E69: =资产负债表!S20 -> 0 | F69: =资产负债表!W20 -> 0 | G69: =资产负债表!X20 -> 0 | H69: =资产负债表!Y20 -> 0 | I69: =资产负债表!Z20 -> 0 | J69: =IF(ISERROR(J66+J67-J68),"—",J66+J67-J68) -> 0 | K69: =IF(ISERROR(K66+K67-K68),"—",K66+K67-K68) -> 0 | L69: =IF(ISERROR(L66+L67-L68),"—",L66+L67-L68) -> 0 | M69: =IF(ISERROR(M66+M67-M68),"—",M66+M67-M68) -> 0 | N69: =IF(ISERROR(N66+N67-N68),"—",N66+N67-N68) -> 0 | O69: =IF(ISERROR(O66+O67-O68),"—",O66+O67-O68) -> 0 | P69: =IF(ISERROR(P66+P67-P68),"—",P66+P67-P68) -> 0 | Q69: =IF(ISERROR(Q66+Q67-Q68),"—",Q66+Q67-Q68) -> 0 | ... S69: =IF(ISERROR(S66+S67-S68),"—",S66+S67-S68) -> 0
A71: 折旧摊销合计 | D71: =现金流量表!O6 -> 0 | E71: =现金流量表!S6 -> 0 | F71: =现金流量表!W6 -> 0 | G71: =现金流量表!X6 -> 0 | H71: =现金流量表!Y6 -> 0 | I71: =现金流量表!Z6 -> 0 | J71: =J63+J68 -> 0 | K71: =K63+K68 -> 0 | L71: =L63+L68 -> 0 | M71: =M63+M68 -> 0 | N71: =N63+N68 -> 0 | O71: =O63+O68 -> 0 | P71: =P63+P68 -> 0 | Q71: =Q63+Q68 -> 0 | ... S71: =S63+S68 -> 0
A73: （四）其他
A74: 其他长期投资 | D74: =资产负债表!O19 -> 0 | E74: =资产负债表!S19 -> 0 | F74: =资产负债表!W19 -> 0 | G74: =资产负债表!X19 -> 0 | H74: =资产负债表!Y19 -> 0 | I74: =资产负债表!Z19 -> 0 | J74: =IF(ISERROR(F74+J75),"—",F74+J75) -> 0 | K74: =IF(ISERROR(J74+K75),"—",J74+K75) -> 0 | L74: =IF(ISERROR(K74+L75),"—",K74+L75) -> 0 | M74: =IF(ISERROR(L74+M75),"—",L74+M75) -> 0 | N74: =IF(ISERROR(M74+N75),"—",M74+N75) -> 0 | O74: =IF(ISERROR(N74+O75),"—",N74+O75) -> 0 | P74: =IF(ISERROR(O74+P75),"—",O74+P75) -> 0 | Q74: =IF(ISERROR(P74+Q75),"—",P74+Q75) -> 0 | R74: =IF(ISERROR(Q74+R75),"—",Q74+R75) -> 0 | S74: =IF(ISERROR(R74+S75),"—",R74+S75) -> 0
A75: 本期增减 | D75: =D74-资产负债表!K19 -> 0 | E75: =E74-D74 -> 0 | F75: =F74-E74 -> 0 | G75: =IF(财务基础数据!$W$2=0,0,G74-F74) -> 0 | H75: =IF(财务基础数据!$W$2<=1,0,H74-G74) -> 0 | I75: =IF(财务基础数据!$W$2<=2,0,I74-H74) -> 0
A77: 租赁土地 | D77: =资产负债表!O21 -> 0 | E77: =资产负债表!S21 -> 0 | F77: =资产负债表!W21 -> 0 | G77: =资产负债表!X21 -> 0 | H77: =资产负债表!Y21 -> 0 | I77: =资产负债表!Z21 -> 0 | J77: =IF(ISERROR(F77+J78),"—",F77+J78) -> 0 | K77: =IF(ISERROR(J77+K78),"—",J77+K78) -> 0 | L77: =IF(ISERROR(K77+L78),"—",K77+L78) -> 0 | M77: =IF(ISERROR(L77+M78),"—",L77+M78) -> 0 | N77: =IF(ISERROR(M77+N78),"—",M77+N78) -> 0 | O77: =IF(ISERROR(N77+O78),"—",N77+O78) -> 0 | P77: =IF(ISERROR(O77+P78),"—",O77+P78) -> 0 | Q77: =IF(ISERROR(P77+Q78),"—",P77+Q78) -> 0 | R77: =IF(ISERROR(Q77+R78),"—",Q77+R78) -> 0 | S77: =IF(ISERROR(R77+S78),"—",R77+S78) -> 0
A78: 本期增减 | D78: =D77-资产负债表!K21 -> 0 | E78: =E77-D77 -> 0 | F78: =F77-E77 -> 0 | G78: =IF(财务基础数据!$W$2=0,0,G77-F77) -> 0 | H78: =IF(财务基础数据!$W$2<=1,0,H77-G77) -> 0 | I78: =IF(财务基础数据!$W$2<=2,0,I77-H77) -> 0
A80: 资本性投资小计 | D80: =IF(ISERROR(D62+D67),"—",D62+D67) -> 0 | E80: =IF(ISERROR(E62+E67),"—",E62+E67) -> 0 | F80: =IF(ISERROR(F62+F67),"—",F62+F67) -> 0 | G80: =IF(ISERROR(G62+G67),"—",G62+G67) -> 0 | H80: =IF(ISERROR(H62+H67),"—",H62+H67) -> 0 | I80: =IF(ISERROR(I62+I67),"—",I62+I67) -> 0 | J80: =IF(ISERROR(J62+J67),"—",J62+J67) -> 0 | K80: =IF(ISERROR(K62+K67),"—",K62+K67) -> 0 | ... S80: =IF(ISERROR(S62+S67),"—",S62+S67) -> 0
A82: 融资预测
A83: =A3 -> 单位：港币(百万)
A84: 会计年度截止日：12/31 | D84: =D4 -> 2019 | E84: =E4 -> 2020 | F84: =F4 -> 2021 | G84: =G4 -> 1Q22 | H84: =H4 -> 1H22 | I84: =I4 -> 3Q22 | J84: =J4 -> 2022E | K84: =K4 -> 2023 | ... S84: =S4 -> 2031
A86: (一)股权融资(含增发、配股、回购等)
A87: 发行股数 | J87: 0 | K87: 0 | L87: 0 | M87: 0 | N87: 0 | O87: 0 | P87: 0 | Q87: 0 | R87: 0 | S87: 0
A88: 发行价格 | J88: 0 | K88: 0 | L88: 0 | M88: 0 | N88: 0 | O88: 0 | P88: 0 | Q88: 0 | R88: 0 | S88: 0
A89: 发行面值 | J89: 1 | K89: 1 | L89: 1 | M89: 1 | N89: 1 | O89: 1 | P89: 1 | Q89: 1 | R89: 1 | S89: 1
A90: 汇率(默认为1，如需换算可手动输入) | J90: 1 | K90: 1 | L90: 1 | M90: 1 | N90: 1 | O90: 1 | P90: 1 | Q90: 1 | R90: 1 | S90: 1
A91: 费用率 | B91: 0 | J91: =$B$91 -> 0 | K91: =$B$91 -> 0 | L91: =$B$91 -> 0 | M91: =$B$91 -> 0 | N91: =$B$91 -> 0 | O91: =$B$91 -> 0 | P91: =$B$91 -> 0 | Q91: =$B$91 -> 0 | ... S91: =$B$91 -> 0
A93: 当期股本增加 | J93: =J89*J87*J90 -> 0 | K93: =K89*K87*K90 -> 0 | L93: =L89*L87*L90 -> 0 | M93: =M89*M87*M90 -> 0 | N93: =N89*N87*N90 -> 0 | O93: =O89*O87*O90 -> 0 | P93: =P89*P87*P90 -> 0 | Q93: =Q89*Q87*Q90 -> 0 | ... S93: =S89*S87*S90 -> 0
A94: 当期储备增加 | J94: =J87*J88*J90*(1-J91)-J93 -> 0 | K94: =K87*K88*K90*(1-K91)-K93 -> 0 | L94: =L87*L88*L90*(1-L91)-L93 -> 0 | M94: =M87*M88*M90*(1-M91)-M93 -> 0 | N94: =N87*N88*N90*(1-N91)-N93 -> 0 | O94: =O87*O88*O90*(1-O91)-O93 -> 0 | P94: =P87*P88*P90*(1-P91)-P93 -> 0 | Q94: =Q87*Q88*Q90*(1-Q91)-Q93 -> 0 | ... S94: =S87*S88*S90*(1-S91)-S93 -> 0
A96: (二)权益分派（送股、转股、分红）
A97: 当期送股/转增股数 | J97: 0 | K97: 0 | L97: 0 | M97: 0 | N97: 0 | O97: 0 | P97: 0 | Q97: 0 | R97: 0 | S97: 0
A98: 当期现金分红总额 | D98: =SUM(财务基础数据!L131:'财务基础数据'!O131)*目录!$D$6 -> 0 | E98: =SUM(财务基础数据!P131:'财务基础数据'!S131)*目录!$D$6 -> 0 | F98: =SUM(财务基础数据!T131:'财务基础数据'!W131)*目录!$D$6 -> 0 | G98: =财务基础数据!X131*目录!$D$6 -> 0 | H98: =财务基础数据!Y131*目录!$D$6 -> 0 | I98: =财务基础数据!Z131*目录!$D$6 -> 0 | J98: =SUM(G98:I98)+财务基础数据!AA131*目录!$D$6 -> 0 | K98: =SUM(财务基础数据!AB131:AE131)*目录!$D$6 -> 0 | L98: =IF(ISERROR(L100*目录!$F$7/0.000001*目录!$D$6),0,L100*目录!$F$7/0.000001*目录!$D$6) -> 0 | M98: =IF(ISERROR(M100*目录!$F$7/0.000001*目录!$D$6),0,M100*目录!$F$7/0.000001*目录!$D$6) -> 0 | N98: =IF(ISERROR(N100*目录!$F$7/0.000001*目录!$D$6),0,N100*目录!$F$7/0.000001*目录!$D$6) -> 0 | O98: =IF(ISERROR(O100*目录!$F$7/0.000001*目录!$D$6),0,O100*目录!$F$7/0.000001*目录!$D$6) -> 0 | P98: =IF(ISERROR(P100*目录!$F$7/0.000001*目录!$D$6),0,P100*目录!$F$7/0.000001*目录!$D$6) -> 0 | Q98: =IF(ISERROR(Q100*目录!$F$7/0.000001*目录!$D$6),0,Q100*目录!$F$7/0.000001*目录!$D$6) -> 0 | R98: =IF(ISERROR(R100*目录!$F$7/0.000001*目录!$D$6),0,R100*目录!$F$7/0.000001*目录!$D$6) -> 0 | S98: =IF(ISERROR(S100*目录!$F$7/0.000001*目录!$D$6),0,S100*目录!$F$7/0.000001*目录!$D$6) -> 0
A99: 股利分配率 | D99: =IF(ISERROR(D98/利润表!O29),"—",D98/利润表!O29) -> — | E99: =IF(ISERROR(E98/利润表!S29),"—",E98/利润表!S29) -> — | F99: =IF(ISERROR(F98/利润表!W29),"—",F98/利润表!W29) -> — | J99: =IF(ISERROR(J98/利润表!AA29),0,J98/利润表!AA29) -> 0 | K99: =IF(ISERROR(K98/利润表!AB29),0,K98/利润表!AB29) -> 0 | L99: =IF(ISERROR(L98/利润表!AC29),0,L98/利润表!AC29) -> 0 | M99: =IF(ISERROR(M98/利润表!AD29),0,M98/利润表!AD29) -> 0 | N99: =IF(ISERROR(N98/利润表!AE29),0,N98/利润表!AE29) -> 0 | O99: =IF(ISERROR(O98/利润表!AF29),0,O98/利润表!AF29) -> 0 | P99: =IF(ISERROR(P98/利润表!AG29),0,P98/利润表!AG29) -> 0 | Q99: =IF(ISERROR(Q98/利润表!AH29),0,Q98/利润表!AH29) -> 0 | ... S99: =IF(ISERROR(S98/利润表!AJ29),0,S98/利润表!AJ29) -> 0
A100: 每股股利 | D100: =SUM(财务基础数据!L130:O130) -> 0 | E100: =SUM(财务基础数据!P130:S130) -> 0 | F100: =SUM(财务基础数据!T130:W130) -> 0 | G100: =财务基础数据!X130 -> 0 | H100: =财务基础数据!Y130 -> 0 | I100: =财务基础数据!Z130 -> 0 | J100: =SUM(G100:I100)+财务基础数据!AA130 -> 0 | K100: =SUM(财务基础数据!AB130:AE130) -> 0 | L100: 0 | M100: 0 | N100: 0 | O100: 0 | P100: 0 | Q100: 0 | R100: 0 | S100: 0
A102: 当期股本增加 | J102: =J97*J89*J90 -> 0 | K102: =K97*K89*K90 -> 0 | L102: =L97*L89*L90 -> 0 | M102: =M97*M89*M90 -> 0 | N102: =N97*N89*N90 -> 0 | O102: =O97*O89*O90 -> 0 | P102: =P97*P89*P90 -> 0 | Q102: =Q97*Q89*Q90 -> 0 | ... S102: =S97*S89*S90 -> 0
A103: 当期储备增加 | J103: =-J98-J102 -> 0 | K103: =-K98-K102 -> 0 | L103: =-L98-L102 -> 0 | M103: =-M98-M102 -> 0 | N103: =-N98-N102 -> 0 | O103: =-O98-O102 -> 0 | P103: =-P98-P102 -> 0 | Q103: =-Q98-Q102 -> 0 | ... S103: =-S98-S102 -> 0
A105: (三)其他变动
A106: 股本增加：
A107: 普通股股本 | J107: 0 | K107: 0 | L107: 0
A108: 优先股 | J108: 0 | K108: 0 | L108: 0
A109: 库存股 | J109: 0 | K109: 0 | L109: 0
A110: 储备增加 | J110: 0 | K110: 0 | L110: 0
A111: 其他变动 | J111: 0 | K111: 0 | L111: 0 | M111: 0 | N111: 0 | O111: 0 | P111: 0 | Q111: 0 | R111: 0 | S111: 0
A113: (四)长期债务
A114: 期初余额 | D114: =资产负债表!K35 -> 0 | E114: =D117 -> 0 | F114: =E117 -> 0 | G114: =F117 -> 0 | H114: =G117 -> 0 | I114: =H117 -> 0 | J114: =F117 -> 0 | K114: =J117 -> 0 | L114: =K117 -> 0 | M114: =L117 -> 0 | N114: =M117 -> 0 | O114: =N117 -> 0 | P114: =O117 -> 0 | Q114: =P117 -> 0 | R114: =Q117 -> 0 | S114: =R117 -> 0
A115: 长期借款当期变动 | D115: =D117-D114 -> 0 | E115: =E117-E114 -> 0 | F115: =F117-F114 -> 0 | G115: =IF(财务基础数据!$W$2=0,0,G117-F117) -> 0 | H115: =IF(财务基础数据!$W$2<=1,0,H117-G117) -> 0 | I115: =IF(财务基础数据!$W$2<=2,0,I117-H117) -> 0 | J115: 0 | K115: 0 | L115: 0 | M115: 0 | N115: 0 | O115: 0 | P115: 0 | Q115: 0 | R115: 0 | S115: 0
A116: 应付债券当期变动 | J116: 0 | K116: 0 | L116: 0 | M116: 0 | N116: 0 | O116: 0 | P116: 0 | Q116: 0 | R116: 0 | S116: 0
A117: 期末余额 | D117: =资产负债表!O35 -> 0 | E117: =资产负债表!S35 -> 0 | F117: =资产负债表!W35 -> 0 | G117: =资产负债表!X35 -> 0 | H117: =资产负债表!Y35 -> 0 | I117: =资产负债表!Z35 -> 0 | J117: =J114+J115+J116 -> 0 | K117: =K114+K115+K116 -> 0 | L117: =L114+L115+L116 -> 0 | M117: =M114+M115+M116 -> 0 | N117: =N114+N115+N116 -> 0 | O117: =O114+O115+O116 -> 0 | P117: =P114+P115+P116 -> 0 | Q117: =Q114+Q115+Q116 -> 0 | ... S117: =S114+S115+S116 -> 0
A118: 长期借款利率 | B118: 0 | J118: =$B$118 -> 0 | K118: =$B$118 -> 0 | L118: =$B$118 -> 0 | M118: =$B$118 -> 0 | N118: =$B$118 -> 0 | O118: =$B$118 -> 0 | P118: =$B$118 -> 0 | Q118: =$B$118 -> 0 | ... S118: =$B$118 -> 0
A119: 利息费用 | J119: =IF(ISERROR(J114*J118+(J115+J116)*J118*0.5),"—",J114*J118+(J115+J116)*J118*0.5) -> 0 | K119: =IF(ISERROR(K114*K118+(K115+K116)*K118*0.5),"—",K114*K118+(K115+K116)*K118*0.5) -> 0 | L119: =IF(ISERROR(L114*L118+(L115+L116)*L118*0.5),"—",L114*L118+(L115+L116)*L118*0.5) -> 0 | M119: =IF(ISERROR(M114*M118+(M115+M116)*M118*0.5),"—",M114*M118+(M115+M116)*M118*0.5) -> 0 | N119: =IF(ISERROR(N114*N118+(N115+N116)*N118*0.5),"—",N114*N118+(N115+N116)*N118*0.5) -> 0 | O119: =IF(ISERROR(O114*O118+(O115+O116)*O118*0.5),"—",O114*O118+(O115+O116)*O118*0.5) -> 0 | P119: =IF(ISERROR(P114*P118+(P115+P116)*P118*0.5),"—",P114*P118+(P115+P116)*P118*0.5) -> 0 | Q119: =IF(ISERROR(Q114*Q118+(Q115+Q116)*Q118*0.5),"—",Q114*Q118+(Q115+Q116)*Q118*0.5) -> 0 | ... S119: =IF(ISERROR(S114*S118+(S115+S116)*S118*0.5),"—",S114*S118+(S115+S116)*S118*0.5) -> 0
A121: (五）短期借款
A122: 期初余额 | D122: =资产负债表!K31 -> 0 | E122: =D124 -> 0 | F122: =E124 -> 0 | G122: =F124 -> 0 | H122: =G124 -> 0 | I122: =H124 -> 0 | J122: =F124 -> 0 | K122: =J124 -> 0 | L122: =K124 -> 0 | M122: =L124 -> 0 | N122: =M124 -> 0 | O122: =N124 -> 0 | P122: =O124 -> 0 | Q122: =P124 -> 0 | R122: =Q124 -> 0 | S122: =R124 -> 0
A123: 当期变动 | D123: =D124-D122 -> 0 | E123: =E124-E122 -> 0 | F123: =F124-F122 -> 0 | G123: =IF(财务基础数据!$W$2=0,0,G124-F124) -> 0 | H123: =IF(财务基础数据!$W$2<=1,0,H124-G124) -> 0 | I123: =IF(财务基础数据!$W$2<=2,0,I124-H124) -> 0
A124: 期末余额 | D124: =资产负债表!O31 -> 0 | E124: =资产负债表!S31 -> 0 | F124: =资产负债表!W31 -> 0 | G124: =资产负债表!X31 -> 0 | H124: =资产负债表!Y31 -> 0 | I124: =资产负债表!Z31 -> 0 | J124: =F124+J123 -> 0 | K124: =J124+K123 -> 0 | L124: =K124+L123 -> 0 | M124: =L124+M123 -> 0 | N124: =M124+N123 -> 0 | O124: =N124+O123 -> 0 | P124: =O124+P123 -> 0 | Q124: =P124+Q123 -> 0 | R124: =Q124+R123 -> 0 | S124: =R124+S123 -> 0
A125: 短期借款利率 | J125: =$B$125 -> 0 | K125: =$B$125 -> 0 | L125: =$B$125 -> 0 | M125: =$B$125 -> 0 | N125: =$B$125 -> 0 | O125: =$B$125 -> 0 | P125: =$B$125 -> 0 | Q125: =$B$125 -> 0 | ... S125: =$B$125 -> 0
A126: 利息费用 | J126: =IF(ISERROR(J122*J125+J123*J125*0.5),0,J122*J125+J123*J125*0.5) -> 0 | K126: =IF(ISERROR(K122*K125+K123*K125*0.5),0,K122*K125+K123*K125*0.5) -> 0 | L126: =IF(ISERROR(L122*L125+L123*L125*0.5),0,L122*L125+L123*L125*0.5) -> 0 | M126: =IF(ISERROR(M122*M125+M123*M125*0.5),0,M122*M125+M123*M125*0.5) -> 0 | N126: =IF(ISERROR(N122*N125+N123*N125*0.5),0,N122*N125+N123*N125*0.5) -> 0 | O126: =IF(ISERROR(O122*O125+O123*O125*0.5),0,O122*O125+O123*O125*0.5) -> 0 | P126: =IF(ISERROR(P122*P125+P123*P125*0.5),0,P122*P125+P123*P125*0.5) -> 0 | Q126: =IF(ISERROR(Q122*Q125+Q123*Q125*0.5),0,Q122*Q125+Q123*Q125*0.5) -> 0 | ... S126: =IF(ISERROR(S122*S125+S123*S125*0.5),0,S122*S125+S123*S125*0.5) -> 0
A128: 利息费用合计 | D128: =利润表!O19 -> 0 | E128: =利润表!S19 -> 0 | F128: =利润表!W19 -> 0 | G128: =利润表!X19 -> 0 | H128: =利润表!Y19 -> 0 | I128: =利润表!Z19 -> 0 | J128: =IF(ISERROR(J119+J126+J129),"0",J119+J126+J129) -> 0 | K128: =IF(ISERROR(K119+K126+K129),"0",K119+K126+K129) -> 0 | L128: =IF(ISERROR(L119+L126+L129),"0",L119+L126+L129) -> 0 | M128: =IF(ISERROR(M119+M126+M129),"0",M119+M126+M129) -> 0 | N128: =IF(ISERROR(N119+N126+N129),"0",N119+N126+N129) -> 0 | O128: =IF(ISERROR(O119+O126+O129),"0",O119+O126+O129) -> 0 | P128: =IF(ISERROR(P119+P126+P129),"0",P119+P126+P129) -> 0 | Q128: =IF(ISERROR(Q119+Q126+Q129),"0",Q119+Q126+Q129) -> 0 | ... S128: =IF(ISERROR(S119+S126+S129),"0",S119+S126+S129) -> 0
A129: 其他调整（如租赁负债利息、汇兑损益等） | J129: 0 | K129: 0 | L129: 0 | M129: 0 | N129: 0 | O129: 0 | P129: 0 | Q129: 0 | R129: 0 | S129: 0
A131: 存款利率 | J131: =$B$131 -> 0 | K131: =$B$131 -> 0 | L131: =$B$131 -> 0 | M131: =$B$131 -> 0 | N131: =$B$131 -> 0 | O131: =$B$131 -> 0 | P131: =$B$131 -> 0 | Q131: =$B$131 -> 0 | ... S131: =$B$131 -> 0
A132: 利息收入 | D132: =利润表!O18 -> 0 | E132: =利润表!S18 -> 0 | F132: =利润表!W18 -> 0 | G132: =利润表!X18 -> 0 | H132: =利润表!Y18 -> 0 | I132: =利润表!Z18 -> 0 | J132: =IF(ISERROR(J135*J131+J133),0,(J135*J131+J133)) -> 0 | K132: =IF(ISERROR(K135*K131+K133),0,(K135*K131+K133)) -> 0 | L132: =IF(ISERROR(L135*L131+L133),0,(L135*L131+L133)) -> 0 | M132: =IF(ISERROR(M135*M131+M133),0,(M135*M131+M133)) -> 0 | N132: =IF(ISERROR(N135*N131+N133),0,(N135*N131+N133)) -> 0 | O132: =IF(ISERROR(O135*O131+O133),0,(O135*O131+O133)) -> 0 | P132: =IF(ISERROR(P135*P131+P133),0,(P135*P131+P133)) -> 0 | Q132: =IF(ISERROR(Q135*Q131+Q133),0,(Q135*Q131+Q133)) -> 0 | ... S132: =IF(ISERROR(S135*S131+S133),0,(S135*S131+S133)) -> 0
A133: 其他调整（如理财收益等） | J133: 0 | K133: 0 | L133: 0 | M133: 0 | N133: 0 | O133: 0 | P133: 0 | Q133: 0 | R133: 0 | S133: 0
...

Sheet 主要财务摘要
B1: 说明：历史年份的收盘价默认为当年最后一个交易日的价格，如需按照最新股价计算历史的每股指标，可在蓝色单元格内手工输入。
H2: =IF(目录!F8="CNY","单位：人民币",IF(目录!F8="USD","单位：美元","单位：港币"))&"("&IF(目录!D7="","元",目录!D7)&")" -> 单位：港币(百万)
B3: 项目\年度 | C3: =利润表!O4 -> 2019 | D3: =利润表!S4 -> 2020 | E3: =利润表!W4 -> 2021 | F3: =利润表!AA4 -> 2022E | G3: =利润表!AB4 -> 2023 | H3: =利润表!AC4 -> 2024
B4: ="总股本("&目录!D7&")" -> 总股本(百万) | C4: =IF(财务基础数据!O128="",目录!F7*1000000*目录!D6,财务基础数据!O128*目录!D6) -> #VALUE! | D4: =IF(财务基础数据!S128="",目录!F7*1000000*目录!D6,财务基础数据!S128*目录!D6) -> #VALUE! | E4: =IF(财务基础数据!W128="",目录!F7*1000000*目录!D6,财务基础数据!W128*目录!D6) -> #VALUE! | F4: =IF(ISERROR(目录!F7*1000000*目录!D6),"—",目录!F7*1000000*目录!D6) -> — | G4: =F4 -> — | H4: =G4 -> —
B5: 收盘价（港币） | C5: =财务基础数据!$O$129 -> 0 | D5: =财务基础数据!$S$129 -> 0 | E5: =财务基础数据!$W$129 -> 0 | F5: =目录!$F$6 -> XXXX | G5: =目录!$F$6 -> XXXX | H5: =目录!$F$6 -> XXXX
B6: 收盘价（汇率换算后） | C6: =IF(目录!$F$10=0,C5,C5*目录!$F$10) -> 0 | D6: =IF(目录!$F$10=0,D5,D5*目录!$F$10) -> 0 | E6: =IF(目录!$F$10=0,E5,E5*目录!$F$10) -> 0 | F6: =IF(目录!$F$10=0,F5,F5*目录!$F$10) -> XXXX | G6: =F6 -> XXXX | H6: =G6 -> XXXX
B7: EV/EBITDA | C7: =IF(ISERROR(((C4*C6)+资产负债表!O55-资产负债表!O6)/利润表!O34),"—",((C4*C6)+资产负债表!O55-资产负债表!O6)/利润表!O34) -> — | D7: =IF(ISERROR(((D4*D6)+资产负债表!S55-资产负债表!S6)/利润表!S34),"—",((D4*D6)+资产负债表!S55-资产负债表!S6)/利润表!S34) -> — | E7: =IF(ISERROR(((E4*E6)+资产负债表!W55-资产负债表!W6)/利润表!W34),"—",((E4*E6)+资产负债表!W55-资产负债表!W6)/利润表!W34) -> — | F7: =IF(ISERROR(((F4*F6)+资产负债表!AA55-资产负债表!AA6)/利润表!AA34),"—",((F4*F6)+资产负债表!AA55-资产负债表!AA6)/利润表!AA34) -> — | G7: =IF(ISERROR(((G4*G6)+资产负债表!AB55-资产负债表!AB6)/利润表!AB34),"—",((G4*G6)+资产负债表!AB55-资产负债表!AB6)/利润表!AB34) -> — | H7: =IF(ISERROR(((H4*H6)+资产负债表!AC55-资产负债表!AC6)/利润表!AC34),"—",((H4*H6)+资产负债表!AC55-资产负债表!AC6)/利润表!AC34) -> —
B8: EV/销售收入 | C8: =IF(ISERROR(((C4*C6)+资产负债表!O55-资产负债表!O6)/利润表!O6),"—",((C4*C6)+资产负债表!O55-资产负债表!O6)/利润表!O6) -> — | D8: =IF(ISERROR(((D4*D6)+资产负债表!S55-资产负债表!S6)/利润表!S6),"—",((D4*D6)+资产负债表!S55-资产负债表!S6)/利润表!S6) -> — | E8: =IF(ISERROR(((E4*E6)+资产负债表!W55-资产负债表!W6)/利润表!W6),"—",((E4*E6)+资产负债表!W55-资产负债表!W6)/利润表!W6) -> — | F8: =IF(ISERROR(((F4*F6)+资产负债表!AA55-资产负债表!AA6)/利润表!AA6),"—",((F4*F6)+资产负债表!AA55-资产负债表!AA6)/利润表!AA6) -> — | G8: =IF(ISERROR(((G4*G6)+资产负债表!AB55-资产负债表!AB6)/利润表!AB6),"—",((G4*G6)+资产负债表!AB55-资产负债表!AB6)/利润表!AB6) -> — | H8: =IF(ISERROR(((H4*H6)+资产负债表!AC55-资产负债表!AC6)/利润表!AC6),"—",((H4*H6)+资产负债表!AC55-资产负债表!AC6)/利润表!AC6) -> —
B9: 营业收入增长率 | C9: =C16 -> — | D9: =D16 -> — | E9: =E16 -> — | F9: =F16 -> — | G9: =G16 -> — | H9: =H16 -> —
B10: 归母净利润增长率 | C10: =C19 -> — | D10: =D19 -> — | E10: =E19 -> — | F10: =F19 -> — | G10: =G19 -> — | H10: =H19 -> —
B11: 净资产收益率ROE | C11: =报表摘要!K35 -> — | D11: =报表摘要!L35 -> — | E11: =报表摘要!M35 -> — | F11: =报表摘要!N35 -> — | G11: =报表摘要!O35 -> — | H11: =报表摘要!P35 -> —
B12: 总资产收益率ROA | C12: =报表摘要!K36 -> — | D12: =报表摘要!L36 -> — | E12: =报表摘要!M36 -> — | F12: =报表摘要!N36 -> — | G12: =报表摘要!O36 -> — | H12: =报表摘要!P36 -> —
B14: 盈利预测 | C14: =C3 -> 2019 | D14: =D3 -> 2020 | E14: =E3 -> 2021 | F14: =F3 -> 2022E | G14: =G3 -> 2023 | H14: =H3 -> 2024
B15: 营业总收入 | C15: =利润表!O6+利润表!O7 -> 0 | D15: =利润表!S6+利润表!S7 -> 0 | E15: =利润表!W6+利润表!W7 -> 0 | F15: =利润表!AA6+利润表!AA7 -> 0 | G15: =利润表!AB6+利润表!AB7 -> 0 | H15: =利润表!AC6+利润表!AC7 -> 0
B16: 增长率（%） | C16: =IF(ISERROR((利润表!O6+利润表!O7-利润表!K6-利润表!K7)/ABS(利润表!K6+利润表!K7)),"—",(利润表!O6+利润表!O7-利润表!K6-利润表!K7)/ABS(利润表!K6+利润表!K7)) -> — | D16: =IF(ISERROR((D15-C15)/ABS(C15)),"—",(D15-C15)/ABS(C15)) -> — | E16: =IF(ISERROR((E15-D15)/ABS(D15)),"—",(E15-D15)/ABS(D15)) -> — | F16: =IF(ISERROR((F15-E15)/ABS(E15)),"—",(F15-E15)/ABS(E15)) -> — | G16: =IF(ISERROR((G15-F15)/ABS(F15)),"—",(G15-F15)/ABS(F15)) -> — | H16: =IF(ISERROR((H15-G15)/ABS(G15)),"—",(H15-G15)/ABS(G15)) -> —
B17: EBITDA | C17: =利润表!O34 -> 0 | D17: =利润表!S34 -> 0 | E17: =利润表!W34 -> 0 | F17: =利润表!AA34 -> 0 | G17: =利润表!AB34 -> 0 | H17: =利润表!AC34 -> 0
B18: 归母净利润 | C18: =利润表!O29 -> 0 | D18: =利润表!S29 -> 0 | E18: =利润表!W29 -> 0 | F18: =利润表!AA29 -> 0 | G18: =利润表!AB29 -> 0 | H18: =利润表!AC29 -> 0
B19: 增长率（%） | C19: =报表摘要!K41 -> — | D19: =报表摘要!L41 -> — | E19: =报表摘要!M41 -> — | F19: =报表摘要!N41 -> — | G19: =报表摘要!O41 -> — | H19: =报表摘要!P41 -> —
B20: 每股收益EPS | C20: =IF(ISERROR(财务基础数据!$O$32),"—",财务基础数据!$O$32) -> 0 | D20: =IF(ISERROR(财务基础数据!$S$32),"—",财务基础数据!$S$32) -> 0 | E20: =IF(ISERROR(财务基础数据!$W$32),"—",财务基础数据!$W$32) -> 0 | F20: =IF(ISERROR(F18/F4),"—",F18/F4) -> — | G20: =IF(ISERROR(G18/G4),"—",G18/G4) -> — | H20: =IF(ISERROR(H18/H4),"—",H18/H4) -> —
B21: 每股净资产 | C21: =IF(ISERROR((资产负债表!O45)/C4),"—",(资产负债表!O45)/C4) -> — | D21: =IF(ISERROR((资产负债表!S45)/D4),"—",(资产负债表!S45)/D4) -> — | E21: =IF(ISERROR((资产负债表!W45)/E4),"—",(资产负债表!W45)/E4) -> — | F21: =IF(ISERROR((资产负债表!AA45)/F4),"—",(资产负债表!AA45)/F4) -> — | G21: =IF(ISERROR((资产负债表!AB45)/G4),"—",(资产负债表!AB45)/G4) -> — | H21: =IF(ISERROR((资产负债表!AC45)/H4),"—",(资产负债表!AC45)/H4) -> —
B22: 市盈率（P/E） | C22: =IF(ISERROR(C6/C20),"—",C6/C20) -> — | D22: =IF(ISERROR(D6/D20),"—",D6/D20) -> — | E22: =IF(ISERROR(E6/E20),"—",E6/E20) -> — | F22: =IF(ISERROR(F6/F20),"—",F6/F20) -> — | G22: =IF(ISERROR(G6/G20),"—",G6/G20) -> — | H22: =IF(ISERROR(H6/H20),"—",H6/H20) -> —
B23: 市净率（P/B） | C23: =IF(ISERROR(C6/C21),"—",C6/C21) -> — | D23: =IF(ISERROR(D6/D21),"—",D6/D21) -> — | E23: =IF(ISERROR(E6/E21),"—",E6/E21) -> — | F23: =IF(ISERROR(F6/F21),"—",F6/F21) -> — | G23: =IF(ISERROR(G6/G21),"—",G6/G21) -> — | H23: =IF(ISERROR(H6/H21),"—",H6/H21) -> —
B24: PE/G | C24: =IF(OR(ISERROR(C22/(C19*100)),C10<0),"—",C22/(C19*100)) -> — | D24: =IF(OR(ISERROR(D22/(D19*100)),D10<0),"—",D22/(D19*100)) -> — | E24: =IF(OR(ISERROR(E22/(E19*100)),E10<0),"—",E22/(E19*100)) -> — | F24: =IF(OR(ISERROR(F22/(F19*100)),F10<0),"—",F22/(F19*100)) -> — | G24: =IF(OR(ISERROR(G22/(G19*100)),G10<0),"—",G22/(G19*100)) -> — | H24: =IF(OR(ISERROR(H22/(H19*100)),H10<0),"—",H22/(H19*100)) -> —
B25: 每股经营性现金流 | C25: =IF(ISERROR(现金流量表!O16/C4),"—",现金流量表!O16/C4) -> — | D25: =IF(ISERROR(现金流量表!S16/D4),"—",现金流量表!S16/D4) -> — | E25: =IF(ISERROR(现金流量表!W16/E4),"—",现金流量表!W16/E4) -> — | F25: =IF(ISERROR(现金流量表!AA16/F4),"—",现金流量表!AA16/F4) -> — | G25: =IF(ISERROR(现金流量表!AB16/G4),"—",现金流量表!AB16/G4) -> — | H25: =IF(ISERROR(现金流量表!AC16/H4),"—",现金流量表!AC16/H4) -> —
E129: =财务基础数据!$S$128 -> 0

Sheet 报表摘要
B3: 损益表 | H3: =主要财务摘要!$H$2 -> 单位：港币(百万) | J3: 资产负债表 | P3: =主要财务摘要!$H$2 -> 单位：港币(百万)
C4: =利润表!O4 -> 2019 | D4: =利润表!S4 -> 2020 | E4: =利润表!W4 -> 2021 | F4: =利润表!AA4 -> 2022E | G4: =利润表!AB4 -> 2023 | H4: =利润表!AC4 -> 2024 | K4: =C4 -> 2019 | L4: =D4 -> 2020 | M4: =E4 -> 2021 | N4: =F4 -> 2022E | O4: =G4 -> 2023 | P4: =H4 -> 2024
B5: 营业收入 | C5: =利润表!O6 -> 0 | D5: =利润表!S6 -> 0 | E5: =利润表!W6 -> 0 | F5: =利润表!AA6 -> 0 | G5: =利润表!AB6 -> 0 | H5: =利润表!AC6 -> 0 | J5: 货币资金 | K5: =资产负债表!O6 -> 0 | L5: =资产负债表!S6 -> 0 | M5: =资产负债表!W6 -> 0 | N5: =资产负债表!AA6 -> 0 | O5: =资产负债表!AB6 -> 0 | P5: =资产负债表!AC6 -> 0
B6: 增长率 | C6: =IF(ISERROR((利润表!O6-利润表!K6)/ABS(利润表!K6)),"—",(利润表!O6-利润表!K6)/ABS(利润表!K6)) -> — | D6: =IF(ISERROR((D5-C5)/ABS(C5)),"—",(D5-C5)/ABS(C5)) -> — | E6: =IF(ISERROR((E5-D5)/ABS(D5)),"—",(E5-D5)/ABS(D5)) -> — | F6: =IF(ISERROR((F5-E5)/ABS(E5)),"—",(F5-E5)/ABS(E5)) -> — | G6: =IF(ISERROR((G5-F5)/ABS(F5)),"—",(G5-F5)/ABS(F5)) -> — | H6: =IF(ISERROR((H5-G5)/ABS(G5)),"—",(H5-G5)/ABS(G5)) -> — | J6: 应收款项 | K6: =资产负债表!O9+资产负债表!O10 -> 0 | L6: =资产负债表!S9+资产负债表!S10 -> 0 | M6: =资产负债表!W9+资产负债表!W10 -> 0 | N6: =资产负债表!AA9+资产负债表!AA10 -> 0 | O6: =资产负债表!AB9+资产负债表!AB10 -> 0 | P6: =资产负债表!AC9+资产负债表!AC10 -> 0
B7: 营业成本 | C7: =利润表!O9 -> 0 | D7: =利润表!S9 -> 0 | E7: =利润表!W9 -> 0 | F7: =利润表!AA9 -> 0 | G7: =利润表!AB9 -> 0 | H7: =利润表!AC9 -> 0 | J7: 存货 | K7: =资产负债表!O11 -> 0 | L7: =资产负债表!S11 -> 0 | M7: =资产负债表!W11 -> 0 | N7: =资产负债表!AA11 -> 0 | O7: =资产负债表!AB11 -> 0 | P7: =资产负债表!AC11 -> 0
B8: %销售收入 | C8: =IF(ISERROR(C7/C5),"—",C7/C5) -> — | D8: =IF(ISERROR(D7/D5),"—",D7/D5) -> — | E8: =IF(ISERROR(E7/E5),"—",E7/E5) -> — | F8: =IF(ISERROR(F7/F5),"—",F7/F5) -> — | G8: =IF(ISERROR(G7/G5),"—",G7/G5) -> — | H8: =IF(ISERROR(H7/H5),"—",H7/H5) -> — | J8: 其他流动资产 | K8: =K9-K5-K6-K7 -> 0 | L8: =L9-L5-L6-L7 -> 0 | M8: =M9-M5-M6-M7 -> 0 | N8: =N9-N5-N6-N7 -> 0 | O8: =O9-O5-O6-O7 -> 0 | P8: =P9-P5-P6-P7 -> 0
B9: 毛利 | C9: =利润表!O16 -> 0 | D9: =利润表!S16 -> 0 | E9: =利润表!W16 -> 0 | F9: =利润表!AA16 -> 0 | G9: =利润表!AB16 -> 0 | H9: =利润表!AC16 -> 0 | J9: 流动资产 | K9: =资产负债表!O13 -> 0 | L9: =资产负债表!S13 -> 0 | M9: =资产负债表!W13 -> 0 | N9: =资产负债表!AA13 -> 0 | O9: =资产负债表!AB13 -> 0 | P9: =资产负债表!AC13 -> 0
B10: %销售收入 | C10: =IF(ISERROR(C9/C5),"—",C9/C5) -> — | D10: =IF(ISERROR(D9/D5),"—",D9/D5) -> — | E10: =IF(ISERROR(E9/E5),"—",E9/E5) -> — | F10: =IF(ISERROR(F9/F5),"—",F9/F5) -> — | G10: =IF(ISERROR(G9/G5),"—",G9/G5) -> — | H10: =IF(ISERROR(H9/H5),"—",H9/H5) -> — | J10: 权益性投资 | K10: =资产负债表!O16 -> 0 | L10: =资产负债表!S16 -> 0 | M10: =资产负债表!W16 -> 0 | N10: =资产负债表!AA16 -> 0 | O10: =资产负债表!AB16 -> 0 | P10: =资产负债表!AC16 -> 0
B11: 其他收入 | C11: =利润表!O7 -> 0 | D11: =利润表!S7 -> 0 | E11: =利润表!W7 -> 0 | F11: =利润表!AA7 -> 0 | G11: =利润表!AB7 -> 0 | H11: =利润表!AC7 -> 0 | J11: 固定资产 | K11: =资产负债表!O15 -> 0 | L11: =资产负债表!S15 -> 0 | M11: =资产负债表!W15 -> 0 | N11: =资产负债表!AA15 -> 0 | O11: =资产负债表!AB15 -> 0 | P11: =资产负债表!AC15 -> 0
B12: %销售收入 | C12: =IF(ISERROR(C11/C5),"—",C11/C5) -> — | D12: =IF(ISERROR(D11/D5),"—",D11/D5) -> — | E12: =IF(ISERROR(E11/E5),"—",E11/E5) -> — | F12: =IF(ISERROR(F11/F5),"—",F11/F5) -> — | G12: =IF(ISERROR(G11/G5),"—",G11/G5) -> — | H12: =IF(ISERROR(H11/H5),"—",H11/H5) -> — | J12: 无形资产 | K12: =资产负债表!O20 -> 0 | L12: =资产负债表!S20 -> 0 | M12: =资产负债表!W20 -> 0 | N12: =资产负债表!AA20 -> 0 | O12: =资产负债表!AB20 -> 0 | P12: =资产负债表!AC20 -> 0
B13: 销售费用 | C13: =利润表!O12 -> 0 | D13: =利润表!S12 -> 0 | E13: =利润表!W12 -> 0 | F13: =利润表!AA12 -> 0 | G13: =利润表!AB12 -> 0 | H13: =利润表!AC12 -> 0 | J13: 非流动资产 | K13: =资产负债表!O23 -> 0 | L13: =资产负债表!S23 -> 0 | M13: =资产负债表!W23 -> 0 | N13: =资产负债表!AA23 -> 0 | O13: =资产负债表!AB23 -> 0 | P13: =资产负债表!AC23 -> 0
B14: %销售收入 | C14: =IF(ISERROR(C13/C5),"—",C13/C5) -> — | D14: =IF(ISERROR(D13/D5),"—",D13/D5) -> — | E14: =IF(ISERROR(E13/E5),"—",E13/E5) -> — | F14: =IF(ISERROR(F13/F5),"—",F13/F5) -> — | G14: =IF(ISERROR(G13/G5),"—",G13/G5) -> — | H14: =IF(ISERROR(H13/H5),"—",H13/H5) -> — | J14: 资产总计 | K14: =资产负债表!O24 -> 0 | L14: =资产负债表!S24 -> 0 | M14: =资产负债表!W24 -> 0 | N14: =资产负债表!AA24 -> 0 | O14: =资产负债表!AB24 -> 0 | P14: =资产负债表!AC24 -> 0
B15: 管理费用 | C15: =利润表!O13 -> 0 | D15: =利润表!S13 -> 0 | E15: =利润表!W13 -> 0 | F15: =利润表!AA13 -> 0 | G15: =利润表!AB13 -> 0 | H15: =利润表!AC13 -> 0 | J15: 应付款项 | K15: =资产负债表!O28 -> 0 | L15: =资产负债表!S28 -> 0 | M15: =资产负债表!W28 -> 0 | N15: =资产负债表!AA28 -> 0 | O15: =资产负债表!AB28 -> 0 | P15: =资产负债表!AC28 -> 0
B16: %销售收入 | C16: =IF(ISERROR(C15/C5),"—",C15/C5) -> — | D16: =IF(ISERROR(D15/D5),"—",D15/D5) -> — | E16: =IF(ISERROR(E15/E5),"—",E15/E5) -> — | F16: =IF(ISERROR(F15/F5),"—",F15/F5) -> — | G16: =IF(ISERROR(G15/G5),"—",G15/G5) -> — | H16: =IF(ISERROR(H15/H5),"—",H15/H5) -> — | J16: 短期借款 | K16: =资产负债表!O31 -> 0 | L16: =资产负债表!S31 -> 0 | M16: =资产负债表!W31 -> 0 | N16: =资产负债表!AA31 -> 0 | O16: =资产负债表!AB31 -> 0 | P16: =资产负债表!AC31 -> 0
B17: 研发费用 | C17: =利润表!O14 -> 0 | D17: =利润表!S14 -> 0 | E17: =利润表!W14 -> 0 | F17: =利润表!AA14 -> 0 | G17: =利润表!AB14 -> 0 | H17: =利润表!AC14 -> 0 | J17: 其他流动负债 | K17: =K18-K15-K16 -> 0 | L17: =L18-L15-L16 -> 0 | M17: =M18-M15-M16 -> 0 | N17: =N18-N15-N16 -> 0 | O17: =O18-O15-O16 -> 0 | P17: =P18-P15-P16 -> 0
B18: %销售收入 | C18: =IF(ISERROR(C17/C5),"—",C17/C5) -> — | D18: =IF(ISERROR(D17/D5),"—",D17/D5) -> — | E18: =IF(ISERROR(E17/E5),"—",E17/E5) -> — | F18: =IF(ISERROR(F17/F5),"—",F17/F5) -> — | G18: =IF(ISERROR(G17/G5),"—",G17/G5) -> — | H18: =IF(ISERROR(H17/H5),"—",H17/H5) -> — | J18: 流动负债 | K18: =资产负债表!O33 -> 0 | L18: =资产负债表!S33 -> 0 | M18: =资产负债表!W33 -> 0 | N18: =资产负债表!AA33 -> 0 | O18: =资产负债表!AB33 -> 0 | P18: =资产负债表!AC33 -> 0
B19: 财务费用 | C19: =利润表!O19-利润表!O18 -> 0 | D19: =利润表!S19-利润表!S18 -> 0 | E19: =利润表!W19-利润表!W18 -> 0 | F19: =利润表!AA19-利润表!AA18 -> 0 | G19: =利润表!AB19-利润表!AB18 -> 0 | H19: =利润表!AC19-利润表!AC18 -> 0 | J19: 长期债务 | K19: =资产负债表!O35 -> 0 | L19: =资产负债表!S35 -> 0 | M19: =资产负债表!W35 -> 0 | N19: =资产负债表!AA35 -> 0 | O19: =资产负债表!AB35 -> 0 | P19: =资产负债表!AC35 -> 0
B20: %销售收入 | C20: =IF(ISERROR(C19/C5),"—",C19/C5) -> — | D20: =IF(ISERROR(D19/D5),"—",D19/D5) -> — | E20: =IF(ISERROR(E19/E5),"—",E19/E5) -> — | F20: =IF(ISERROR(F19/F5),"—",F19/F5) -> — | G20: =IF(ISERROR(G19/G5),"—",G19/G5) -> — | H20: =IF(ISERROR(H19/H5),"—",H19/H5) -> — | J20: 其他长期负债 | K20: =K21-K19 -> 0 | L20: =L21-L19 -> 0 | M20: =M21-M19 -> 0 | N20: =N21-N19 -> 0 | O20: =O21-O19 -> 0 | P20: =P21-P19 -> 0
B21: 息税前利润（EBIT） | C21: =利润表!O35 -> 0 | D21: =利润表!S35 -> 0 | E21: =利润表!W35 -> 0 | F21: =利润表!AA35 -> 0 | G21: =利润表!AB35 -> 0 | H21: =利润表!AC35 -> 0 | J21: 非流动负债 | K21: =资产负债表!O37 -> 0 | L21: =资产负债表!S37 -> 0 | M21: =资产负债表!W37 -> 0 | N21: =资产负债表!AA37 -> 0 | O21: =资产负债表!AB37 -> 0 | P21: =资产负债表!AC37 -> 0
B22: %销售收入 | C22: =IF(ISERROR(C21/C5),"—",C21/C5) -> — | D22: =IF(ISERROR(D21/D5),"—",D21/D5) -> — | E22: =IF(ISERROR(E21/E5),"—",E21/E5) -> — | F22: =IF(ISERROR(F21/F5),"—",F21/F5) -> — | G22: =IF(ISERROR(G21/G5),"—",G21/G5) -> — | H22: =IF(ISERROR(H21/H5),"—",H21/H5) -> — | J22: 负债总计 | K22: =资产负债表!O38 -> 0 | L22: =资产负债表!S38 -> 0 | M22: =资产负债表!W38 -> 0 | N22: =资产负债表!AA38 -> 0 | O22: =资产负债表!AB38 -> 0 | P22: =资产负债表!AC38 -> 0
B23: 投资收益 | C23: =利润表!O20 -> 0 | D23: =利润表!S20 -> 0 | E23: =利润表!W20 -> 0 | F23: =利润表!AA20 -> 0 | G23: =利润表!AB20 -> 0 | H23: =利润表!AC20 -> 0 | J23: 归属母公司股东权益 | K23: =资产负债表!O45 -> 0 | L23: =资产负债表!S45 -> 0 | M23: =资产负债表!W45 -> 0 | N23: =资产负债表!AA45 -> 0 | O23: =资产负债表!AB45 -> 0 | P23: =资产负债表!AC45 -> 0
B24: %税前利润 | C24: =IF(ISERROR(C23/C25),"—",C23/C25) -> — | D24: =IF(ISERROR(D23/D25),"—",D23/D25) -> — | E24: =IF(ISERROR(E23/E25),"—",E23/E25) -> — | F24: =IF(ISERROR(F23/F25),"—",F23/F25) -> — | G24: =IF(ISERROR(G23/G25),"—",G23/G25) -> — | H24: =IF(ISERROR(H23/H25),"—",H23/H25) -> — | J24: 少数股东权益 | K24: =资产负债表!O46 -> 0 | L24: =资产负债表!S46 -> 0 | M24: =资产负债表!W46 -> 0 | N24: =资产负债表!AA46 -> 0 | O24: =资产负债表!AB46 -> 0 | P24: =资产负债表!AC46 -> 0
B25: 除税前利润 | C25: =利润表!O24 -> 0 | D25: =利润表!S24 -> 0 | E25: =利润表!W24 -> 0 | F25: =利润表!AA24 -> 0 | G25: =利润表!AB24 -> 0 | H25: =利润表!AC24 -> 0 | J25: 负债股东权益合计 | K25: =资产负债表!O48 -> 0 | L25: =资产负债表!S48 -> 0 | M25: =资产负债表!W48 -> 0 | N25: =资产负债表!AA48 -> 0 | O25: =资产负债表!AB48 -> 0 | P25: =资产负债表!AC48 -> 0
B26: 利润率 | C26: =IF(ISERROR(C25/C5),"—",C25/C5) -> — | D26: =IF(ISERROR(D25/D5),"—",D25/D5) -> — | E26: =IF(ISERROR(E25/E5),"—",E25/E5) -> — | F26: =IF(ISERROR(F25/F5),"—",F25/F5) -> — | G26: =IF(ISERROR(G25/G5),"—",G25/G5) -> — | H26: =IF(ISERROR(H25/H5),"—",H25/H5) -> —
B27: 所得税 | C27: =利润表!O25 -> 0 | D27: =利润表!S25 -> 0 | E27: =利润表!W25 -> 0 | F27: =利润表!AA25 -> 0 | G27: =利润表!AB25 -> 0 | H27: =利润表!AC25 -> 0 | J27: 比率分析
B28: 所得税率 | C28: =IF(ISERROR(C27/C25),"—",C27/C25) -> — | D28: =IF(ISERROR(D27/D25),"—",D27/D25) -> — | E28: =IF(ISERROR(E27/E25),"—",E27/E25) -> — | F28: =IF(ISERROR(F27/F25),"—",F27/F25) -> — | G28: =IF(ISERROR(G27/G25),"—",G27/G25) -> — | H28: =IF(ISERROR(H27/H25),"—",H27/H25) -> — | K28: =C4 -> 2019 | L28: =D4 -> 2020 | M28: =E4 -> 2021 | N28: =F4 -> 2022E | O28: =G4 -> 2023 | P28: =H4 -> 2024
B29: 净利润(含少数股东损益) | C29: =C25-C27 -> 0 | D29: =D25-D27 -> 0 | E29: =E25-E27 -> 0 | F29: =F25-F27 -> 0 | G29: =G25-G27 -> 0 | H29: =H25-H27 -> 0 | J29: 每股指标
B30: 少数股东损益 | C30: =利润表!O27 -> 0 | D30: =利润表!S27 -> 0 | E30: =利润表!W27 -> 0 | F30: =利润表!AA27 -> 0 | G30: =利润表!AB27 -> 0 | H30: =利润表!AC27 -> 0 | J30: 每股收益 | K30: =主要财务摘要!C20 -> 0 | L30: =主要财务摘要!D20 -> 0 | M30: =主要财务摘要!E20 -> 0 | N30: =主要财务摘要!F20 -> — | O30: =主要财务摘要!G20 -> — | P30: =主要财务摘要!H20 -> —
B31: 归属于母公司的净利润 | C31: =利润表!O29 -> 0 | D31: =利润表!S29 -> 0 | E31: =利润表!W29 -> 0 | F31: =利润表!AA29 -> 0 | G31: =利润表!AB29 -> 0 | H31: =利润表!AC29 -> 0 | J31: 每股净资产 | K31: =主要财务摘要!C21 -> — | L31: =主要财务摘要!D21 -> — | M31: =主要财务摘要!E21 -> — | N31: =主要财务摘要!F21 -> — | O31: =主要财务摘要!G21 -> — | P31: =主要财务摘要!H21 -> —
B32: 增长率 | C32: =IF(ISERROR((利润表!O29-利润表!K29)/ABS(利润表!K29)),"—",(利润表!O29-利润表!K29)/ABS(利润表!K29)) -> — | D32: =IF(ISERROR((D31-C31)/ABS(C31)),"—",(D31-C31)/ABS(C31)) -> — | E32: =IF(ISERROR((E31-D31)/ABS(D31)),"—",(E31-D31)/ABS(D31)) -> — | F32: =IF(ISERROR((F31-E31)/ABS(E31)),"—",(F31-E31)/ABS(E31)) -> — | G32: =IF(ISERROR((G31-F31)/ABS(F31)),"—",(G31-F31)/ABS(F31)) -> — | H32: =IF(ISERROR((H31-G31)/ABS(G31)),"—",(H31-G31)/ABS(G31)) -> — | J32: 每股经营现金净流 | K32: =主要财务摘要!C25 -> — | L32: =主要财务摘要!D25 -> — | M32: =主要财务摘要!E25 -> — | N32: =主要财务摘要!F25 -> — | O32: =主要财务摘要!G25 -> — | P32: =主要财务摘要!H25 -> —
B33: 净利率 | C33: =IF(ISERROR(C31/C5),"—",C31/C5) -> — | D33: =IF(ISERROR(D31/D5),"—",D31/D5) -> — | E33: =IF(ISERROR(E31/E5),"—",E31/E5) -> — | F33: =IF(ISERROR(F31/F5),"—",F31/F5) -> — | G33: =IF(ISERROR(G31/G5),"—",G31/G5) -> — | H33: =IF(ISERROR(H31/H5),"—",H31/H5) -> — | J33: 每股股利 | K33: =资产预测!D100 -> 0 | L33: =资产预测!E100 -> 0 | M33: =资产预测!F100 -> 0 | N33: =IF(ISERROR(资产预测!J100),"—",资产预测!J100) -> 0 | O33: =IF(ISERROR(资产预测!K100),"—",资产预测!K100) -> 0 | P33: =IF(ISERROR(资产预测!L100),"—",资产预测!L100) -> 0
J34: 回报率
J35: 净资产收益率 | K35: =IF(ISERROR(C31/K23),"—",C31/K23) -> — | L35: =IF(ISERROR(D31/L23),"—",D31/L23) -> — | M35: =IF(ISERROR(E31/M23),"—",E31/M23) -> — | N35: =IF(ISERROR(F31/N23),"—",F31/N23) -> — | O35: =IF(ISERROR(G31/O23),"—",G31/O23) -> — | P35: =IF(ISERROR(H31/P23),"—",H31/P23) -> —
J36: 总资产收益率 | K36: =IF(ISERROR(C31/K25),"—",C31/K25) -> — | L36: =IF(ISERROR(D31/L25),"—",D31/L25) -> — | M36: =IF(ISERROR(E31/M25),"—",E31/M25) -> — | N36: =IF(ISERROR(F31/N25),"—",F31/N25) -> — | O36: =IF(ISERROR(G31/O25),"—",G31/O25) -> — | P36: =IF(ISERROR(H31/P25),"—",H31/P25) -> —
J37: 投入资本收益率 | K37: =IF(ISERROR(C21*(1-利润表!O25/利润表!O24)/资产负债表!O58),"—",C21*(1-利润表!O25/利润表!O24)/资产负债表!O58) -> — | L37: =IF(ISERROR(D21*(1-利润表!S25/利润表!S24)/资产负债表!S58),"—",D21*(1-利润表!S25/利润表!S24)/资产负债表!S58) -> — | M37: =IF(ISERROR(E21*(1-利润表!W25/利润表!W24)/资产负债表!W58),"—",E21*(1-利润表!W25/利润表!W24)/资产负债表!W58) -> — | N37: =IF(ISERROR(F21*(1-利润表!AA25/利润表!AA24)/资产负债表!AA58),"—",F21*(1-利润表!AA25/利润表!AA24)/资产负债表!AA58) -> — | O37: =IF(ISERROR(G21*(1-利润表!AB25/利润表!AB24)/资产负债表!AB58),"—",G21*(1-利润表!AB25/利润表!AB24)/资产负债表!AB58) -> — | P37: =IF(ISERROR(H21*(1-利润表!AC25/利润表!AC24)/资产负债表!AC58),"—",H21*(1-利润表!AC25/利润表!AC24)/资产负债表!AC58) -> —
B38: 现金流量表 | H38: =主要财务摘要!$H$2 -> 单位：港币(百万) | J38: 增长率
C39: =C4 -> 2019 | D39: =D4 -> 2020 | E39: =E4 -> 2021 | F39: =F4 -> 2022E | G39: =G4 -> 2023 | H39: =H4 -> 2024 | J39: 营业收入增长率 | K39: =C6 -> — | L39: =D6 -> — | M39: =E6 -> — | N39: =F6 -> — | O39: =G6 -> — | P39: =H6 -> —
B40: 净利润 | C40: =利润表!O29 -> 0 | D40: =利润表!S29 -> 0 | E40: =利润表!W29 -> 0 | F40: =利润表!AA29 -> 0 | G40: =利润表!AB29 -> 0 | H40: =利润表!AC29 -> 0 | J40: EBIT增长率 | K40: =IF(ISERROR((利润表!O35-利润表!K35)/ABS(利润表!K35)),"—",(利润表!O35-利润表!K35)/ABS(利润表!K35)) -> — | L40: =IF(ISERROR((利润表!S35-利润表!O35)/ABS(利润表!O35)),"—",(利润表!S35-利润表!O35)/ABS(利润表!O35)) -> — | M40: =IF(ISERROR((利润表!W35-利润表!S35)/ABS(利润表!S35)),"—",(利润表!W35-利润表!S35)/ABS(利润表!S35)) -> — | N40: =IF(ISERROR((利润表!AA35-利润表!W35)/ABS(利润表!W35)),"—",(利润表!AA35-利润表!W35)/ABS(利润表!W35)) -> — | O40: =IF(ISERROR((利润表!AB35-利润表!AA35)/ABS(利润表!AA35)),"—",(利润表!AB35-利润表!AA35)/ABS(利润表!AA35)) -> — | P40: =IF(ISERROR((利润表!AC35-利润表!AB35)/ABS(利润表!AB35)),"—",(利润表!AC35-利润表!AB35)/ABS(利润表!AB35)) -> —
B41: 少数股东损益 | C41: =利润表!O27 -> 0 | D41: =利润表!S27 -> 0 | E41: =利润表!W27 -> 0 | F41: =利润表!AA27 -> 0 | G41: =利润表!AB27 -> 0 | H41: =利润表!AC27 -> 0 | J41: 净利润增长率 | K41: =IF(ISERROR((利润表!O29-利润表!K29)/ABS(利润表!K29)),"—",(利润表!O29-利润表!K29)/ABS(利润表!K29)) -> — | L41: =IF(ISERROR((利润表!S29-利润表!O29)/ABS(利润表!O29)),"—",(利润表!S29-利润表!O29)/ABS(利润表!O29)) -> — | M41: =IF(ISERROR((利润表!W29-利润表!S29)/ABS(利润表!S29)),"—",(利润表!W29-利润表!S29)/ABS(利润表!S29)) -> — | N41: =IF(ISERROR((利润表!AA29-利润表!W29)/ABS(利润表!W29)),"—",(利润表!AA29-利润表!W29)/ABS(利润表!W29)) -> — | O41: =IF(ISERROR((利润表!AB29-利润表!AA29)/ABS(利润表!AA29)),"—",(利润表!AB29-利润表!AA29)/ABS(利润表!AA29)) -> — | P41: =IF(ISERROR((利润表!AC29-利润表!AB29)/ABS(利润表!AB29)),"—",(利润表!AC29-利润表!AB29)/ABS(利润表!AB29)) -> —
B42: 营运资金变动 | C42: =现金流量表!$O$7 -> 0 | D42: =现金流量表!$S$7 -> 0 | E42: =现金流量表!$W$7 -> 0 | F42: =现金流量表!$AA$7 -> 0 | G42: =现金流量表!$AB$7 -> 0 | H42: =现金流量表!$AC$7 -> 0 | J42: 总资产增长率 | K42: =IF(ISERROR((资产负债表!O24-资产负债表!K24)/ABS(资产负债表!K24)),"—",(资产负债表!O24-资产负债表!K24)/ABS(资产负债表!K24)) -> — | L42: =IF(ISERROR((资产负债表!S24-资产负债表!O24)/ABS(资产负债表!O24)),"—",(资产负债表!S24-资产负债表!O24)/ABS(资产负债表!O24)) -> — | M42: =IF(ISERROR((资产负债表!W24-资产负债表!S24)/ABS(资产负债表!S24)),"—",(资产负债表!W24-资产负债表!S24)/ABS(资产负债表!S24)) -> — | N42: =IF(ISERROR((资产负债表!AA24-资产负债表!W24)/ABS(资产负债表!W24)),"—",(资产负债表!AA24-资产负债表!W24)/ABS(资产负债表!W24)) -> — | O42: =IF(ISERROR((资产负债表!AB24-资产负债表!AA24)/ABS(资产负债表!AA24)),"—",(资产负债表!AB24-资产负债表!AA24)/ABS(资产负债表!AA24)) -> — | P42: =IF(ISERROR((资产负债表!AC24-资产负债表!AB24)/ABS(资产负债表!AB24)),"—",(资产负债表!AC24-资产负债表!AB24)/ABS(资产负债表!AB24)) -> —
B43: 其他变动 | C43: =C44-C42-C41-C40 -> 0 | D43: =D44-D42-D41-D40 -> 0 | E43: =E44-E42-E41-E40 -> 0 | F43: =F44-F42-F41-F40 -> 0 | G43: =G44-G42-G41-G40 -> 0 | H43: =H44-H42-H41-H40 -> 0 | J43: 资产管理能力
B44: 经营活动现金流量净额 | C44: =现金流量表!$O$16 -> 0 | D44: =现金流量表!$S$16 -> 0 | E44: =现金流量表!$W$16 -> 0 | F44: =现金流量表!$AA$16 -> 0 | G44: =现金流量表!$AB$16 -> 0 | H44: =现金流量表!$AC$16 -> 0 | J44: 应收账款周转天数 | K44: =IF(ISERROR(360/(资产预测!D5*2/(资产预测!D9+资产负债表!K9))),"—",360/(资产预测!D5*2/(资产预测!D9+资产负债表!K9))) -> — | L44: =IF(ISERROR(360/(资产预测!E5*2/(资产预测!E9+资产预测!D9))),"—",360/(资产预测!E5*2/(资产预测!E9+资产预测!D9))) -> — | M44: =IF(ISERROR(360/(资产预测!F5*2/(资产预测!F9+资产预测!E9))),"—",360/(资产预测!F5*2/(资产预测!F9+资产预测!E9))) -> — | N44: =IF(ISERROR(360/(资产预测!J5*2/(资产预测!J9+资产预测!F9))),"—",360/(资产预测!J5*2/(资产预测!J9+资产预测!F9))) -> — | O44: =IF(ISERROR(360/(资产预测!K5*2/(资产预测!K9+资产预测!J9))),"—",360/(资产预测!K5*2/(资产预测!K9+资产预测!J9))) -> — | P44: =IF(ISERROR(360/(资产预测!L5*2/(资产预测!L9+资产预测!K9))),"—",360/(资产预测!L5*2/(资产预测!L9+资产预测!K9))) -> — | Q44: 此处周转天数按照相关科目的期初期末平均值计算
B45: 资本开支 | C45: =现金流量表!$O$17 -> 0 | D45: =现金流量表!$S$17 -> 0 | E45: =现金流量表!$W$17 -> 0 | F45: =现金流量表!$AA$17 -> 0 | G45: =现金流量表!$AB$17 -> 0 | H45: =现金流量表!$AC$17 -> 0 | J45: 存货周转天数 | K45: =IF(ISERROR(360/(资产预测!D6*2/(资产预测!D13+资产负债表!K11))),"—",360/(资产预测!D6*2/(资产预测!D13+资产负债表!K11))) -> — | L45: =IF(ISERROR(360/(资产预测!E6*2/(资产预测!E13+资产预测!D13))),"—",360/(资产预测!E6*2/(资产预测!E13+资产预测!D13))) -> — | M45: =IF(ISERROR(360/(资产预测!F6*2/(资产预测!F13+资产预测!E13))),"—",360/(资产预测!F6*2/(资产预测!F13+资产预测!E13))) -> — | N45: =IF(ISERROR(360/(资产预测!J6*2/(资产预测!J13+资产预测!F13))),"—",360/(资产预测!J6*2/(资产预测!J13+资产预测!F13))) -> — | O45: =IF(ISERROR(360/(资产预测!K6*2/(资产预测!K13+资产预测!J13))),"—",360/(资产预测!K6*2/(资产预测!K13+资产预测!J13))) -> — | P45: =IF(ISERROR(360/(资产预测!L6*2/(资产预测!L13+资产预测!K13))),"—",360/(资产预测!L6*2/(资产预测!L13+资产预测!K13))) -> —
B46: 投资 | C46: =现金流量表!$O$21 -> 0 | D46: =现金流量表!$S$21 -> 0 | E46: =现金流量表!$W$21 -> 0 | F46: =现金流量表!$AA$21 -> 0 | G46: =现金流量表!$AB$21 -> 0 | H46: =现金流量表!$AC$21 -> 0 | J46: 应付账款周转天数 | K46: =IF(ISERROR(360/(资产预测!D6*2/(资产预测!D24+资产负债表!K28))),"—",360/(资产预测!D6*2/(资产预测!D24+资产负债表!K28))) -> — | L46: =IF(ISERROR(360/(资产预测!E6*2/(资产预测!E24+资产预测!D24))),"—",360/(资产预测!E6*2/(资产预测!E24+资产预测!D24))) -> — | M46: =IF(ISERROR(360/(资产预测!F6*2/(资产预测!F24+资产预测!E24))),"—",360/(资产预测!F6*2/(资产预测!F24+资产预测!E24))) -> — | N46: =IF(ISERROR(360/(资产预测!J6*2/(资产预测!J24+资产预测!F24))),"—",360/(资产预测!J6*2/(资产预测!J24+资产预测!F24))) -> — | O46: =IF(ISERROR(360/(资产预测!K6*2/(资产预测!K24+资产预测!J24))),"—",360/(资产预测!K6*2/(资产预测!K24+资产预测!J24))) -> — | P46: =IF(ISERROR(360/(资产预测!L6*2/(资产预测!L24+资产预测!K24))),"—",360/(资产预测!L6*2/(资产预测!L24+资产预测!K24))) -> —
B47: 其他 | C47: =C48-C45-C46 -> 0 | D47: =D48-D45-D46 -> 0 | E47: =E48-E45-E46 -> 0 | F47: =F48-F45-F46 -> 0 | G47: =G48-G45-G46 -> 0 | H47: =H48-H45-H46 -> 0 | J47: 固定资产周转天数 | K47: =IF(ISERROR(360/(利润表!O6*2/(资产负债表!O15+资产负债表!K15))),"—",360/(利润表!O6*2/(资产负债表!O15+资产负债表!K15))) -> — | L47: =IF(ISERROR(360/(利润表!S6*2/(资产负债表!S15+资产负债表!O15))),"—",360/(利润表!S6*2/(资产负债表!S15+资产负债表!O15))) -> — | M47: =IF(ISERROR(360/(利润表!W6*2/(资产负债表!W15+资产负债表!S15))),"—",360/(利润表!W6*2/(资产负债表!W15+资产负债表!S15))) -> — | N47: =IF(ISERROR(360/(利润表!AA6*2/(资产负债表!AA15+资产负债表!W15))),"—",360/(利润表!AA6*2/(资产负债表!AA15+资产负债表!W15))) -> — | O47: =IF(ISERROR(360/(利润表!AB6*2/(资产负债表!AB15+资产负债表!AA15))),"—",360/(利润表!AB6*2/(资产负债表!AB15+资产负债表!AA15))) -> — | P47: =IF(ISERROR(360/(利润表!AC6*2/(资产负债表!AC15+资产负债表!AB15))),"—",360/(利润表!AC6*2/(资产负债表!AC15+资产负债表!AB15))) -> —
B48: 投资活动现金流量净额 | C48: =现金流量表!$O$29 -> 0 | D48: =现金流量表!$S$29 -> 0 | E48: =现金流量表!$W$29 -> 0 | F48: =现金流量表!$AA$29 -> 0 | G48: =现金流量表!$AB$29 -> 0 | H48: =现金流量表!$AC$29 -> 0 | J48: 偿债能力
B49: 股权募资 | C49: =现金流量表!$O$31 -> 0 | D49: =现金流量表!$S$31 -> 0 | E49: =现金流量表!$W$31 -> 0 | F49: =现金流量表!$AA$31 -> 0 | G49: =现金流量表!$AB$31 -> 0 | H49: =现金流量表!$AC$31 -> 0 | J49: 流动比率 | K49: =IF(ISERROR(资产负债表!O13/资产负债表!O33),"—",资产负债表!O13/资产负债表!O33) -> — | L49: =IF(ISERROR(资产负债表!S13/资产负债表!S33),"—",资产负债表!S13/资产负债表!S33) -> — | M49: =IF(ISERROR(资产负债表!W13/资产负债表!W33),"—",资产负债表!W13/资产负债表!W33) -> — | N49: =IF(ISERROR(资产负债表!AA13/资产负债表!AA33),"—",资产负债表!AA13/资产负债表!AA33) -> — | O49: =IF(ISERROR(资产负债表!AB13/资产负债表!AB33),"—",资产负债表!AB13/资产负债表!AB33) -> — | P49: =IF(ISERROR(资产负债表!AC13/资产负债表!AC33),"—",资产负债表!AC13/资产负债表!AC33) -> —
B50: 债权募资 | C50: =现金流量表!$O$30 -> 0 | D50: =现金流量表!$S$30 -> 0 | E50: =现金流量表!$W$30 -> 0 | F50: =现金流量表!$AA$30 -> 0 | G50: =现金流量表!$AB$30 -> 0 | H50: =现金流量表!$AC$30 -> 0 | J50: 速动比率 | K50: =IF(ISERROR((资产负债表!O13-资产负债表!O11-资产负债表!O12)/资产负债表!O33),"—",(资产负债表!O13-资产负债表!O11-资产负债表!O12)/资产负债表!O33) -> — | L50: =IF(ISERROR((资产负债表!S13-资产负债表!S11-资产负债表!S12)/资产负债表!S33),"—",(资产负债表!S13-资产负债表!S11-资产负债表!S12)/资产负债表!S33) -> — | M50: =IF(ISERROR((资产负债表!W13-资产负债表!W11-资产负债表!W12)/资产负债表!W33),"—",(资产负债表!W13-资产负债表!W11-资产负债表!W12)/资产负债表!W33) -> — | N50: =IF(ISERROR((资产负债表!AA13-资产负债表!AA11-资产负债表!AA12)/资产负债表!AA33),"—",(资产负债表!AA13-资产负债表!AA11-资产负债表!AA12)/资产负债表!AA33) -> — | O50: =IF(ISERROR((资产负债表!AB13-资产负债表!AB11-资产负债表!AB12)/资产负债表!AB33),"—",(资产负债表!AB13-资产负债表!AB11-资产负债表!AB12)/资产负债表!AB33) -> — | P50: =IF(ISERROR((资产负债表!AC13-资产负债表!AC11-资产负债表!AC12)/资产负债表!AC33),"—",(资产负债表!AC13-资产负债表!AC11-资产负债表!AC12)/资产负债表!AC33) -> —
B51: 其他 | C51: =C52-C49-C50 -> 0 | D51: =D52-D49-D50 -> 0 | E51: =E52-E49-E50 -> 0 | F51: =F52-F49-F50 -> 0 | G51: =G52-G49-G50 -> 0 | H51: =H52-H49-H50 -> 0 | J51: 净负债/股东权益 | K51: =IF(ISERROR((资产负债表!O55-资产负债表!O6)/资产负债表!O47),"—",(资产负债表!O55-资产负债表!O6)/资产负债表!O47) -> — | L51: =IF(ISERROR((资产负债表!S55-资产负债表!S6)/资产负债表!S47),"—",(资产负债表!S55-资产负债表!S6)/资产负债表!S47) -> — | M51: =IF(ISERROR((资产负债表!W55-资产负债表!W6)/资产负债表!W47),"—",(资产负债表!W55-资产负债表!W6)/资产负债表!W47) -> — | N51: =IF(ISERROR((资产负债表!AA55-资产负债表!AA6)/资产负债表!AA47),"—",(资产负债表!AA55-资产负债表!AA6)/资产负债表!AA47) -> — | O51: =IF(ISERROR((资产负债表!AB55-资产负债表!AB6)/资产负债表!AB47),"—",(资产负债表!AB55-资产负债表!AB6)/资产负债表!AB47) -> — | P51: =IF(ISERROR((资产负债表!AC55-资产负债表!AC6)/资产负债表!AC47),"—",(资产负债表!AC55-资产负债表!AC6)/资产负债表!AC47) -> —
B52: 筹资活动现金流量净额 | C52: =现金流量表!$O$34 -> 0 | D52: =现金流量表!$S$34 -> 0 | E52: =现金流量表!$W$34 -> 0 | F52: =现金流量表!$AA$34 -> 0 | G52: =现金流量表!$AB$34 -> 0 | H52: =现金流量表!$AC$34 -> 0 | J52: EBIT利息保障倍数 | K52: =IF(ISERROR(利润表!O35/利润表!O19),"—",利润表!O35/利润表!O19) -> — | L52: =IF(ISERROR(利润表!S35/利润表!S19),"—",利润表!S35/利润表!S19) -> — | M52: =IF(ISERROR(利润表!W35/利润表!W19),"—",利润表!W35/利润表!W19) -> — | N52: =IF(ISERROR(利润表!AA35/利润表!AA19),"—",利润表!AA35/利润表!AA19) -> — | O52: =IF(ISERROR(利润表!AB35/利润表!AB19),"—",利润表!AB35/利润表!AB19) -> — | P52: =IF(ISERROR(利润表!AC35/利润表!AC19),"—",利润表!AC35/利润表!AC19) -> —
B53: 现金净变动 | C53: =现金流量表!$O$36 -> 0 | D53: =现金流量表!$S$36 -> 0 | E53: =现金流量表!$W$36 -> 0 | F53: =现金流量表!$AA$36 -> 0 | G53: =现金流量表!$AB$36 -> 0 | H53: =现金流量表!$AC$36 -> 0 | J53: 资产负债率 | K53: =IF(ISERROR(K22/K14),"—",K22/K14) -> — | L53: =IF(ISERROR(L22/L14),"—",L22/L14) -> — | M53: =IF(ISERROR(M22/M14),"—",M22/M14) -> — | N53: =IF(ISERROR(N22/N14),"—",N22/N14) -> — | O53: =IF(ISERROR(O22/O14),"—",O22/O14) -> — | P53: =IF(ISERROR(P22/P14),"—",P22/P14) -> —

Sheet 资产负债表
B2: 资产负债表
B3: =主要财务摘要!H2 -> 单位：港币(百万)
B4: 报告截止日： | D4: =财务基础数据!D5 -> 1Q17 | E4: =财务基础数据!E5 -> 1H17 | F4: =财务基础数据!F5 -> 3Q17 | G4: =财务基础数据!G5 -> 2017 | H4: =财务基础数据!H5 -> 1Q18 | I4: =财务基础数据!I5 -> 1H18 | J4: =财务基础数据!J5 -> 3Q18 | K4: =财务基础数据!K5 -> 2018 | ... Z4: =财务基础数据!Z5 -> 3Q22 | AA4: =财务基础数据!AA5&"E" -> 2022E | AB4: =财务基础数据!AA5+1 -> 2023 | AC4: =AB4+1 -> 2024 | AD4: =AC4+1 -> 2025 | AE4: =AD4+1 -> 2026 | AF4: =AE4+1 -> 2027 | AG4: =AF4+1 -> 2028 | AH4: =AG4+1 -> 2029 | AI4: =AH4+1 -> 2030 | AJ4: =AI4+1 -> 2031
B5: 流动资产:
B6: 现金及现金等价物 | D6: =(财务基础数据!D44)*目录!$D$6 -> 0 | E6: =(财务基础数据!E44)*目录!$D$6 -> 0 | F6: =(财务基础数据!F44)*目录!$D$6 -> 0 | G6: =(财务基础数据!G44)*目录!$D$6 -> 0 | H6: =(财务基础数据!H44)*目录!$D$6 -> 0 | I6: =(财务基础数据!I44)*目录!$D$6 -> 0 | J6: =(财务基础数据!J44)*目录!$D$6 -> 0 | K6: =(财务基础数据!K44)*目录!$D$6 -> 0 | ... Z6: =(财务基础数据!Z44)*目录!$D$6 -> 0 | AA6: =现金流量表!AA38 -> 0 | AB6: =现金流量表!AB38 -> 0 | AC6: =现金流量表!AC38 -> 0 | AD6: =现金流量表!AD38 -> 0 | AE6: =现金流量表!AE38 -> 0 | AF6: =现金流量表!AF38 -> 0 | AG6: =现金流量表!AG38 -> 0 | AH6: =现金流量表!AH38 -> 0 | ... AJ6: =现金流量表!AJ38 -> 0
B7: 交易性金融资产 | D7: =(财务基础数据!D45)*目录!$D$6 -> 0 | E7: =(财务基础数据!E45)*目录!$D$6 -> 0 | F7: =(财务基础数据!F45)*目录!$D$6 -> 0 | G7: =(财务基础数据!G45)*目录!$D$6 -> 0 | H7: =(财务基础数据!H45)*目录!$D$6 -> 0 | I7: =(财务基础数据!I45)*目录!$D$6 -> 0 | J7: =(财务基础数据!J45)*目录!$D$6 -> 0 | K7: =(财务基础数据!K45)*目录!$D$6 -> 0 | ... Z7: =(财务基础数据!Z45)*目录!$D$6 -> 0 | AA7: =资产预测!J40 -> 0 | AB7: =资产预测!K40 -> 0 | AC7: =资产预测!L40 -> 0 | AD7: =资产预测!M40 -> 0 | AE7: =资产预测!N40 -> 0 | AF7: =资产预测!O40 -> 0 | AG7: =资产预测!P40 -> 0 | AH7: =资产预测!Q40 -> 0 | ... AJ7: =资产预测!S40 -> 0
B8: 其他短期投资 | D8: =(财务基础数据!D46)*目录!$D$6 -> 0 | E8: =(财务基础数据!E46)*目录!$D$6 -> 0 | F8: =(财务基础数据!F46)*目录!$D$6 -> 0 | G8: =(财务基础数据!G46)*目录!$D$6 -> 0 | H8: =(财务基础数据!H46)*目录!$D$6 -> 0 | I8: =(财务基础数据!I46)*目录!$D$6 -> 0 | J8: =(财务基础数据!J46)*目录!$D$6 -> 0 | K8: =(财务基础数据!K46)*目录!$D$6 -> 0 | ... Z8: =(财务基础数据!Z46)*目录!$D$6 -> 0 | AA8: =资产预测!J43 -> 0 | AB8: =资产预测!K43 -> 0 | AC8: =资产预测!L43 -> 0 | AD8: =资产预测!M43 -> 0 | AE8: =资产预测!N43 -> 0 | AF8: =资产预测!O43 -> 0 | AG8: =资产预测!P43 -> 0 | AH8: =资产预测!Q43 -> 0 | ... AJ8: =资产预测!S43 -> 0
B9: 应收账款及票据 | D9: =(财务基础数据!D48)*目录!$D$6 -> 0 | E9: =(财务基础数据!E48)*目录!$D$6 -> 0 | F9: =(财务基础数据!F48)*目录!$D$6 -> 0 | G9: =(财务基础数据!G48)*目录!$D$6 -> 0 | H9: =(财务基础数据!H48)*目录!$D$6 -> 0 | I9: =(财务基础数据!I48)*目录!$D$6 -> 0 | J9: =(财务基础数据!J48)*目录!$D$6 -> 0 | K9: =(财务基础数据!K48)*目录!$D$6 -> 0 | ... Z9: =(财务基础数据!Z48)*目录!$D$6 -> 0 | AA9: =资产预测!J9 -> 0 | AB9: =资产预测!K9 -> 0 | AC9: =资产预测!L9 -> 0 | AD9: =资产预测!M9 -> 0 | AE9: =资产预测!N9 -> 0 | AF9: =资产预测!O9 -> 0 | AG9: =资产预测!P9 -> 0 | AH9: =资产预测!Q9 -> 0 | ... AJ9: =资产预测!S9 -> 0
B10: 其他应收款 | D10: =(财务基础数据!D49)*目录!$D$6 -> 0 | E10: =(财务基础数据!E49)*目录!$D$6 -> 0 | F10: =(财务基础数据!F49)*目录!$D$6 -> 0 | G10: =(财务基础数据!G49)*目录!$D$6 -> 0 | H10: =(财务基础数据!H49)*目录!$D$6 -> 0 | I10: =(财务基础数据!I49)*目录!$D$6 -> 0 | J10: =(财务基础数据!J49)*目录!$D$6 -> 0 | K10: =(财务基础数据!K49)*目录!$D$6 -> 0 | ... Z10: =(财务基础数据!Z49)*目录!$D$6 -> 0 | AA10: =资产预测!J17 -> 0 | AB10: =资产预测!K17 -> 0 | AC10: =资产预测!L17 -> 0 | AD10: =资产预测!M17 -> 0 | AE10: =资产预测!N17 -> 0 | AF10: =资产预测!O17 -> 0 | AG10: =资产预测!P17 -> 0 | AH10: =资产预测!Q17 -> 0 | ... AJ10: =资产预测!S17 -> 0
B11: 存货 | D11: =(财务基础数据!D50)*目录!$D$6 -> 0 | E11: =(财务基础数据!E50)*目录!$D$6 -> 0 | F11: =(财务基础数据!F50)*目录!$D$6 -> 0 | G11: =(财务基础数据!G50)*目录!$D$6 -> 0 | H11: =(财务基础数据!H50)*目录!$D$6 -> 0 | I11: =(财务基础数据!I50)*目录!$D$6 -> 0 | J11: =(财务基础数据!J50)*目录!$D$6 -> 0 | K11: =(财务基础数据!K50)*目录!$D$6 -> 0 | ... Z11: =(财务基础数据!Z50)*目录!$D$6 -> 0 | AA11: =资产预测!J13 -> 0 | AB11: =资产预测!K13 -> 0 | AC11: =资产预测!L13 -> 0 | AD11: =资产预测!M13 -> 0 | AE11: =资产预测!N13 -> 0 | AF11: =资产预测!O13 -> 0 | AG11: =资产预测!P13 -> 0 | AH11: =资产预测!Q13 -> 0 | ... AJ11: =资产预测!S13 -> 0
B12: 其他流动资产 | D12: =(财务基础数据!D51)*目录!$D$6 -> 0 | E12: =(财务基础数据!E51)*目录!$D$6 -> 0 | F12: =(财务基础数据!F51)*目录!$D$6 -> 0 | G12: =(财务基础数据!G51)*目录!$D$6 -> 0 | H12: =(财务基础数据!H51)*目录!$D$6 -> 0 | I12: =(财务基础数据!I51)*目录!$D$6 -> 0 | J12: =(财务基础数据!J51)*目录!$D$6 -> 0 | K12: =(财务基础数据!K51)*目录!$D$6 -> 0 | ... Z12: =(财务基础数据!Z51)*目录!$D$6 -> 0 | AA12: =资产预测!J20 -> 0 | AB12: =资产预测!K20 -> 0 | AC12: =资产预测!L20 -> 0 | AD12: =资产预测!M20 -> 0 | AE12: =资产预测!N20 -> 0 | AF12: =资产预测!O20 -> 0 | AG12: =资产预测!P20 -> 0 | AH12: =资产预测!Q20 -> 0 | ... AJ12: =资产预测!S20 -> 0
B13: 流动资产合计 | D13: =SUM(D6:D12) -> 0 | E13: =SUM(E6:E12) -> 0 | F13: =SUM(F6:F12) -> 0 | G13: =SUM(G6:G12) -> 0 | H13: =SUM(H6:H12) -> 0 | I13: =SUM(I6:I12) -> 0 | J13: =SUM(J6:J12) -> 0 | K13: =SUM(K6:K12) -> 0 | ... AJ13: =SUM(AJ6:AJ12) -> 0
B14: 非流动资产:
B15: 固定资产净值 | D15: =(财务基础数据!D53)*目录!$D$6 -> 0 | E15: =(财务基础数据!E53)*目录!$D$6 -> 0 | F15: =(财务基础数据!F53)*目录!$D$6 -> 0 | G15: =(财务基础数据!G53)*目录!$D$6 -> 0 | H15: =(财务基础数据!H53)*目录!$D$6 -> 0 | I15: =(财务基础数据!I53)*目录!$D$6 -> 0 | J15: =(财务基础数据!J53)*目录!$D$6 -> 0 | K15: =(财务基础数据!K53)*目录!$D$6 -> 0 | ... Z15: =(财务基础数据!Z53)*目录!$D$6 -> 0 | AA15: =资产预测!J64 -> 0 | AB15: =资产预测!K64 -> 0 | AC15: =资产预测!L64 -> 0 | AD15: =资产预测!M64 -> 0 | AE15: =资产预测!N64 -> 0 | AF15: =资产预测!O64 -> 0 | AG15: =资产预测!P64 -> 0 | AH15: =资产预测!Q64 -> 0 | ... AJ15: =资产预测!S64 -> 0
B16: 权益性投资 | D16: =(财务基础数据!D54)*目录!$D$6 -> 0 | E16: =(财务基础数据!E54)*目录!$D$6 -> 0 | F16: =(财务基础数据!F54)*目录!$D$6 -> 0 | G16: =(财务基础数据!G54)*目录!$D$6 -> 0 | H16: =(财务基础数据!H54)*目录!$D$6 -> 0 | I16: =(财务基础数据!I54)*目录!$D$6 -> 0 | J16: =(财务基础数据!J54)*目录!$D$6 -> 0 | K16: =(财务基础数据!K54)*目录!$D$6 -> 0 | ... Z16: =(财务基础数据!Z54)*目录!$D$6 -> 0 | AA16: =资产预测!J51 -> 0 | AB16: =资产预测!K51 -> 0 | AC16: =资产预测!L51 -> 0 | AD16: =资产预测!M51 -> 0 | AE16: =资产预测!N51 -> 0 | AF16: =资产预测!O51 -> 0 | AG16: =资产预测!P51 -> 0 | AH16: =资产预测!Q51 -> 0 | ... AJ16: =资产预测!S51 -> 0
B17: 债务工具 | D17: =(财务基础数据!D55)*目录!$D$6 -> 0 | E17: =(财务基础数据!E55)*目录!$D$6 -> 0 | F17: =(财务基础数据!F55)*目录!$D$6 -> 0 | G17: =(财务基础数据!G55)*目录!$D$6 -> 0 | H17: =(财务基础数据!H55)*目录!$D$6 -> 0 | I17: =(财务基础数据!I55)*目录!$D$6 -> 0 | J17: =(财务基础数据!J55)*目录!$D$6 -> 0 | K17: =(财务基础数据!K55)*目录!$D$6 -> 0 | ... Z17: =(财务基础数据!Z55)*目录!$D$6 -> 0 | AA17: =资产预测!J54 -> 0 | AB17: =资产预测!K54 -> 0 | AC17: =资产预测!L54 -> 0 | AD17: =资产预测!M54 -> 0 | AE17: =资产预测!N54 -> 0 | AF17: =资产预测!O54 -> 0 | AG17: =资产预测!P54 -> 0 | AH17: =资产预测!Q54 -> 0 | ... AJ17: =资产预测!S54 -> 0
B18: 可供出售投资 | D18: =(财务基础数据!D56)*目录!$D$6 -> 0 | E18: =(财务基础数据!E56)*目录!$D$6 -> 0 | F18: =(财务基础数据!F56)*目录!$D$6 -> 0 | G18: =(财务基础数据!G56)*目录!$D$6 -> 0 | H18: =(财务基础数据!H56)*目录!$D$6 -> 0 | I18: =(财务基础数据!I56)*目录!$D$6 -> 0 | J18: =(财务基础数据!J56)*目录!$D$6 -> 0 | K18: =(财务基础数据!K56)*目录!$D$6 -> 0 | ... Z18: =(财务基础数据!Z56)*目录!$D$6 -> 0 | AA18: =资产预测!J57 -> 0 | AB18: =资产预测!K57 -> 0 | AC18: =资产预测!L57 -> 0 | AD18: =资产预测!M57 -> 0 | AE18: =资产预测!N57 -> 0 | AF18: =资产预测!O57 -> 0 | AG18: =资产预测!P57 -> 0 | AH18: =资产预测!Q57 -> 0 | ... AJ18: =资产预测!S57 -> 0
B19: 其他长期投资 | D19: =(财务基础数据!D57)*目录!$D$6 -> 0 | E19: =(财务基础数据!E57)*目录!$D$6 -> 0 | F19: =(财务基础数据!F57)*目录!$D$6 -> 0 | G19: =(财务基础数据!G57)*目录!$D$6 -> 0 | H19: =(财务基础数据!H57)*目录!$D$6 -> 0 | I19: =(财务基础数据!I57)*目录!$D$6 -> 0 | J19: =(财务基础数据!J57)*目录!$D$6 -> 0 | K19: =(财务基础数据!K57)*目录!$D$6 -> 0 | ... Z19: =(财务基础数据!Z57)*目录!$D$6 -> 0 | AA19: =资产预测!J74 -> 0 | AB19: =资产预测!K74 -> 0 | AC19: =资产预测!L74 -> 0 | AD19: =资产预测!M74 -> 0 | AE19: =资产预测!N74 -> 0 | AF19: =资产预测!O74 -> 0 | AG19: =资产预测!P74 -> 0 | AH19: =资产预测!Q74 -> 0 | ... AJ19: =资产预测!S74 -> 0
B20: 商誉及无形资产 | D20: =(财务基础数据!D58)*目录!$D$6 -> 0 | E20: =(财务基础数据!E58)*目录!$D$6 -> 0 | F20: =(财务基础数据!F58)*目录!$D$6 -> 0 | G20: =(财务基础数据!G58)*目录!$D$6 -> 0 | H20: =(财务基础数据!H58)*目录!$D$6 -> 0 | I20: =(财务基础数据!I58)*目录!$D$6 -> 0 | J20: =(财务基础数据!J58)*目录!$D$6 -> 0 | K20: =(财务基础数据!K58)*目录!$D$6 -> 0 | ... Z20: =(财务基础数据!Z58)*目录!$D$6 -> 0 | AA20: =资产预测!J69 -> 0 | AB20: =资产预测!K69 -> 0 | AC20: =资产预测!L69 -> 0 | AD20: =资产预测!M69 -> 0 | AE20: =资产预测!N69 -> 0 | AF20: =资产预测!O69 -> 0 | AG20: =资产预测!P69 -> 0 | AH20: =资产预测!Q69 -> 0 | ... AJ20: =资产预测!S69 -> 0
B21: 租赁土地 | D21: =(财务基础数据!D60)*目录!$D$6 -> 0 | E21: =(财务基础数据!E60)*目录!$D$6 -> 0 | F21: =(财务基础数据!F60)*目录!$D$6 -> 0 | G21: =(财务基础数据!G60)*目录!$D$6 -> 0 | H21: =(财务基础数据!H60)*目录!$D$6 -> 0 | I21: =(财务基础数据!I60)*目录!$D$6 -> 0 | J21: =(财务基础数据!J60)*目录!$D$6 -> 0 | K21: =(财务基础数据!K60)*目录!$D$6 -> 0 | ... Z21: =(财务基础数据!Z60)*目录!$D$6 -> 0 | AA21: =资产预测!J77 -> 0 | AB21: =资产预测!K77 -> 0 | AC21: =资产预测!L77 -> 0 | AD21: =资产预测!M77 -> 0 | AE21: =资产预测!N77 -> 0 | AF21: =资产预测!O77 -> 0 | AG21: =资产预测!P77 -> 0 | AH21: =资产预测!Q77 -> 0 | ... AJ21: =资产预测!S77 -> 0
B22: 其他非流动资产 | D22: =(财务基础数据!D61)*目录!$D$6 -> 0 | E22: =(财务基础数据!E61)*目录!$D$6 -> 0 | F22: =(财务基础数据!F61)*目录!$D$6 -> 0 | G22: =(财务基础数据!G61)*目录!$D$6 -> 0 | H22: =(财务基础数据!H61)*目录!$D$6 -> 0 | I22: =(财务基础数据!I61)*目录!$D$6 -> 0 | J22: =(财务基础数据!J61)*目录!$D$6 -> 0 | K22: =(财务基础数据!K61)*目录!$D$6 -> 0 | ... Z22: =(财务基础数据!Z61)*目录!$D$6 -> 0 | AA22: =IF(财务基础数据!W$2=0,W22,IF(财务基础数据!W$2=1,X22,IF(财务基础数据!W$2=2,Y22,Z22))) -> 0 | AB22: =AA22 -> 0 | AC22: =AB22 -> 0 | AD22: =AC22 -> 0 | AE22: =AD22 -> 0 | AF22: =AE22 -> 0 | AG22: =AF22 -> 0 | AH22: =AG22 -> 0 | AI22: =AH22 -> 0 | AJ22: =AI22 -> 0
B23: 非流动资产合计 | D23: =SUM(D15:D22) -> 0 | E23: =SUM(E15:E22) -> 0 | F23: =SUM(F15:F22) -> 0 | G23: =SUM(G15:G22) -> 0 | H23: =SUM(H15:H22) -> 0 | I23: =SUM(I15:I22) -> 0 | J23: =SUM(J15:J22) -> 0 | K23: =SUM(K15:K22) -> 0 | ... AJ23: =SUM(AJ15:AJ22) -> 0
B24: 资产总额 | D24: =D13+D23 -> 0 | E24: =E13+E23 -> 0 | F24: =F13+F23 -> 0 | G24: =G13+G23 -> 0 | H24: =H13+H23 -> 0 | I24: =I13+I23 -> 0 | J24: =J13+J23 -> 0 | K24: =K13+K23 -> 0 | ... Z24: =Z13+Z23 -> 0 | AA24: =IF(ISERROR(AA23+AA13),"0",AA23+AA13) -> 0 | AB24: =IF(ISERROR(AB23+AB13),"0",AB23+AB13) -> 0 | AC24: =IF(ISERROR(AC23+AC13),"0",AC23+AC13) -> 0 | AD24: =IF(ISERROR(AD23+AD13),"0",AD23+AD13) -> 0 | AE24: =IF(ISERROR(AE23+AE13),"0",AE23+AE13) -> 0 | AF24: =IF(ISERROR(AF23+AF13),"0",AF23+AF13) -> 0 | AG24: =IF(ISERROR(AG23+AG13),"0",AG23+AG13) -> 0 | AH24: =IF(ISERROR(AH23+AH13),"0",AH23+AH13) -> 0 | ... AJ24: =IF(ISERROR(AJ23+AJ13),"0",AJ23+AJ13) -> 0
B25: 资产检查： | D25: =财务基础数据!D63*目录!$D$6-D24 -> 0 | E25: =财务基础数据!E63*目录!$D$6-E24 -> 0 | F25: =财务基础数据!F63*目录!$D$6-F24 -> 0 | G25: =财务基础数据!G63*目录!$D$6-G24 -> 0 | H25: =财务基础数据!H63*目录!$D$6-H24 -> 0 | I25: =财务基础数据!I63*目录!$D$6-I24 -> 0 | J25: =财务基础数据!J63*目录!$D$6-J24 -> 0 | K25: =财务基础数据!K63*目录!$D$6-K24 -> 0 | ... Z25: =财务基础数据!Z63*目录!$D$6-Z24 -> 0
B27: 流动负债：
B28: 应付账款及票据 | D28: =(财务基础数据!D64)*目录!$D$6 -> 0 | E28: =(财务基础数据!E64)*目录!$D$6 -> 0 | F28: =(财务基础数据!F64)*目录!$D$6 -> 0 | G28: =(财务基础数据!G64)*目录!$D$6 -> 0 | H28: =(财务基础数据!H64)*目录!$D$6 -> 0 | I28: =(财务基础数据!I64)*目录!$D$6 -> 0 | J28: =(财务基础数据!J64)*目录!$D$6 -> 0 | K28: =(财务基础数据!K64)*目录!$D$6 -> 0 | ... Z28: =(财务基础数据!Z64)*目录!$D$6 -> 0 | AA28: =资产预测!J24 -> 0 | AB28: =资产预测!K24 -> 0 | AC28: =资产预测!L24 -> 0 | AD28: =资产预测!M24 -> 0 | AE28: =资产预测!N24 -> 0 | AF28: =资产预测!O24 -> 0 | AG28: =资产预测!P24 -> 0 | AH28: =资产预测!Q24 -> 0 | ... AJ28: =资产预测!S24 -> 0
B29: 应交税金 | D29: =(财务基础数据!D65)*目录!$D$6 -> 0 | E29: =(财务基础数据!E65)*目录!$D$6 -> 0 | F29: =(财务基础数据!F65)*目录!$D$6 -> 0 | G29: =(财务基础数据!G65)*目录!$D$6 -> 0 | H29: =(财务基础数据!H65)*目录!$D$6 -> 0 | I29: =(财务基础数据!I65)*目录!$D$6 -> 0 | J29: =(财务基础数据!J65)*目录!$D$6 -> 0 | K29: =(财务基础数据!K65)*目录!$D$6 -> 0 | ... Z29: =(财务基础数据!Z65)*目录!$D$6 -> 0 | AA29: =资产预测!J31 -> 0 | AB29: =资产预测!K31 -> 0 | AC29: =资产预测!L31 -> 0 | AD29: =资产预测!M31 -> 0 | AE29: =资产预测!N31 -> 0 | AF29: =资产预测!O31 -> 0 | AG29: =资产预测!P31 -> 0 | AH29: =资产预测!Q31 -> 0 | ... AJ29: =资产预测!S31 -> 0
B30: 交易性金融负债 | D30: =(财务基础数据!D66)*目录!$D$6 -> 0 | E30: =(财务基础数据!E66)*目录!$D$6 -> 0 | F30: =(财务基础数据!F66)*目录!$D$6 -> 0 | G30: =(财务基础数据!G66)*目录!$D$6 -> 0 | H30: =(财务基础数据!H66)*目录!$D$6 -> 0 | I30: =(财务基础数据!I66)*目录!$D$6 -> 0 | J30: =(财务基础数据!J66)*目录!$D$6 -> 0 | K30: =(财务基础数据!K66)*目录!$D$6 -> 0 | ... Z30: =(财务基础数据!Z66)*目录!$D$6 -> 0 | AA30: =资产预测!J46 -> 0 | AB30: =资产预测!K46 -> 0 | AC30: =资产预测!L46 -> 0 | AD30: =资产预测!M46 -> 0 | AE30: =资产预测!N46 -> 0 | AF30: =资产预测!O46 -> 0 | AG30: =资产预测!P46 -> 0 | AH30: =资产预测!Q46 -> 0 | ... AJ30: =资产预测!S46 -> 0
B31: 短期借款 | D31: =(财务基础数据!D67)*目录!$D$6 -> 0 | E31: =(财务基础数据!E67)*目录!$D$6 -> 0 | F31: =(财务基础数据!F67)*目录!$D$6 -> 0 | G31: =(财务基础数据!G67)*目录!$D$6 -> 0 | H31: =(财务基础数据!H67)*目录!$D$6 -> 0 | I31: =(财务基础数据!I67)*目录!$D$6 -> 0 | J31: =(财务基础数据!J67)*目录!$D$6 -> 0 | K31: =(财务基础数据!K67)*目录!$D$6 -> 0 | ... Z31: =(财务基础数据!Z67)*目录!$D$6 -> 0 | AA31: =资产预测!J124 -> 0 | AB31: =资产预测!K124 -> 0 | AC31: =资产预测!L124 -> 0 | AD31: =资产预测!M124 -> 0 | AE31: =资产预测!N124 -> 0 | AF31: =资产预测!O124 -> 0 | AG31: =资产预测!P124 -> 0 | AH31: =资产预测!Q124 -> 0 | ... AJ31: =资产预测!S124 -> 0
B32: 其他流动负债 | D32: =(财务基础数据!D68)*目录!$D$6 -> 0 | E32: =(财务基础数据!E68)*目录!$D$6 -> 0 | F32: =(财务基础数据!F68)*目录!$D$6 -> 0 | G32: =(财务基础数据!G68)*目录!$D$6 -> 0 | H32: =(财务基础数据!H68)*目录!$D$6 -> 0 | I32: =(财务基础数据!I68)*目录!$D$6 -> 0 | J32: =(财务基础数据!J68)*目录!$D$6 -> 0 | K32: =(财务基础数据!K68)*目录!$D$6 -> 0 | ... Z32: =(财务基础数据!Z68)*目录!$D$6 -> 0 | AA32: =资产预测!J28 -> 0 | AB32: =资产预测!K28 -> 0 | AC32: =资产预测!L28 -> 0 | AD32: =资产预测!M28 -> 0 | AE32: =资产预测!N28 -> 0 | AF32: =资产预测!O28 -> 0 | AG32: =资产预测!P28 -> 0 | AH32: =资产预测!Q28 -> 0 | ... AJ32: =资产预测!S28 -> 0
B33: 流动负债合计 | D33: =SUM(D28:D32) -> 0 | E33: =SUM(E28:E32) -> 0 | F33: =SUM(F28:F32) -> 0 | G33: =SUM(G28:G32) -> 0 | H33: =SUM(H28:H32) -> 0 | I33: =SUM(I28:I32) -> 0 | J33: =SUM(J28:J32) -> 0 | K33: =SUM(K28:K32) -> 0 | ... AJ33: =SUM(AJ28:AJ32) -> 0
B34: 非流动负债：
B35: 长期债务（长期借款、应付债券） | D35: =(财务基础数据!D70)*目录!$D$6 -> 0 | E35: =(财务基础数据!E70)*目录!$D$6 -> 0 | F35: =(财务基础数据!F70)*目录!$D$6 -> 0 | G35: =(财务基础数据!G70)*目录!$D$6 -> 0 | H35: =(财务基础数据!H70)*目录!$D$6 -> 0 | I35: =(财务基础数据!I70)*目录!$D$6 -> 0 | J35: =(财务基础数据!J70)*目录!$D$6 -> 0 | K35: =(财务基础数据!K70)*目录!$D$6 -> 0 | ... Z35: =(财务基础数据!Z70)*目录!$D$6 -> 0 | AA35: =资产预测!J117 -> 0 | AB35: =资产预测!K117 -> 0 | AC35: =资产预测!L117 -> 0 | AD35: =资产预测!M117 -> 0 | AE35: =资产预测!N117 -> 0 | AF35: =资产预测!O117 -> 0 | AG35: =资产预测!P117 -> 0 | AH35: =资产预测!Q117 -> 0 | ... AJ35: =资产预测!S117 -> 0
B36: 其他非流动负债 | D36: =(财务基础数据!D71)*目录!$D$6 -> 0 | E36: =(财务基础数据!E71)*目录!$D$6 -> 0 | F36: =(财务基础数据!F71)*目录!$D$6 -> 0 | G36: =(财务基础数据!G71)*目录!$D$6 -> 0 | H36: =(财务基础数据!H71)*目录!$D$6 -> 0 | I36: =(财务基础数据!I71)*目录!$D$6 -> 0 | J36: =(财务基础数据!J71)*目录!$D$6 -> 0 | K36: =(财务基础数据!K71)*目录!$D$6 -> 0 | ... Z36: =(财务基础数据!Z71)*目录!$D$6 -> 0 | AA36: =IF(财务基础数据!W$2=0,W36,IF(财务基础数据!W$2=1,X36,IF(财务基础数据!W$2=2,Y36,Z36))) -> 0 | AB36: =AA36 -> 0 | AC36: =AB36 -> 0 | AD36: =AC36 -> 0 | AE36: =AD36 -> 0 | AF36: =AE36 -> 0 | AG36: =AF36 -> 0 | AH36: =AG36 -> 0 | AI36: =AH36 -> 0 | AJ36: =AI36 -> 0
B37: 非流动负债合计 | D37: =SUM(D35:D36) -> 0 | E37: =SUM(E35:E36) -> 0 | F37: =SUM(F35:F36) -> 0 | G37: =SUM(G35:G36) -> 0 | H37: =SUM(H35:H36) -> 0 | I37: =SUM(I35:I36) -> 0 | J37: =SUM(J35:J36) -> 0 | K37: =SUM(K35:K36) -> 0 | ... AJ37: =SUM(AJ35:AJ36) -> 0
B38: 总负债 | D38: =D33+D37 -> 0 | E38: =E33+E37 -> 0 | F38: =F33+F37 -> 0 | G38: =G33+G37 -> 0 | H38: =H33+H37 -> 0 | I38: =I33+I37 -> 0 | J38: =J33+J37 -> 0 | K38: =K33+K37 -> 0 | ... AJ38: =AJ33+AJ37 -> 0
B39: 股东权益：
B40: 优先股 | D40: =(财务基础数据!D74)*目录!$D$6 -> 0 | E40: =(财务基础数据!E74)*目录!$D$6 -> 0 | F40: =(财务基础数据!F74)*目录!$D$6 -> 0 | G40: =(财务基础数据!G74)*目录!$D$6 -> 0 | H40: =(财务基础数据!H74)*目录!$D$6 -> 0 | I40: =(财务基础数据!I74)*目录!$D$6 -> 0 | J40: =(财务基础数据!J74)*目录!$D$6 -> 0 | K40: =(财务基础数据!K74)*目录!$D$6 -> 0 | ... Z40: =(财务基础数据!Z74)*目录!$D$6 -> 0 | AA40: =W40+资产预测!J108 -> 0 | AB40: =AA40+资产预测!K108 -> 0 | AC40: =AB40+资产预测!L108 -> 0 | AD40: =AC40+资产预测!M108 -> 0 | AE40: =AD40+资产预测!N108 -> 0 | AF40: =AE40+资产预测!O108 -> 0 | AG40: =AF40+资产预测!P108 -> 0 | AH40: =AG40+资产预测!Q108 -> 0 | AI40: =AH40+资产预测!R108 -> 0 | AJ40: =AI40+资产预测!S108 -> 0
B41: 库存股 | D41: =(财务基础数据!D80)*目录!$D$6 -> 0 | E41: =(财务基础数据!E80)*目录!$D$6 -> 0 | F41: =(财务基础数据!F80)*目录!$D$6 -> 0 | G41: =(财务基础数据!G80)*目录!$D$6 -> 0 | H41: =(财务基础数据!H80)*目录!$D$6 -> 0 | I41: =(财务基础数据!I80)*目录!$D$6 -> 0 | J41: =(财务基础数据!J80)*目录!$D$6 -> 0 | K41: =(财务基础数据!K80)*目录!$D$6 -> 0 | ... Z41: =(财务基础数据!Z80)*目录!$D$6 -> 0 | AA41: =W41+资产预测!J109 -> 0 | AB41: =AA41+资产预测!K109 -> 0 | AC41: =AB41+资产预测!L109 -> 0 | AD41: =AC41+资产预测!M109 -> 0 | AE41: =AD41+资产预测!N109 -> 0 | AF41: =AE41+资产预测!O109 -> 0 | AG41: =AF41+资产预测!P109 -> 0 | AH41: =AG41+资产预测!Q109 -> 0 | AI41: =AH41+资产预测!R109 -> 0 | AJ41: =AI41+资产预测!S109 -> 0
B42: 普通股股本 | D42: =(财务基础数据!D75)*目录!$D$6 -> 0 | E42: =(财务基础数据!E75)*目录!$D$6 -> 0 | F42: =(财务基础数据!F75)*目录!$D$6 -> 0 | G42: =(财务基础数据!G75)*目录!$D$6 -> 0 | H42: =(财务基础数据!H75)*目录!$D$6 -> 0 | I42: =(财务基础数据!I75)*目录!$D$6 -> 0 | J42: =(财务基础数据!J75)*目录!$D$6 -> 0 | K42: =(财务基础数据!K75)*目录!$D$6 -> 0 | ... Z42: =(财务基础数据!Z75)*目录!$D$6 -> 0 | AA42: =W42+资产预测!J93+资产预测!J102+资产预测!J107 -> 0 | AB42: =AA42+资产预测!K93+资产预测!K102+资产预测!K107 -> 0 | AC42: =AB42+资产预测!L93+资产预测!L102+资产预测!L107 -> 0 | AD42: =AC42+资产预测!M93+资产预测!M102+资产预测!M107 -> 0 | AE42: =AD42+资产预测!N93+资产预测!N102+资产预测!N107 -> 0 | AF42: =AE42+资产预测!O93+资产预测!O102+资产预测!O107 -> 0 | AG42: =AF42+资产预测!P93+资产预测!P102+资产预测!P107 -> 0 | AH42: =AG42+资产预测!Q93+资产预测!Q102+资产预测!Q107 -> 0 | AI42: =AH42+资产预测!R93+资产预测!R102+资产预测!R107 -> 0 | AJ42: =AI42+资产预测!S93+资产预测!S102+资产预测!S107 -> 0
B43: 储备 | D43: =(财务基础数据!D76)*目录!$D$6 -> 0 | E43: =(财务基础数据!E76)*目录!$D$6 -> 0 | F43: =(财务基础数据!F76)*目录!$D$6 -> 0 | G43: =(财务基础数据!G76)*目录!$D$6 -> 0 | H43: =(财务基础数据!H76)*目录!$D$6 -> 0 | I43: =(财务基础数据!I76)*目录!$D$6 -> 0 | J43: =(财务基础数据!J76)*目录!$D$6 -> 0 | K43: =(财务基础数据!K76)*目录!$D$6 -> 0 | ... Z43: =(财务基础数据!Z76)*目录!$D$6 -> 0 | AA43: =IF(ISERROR(W43+资产预测!J110+利润表!AA29+资产预测!J94+资产预测!J103+现金流量表!AA35),"0",W43+资产预测!J110+利润表!AA29+资产预测!J94+资产预测!J103+现金流量表!AA35) -> 0 | AB43: =IF(ISERROR(AA43+资产预测!K110+利润表!AB29+资产预测!K94+资产预测!K103+现金流量表!AB35),"0",AA43+资产预测!K110+利润表!AB29+资产预测!K94+资产预测!K103+现金流量表!AB35) -> 0 | AC43: =IF(ISERROR(AB43+资产预测!L110+利润表!AC29+资产预测!L94+资产预测!L103+现金流量表!AC35),"0",AB43+资产预测!L110+利润表!AC29+资产预测!L94+资产预测!L103+现金流量表!AC35) -> 0 | AD43: =IF(ISERROR(AC43+资产预测!M110+利润表!AD29+资产预测!M94+资产预测!M103+现金流量表!AD35),"0",AC43+资产预测!M110+利润表!AD29+资产预测!M94+资产预测!M103+现金流量表!AD35) -> 0 | AE43: =IF(ISERROR(AD43+资产预测!N110+利润表!AE29+资产预测!N94+资产预测!N103+现金流量表!AE35),"0",AD43+资产预测!N110+利润表!AE29+资产预测!N94+资产预测!N103+现金流量表!AE35) -> 0 | AF43: =IF(ISERROR(AE43+资产预测!O110+利润表!AF29+资产预测!O94+资产预测!O103+现金流量表!AF35),"0",AE43+资产预测!O110+利润表!AF29+资产预测!O94+资产预测!O103+现金流量表!AF35) -> 0 | AG43: =IF(ISERROR(AF43+资产预测!P110+利润表!AG29+资产预测!P94+资产预测!P103+现金流量表!AG35),"0",AF43+资产预测!P110+利润表!AG29+资产预测!P94+资产预测!P103+现金流量表!AG35) -> 0 | AH43: =IF(ISERROR(AG43+资产预测!Q110+利润表!AH29+资产预测!Q94+资产预测!Q103+现金流量表!AH35),"0",AG43+资产预测!Q110+利润表!AH29+资产预测!Q94+资产预测!Q103+现金流量表!AH35) -> 0 | AI43: =IF(ISERROR(AH43+资产预测!R110+利润表!AI29+资产预测!R94+资产预测!R103+现金流量表!AI35),"0",AH43+资产预测!R110+利润表!AI29+资产预测!R94+资产预测!R103+现金流量表!AI35) -> 0 | AJ43: =IF(ISERROR(AI43+资产预测!S110+利润表!AJ29+资产预测!S94+资产预测!S103+现金流量表!AJ35),"0",AI43+资产预测!S110+利润表!AJ29+资产预测!S94+资产预测!S103+现金流量表!AJ35) -> 0
B44: 其他 | D44: =(财务基础数据!D81)*目录!$D$6 -> 0 | E44: =(财务基础数据!E81)*目录!$D$6 -> 0 | F44: =(财务基础数据!F81)*目录!$D$6 -> 0 | G44: =(财务基础数据!G81)*目录!$D$6 -> 0 | H44: =(财务基础数据!H81)*目录!$D$6 -> 0 | I44: =(财务基础数据!I81)*目录!$D$6 -> 0 | J44: =(财务基础数据!J81)*目录!$D$6 -> 0 | K44: =(财务基础数据!K81)*目录!$D$6 -> 0 | ... Z44: =(财务基础数据!Z81)*目录!$D$6 -> 0 | AA44: =W44+资产预测!J111 -> 0 | AB44: =AA44+资产预测!K111 -> 0 | AC44: =AB44+资产预测!L111 -> 0 | AD44: =AC44+资产预测!M111 -> 0 | AE44: =AD44+资产预测!N111 -> 0 | AF44: =AE44+资产预测!O111 -> 0 | AG44: =AF44+资产预测!P111 -> 0 | AH44: =AG44+资产预测!Q111 -> 0 | AI44: =AH44+资产预测!R111 -> 0 | AJ44: =AI44+资产预测!S111 -> 0
B45: 归属母公司股东权益 | D45: =D40+D42+D43+D44-D41 -> 0 | E45: =E40+E42+E43+E44-E41 -> 0 | F45: =F40+F42+F43+F44-F41 -> 0 | G45: =G40+G42+G43+G44-G41 -> 0 | H45: =H40+H42+H43+H44-H41 -> 0 | I45: =I40+I42+I43+I44-I41 -> 0 | J45: =J40+J42+J43+J44-J41 -> 0 | K45: =K40+K42+K43+K44-K41 -> 0 | ... Z45: =Z40+Z42+Z43+Z44-Z41 -> 0 | AA45: =IF(ISERROR(AA40-AA41+AA42+AA43+AA44),"0",AA40-AA41+AA42+AA43+AA44) -> 0 | AB45: =IF(ISERROR(AB40-AB41+AB42+AB43+AB44),"0",AB40-AB41+AB42+AB43+AB44) -> 0 | AC45: =IF(ISERROR(AC40-AC41+AC42+AC43+AC44),"0",AC40-AC41+AC42+AC43+AC44) -> 0 | AD45: =IF(ISERROR(AD40-AD41+AD42+AD43+AD44),"0",AD40-AD41+AD42+AD43+AD44) -> 0 | AE45: =IF(ISERROR(AE40-AE41+AE42+AE43+AE44),"0",AE40-AE41+AE42+AE43+AE44) -> 0 | AF45: =IF(ISERROR(AF40-AF41+AF42+AF43+AF44),"0",AF40-AF41+AF42+AF43+AF44) -> 0 | AG45: =IF(ISERROR(AG40-AG41+AG42+AG43+AG44),"0",AG40-AG41+AG42+AG43+AG44) -> 0 | AH45: =IF(ISERROR(AH40-AH41+AH42+AH43+AH44),"0",AH40-AH41+AH42+AH43+AH44) -> 0 | ... AJ45: =IF(ISERROR(AJ40-AJ41+AJ42+AJ43+AJ44),"0",AJ40-AJ41+AJ42+AJ43+AJ44) -> 0
B46: 少数股东权益 | D46: =(财务基础数据!D84)*目录!$D$6 -> 0 | E46: =(财务基础数据!E84)*目录!$D$6 -> 0 | F46: =(财务基础数据!F84)*目录!$D$6 -> 0 | G46: =(财务基础数据!G84)*目录!$D$6 -> 0 | H46: =(财务基础数据!H84)*目录!$D$6 -> 0 | I46: =(财务基础数据!I84)*目录!$D$6 -> 0 | J46: =(财务基础数据!J84)*目录!$D$6 -> 0 | K46: =(财务基础数据!K84)*目录!$D$6 -> 0 | ... Z46: =(财务基础数据!Z84)*目录!$D$6 -> 0 | AA46: =IF(ISERROR(W46+利润表!AA27),"0",W46+利润表!AA27) -> 0 | AB46: =IF(ISERROR(AA46+利润表!AB27),"0",AA46+利润表!AB27) -> 0 | AC46: =IF(ISERROR(AB46+利润表!AC27),"0",AB46+利润表!AC27) -> 0 | AD46: =IF(ISERROR(AC46+利润表!AD27),"0",AC46+利润表!AD27) -> 0 | AE46: =IF(ISERROR(AD46+利润表!AE27),"0",AD46+利润表!AE27) -> 0 | AF46: =IF(ISERROR(AE46+利润表!AF27),"0",AE46+利润表!AF27) -> 0 | AG46: =IF(ISERROR(AF46+利润表!AG27),"0",AF46+利润表!AG27) -> 0 | AH46: =IF(ISERROR(AG46+利润表!AH27),"0",AG46+利润表!AH27) -> 0 | AI46: =IF(ISERROR(AH46+利润表!AI27),"0",AH46+利润表!AI27) -> 0 | AJ46: =IF(ISERROR(AI46+利润表!AJ27),"0",AI46+利润表!AJ27) -> 0
B47: 股东权益合计 | D47: =D45+D46 -> 0 | E47: =E45+E46 -> 0 | F47: =F45+F46 -> 0 | G47: =G45+G46 -> 0 | H47: =H45+H46 -> 0 | I47: =I45+I46 -> 0 | J47: =J45+J46 -> 0 | K47: =K45+K46 -> 0 | ... Z47: =Z45+Z46 -> 0 | AA47: =IF(ISERROR(AA45+AA46),"0",AA45+AA46) -> 0 | AB47: =IF(ISERROR(AB45+AB46),"0",AB45+AB46) -> 0 | AC47: =IF(ISERROR(AC45+AC46),"0",AC45+AC46) -> 0 | AD47: =IF(ISERROR(AD45+AD46),"0",AD45+AD46) -> 0 | AE47: =IF(ISERROR(AE45+AE46),"0",AE45+AE46) -> 0 | AF47: =IF(ISERROR(AF45+AF46),"0",AF45+AF46) -> 0 | AG47: =IF(ISERROR(AG45+AG46),"0",AG45+AG46) -> 0 | AH47: =IF(ISERROR(AH45+AH46),"0",AH45+AH46) -> 0 | ... AJ47: =IF(ISERROR(AJ45+AJ46),"0",AJ45+AJ46) -> 0
B48: 负债及股东权益合计 | D48: =D38+D47 -> 0 | E48: =E38+E47 -> 0 | F48: =F38+F47 -> 0 | G48: =G38+G47 -> 0 | H48: =H38+H47 -> 0 | I48: =I38+I47 -> 0 | J48: =J38+J47 -> 0 | K48: =K38+K47 -> 0 | ... Z48: =Z38+Z47 -> 0 | AA48: =IF(ISERROR(AA38+AA47),"0",AA38+AA47) -> 0 | AB48: =IF(ISERROR(AB38+AB47),"0",AB38+AB47) -> 0 | AC48: =IF(ISERROR(AC38+AC47),"0",AC38+AC47) -> 0 | AD48: =IF(ISERROR(AD38+AD47),"0",AD38+AD47) -> 0 | AE48: =IF(ISERROR(AE38+AE47),"0",AE38+AE47) -> 0 | AF48: =IF(ISERROR(AF38+AF47),"0",AF38+AF47) -> 0 | AG48: =IF(ISERROR(AG38+AG47),"0",AG38+AG47) -> 0 | AH48: =IF(ISERROR(AH38+AH47),"0",AH38+AH47) -> 0 | ... AJ48: =IF(ISERROR(AJ38+AJ47),"0",AJ38+AJ47) -> 0
B49: 负债检查： | D49: =财务基础数据!D73*目录!$D$6-资产负债表!D38 -> 0 | E49: =财务基础数据!E73*目录!$D$6-资产负债表!E38 -> 0 | F49: =财务基础数据!F73*目录!$D$6-资产负债表!F38 -> 0 | G49: =财务基础数据!G73*目录!$D$6-资产负债表!G38 -> 0 | H49: =财务基础数据!H73*目录!$D$6-资产负债表!H38 -> 0 | I49: =财务基础数据!I73*目录!$D$6-资产负债表!I38 -> 0 | J49: =财务基础数据!J73*目录!$D$6-资产负债表!J38 -> 0 | K49: =财务基础数据!K73*目录!$D$6-资产负债表!K38 -> 0 | ... Z49: =财务基础数据!Z73*目录!$D$6-资产负债表!Z38 -> 0
B50: 权益检查： | D50: =财务基础数据!D85*目录!$D$6-资产负债表!D47 -> 0 | E50: =财务基础数据!E85*目录!$D$6-资产负债表!E47 -> 0 | F50: =财务基础数据!F85*目录!$D$6-资产负债表!F47 -> 0 | G50: =财务基础数据!G85*目录!$D$6-资产负债表!G47 -> 0 | H50: =财务基础数据!H85*目录!$D$6-资产负债表!H47 -> 0 | I50: =财务基础数据!I85*目录!$D$6-资产负债表!I47 -> 0 | J50: =财务基础数据!J85*目录!$D$6-资产负债表!J47 -> 0 | K50: =财务基础数据!K85*目录!$D$6-资产负债表!K47 -> 0 | ... Z50: =财务基础数据!Z85*目录!$D$6-资产负债表!Z47 -> 0
B51: 检查： | D51: =D24-D48 -> 0 | E51: =E24-E48 -> 0 | F51: =F24-F48 -> 0 | G51: =G24-G48 -> 0 | H51: =H24-H48 -> 0 | I51: =I24-I48 -> 0 | J51: =J24-J48 -> 0 | K51: =K24-K48 -> 0 | ... AJ51: =AJ24-AJ48 -> 0
B53: 营运资本 | D53: =D13-D6-D7-D33+D30+D31 -> 0 | E53: =E13-E6-E7-E33+E30+E31 -> 0 | F53: =F13-F6-F7-F33+F30+F31 -> 0 | G53: =G13-G6-G7-G33+G30+G31 -> 0 | H53: =H13-H6-H7-H33+H30+H31 -> 0 | I53: =I13-I6-I7-I33+I30+I31 -> 0 | J53: =J13-J6-J7-J33+J30+J31 -> 0 | K53: =K13-K6-K7-K33+K30+K31 -> 0 | ... AJ53: =AJ13-AJ6-AJ7-AJ33+AJ30+AJ31 -> 0
B54: 资产负债率 | D54: =IF(ISERROR(D38/D24),"—",D38/D24) -> — | E54: =IF(ISERROR(E38/E24),"—",E38/E24) -> — | F54: =IF(ISERROR(F38/F24),"—",F38/F24) -> — | G54: =IF(ISERROR(G38/G24),"—",G38/G24) -> — | H54: =IF(ISERROR(H38/H24),"—",H38/H24) -> — | I54: =IF(ISERROR(I38/I24),"—",I38/I24) -> — | J54: =IF(ISERROR(J38/J24),"—",J38/J24) -> — | K54: =IF(ISERROR(K38/K24),"—",K38/K24) -> — | ... AJ54: =IF(ISERROR(AJ38/AJ24),"—",AJ38/AJ24) -> —
B55: 付息债务 | D55: =D31+D35 -> 0 | E55: =E31+E35 -> 0 | F55: =F31+F35 -> 0 | G55: =G31+G35 -> 0 | H55: =H31+H35 -> 0 | I55: =I31+I35 -> 0 | J55: =J31+J35 -> 0 | K55: =K31+K35 -> 0 | ... AJ55: =AJ31+AJ35 -> 0
B56: 有息负债率 | D56: =IF(ISERROR(D55/D38),"—",D55/D38) -> — | E56: =IF(ISERROR(E55/E38),"—",E55/E38) -> — | F56: =IF(ISERROR(F55/F38),"—",F55/F38) -> — | G56: =IF(ISERROR(G55/G38),"—",G55/G38) -> — | H56: =IF(ISERROR(H55/H38),"—",H55/H38) -> — | I56: =IF(ISERROR(I55/I38),"—",I55/I38) -> — | J56: =IF(ISERROR(J55/J38),"—",J55/J38) -> — | K56: =IF(ISERROR(K55/K38),"—",K55/K38) -> — | ... AJ56: =IF(ISERROR(AJ55/AJ38),"—",AJ55/AJ38) -> —
B57: 非核心资产 | D57: =D6+D7+D16+D17+D18+D19 -> 0 | E57: =E6+E7+E16+E17+E18+E19 -> 0 | F57: =F6+F7+F16+F17+F18+F19 -> 0 | G57: =G6+G7+G16+G17+G18+G19 -> 0 | H57: =H6+H7+H16+H17+H18+H19 -> 0 | I57: =I6+I7+I16+I17+I18+I19 -> 0 | J57: =J6+J7+J16+J17+J18+J19 -> 0 | K57: =K6+K7+K16+K17+K18+K19 -> 0 | ... AJ57: =AJ6+AJ7+AJ16+AJ17+AJ18+AJ19 -> 0
B58: 投入资本IC | D58: =D55+D47 -> 0 | E58: =E55+E47 -> 0 | F58: =F55+F47 -> 0 | G58: =G55+G47 -> 0 | H58: =H55+H47 -> 0 | I58: =I55+I47 -> 0 | J58: =J55+J47 -> 0 | K58: =K55+K47 -> 0 | ... AJ58: =AJ55+AJ47 -> 0

Sheet 利润表
B2: 利润表
B3: =主要财务摘要!H2 -> 单位：港币(百万)
B4: 报告期间： | D4: =资产负债表!D4 -> 1Q17 | E4: =资产负债表!E4 -> 1H17 | F4: =资产负债表!F4 -> 3Q17 | G4: =资产负债表!G4 -> 2017 | H4: =资产负债表!H4 -> 1Q18 | I4: =资产负债表!I4 -> 1H18 | J4: =资产负债表!J4 -> 3Q18 | K4: =资产负债表!K4 -> 2018 | ... AJ4: =资产负债表!AJ4 -> 2031
B5: 营业总收入 | D5: =D6+D7 -> 0 | E5: =E6+E7 -> 0 | F5: =F6+F7 -> 0 | G5: =G6+G7 -> 0 | H5: =H6+H7 -> 0 | I5: =I6+I7 -> 0 | J5: =J6+J7 -> 0 | K5: =K6+K7 -> 0 | ... AJ5: =AJ6+AJ7 -> 0
B6: 营业收入 | D6: =(财务基础数据!D7)*目录!$D$6 -> 0 | E6: =(财务基础数据!E7)*目录!$D$6 -> 0 | F6: =(财务基础数据!F7)*目录!$D$6 -> 0 | G6: =(财务基础数据!G7)*目录!$D$6 -> 0 | H6: =(财务基础数据!H7)*目录!$D$6 -> 0 | I6: =(财务基础数据!I7)*目录!$D$6 -> 0 | J6: =(财务基础数据!J7)*目录!$D$6 -> 0 | K6: =(财务基础数据!K7)*目录!$D$6 -> 0 | ... Z6: =(财务基础数据!Z7)*目录!$D$6 -> 0 | AA6: =销售预测!J4 -> 0 | AB6: =销售预测!K4 -> 0 | AC6: =销售预测!L4 -> 0 | AD6: =销售预测!M4 -> 0 | AE6: =销售预测!N4 -> 0 | AF6: =销售预测!O4 -> 0 | AG6: =销售预测!P4 -> 0 | AH6: =销售预测!Q4 -> 0 | ... AJ6: =销售预测!S4 -> 0
B7: 其他收入 | D7: =(财务基础数据!D8)*目录!$D$6 -> 0 | E7: =(财务基础数据!E8)*目录!$D$6 -> 0 | F7: =(财务基础数据!F8)*目录!$D$6 -> 0 | G7: =(财务基础数据!G8)*目录!$D$6 -> 0 | H7: =(财务基础数据!H8)*目录!$D$6 -> 0 | I7: =(财务基础数据!I8)*目录!$D$6 -> 0 | J7: =(财务基础数据!J8)*目录!$D$6 -> 0 | K7: =(财务基础数据!K8)*目录!$D$6 -> 0 | ... Z7: =(财务基础数据!Z8)*目录!$D$6 -> 0 | AA7: =销售预测!J6 -> 0 | AB7: =销售预测!K6 -> 0 | AC7: =销售预测!L6 -> 0 | AD7: =销售预测!M6 -> 0 | AE7: =销售预测!N6 -> 0 | AF7: =销售预测!O6 -> 0 | AG7: =销售预测!P6 -> 0 | AH7: =销售预测!Q6 -> 0 | ... AJ7: =销售预测!S6 -> 0
B8: 营业总支出 | D8: =利润表!D9+利润表!D10 -> 0 | E8: =利润表!E9+利润表!E10 -> 0 | F8: =利润表!F9+利润表!F10 -> 0 | G8: =利润表!G9+利润表!G10 -> 0 | H8: =利润表!H9+利润表!H10 -> 0 | I8: =利润表!I9+利润表!I10 -> 0 | J8: =利润表!J9+利润表!J10 -> 0 | K8: =利润表!K9+利润表!K10 -> 0 | ... Z8: =利润表!Z9+利润表!Z10 -> 0 | AA8: =AA9+AA10 -> 0 | AB8: =AB9+AB10 -> 0 | AC8: =AC9+AC10 -> 0 | AD8: =AD9+AD10 -> 0 | AE8: =AE9+AE10 -> 0 | AF8: =AF9+AF10 -> 0 | AG8: =AG9+AG10 -> 0 | AH8: =AH9+AH10 -> 0 | ... AJ8: =AJ9+AJ10 -> 0
B9: 营业成本 | D9: =(财务基础数据!D10)*目录!$D$6 -> 0 | E9: =(财务基础数据!E10)*目录!$D$6 -> 0 | F9: =(财务基础数据!F10)*目录!$D$6 -> 0 | G9: =(财务基础数据!G10)*目录!$D$6 -> 0 | H9: =(财务基础数据!H10)*目录!$D$6 -> 0 | I9: =(财务基础数据!I10)*目录!$D$6 -> 0 | J9: =(财务基础数据!J10)*目录!$D$6 -> 0 | K9: =(财务基础数据!K10)*目录!$D$6 -> 0 | ... Z9: =(财务基础数据!Z10)*目录!$D$6 -> 0 | AA9: =销售预测!J7 -> 0 | AB9: =销售预测!K7 -> 0 | AC9: =销售预测!L7 -> 0 | AD9: =销售预测!M7 -> 0 | AE9: =销售预测!N7 -> 0 | AF9: =销售预测!O7 -> 0 | AG9: =销售预测!P7 -> 0 | AH9: =销售预测!Q7 -> 0 | ... AJ9: =销售预测!S7 -> 0
B10: 营业开支： | D10: =财务基础数据!D11*目录!$D$6 -> 0 | E10: =财务基础数据!E11*目录!$D$6 -> 0 | F10: =财务基础数据!F11*目录!$D$6 -> 0 | G10: =财务基础数据!G11*目录!$D$6 -> 0 | H10: =财务基础数据!H11*目录!$D$6 -> 0 | I10: =财务基础数据!I11*目录!$D$6 -> 0 | J10: =财务基础数据!J11*目录!$D$6 -> 0 | K10: =财务基础数据!K11*目录!$D$6 -> 0 | ... Z10: =财务基础数据!Z11*目录!$D$6 -> 0 | AA10: =AA11+AA14+AA15 -> 0 | AB10: =AB11+AB14+AB15 -> 0 | AC10: =AC11+AC14+AC15 -> 0 | AD10: =AD11+AD14+AD15 -> 0 | AE10: =AE11+AE14+AE15 -> 0 | AF10: =AF11+AF14+AF15 -> 0 | AG10: =AG11+AG14+AG15 -> 0 | AH10: =AH11+AH14+AH15 -> 0 | ... AJ10: =AJ11+AJ14+AJ15 -> 0
B11: 一般费用： | D11: =(财务基础数据!D12)*目录!$D$6 -> 0 | E11: =(财务基础数据!E12)*目录!$D$6 -> 0 | F11: =(财务基础数据!F12)*目录!$D$6 -> 0 | G11: =(财务基础数据!G12)*目录!$D$6 -> 0 | H11: =(财务基础数据!H12)*目录!$D$6 -> 0 | I11: =(财务基础数据!I12)*目录!$D$6 -> 0 | J11: =(财务基础数据!J12)*目录!$D$6 -> 0 | K11: =(财务基础数据!K12)*目录!$D$6 -> 0 | ... Z11: =(财务基础数据!Z12)*目录!$D$6 -> 0 | AA11: =AA12+AA13 -> 0 | AB11: =AB12+AB13 -> 0 | AC11: =AC12+AC13 -> 0 | AD11: =AD12+AD13 -> 0 | AE11: =AE12+AE13 -> 0 | AF11: =AF12+AF13 -> 0 | AG11: =AG12+AG13 -> 0 | AH11: =AH12+AH13 -> 0 | ... AJ11: =AJ12+AJ13 -> 0
B12: 销售费用 | D12: =(财务基础数据!D13)*目录!$D$6 -> 0 | E12: =(财务基础数据!E13)*目录!$D$6 -> 0 | F12: =(财务基础数据!F13)*目录!$D$6 -> 0 | G12: =(财务基础数据!G13)*目录!$D$6 -> 0 | H12: =(财务基础数据!H13)*目录!$D$6 -> 0 | I12: =(财务基础数据!I13)*目录!$D$6 -> 0 | J12: =(财务基础数据!J13)*目录!$D$6 -> 0 | K12: =(财务基础数据!K13)*目录!$D$6 -> 0 | ... Z12: =(财务基础数据!Z13)*目录!$D$6 -> 0 | AA12: =销售预测!J15 -> 0 | AB12: =销售预测!K15 -> 0 | AC12: =销售预测!L15 -> 0 | AD12: =销售预测!M15 -> 0 | AE12: =销售预测!N15 -> 0 | AF12: =销售预测!O15 -> 0 | AG12: =销售预测!P15 -> 0 | AH12: =销售预测!Q15 -> 0 | ... AJ12: =销售预测!S15 -> 0
B13: 管理费用 | D13: =(财务基础数据!D14)*目录!$D$6 -> 0 | E13: =(财务基础数据!E14)*目录!$D$6 -> 0 | F13: =(财务基础数据!F14)*目录!$D$6 -> 0 | G13: =(财务基础数据!G14)*目录!$D$6 -> 0 | H13: =(财务基础数据!H14)*目录!$D$6 -> 0 | I13: =(财务基础数据!I14)*目录!$D$6 -> 0 | J13: =(财务基础数据!J14)*目录!$D$6 -> 0 | K13: =(财务基础数据!K14)*目录!$D$6 -> 0 | ... Z13: =(财务基础数据!Z14)*目录!$D$6 -> 0 | AA13: =销售预测!J18 -> 0 | AB13: =销售预测!K18 -> 0 | AC13: =销售预测!L18 -> 0 | AD13: =销售预测!M18 -> 0 | AE13: =销售预测!N18 -> 0 | AF13: =销售预测!O18 -> 0 | AG13: =销售预测!P18 -> 0 | AH13: =销售预测!Q18 -> 0 | ... AJ13: =销售预测!S18 -> 0
B14: 研发费用 | D14: =(财务基础数据!D15)*目录!$D$6 -> 0 | E14: =(财务基础数据!E15)*目录!$D$6 -> 0 | F14: =(财务基础数据!F15)*目录!$D$6 -> 0 | G14: =(财务基础数据!G15)*目录!$D$6 -> 0 | H14: =(财务基础数据!H15)*目录!$D$6 -> 0 | I14: =(财务基础数据!I15)*目录!$D$6 -> 0 | J14: =(财务基础数据!J15)*目录!$D$6 -> 0 | K14: =(财务基础数据!K15)*目录!$D$6 -> 0 | ... Z14: =(财务基础数据!Z15)*目录!$D$6 -> 0 | AA14: =销售预测!J21 -> 0 | AB14: =销售预测!K21 -> 0 | AC14: =销售预测!L21 -> 0 | AD14: =销售预测!M21 -> 0 | AE14: =销售预测!N21 -> 0 | AF14: =销售预测!O21 -> 0 | AG14: =销售预测!P21 -> 0 | AH14: =销售预测!Q21 -> 0 | ... AJ14: =销售预测!S21 -> 0
B15: 其他费用 | D15: =(财务基础数据!D16)*目录!$D$6 -> 0 | E15: =(财务基础数据!E16)*目录!$D$6 -> 0 | F15: =(财务基础数据!F16)*目录!$D$6 -> 0 | G15: =(财务基础数据!G16)*目录!$D$6 -> 0 | H15: =(财务基础数据!H16)*目录!$D$6 -> 0 | I15: =(财务基础数据!I16)*目录!$D$6 -> 0 | J15: =(财务基础数据!J16)*目录!$D$6 -> 0 | K15: =(财务基础数据!K16)*目录!$D$6 -> 0 | ... Z15: =(财务基础数据!Z16)*目录!$D$6 -> 0 | AA15: =销售预测!J24 -> 0 | AB15: =销售预测!K24 -> 0 | AC15: =销售预测!L24 -> 0 | AD15: =销售预测!M24 -> 0 | AE15: =销售预测!N24 -> 0 | AF15: =销售预测!O24 -> 0 | AG15: =销售预测!P24 -> 0 | AH15: =销售预测!Q24 -> 0 | ... AJ15: =销售预测!S24 -> 0
B16: 毛利 | D16: =(财务基础数据!D18)*目录!$D$6 -> 0 | E16: =(财务基础数据!E18)*目录!$D$6 -> 0 | F16: =(财务基础数据!F18)*目录!$D$6 -> 0 | G16: =(财务基础数据!G18)*目录!$D$6 -> 0 | H16: =(财务基础数据!H18)*目录!$D$6 -> 0 | I16: =(财务基础数据!I18)*目录!$D$6 -> 0 | J16: =(财务基础数据!J18)*目录!$D$6 -> 0 | K16: =(财务基础数据!K18)*目录!$D$6 -> 0 | ... Z16: =(财务基础数据!Z18)*目录!$D$6 -> 0 | AA16: =销售预测!J9 -> 0 | AB16: =销售预测!K9 -> 0 | AC16: =销售预测!L9 -> 0 | AD16: =销售预测!M9 -> 0 | AE16: =销售预测!N9 -> 0 | AF16: =销售预测!O9 -> 0 | AG16: =销售预测!P9 -> 0 | AH16: =销售预测!Q9 -> 0 | ... AJ16: =销售预测!S9 -> 0
B17: 营业利润 | D17: =财务基础数据!D17*目录!$D$6 -> 0 | E17: =财务基础数据!E17*目录!$D$6 -> 0 | F17: =财务基础数据!F17*目录!$D$6 -> 0 | G17: =财务基础数据!G17*目录!$D$6 -> 0 | H17: =财务基础数据!H17*目录!$D$6 -> 0 | I17: =财务基础数据!I17*目录!$D$6 -> 0 | J17: =财务基础数据!J17*目录!$D$6 -> 0 | K17: =财务基础数据!K17*目录!$D$6 -> 0 | ... Z17: =财务基础数据!Z17*目录!$D$6 -> 0 | AA17: =AA5-AA8 -> 0 | AB17: =AB5-AB8 -> 0 | AC17: =AC5-AC8 -> 0 | AD17: =AD5-AD8 -> 0 | AE17: =AE5-AE8 -> 0 | AF17: =AF5-AF8 -> 0 | AG17: =AG5-AG8 -> 0 | AH17: =AH5-AH8 -> 0 | ... AJ17: =AJ5-AJ8 -> 0
B18: 利息收入 | D18: =(财务基础数据!D19)*目录!$D$6 -> 0 | E18: =(财务基础数据!E19)*目录!$D$6 -> 0 | F18: =(财务基础数据!F19)*目录!$D$6 -> 0 | G18: =(财务基础数据!G19)*目录!$D$6 -> 0 | H18: =(财务基础数据!H19)*目录!$D$6 -> 0 | I18: =(财务基础数据!I19)*目录!$D$6 -> 0 | J18: =(财务基础数据!J19)*目录!$D$6 -> 0 | K18: =(财务基础数据!K19)*目录!$D$6 -> 0 | ... Z18: =(财务基础数据!Z19)*目录!$D$6 -> 0 | AA18: =资产预测!J132 -> 0 | AB18: =资产预测!K132 -> 0 | AC18: =资产预测!L132 -> 0 | AD18: =资产预测!M132 -> 0 | AE18: =资产预测!N132 -> 0 | AF18: =资产预测!O132 -> 0 | AG18: =资产预测!P132 -> 0 | AH18: =资产预测!Q132 -> 0 | ... AJ18: =资产预测!S132 -> 0
B19: 利息支出 | D19: =(财务基础数据!D20)*目录!$D$6 -> 0 | E19: =(财务基础数据!E20)*目录!$D$6 -> 0 | F19: =(财务基础数据!F20)*目录!$D$6 -> 0 | G19: =(财务基础数据!G20)*目录!$D$6 -> 0 | H19: =(财务基础数据!H20)*目录!$D$6 -> 0 | I19: =(财务基础数据!I20)*目录!$D$6 -> 0 | J19: =(财务基础数据!J20)*目录!$D$6 -> 0 | K19: =(财务基础数据!K20)*目录!$D$6 -> 0 | ... Z19: =(财务基础数据!Z20)*目录!$D$6 -> 0 | AA19: =资产预测!J128 -> 0 | AB19: =资产预测!K128 -> 0 | AC19: =资产预测!L128 -> 0 | AD19: =资产预测!M128 -> 0 | AE19: =资产预测!N128 -> 0 | AF19: =资产预测!O128 -> 0 | AG19: =资产预测!P128 -> 0 | AH19: =资产预测!Q128 -> 0 | ... AJ19: =资产预测!S128 -> 0
B20: 权益性投资损益 | D20: =(财务基础数据!D21)*目录!$D$6 -> 0 | E20: =(财务基础数据!E21)*目录!$D$6 -> 0 | F20: =(财务基础数据!F21)*目录!$D$6 -> 0 | G20: =(财务基础数据!G21)*目录!$D$6 -> 0 | H20: =(财务基础数据!H21)*目录!$D$6 -> 0 | I20: =(财务基础数据!I21)*目录!$D$6 -> 0 | J20: =(财务基础数据!J21)*目录!$D$6 -> 0 | K20: =(财务基础数据!K21)*目录!$D$6 -> 0 | ... Z20: =(财务基础数据!Z21)*目录!$D$6 -> 0 | AA20: =销售预测!J27 -> 0 | AB20: =销售预测!K27 -> 0 | AC20: =销售预测!L27 -> 0 | AD20: =销售预测!M27 -> 0 | AE20: =销售预测!N27 -> 0 | AF20: =销售预测!O27 -> 0 | AG20: =销售预测!P27 -> 0 | AH20: =销售预测!Q27 -> 0 | ... AJ20: =销售预测!S27 -> 0
B21: 其他非经营性损益 | D21: =财务基础数据!D36*目录!$D$6 -> 0 | E21: =财务基础数据!E36*目录!$D$6 -> 0 | F21: =财务基础数据!F36*目录!$D$6 -> 0 | G21: =财务基础数据!G36*目录!$D$6 -> 0 | H21: =财务基础数据!H36*目录!$D$6 -> 0 | I21: =财务基础数据!I36*目录!$D$6 -> 0 | J21: =财务基础数据!J36*目录!$D$6 -> 0 | K21: =财务基础数据!K36*目录!$D$6 -> 0 | ... Z21: =财务基础数据!Z36*目录!$D$6 -> 0 | AA21: =销售预测!J30 -> 0 | AB21: =销售预测!K30 -> 0 | AC21: =销售预测!L30 -> 0 | AD21: =销售预测!M30 -> 0 | AE21: =销售预测!N30 -> 0 | AF21: =销售预测!O30 -> 0 | AG21: =销售预测!P30 -> 0 | AH21: =销售预测!Q30 -> 0 | ... AJ21: =销售预测!S30 -> 0
B22: 非经常项目前利润 | D22: =财务基础数据!D33*目录!$D$6 -> 0 | E22: =财务基础数据!E33*目录!$D$6 -> 0 | F22: =财务基础数据!F33*目录!$D$6 -> 0 | G22: =财务基础数据!G33*目录!$D$6 -> 0 | H22: =财务基础数据!H33*目录!$D$6 -> 0 | I22: =财务基础数据!I33*目录!$D$6 -> 0 | J22: =财务基础数据!J33*目录!$D$6 -> 0 | K22: =财务基础数据!K33*目录!$D$6 -> 0 | ... Z22: =财务基础数据!Z33*目录!$D$6 -> 0 | AA22: =AA17+AA18-AA19+AA20+AA21 -> 0 | AB22: =AB17+AB18-AB19+AB20+AB21 -> 0 | AC22: =AC17+AC18-AC19+AC20+AC21 -> 0 | AD22: =AD17+AD18-AD19+AD20+AD21 -> 0 | AE22: =AE17+AE18-AE19+AE20+AE21 -> 0 | AF22: =AF17+AF18-AF19+AF20+AF21 -> 0 | AG22: =AG17+AG18-AG19+AG20+AG21 -> 0 | AH22: =AH17+AH18-AH19+AH20+AH21 -> 0 | ... AJ22: =AJ17+AJ18-AJ19+AJ20+AJ21 -> 0
B23: 非经常项目损益 | D23: =财务基础数据!D34*目录!$D$6 -> 0 | E23: =财务基础数据!E34*目录!$D$6 -> 0 | F23: =财务基础数据!F34*目录!$D$6 -> 0 | G23: =财务基础数据!G34*目录!$D$6 -> 0 | H23: =财务基础数据!H34*目录!$D$6 -> 0 | I23: =财务基础数据!I34*目录!$D$6 -> 0 | J23: =财务基础数据!J34*目录!$D$6 -> 0 | K23: =财务基础数据!K34*目录!$D$6 -> 0 | ... Z23: =财务基础数据!Z34*目录!$D$6 -> 0 | AA23: =IF(财务基础数据!W$2=0,W23,IF(财务基础数据!W$2=1,X23,IF(财务基础数据!W$2=2,Y23,Z23))) -> 0 | AB23: =AA23 -> 0 | AC23: =AB23 -> 0 | AD23: =AC23 -> 0 | AE23: =AD23 -> 0 | AF23: =AE23 -> 0 | AG23: =AF23 -> 0 | AH23: =AG23 -> 0 | AI23: =AH23 -> 0 | AJ23: =AI23 -> 0
B24: 除税前利润 | D24: =(财务基础数据!D23)*目录!$D$6 -> 0 | E24: =(财务基础数据!E23)*目录!$D$6 -> 0 | F24: =(财务基础数据!F23)*目录!$D$6 -> 0 | G24: =(财务基础数据!G23)*目录!$D$6 -> 0 | H24: =(财务基础数据!H23)*目录!$D$6 -> 0 | I24: =(财务基础数据!I23)*目录!$D$6 -> 0 | J24: =(财务基础数据!J23)*目录!$D$6 -> 0 | K24: =(财务基础数据!K23)*目录!$D$6 -> 0 | ... Z24: =(财务基础数据!Z23)*目录!$D$6 -> 0 | AA24: =AA22+AA23 -> 0 | AB24: =AB22+AB23 -> 0 | AC24: =AC22+AC23 -> 0 | AD24: =AD22+AD23 -> 0 | AE24: =AE22+AE23 -> 0 | AF24: =AF22+AF23 -> 0 | AG24: =AG22+AG23 -> 0 | AH24: =AH22+AH23 -> 0 | ... AJ24: =AJ22+AJ23 -> 0
B25: 所得税支出 | D25: =(财务基础数据!D24)*目录!$D$6 -> 0 | E25: =(财务基础数据!E24)*目录!$D$6 -> 0 | F25: =(财务基础数据!F24)*目录!$D$6 -> 0 | G25: =(财务基础数据!G24)*目录!$D$6 -> 0 | H25: =(财务基础数据!H24)*目录!$D$6 -> 0 | I25: =(财务基础数据!I24)*目录!$D$6 -> 0 | J25: =(财务基础数据!J24)*目录!$D$6 -> 0 | K25: =(财务基础数据!K24)*目录!$D$6 -> 0 | ... Z25: =(财务基础数据!Z24)*目录!$D$6 -> 0 | AA25: =销售预测!J33 -> 0 | AB25: =销售预测!K33 -> 0 | AC25: =销售预测!L33 -> 0 | AD25: =销售预测!M33 -> 0 | AE25: =销售预测!N33 -> 0 | AF25: =销售预测!O33 -> 0 | AG25: =销售预测!P33 -> 0 | AH25: =销售预测!Q33 -> 0 | ... AJ25: =销售预测!S33 -> 0
B26: 净利润(含少数股东损益) | D26: =D24-D25 -> 0 | E26: =E24-E25 -> 0 | F26: =F24-F25 -> 0 | G26: =G24-G25 -> 0 | H26: =H24-H25 -> 0 | I26: =I24-I25 -> 0 | J26: =J24-J25 -> 0 | K26: =K24-K25 -> 0 | ... AJ26: =AJ24-AJ25 -> 0
B27: 少数股东损益 | D27: =(财务基础数据!D25)*目录!$D$6 -> 0 | E27: =(财务基础数据!E25)*目录!$D$6 -> 0 | F27: =(财务基础数据!F25)*目录!$D$6 -> 0 | G27: =(财务基础数据!G25)*目录!$D$6 -> 0 | H27: =(财务基础数据!H25)*目录!$D$6 -> 0 | I27: =(财务基础数据!I25)*目录!$D$6 -> 0 | J27: =(财务基础数据!J25)*目录!$D$6 -> 0 | K27: =(财务基础数据!K25)*目录!$D$6 -> 0 | ... Z27: =(财务基础数据!Z25)*目录!$D$6 -> 0 | AA27: =销售预测!J36 -> 0 | AB27: =销售预测!K36 -> 0 | AC27: =销售预测!L36 -> 0 | AD27: =销售预测!M36 -> 0 | AE27: =销售预测!N36 -> 0 | AF27: =销售预测!O36 -> 0 | AG27: =销售预测!P36 -> 0 | AH27: =销售预测!Q36 -> 0 | ... AJ27: =销售预测!S36 -> 0
B28: 非持续经营净利润 | D28: =财务基础数据!D37*目录!$D$6 -> 0 | E28: =财务基础数据!E37*目录!$D$6 -> 0 | F28: =财务基础数据!F37*目录!$D$6 -> 0 | G28: =财务基础数据!G37*目录!$D$6 -> 0 | H28: =财务基础数据!H37*目录!$D$6 -> 0 | I28: =财务基础数据!I37*目录!$D$6 -> 0 | J28: =财务基础数据!J37*目录!$D$6 -> 0 | K28: =财务基础数据!K37*目录!$D$6 -> 0 | ... Z28: =财务基础数据!Z37*目录!$D$6 -> 0 | AA28: =IF(财务基础数据!W$2=0,W28,IF(财务基础数据!W$2=1,X28,IF(财务基础数据!W$2=2,Y28,Z28))) -> 0 | AB28: =AA28 -> 0 | AC28: =AB28 -> 0 | AD28: =AC28 -> 0 | AE28: =AD28 -> 0 | AF28: =AE28 -> 0 | AG28: =AF28 -> 0 | AH28: =AG28 -> 0 | AI28: =AH28 -> 0 | AJ28: =AI28 -> 0
B29: 净利润 | D29: =财务基础数据!D26*目录!$D$6 -> 0 | E29: =财务基础数据!E26*目录!$D$6 -> 0 | F29: =财务基础数据!F26*目录!$D$6 -> 0 | G29: =财务基础数据!G26*目录!$D$6 -> 0 | H29: =财务基础数据!H26*目录!$D$6 -> 0 | I29: =财务基础数据!I26*目录!$D$6 -> 0 | J29: =财务基础数据!J26*目录!$D$6 -> 0 | K29: =财务基础数据!K26*目录!$D$6 -> 0 | ... Z29: =财务基础数据!Z26*目录!$D$6 -> 0 | AA29: =AA26-AA27+AA28 -> 0 | AB29: =AB26-AB27+AB28 -> 0 | AC29: =AC26-AC27+AC28 -> 0 | AD29: =AD26-AD27+AD28 -> 0 | AE29: =AE26-AE27+AE28 -> 0 | AF29: =AF26-AF27+AF28 -> 0 | AG29: =AG26-AG27+AG28 -> 0 | AH29: =AH26-AH27+AH28 -> 0 | ... AJ29: =AJ26-AJ27+AJ28 -> 0
B30: 优先股利及其他调整项 | D30: =财务基础数据!D35*目录!$D$6 -> 0 | E30: =财务基础数据!E35*目录!$D$6 -> 0 | F30: =财务基础数据!F35*目录!$D$6 -> 0 | G30: =财务基础数据!G35*目录!$D$6 -> 0 | H30: =财务基础数据!H35*目录!$D$6 -> 0 | I30: =财务基础数据!I35*目录!$D$6 -> 0 | J30: =财务基础数据!J35*目录!$D$6 -> 0 | K30: =财务基础数据!K35*目录!$D$6 -> 0 | ... Z30: =财务基础数据!Z35*目录!$D$6 -> 0 | AA30: =IF(财务基础数据!W$2=0,W30,IF(财务基础数据!W$2=1,X30,IF(财务基础数据!W$2=2,Y30,Z30))) -> 0 | AB30: =AA30 -> 0 | AC30: =AB30 -> 0 | AD30: =AC30 -> 0 | AE30: =AD30 -> 0 | AF30: =AE30 -> 0 | AG30: =AF30 -> 0 | AH30: =AG30 -> 0 | AI30: =AH30 -> 0 | AJ30: =AI30 -> 0
B31: 归属普通股东净利润 | D31: =(财务基础数据!D27)*目录!$D$6 -> 0 | E31: =(财务基础数据!E27)*目录!$D$6 -> 0 | F31: =(财务基础数据!F27)*目录!$D$6 -> 0 | G31: =(财务基础数据!G27)*目录!$D$6 -> 0 | H31: =(财务基础数据!H27)*目录!$D$6 -> 0 | I31: =(财务基础数据!I27)*目录!$D$6 -> 0 | J31: =(财务基础数据!J27)*目录!$D$6 -> 0 | K31: =(财务基础数据!K27)*目录!$D$6 -> 0 | ... Z31: =(财务基础数据!Z27)*目录!$D$6 -> 0 | AA31: =AA29-AA30 -> 0 | AB31: =AB29-AB30 -> 0 | AC31: =AC29-AC30 -> 0 | AD31: =AD29-AD30 -> 0 | AE31: =AE29-AE30 -> 0 | AF31: =AF29-AF30 -> 0 | AG31: =AG29-AG30 -> 0 | AH31: =AH29-AH30 -> 0 | ... AJ31: =AJ29-AJ30 -> 0
B34: EBITDA | E34: =E35+现金流量表!E6 -> 0 | G34: =G35+现金流量表!G6 -> 0 | I34: =I35+现金流量表!I6 -> 0 | K34: =K35+现金流量表!K6 -> 0 | M34: =M35+现金流量表!M6 -> 0 | O34: =O35+现金流量表!O6 -> 0 | Q34: =Q35+现金流量表!Q6 -> 0 | S34: =S35+现金流量表!S6 -> 0 | U34: =U35+现金流量表!U6 -> 0 | W34: =W35+现金流量表!W6 -> 0 | Y34: =Y35+现金流量表!Y6 -> 0 | AA34: =AA35+现金流量表!AA6 -> 0 | AB34: =AB35+现金流量表!AB6 -> 0 | AC34: =AC35+现金流量表!AC6 -> 0 | AD34: =AD35+现金流量表!AD6 -> 0 | AE34: =AE35+现金流量表!AE6 -> 0 | AF34: =AF35+现金流量表!AF6 -> 0 | AG34: =AG35+现金流量表!AG6 -> 0 | AH34: =AH35+现金流量表!AH6 -> 0 | ... AJ34: =AJ35+现金流量表!AJ6 -> 0
B35: EBIT | E35: =E24+E19-E18 -> 0 | G35: =G24+G19-G18 -> 0 | I35: =I24+I19-I18 -> 0 | K35: =K24+K19-K18 -> 0 | M35: =M24+M19-M18 -> 0 | O35: =O24+O19-O18 -> 0 | Q35: =Q24+Q19-Q18 -> 0 | S35: =S24+S19-S18 -> 0 | U35: =U24+U19-U18 -> 0 | W35: =W24+W19-W18 -> 0 | Y35: =Y24+Y19-Y18 -> 0 | AA35: =AA24+AA19-AA18 -> 0 | AB35: =AB24+AB19-AB18 -> 0 | AC35: =AC24+AC19-AC18 -> 0 | AD35: =AD24+AD19-AD18 -> 0 | AE35: =AE24+AE19-AE18 -> 0 | AF35: =AF24+AF19-AF18 -> 0 | AG35: =AG24+AG19-AG18 -> 0 | AH35: =AH24+AH19-AH18 -> 0 | ... AJ35: =AJ24+AJ19-AJ18 -> 0

Sheet 现金流量表
B2: 现金流量表
B3: =主要财务摘要!H2 -> 单位：港币(百万) | W3: 由于港股公司业绩公告可能未披露现金流量表数据，可在黄色边框单元格中手动填值。
B4: 报告期间： | D4: =财务基础数据!D5 -> 1Q17 | E4: =财务基础数据!E5 -> 1H17 | F4: =财务基础数据!F5 -> 3Q17 | G4: =财务基础数据!G5 -> 2017 | H4: =财务基础数据!H5 -> 1Q18 | I4: =财务基础数据!I5 -> 1H18 | J4: =财务基础数据!J5 -> 3Q18 | K4: =财务基础数据!K5 -> 2018 | ... Z4: =财务基础数据!Z5 -> 3Q22 | AA4: =资产负债表!AA4 -> 2022E | AB4: =资产负债表!AB4 -> 2023 | AC4: =资产负债表!AC4 -> 2024 | AD4: =资产负债表!AD4 -> 2025 | AE4: =资产负债表!AE4 -> 2026 | AF4: =资产负债表!AF4 -> 2027 | AG4: =资产负债表!AG4 -> 2028 | AH4: =资产负债表!AH4 -> 2029 | ... AJ4: =资产负债表!AJ4 -> 2031
B5: 净利润 | D5: =(财务基础数据!D98)*目录!$D$6 -> 0 | E5: =(财务基础数据!E98)*目录!$D$6 -> 0 | F5: =(财务基础数据!F98)*目录!$D$6 -> 0 | G5: =(财务基础数据!G98)*目录!$D$6 -> 0 | H5: =(财务基础数据!H98)*目录!$D$6 -> 0 | I5: =(财务基础数据!I98)*目录!$D$6 -> 0 | J5: =(财务基础数据!J98)*目录!$D$6 -> 0 | K5: =(财务基础数据!K98)*目录!$D$6 -> 0 | ... Z5: =(财务基础数据!Z98)*目录!$D$6 -> 0 | AA5: =利润表!AA29 -> 0 | AB5: =利润表!AB29 -> 0 | AC5: =利润表!AC29 -> 0 | AD5: =利润表!AD29 -> 0 | AE5: =利润表!AE29 -> 0 | AF5: =利润表!AF29 -> 0 | AG5: =利润表!AG29 -> 0 | AH5: =利润表!AH29 -> 0 | ... AJ5: =利润表!AJ29 -> 0
B6: 折旧与摊销 | D6: =(财务基础数据!D99)*目录!$D$6 -> 0 | E6: =(财务基础数据!E99)*目录!$D$6 -> 0 | F6: =(财务基础数据!F99)*目录!$D$6 -> 0 | G6: =(财务基础数据!G99)*目录!$D$6 -> 0 | H6: =(财务基础数据!H99)*目录!$D$6 -> 0 | I6: =(财务基础数据!I99)*目录!$D$6 -> 0 | J6: =(财务基础数据!J99)*目录!$D$6 -> 0 | K6: =(财务基础数据!K99)*目录!$D$6 -> 0 | ... Z6: =(财务基础数据!Z99)*目录!$D$6 -> 0 | AA6: =资产预测!J63+资产预测!J68 -> 0 | AB6: =资产预测!K63+资产预测!K68 -> 0 | AC6: =资产预测!L63+资产预测!L68 -> 0 | AD6: =资产预测!M63+资产预测!M68 -> 0 | AE6: =资产预测!N63+资产预测!N68 -> 0 | AF6: =资产预测!O63+资产预测!O68 -> 0 | AG6: =资产预测!P63+资产预测!P68 -> 0 | AH6: =资产预测!Q63+资产预测!Q68 -> 0 | ... AJ6: =资产预测!S63+资产预测!S68 -> 0
B7: 营运资本变动： | D7: =(财务基础数据!D100)*目录!$D$6 -> 0 | E7: =(财务基础数据!E100)*目录!$D$6 -> 0 | F7: =(财务基础数据!F100)*目录!$D$6 -> 0 | G7: =(财务基础数据!G100)*目录!$D$6 -> 0 | H7: =(财务基础数据!H100)*目录!$D$6 -> 0 | I7: =(财务基础数据!I100)*目录!$D$6 -> 0 | J7: =(财务基础数据!J100)*目录!$D$6 -> 0 | K7: =(财务基础数据!K100)*目录!$D$6 -> 0 | ... Z7: =(财务基础数据!Z100)*目录!$D$6 -> 0 | AA7: =SUM(AA8:AA14) -> 0 | AB7: =SUM(AB8:AB14) -> 0 | AC7: =SUM(AC8:AC14) -> 0 | AD7: =SUM(AD8:AD14) -> 0 | AE7: =SUM(AE8:AE14) -> 0 | AF7: =SUM(AF8:AF14) -> 0 | AG7: =SUM(AG8:AG14) -> 0 | AH7: =SUM(AH8:AH14) -> 0 | ... AJ7: =SUM(AJ8:AJ14) -> 0
B8: 应收账款及票据的减少 | AA8: =IF(ISERROR(资产负债表!W9-资产负债表!AA9),"0",资产负债表!W9-资产负债表!AA9) -> 0 | AB8: =IF(ISERROR(资产负债表!AA9-资产负债表!AB9),"0",资产负债表!AA9-资产负债表!AB9) -> 0 | AC8: =IF(ISERROR(资产负债表!AB9-资产负债表!AC9),"0",资产负债表!AB9-资产负债表!AC9) -> 0 | AD8: =IF(ISERROR(资产负债表!AC9-资产负债表!AD9),"0",资产负债表!AC9-资产负债表!AD9) -> 0 | AE8: =IF(ISERROR(资产负债表!AD9-资产负债表!AE9),"0",资产负债表!AD9-资产负债表!AE9) -> 0 | AF8: =IF(ISERROR(资产负债表!AE9-资产负债表!AF9),"0",资产负债表!AE9-资产负债表!AF9) -> 0 | AG8: =IF(ISERROR(资产负债表!AF9-资产负债表!AG9),"0",资产负债表!AF9-资产负债表!AG9) -> 0 | AH8: =IF(ISERROR(资产负债表!AG9-资产负债表!AH9),"0",资产负债表!AG9-资产负债表!AH9) -> 0 | AI8: =IF(ISERROR(资产负债表!AH9-资产负债表!AI9),"0",资产负债表!AH9-资产负债表!AI9) -> 0 | AJ8: =IF(ISERROR(资产负债表!AI9-资产负债表!AJ9),"0",资产负债表!AI9-资产负债表!AJ9) -> 0
B9: 其他应收款的减少 | AA9: =IF(ISERROR(资产负债表!W10-资产负债表!AA10),"0",资产负债表!W10-资产负债表!AA10) -> 0 | AB9: =IF(ISERROR(资产负债表!AA10-资产负债表!AB10),"0",资产负债表!AA10-资产负债表!AB10) -> 0 | AC9: =IF(ISERROR(资产负债表!AB10-资产负债表!AC10),"0",资产负债表!AB10-资产负债表!AC10) -> 0 | AD9: =IF(ISERROR(资产负债表!AC10-资产负债表!AD10),"0",资产负债表!AC10-资产负债表!AD10) -> 0 | AE9: =IF(ISERROR(资产负债表!AD10-资产负债表!AE10),"0",资产负债表!AD10-资产负债表!AE10) -> 0 | AF9: =IF(ISERROR(资产负债表!AE10-资产负债表!AF10),"0",资产负债表!AE10-资产负债表!AF10) -> 0 | AG9: =IF(ISERROR(资产负债表!AF10-资产负债表!AG10),"0",资产负债表!AF10-资产负债表!AG10) -> 0 | AH9: =IF(ISERROR(资产负债表!AG10-资产负债表!AH10),"0",资产负债表!AG10-资产负债表!AH10) -> 0 | AI9: =IF(ISERROR(资产负债表!AH10-资产负债表!AI10),"0",资产负债表!AH10-资产负债表!AI10) -> 0 | AJ9: =IF(ISERROR(资产负债表!AI10-资产负债表!AJ10),"0",资产负债表!AI10-资产负债表!AJ10) -> 0
B10: 存货的减少 | AA10: =IF(ISERROR(资产负债表!W11-资产负债表!AA11),"0",资产负债表!W11-资产负债表!AA11) -> 0 | AB10: =IF(ISERROR(资产负债表!AA11-资产负债表!AB11),"0",资产负债表!AA11-资产负债表!AB11) -> 0 | AC10: =IF(ISERROR(资产负债表!AB11-资产负债表!AC11),"0",资产负债表!AB11-资产负债表!AC11) -> 0 | AD10: =IF(ISERROR(资产负债表!AC11-资产负债表!AD11),"0",资产负债表!AC11-资产负债表!AD11) -> 0 | AE10: =IF(ISERROR(资产负债表!AD11-资产负债表!AE11),"0",资产负债表!AD11-资产负债表!AE11) -> 0 | AF10: =IF(ISERROR(资产负债表!AE11-资产负债表!AF11),"0",资产负债表!AE11-资产负债表!AF11) -> 0 | AG10: =IF(ISERROR(资产负债表!AF11-资产负债表!AG11),"0",资产负债表!AF11-资产负债表!AG11) -> 0 | AH10: =IF(ISERROR(资产负债表!AG11-资产负债表!AH11),"0",资产负债表!AG11-资产负债表!AH11) -> 0 | AI10: =IF(ISERROR(资产负债表!AH11-资产负债表!AI11),"0",资产负债表!AH11-资产负债表!AI11) -> 0 | AJ10: =IF(ISERROR(资产负债表!AI11-资产负债表!AJ11),"0",资产负债表!AI11-资产负债表!AJ11) -> 0
B11: 其他流动资产的减少 | AA11: =IF(ISERROR(资产负债表!W12-资产负债表!AA12),"0",资产负债表!W12-资产负债表!AA12) -> 0 | AB11: =IF(ISERROR(资产负债表!AA12-资产负债表!AB12),"0",资产负债表!AA12-资产负债表!AB12) -> 0 | AC11: =IF(ISERROR(资产负债表!AB12-资产负债表!AC12),"0",资产负债表!AB12-资产负债表!AC12) -> 0 | AD11: =IF(ISERROR(资产负债表!AC12-资产负债表!AD12),"0",资产负债表!AC12-资产负债表!AD12) -> 0 | AE11: =IF(ISERROR(资产负债表!AD12-资产负债表!AE12),"0",资产负债表!AD12-资产负债表!AE12) -> 0 | AF11: =IF(ISERROR(资产负债表!AE12-资产负债表!AF12),"0",资产负债表!AE12-资产负债表!AF12) -> 0 | AG11: =IF(ISERROR(资产负债表!AF12-资产负债表!AG12),"0",资产负债表!AF12-资产负债表!AG12) -> 0 | AH11: =IF(ISERROR(资产负债表!AG12-资产负债表!AH12),"0",资产负债表!AG12-资产负债表!AH12) -> 0 | AI11: =IF(ISERROR(资产负债表!AH12-资产负债表!AI12),"0",资产负债表!AH12-资产负债表!AI12) -> 0 | AJ11: =IF(ISERROR(资产负债表!AI12-资产负债表!AJ12),"0",资产负债表!AI12-资产负债表!AJ12) -> 0
B12: 应付账款及票据的增加 | AA12: =IF(ISERROR(资产负债表!AA28-资产负债表!W28),"0",资产负债表!AA28-资产负债表!W28) -> 0 | AB12: =IF(ISERROR(资产负债表!AB28-资产负债表!AA28),"0",资产负债表!AB28-资产负债表!AA28) -> 0 | AC12: =IF(ISERROR(资产负债表!AC28-资产负债表!AB28),"0",资产负债表!AC28-资产负债表!AB28) -> 0 | AD12: =IF(ISERROR(资产负债表!AD28-资产负债表!AC28),"0",资产负债表!AD28-资产负债表!AC28) -> 0 | AE12: =IF(ISERROR(资产负债表!AE28-资产负债表!AD28),"0",资产负债表!AE28-资产负债表!AD28) -> 0 | AF12: =IF(ISERROR(资产负债表!AF28-资产负债表!AE28),"0",资产负债表!AF28-资产负债表!AE28) -> 0 | AG12: =IF(ISERROR(资产负债表!AG28-资产负债表!AF28),"0",资产负债表!AG28-资产负债表!AF28) -> 0 | AH12: =IF(ISERROR(资产负债表!AH28-资产负债表!AG28),"0",资产负债表!AH28-资产负债表!AG28) -> 0 | AI12: =IF(ISERROR(资产负债表!AI28-资产负债表!AH28),"0",资产负债表!AI28-资产负债表!AH28) -> 0 | AJ12: =IF(ISERROR(资产负债表!AJ28-资产负债表!AI28),"0",资产负债表!AJ28-资产负债表!AI28) -> 0
B13: 应交税金的增加 | AA13: =IF(ISERROR(资产负债表!AA29-资产负债表!W29),"0",资产负债表!AA29-资产负债表!W29) -> 0 | AB13: =IF(ISERROR(资产负债表!AB29-资产负债表!AA29),"0",资产负债表!AB29-资产负债表!AA29) -> 0 | AC13: =IF(ISERROR(资产负债表!AC29-资产负债表!AB29),"0",资产负债表!AC29-资产负债表!AB29) -> 0 | AD13: =IF(ISERROR(资产负债表!AD29-资产负债表!AC29),"0",资产负债表!AD29-资产负债表!AC29) -> 0 | AE13: =IF(ISERROR(资产负债表!AE29-资产负债表!AD29),"0",资产负债表!AE29-资产负债表!AD29) -> 0 | AF13: =IF(ISERROR(资产负债表!AF29-资产负债表!AE29),"0",资产负债表!AF29-资产负债表!AE29) -> 0 | AG13: =IF(ISERROR(资产负债表!AG29-资产负债表!AF29),"0",资产负债表!AG29-资产负债表!AF29) -> 0 | AH13: =IF(ISERROR(资产负债表!AH29-资产负债表!AG29),"0",资产负债表!AH29-资产负债表!AG29) -> 0 | AI13: =IF(ISERROR(资产负债表!AI29-资产负债表!AH29),"0",资产负债表!AI29-资产负债表!AH29) -> 0 | AJ13: =IF(ISERROR(资产负债表!AJ29-资产负债表!AI29),"0",资产负债表!AJ29-资产负债表!AI29) -> 0
B14: 其他流动负债的增加 | AA14: =IF(ISERROR(资产负债表!AA32-资产负债表!W32),"0",资产负债表!AA32-资产负债表!W32) -> 0 | AB14: =IF(ISERROR(资产负债表!AB32-资产负债表!AA32),"0",资产负债表!AB32-资产负债表!AA32) -> 0 | AC14: =IF(ISERROR(资产负债表!AC32-资产负债表!AB32),"0",资产负债表!AC32-资产负债表!AB32) -> 0 | AD14: =IF(ISERROR(资产负债表!AD32-资产负债表!AC32),"0",资产负债表!AD32-资产负债表!AC32) -> 0 | AE14: =IF(ISERROR(资产负债表!AE32-资产负债表!AD32),"0",资产负债表!AE32-资产负债表!AD32) -> 0 | AF14: =IF(ISERROR(资产负债表!AF32-资产负债表!AE32),"0",资产负债表!AF32-资产负债表!AE32) -> 0 | AG14: =IF(ISERROR(资产负债表!AG32-资产负债表!AF32),"0",资产负债表!AG32-资产负债表!AF32) -> 0 | AH14: =IF(ISERROR(资产负债表!AH32-资产负债表!AG32),"0",资产负债表!AH32-资产负债表!AG32) -> 0 | AI14: =IF(ISERROR(资产负债表!AI32-资产负债表!AH32),"0",资产负债表!AI32-资产负债表!AH32) -> 0 | AJ14: =IF(ISERROR(资产负债表!AJ32-资产负债表!AI32),"0",资产负债表!AJ32-资产负债表!AI32) -> 0
B15: 其他调整 | D15: =(财务基础数据!D101)*目录!$D$6 -> 0 | E15: =(财务基础数据!E101)*目录!$D$6 -> 0 | F15: =(财务基础数据!F101)*目录!$D$6 -> 0 | G15: =(财务基础数据!G101)*目录!$D$6 -> 0 | H15: =(财务基础数据!H101)*目录!$D$6 -> 0 | I15: =(财务基础数据!I101)*目录!$D$6 -> 0 | J15: =(财务基础数据!J101)*目录!$D$6 -> 0 | K15: =(财务基础数据!K101)*目录!$D$6 -> 0 | ... Z15: =(财务基础数据!Z101)*目录!$D$6 -> 0 | AA15: =利润表!AA19-利润表!AA20-利润表!AA21+利润表!AA27-利润表!AA23 -> 0 | AB15: =利润表!AB19-利润表!AB20-利润表!AB21+利润表!AB27-利润表!AB23 -> 0 | AC15: =利润表!AC19-利润表!AC20-利润表!AC21+利润表!AC27-利润表!AC23 -> 0 | AD15: =利润表!AD19-利润表!AD20-利润表!AD21+利润表!AD27-利润表!AD23 -> 0 | AE15: =利润表!AE19-利润表!AE20-利润表!AE21+利润表!AE27-利润表!AE23 -> 0 | AF15: =利润表!AF19-利润表!AF20-利润表!AF21+利润表!AF27-利润表!AF23 -> 0 | AG15: =利润表!AG19-利润表!AG20-利润表!AG21+利润表!AG27-利润表!AG23 -> 0 | AH15: =利润表!AH19-利润表!AH20-利润表!AH21+利润表!AH27-利润表!AH23 -> 0 | ... AJ15: =利润表!AJ19-利润表!AJ20-利润表!AJ21+利润表!AJ27-利润表!AJ23 -> 0
B16: 经营活动产生的现金流量净额 | D16: =(财务基础数据!D102)*目录!$D$6 -> 0 | E16: =(财务基础数据!E102)*目录!$D$6 -> 0 | F16: =(财务基础数据!F102)*目录!$D$6 -> 0 | G16: =(财务基础数据!G102)*目录!$D$6 -> 0 | H16: =(财务基础数据!H102)*目录!$D$6 -> 0 | I16: =(财务基础数据!I102)*目录!$D$6 -> 0 | J16: =(财务基础数据!J102)*目录!$D$6 -> 0 | K16: =(财务基础数据!K102)*目录!$D$6 -> 0 | ... Z16: =(财务基础数据!Z102)*目录!$D$6 -> 0 | AA16: =AA5+AA6+AA7+AA15 -> 0 | AB16: =AB5+AB6+AB7+AB15 -> 0 | AC16: =AC5+AC6+AC7+AC15 -> 0 | AD16: =AD5+AD6+AD7+AD15 -> 0 | AE16: =AE5+AE6+AE7+AE15 -> 0 | AF16: =AF5+AF6+AF7+AF15 -> 0 | AG16: =AG5+AG6+AG7+AG15 -> 0 | AH16: =AH5+AH6+AH7+AH15 -> 0 | ... AJ16: =AJ5+AJ6+AJ7+AJ15 -> 0
B17: 资本性支出： | D17: =(-财务基础数据!D104)*目录!$D$6 -> 0 | E17: =(-财务基础数据!E104)*目录!$D$6 -> 0 | F17: =(-财务基础数据!F104)*目录!$D$6 -> 0 | G17: =(-财务基础数据!G104)*目录!$D$6 -> 0 | H17: =(-财务基础数据!H104)*目录!$D$6 -> 0 | I17: =(-财务基础数据!I104)*目录!$D$6 -> 0 | J17: =(-财务基础数据!J104)*目录!$D$6 -> 0 | K17: =(-财务基础数据!K104)*目录!$D$6 -> 0 | ... Z17: =(-财务基础数据!Z104)*目录!$D$6 -> 0 | AA17: =IF(ISERROR(AA18+AA19),"0",AA18+AA19) -> 0 | AB17: =IF(ISERROR(AB18+AB19),"0",AB18+AB19) -> 0 | AC17: =IF(ISERROR(AC18+AC19),"0",AC18+AC19) -> 0 | AD17: =IF(ISERROR(AD18+AD19),"0",AD18+AD19) -> 0 | AE17: =IF(ISERROR(AE18+AE19),"0",AE18+AE19) -> 0 | AF17: =IF(ISERROR(AF18+AF19),"0",AF18+AF19) -> 0 | AG17: =IF(ISERROR(AG18+AG19),"0",AG18+AG19) -> 0 | AH17: =IF(ISERROR(AH18+AH19),"0",AH18+AH19) -> 0 | ... AJ17: =IF(ISERROR(AJ18+AJ19),"0",AJ18+AJ19) -> 0
B18: 固定资产 | AA18: =-资产预测!J62 -> 0 | AB18: =-资产预测!K62 -> 0 | AC18: =-资产预测!L62 -> 0 | AD18: =-资产预测!M62 -> 0 | AE18: =-资产预测!N62 -> 0 | AF18: =-资产预测!O62 -> 0 | AG18: =-资产预测!P62 -> 0 | AH18: =-资产预测!Q62 -> 0 | ... AJ18: =-资产预测!S62 -> 0
B19: 商誉及无形资产 | AA19: =-资产预测!J67 -> 0 | AB19: =-资产预测!K67 -> 0 | AC19: =-资产预测!L67 -> 0 | AD19: =-资产预测!M67 -> 0 | AE19: =-资产预测!N67 -> 0 | AF19: =-资产预测!O67 -> 0 | AG19: =-资产预测!P67 -> 0 | AH19: =-资产预测!Q67 -> 0 | ... AJ19: =-资产预测!S67 -> 0
B20: 权益性投资损益 | AA20: =利润表!AA20 -> 0 | AB20: =利润表!AB20 -> 0 | AC20: =利润表!AC20 -> 0 | AD20: =利润表!AD20 -> 0 | AE20: =利润表!AE20 -> 0 | AF20: =利润表!AF20 -> 0 | AG20: =利润表!AG20 -> 0 | AH20: =利润表!AH20 -> 0 | ... AJ20: =利润表!AJ20 -> 0
B21: 投资增减： | D21: =(财务基础数据!D106-财务基础数据!D105)*目录!$D$6 -> 0 | E21: =(财务基础数据!E106-财务基础数据!E105)*目录!$D$6 -> 0 | F21: =(财务基础数据!F106-财务基础数据!F105)*目录!$D$6 -> 0 | G21: =(财务基础数据!G106-财务基础数据!G105)*目录!$D$6 -> 0 | H21: =(财务基础数据!H106-财务基础数据!H105)*目录!$D$6 -> 0 | I21: =(财务基础数据!I106-财务基础数据!I105)*目录!$D$6 -> 0 | J21: =(财务基础数据!J106-财务基础数据!J105)*目录!$D$6 -> 0 | K21: =(财务基础数据!K106-财务基础数据!K105)*目录!$D$6 -> 0 | ... Z21: =(财务基础数据!Z106-财务基础数据!Z105)*目录!$D$6 -> 0 | AA21: =IF(ISERROR(AA22+AA23+AA24+AA25+AA26+AA27),"0",AA22+AA23+AA24+AA25+AA26+AA27) -> 0 | AB21: =IF(ISERROR(AB22+AB23+AB24+AB25+AB26+AB27),"0",AB22+AB23+AB24+AB25+AB26+AB27) -> 0 | AC21: =IF(ISERROR(AC22+AC23+AC24+AC25+AC26+AC27),"0",AC22+AC23+AC24+AC25+AC26+AC27) -> 0 | AD21: =IF(ISERROR(AD22+AD23+AD24+AD25+AD26+AD27),"0",AD22+AD23+AD24+AD25+AD26+AD27) -> 0 | AE21: =IF(ISERROR(AE22+AE23+AE24+AE25+AE26+AE27),"0",AE22+AE23+AE24+AE25+AE26+AE27) -> 0 | AF21: =IF(ISERROR(AF22+AF23+AF24+AF25+AF26+AF27),"0",AF22+AF23+AF24+AF25+AF26+AF27) -> 0 | AG21: =IF(ISERROR(AG22+AG23+AG24+AG25+AG26+AG27),"0",AG22+AG23+AG24+AG25+AG26+AG27) -> 0 | AH21: =IF(ISERROR(AH22+AH23+AH24+AH25+AH26+AH27),"0",AH22+AH23+AH24+AH25+AH26+AH27) -> 0 | ... AJ21: =IF(ISERROR(AJ22+AJ23+AJ24+AJ25+AJ26+AJ27),"0",AJ22+AJ23+AJ24+AJ25+AJ26+AJ27) -> 0
B22: 金融资产投资 | AA22: =-资产预测!J41+资产预测!J47 -> 0 | AB22: =-资产预测!K41+资产预测!K47 -> 0 | AC22: =-资产预测!L41+资产预测!L47 -> 0 | AD22: =-资产预测!M41+资产预测!M47 -> 0 | AE22: =-资产预测!N41+资产预测!N47 -> 0 | AF22: =-资产预测!O41+资产预测!O47 -> 0 | AG22: =-资产预测!P41+资产预测!P47 -> 0 | AH22: =-资产预测!Q41+资产预测!Q47 -> 0 | ... AJ22: =-资产预测!S41+资产预测!S47 -> 0
B23: 其他短期投资 | AA23: =-资产预测!J44 -> 0 | AB23: =-资产预测!K44 -> 0 | AC23: =-资产预测!L44 -> 0 | AD23: =-资产预测!M44 -> 0 | AE23: =-资产预测!N44 -> 0 | AF23: =-资产预测!O44 -> 0 | AG23: =-资产预测!P44 -> 0 | AH23: =-资产预测!Q44 -> 0 | ... AJ23: =-资产预测!S44 -> 0
B24: 权益性投资 | AA24: =-资产预测!J52 -> 0 | AB24: =-资产预测!K52 -> 0 | AC24: =-资产预测!L52 -> 0 | AD24: =-资产预测!M52 -> 0 | AE24: =-资产预测!N52 -> 0 | AF24: =-资产预测!O52 -> 0 | AG24: =-资产预测!P52 -> 0 | AH24: =-资产预测!Q52 -> 0 | ... AJ24: =-资产预测!S52 -> 0
B25: 持有至到期投资 | AA25: =-资产预测!J55 -> 0 | AB25: =-资产预测!K55 -> 0 | AC25: =-资产预测!L55 -> 0 | AD25: =-资产预测!M55 -> 0 | AE25: =-资产预测!N55 -> 0 | AF25: =-资产预测!O55 -> 0 | AG25: =-资产预测!P55 -> 0 | AH25: =-资产预测!Q55 -> 0 | ... AJ25: =-资产预测!S55 -> 0
B26: 可供出售投资 | AA26: =-资产预测!J58 -> 0 | AB26: =-资产预测!K58 -> 0 | AC26: =-资产预测!L58 -> 0 | AD26: =-资产预测!M58 -> 0 | AE26: =-资产预测!N58 -> 0 | AF26: =-资产预测!O58 -> 0 | AG26: =-资产预测!P58 -> 0 | AH26: =-资产预测!Q58 -> 0 | ... AJ26: =-资产预测!S58 -> 0
B27: 其他长期投资 | AA27: =-资产预测!J75-资产预测!J78 -> 0 | AB27: =-资产预测!K75-资产预测!K78 -> 0 | AC27: =-资产预测!L75-资产预测!L78 -> 0 | AD27: =-资产预测!M75-资产预测!M78 -> 0 | AE27: =-资产预测!N75-资产预测!N78 -> 0 | AF27: =-资产预测!O75-资产预测!O78 -> 0 | AG27: =-资产预测!P75-资产预测!P78 -> 0 | AH27: =-资产预测!Q75-资产预测!Q78 -> 0 | ... AJ27: =-资产预测!S75-资产预测!S78 -> 0
B28: 其他投资活动 | D28: =(财务基础数据!D107+财务基础数据!D103)*目录!$D$6 -> 0 | E28: =(财务基础数据!E107+财务基础数据!E103)*目录!$D$6 -> 0 | F28: =(财务基础数据!F107+财务基础数据!F103)*目录!$D$6 -> 0 | G28: =(财务基础数据!G107+财务基础数据!G103)*目录!$D$6 -> 0 | H28: =(财务基础数据!H107+财务基础数据!H103)*目录!$D$6 -> 0 | I28: =(财务基础数据!I107+财务基础数据!I103)*目录!$D$6 -> 0 | J28: =(财务基础数据!J107+财务基础数据!J103)*目录!$D$6 -> 0 | K28: =(财务基础数据!K107+财务基础数据!K103)*目录!$D$6 -> 0 | ... Z28: =(财务基础数据!Z107+财务基础数据!Z103)*目录!$D$6 -> 0 | AA28: =资产负债表!W22-资产负债表!AA22+资产负债表!AA36-资产负债表!W36+利润表!AA23+利润表!AA21 -> 0 | AB28: =资产负债表!AA22-资产负债表!AB22+资产负债表!AB36-资产负债表!AA36+利润表!AB23+利润表!AB21 -> 0 | AC28: =资产负债表!AB22-资产负债表!AC22+资产负债表!AC36-资产负债表!AB36+利润表!AC23+利润表!AC21 -> 0 | AD28: =资产负债表!AC22-资产负债表!AD22+资产负债表!AD36-资产负债表!AC36+利润表!AD23+利润表!AD21 -> 0 | AE28: =资产负债表!AD22-资产负债表!AE22+资产负债表!AE36-资产负债表!AD36+利润表!AE23+利润表!AE21 -> 0 | AF28: =资产负债表!AE22-资产负债表!AF22+资产负债表!AF36-资产负债表!AE36+利润表!AF23+利润表!AF21 -> 0 | AG28: =资产负债表!AF22-资产负债表!AG22+资产负债表!AG36-资产负债表!AF36+利润表!AG23+利润表!AG21 -> 0 | AH28: =资产负债表!AG22-资产负债表!AH22+资产负债表!AH36-资产负债表!AG36+利润表!AH23+利润表!AH21 -> 0 | AI28: =资产负债表!AH22-资产负债表!AI22+资产负债表!AI36-资产负债表!AH36+利润表!AI23+利润表!AI21 -> 0 | AJ28: =资产负债表!AI22-资产负债表!AJ22+资产负债表!AJ36-资产负债表!AI36+利润表!AJ23+利润表!AJ21 -> 0
B29: 投资活动产生的现金流量净额 | D29: =(财务基础数据!D108)*目录!$D$6 -> 0 | E29: =(财务基础数据!E108)*目录!$D$6 -> 0 | F29: =(财务基础数据!F108)*目录!$D$6 -> 0 | G29: =(财务基础数据!G108)*目录!$D$6 -> 0 | H29: =(财务基础数据!H108)*目录!$D$6 -> 0 | I29: =(财务基础数据!I108)*目录!$D$6 -> 0 | J29: =(财务基础数据!J108)*目录!$D$6 -> 0 | K29: =(财务基础数据!K108)*目录!$D$6 -> 0 | ... Z29: =(财务基础数据!Z108)*目录!$D$6 -> 0 | AA29: =IF(ISERROR(AA17+AA21+AA28+AA20),"0",AA17+AA21+AA28+AA20) -> 0 | AB29: =IF(ISERROR(AB17+AB21+AB28+AB20),"0",AB17+AB21+AB28+AB20) -> 0 | AC29: =IF(ISERROR(AC17+AC21+AC28+AC20),"0",AC17+AC21+AC28+AC20) -> 0 | AD29: =IF(ISERROR(AD17+AD21+AD28+AD20),"0",AD17+AD21+AD28+AD20) -> 0 | AE29: =IF(ISERROR(AE17+AE21+AE28+AE20),"0",AE17+AE21+AE28+AE20) -> 0 | AF29: =IF(ISERROR(AF17+AF21+AF28+AF20),"0",AF17+AF21+AF28+AF20) -> 0 | AG29: =IF(ISERROR(AG17+AG21+AG28+AG20),"0",AG17+AG21+AG28+AG20) -> 0 | AH29: =IF(ISERROR(AH17+AH21+AH28+AH20),"0",AH17+AH21+AH28+AH20) -> 0 | ... AJ29: =IF(ISERROR(AJ17+AJ21+AJ28+AJ20),"0",AJ17+AJ21+AJ28+AJ20) -> 0
B30: 债权融资 | D30: =(财务基础数据!D109-财务基础数据!D110)*目录!$D$6 -> 0 | E30: =(财务基础数据!E109-财务基础数据!E110)*目录!$D$6 -> 0 | F30: =(财务基础数据!F109-财务基础数据!F110)*目录!$D$6 -> 0 | G30: =(财务基础数据!G109-财务基础数据!G110)*目录!$D$6 -> 0 | H30: =(财务基础数据!H109-财务基础数据!H110)*目录!$D$6 -> 0 | I30: =(财务基础数据!I109-财务基础数据!I110)*目录!$D$6 -> 0 | J30: =(财务基础数据!J109-财务基础数据!J110)*目录!$D$6 -> 0 | K30: =(财务基础数据!K109-财务基础数据!K110)*目录!$D$6 -> 0 | ... Z30: =(财务基础数据!Z109-财务基础数据!Z110)*目录!$D$6 -> 0 | AA30: =资产预测!J115+资产预测!J116+资产预测!J123 -> 0 | AB30: =资产预测!K115+资产预测!K116+资产预测!K123 -> 0 | AC30: =资产预测!L115+资产预测!L116+资产预测!L123 -> 0 | AD30: =资产预测!M115+资产预测!M116+资产预测!M123 -> 0 | AE30: =资产预测!N115+资产预测!N116+资产预测!N123 -> 0 | AF30: =资产预测!O115+资产预测!O116+资产预测!O123 -> 0 | AG30: =资产预测!P115+资产预测!P116+资产预测!P123 -> 0 | AH30: =资产预测!Q115+资产预测!Q116+资产预测!Q123 -> 0 | ... AJ30: =资产预测!S115+资产预测!S116+资产预测!S123 -> 0
B31: 股权融资 | D31: =(财务基础数据!D111-财务基础数据!D112)*目录!$D$6 -> 0 | E31: =(财务基础数据!E111-财务基础数据!E112)*目录!$D$6 -> 0 | F31: =(财务基础数据!F111-财务基础数据!F112)*目录!$D$6 -> 0 | G31: =(财务基础数据!G111-财务基础数据!G112)*目录!$D$6 -> 0 | H31: =(财务基础数据!H111-财务基础数据!H112)*目录!$D$6 -> 0 | I31: =(财务基础数据!I111-财务基础数据!I112)*目录!$D$6 -> 0 | J31: =(财务基础数据!J111-财务基础数据!J112)*目录!$D$6 -> 0 | K31: =(财务基础数据!K111-财务基础数据!K112)*目录!$D$6 -> 0 | ... Z31: =(财务基础数据!Z111-财务基础数据!Z112)*目录!$D$6 -> 0 | AA31: =资产预测!J93+资产预测!J94+资产预测!J107+资产预测!J108-资产预测!J109+资产预测!J110 -> 0 | AB31: =资产预测!K93+资产预测!K94+资产预测!K107+资产预测!K108-资产预测!K109+资产预测!K110 -> 0 | AC31: =资产预测!L93+资产预测!L94+资产预测!L107+资产预测!L108-资产预测!L109+资产预测!L110 -> 0 | AD31: =资产预测!M93+资产预测!M94+资产预测!M107+资产预测!M108-资产预测!M109+资产预测!M110 -> 0 | AE31: =资产预测!N93+资产预测!N94+资产预测!N107+资产预测!N108-资产预测!N109+资产预测!N110 -> 0 | AF31: =资产预测!O93+资产预测!O94+资产预测!O107+资产预测!O108-资产预测!O109+资产预测!O110 -> 0 | AG31: =资产预测!P93+资产预测!P94+资产预测!P107+资产预测!P108-资产预测!P109+资产预测!P110 -> 0 | AH31: =资产预测!Q93+资产预测!Q94+资产预测!Q107+资产预测!Q108-资产预测!Q109+资产预测!Q110 -> 0 | ... AJ31: =资产预测!S93+资产预测!S94+资产预测!S107+资产预测!S108-资产预测!S109+资产预测!S110 -> 0
B32: 支付的股利 | D32: =-(财务基础数据!D113)*目录!$D$6 -> 0 | E32: =-(财务基础数据!E113)*目录!$D$6 -> 0 | F32: =-(财务基础数据!F113)*目录!$D$6 -> 0 | G32: =-(财务基础数据!G113)*目录!$D$6 -> 0 | H32: =-(财务基础数据!H113)*目录!$D$6 -> 0 | I32: =-(财务基础数据!I113)*目录!$D$6 -> 0 | J32: =-(财务基础数据!J113)*目录!$D$6 -> 0 | K32: =-(财务基础数据!K113)*目录!$D$6 -> 0 | ... Z32: =-(财务基础数据!Z113)*目录!$D$6 -> 0 | AA32: =-资产预测!J98 -> 0 | AB32: =-资产预测!K98 -> 0 | AC32: =-资产预测!L98 -> 0 | AD32: =-资产预测!M98 -> 0 | AE32: =-资产预测!N98 -> 0 | AF32: =-资产预测!O98 -> 0 | AG32: =-资产预测!P98 -> 0 | AH32: =-资产预测!Q98 -> 0 | ... AJ32: =-资产预测!S98 -> 0
B33: 其他 | D33: =(财务基础数据!D114)*目录!$D$6 -> 0 | E33: =(财务基础数据!E114)*目录!$D$6 -> 0 | F33: =(财务基础数据!F114)*目录!$D$6 -> 0 | G33: =(财务基础数据!G114)*目录!$D$6 -> 0 | H33: =(财务基础数据!H114)*目录!$D$6 -> 0 | I33: =(财务基础数据!I114)*目录!$D$6 -> 0 | J33: =(财务基础数据!J114)*目录!$D$6 -> 0 | K33: =(财务基础数据!K114)*目录!$D$6 -> 0 | ... Z33: =(财务基础数据!Z114)*目录!$D$6 -> 0 | AA33: =资产预测!J111-利润表!AA19 -> 0 | AB33: =资产预测!K111-利润表!AB19 -> 0 | AC33: =资产预测!L111-利润表!AC19 -> 0 | AD33: =资产预测!M111-利润表!AD19 -> 0 | AE33: =资产预测!N111-利润表!AE19 -> 0 | AF33: =资产预测!O111-利润表!AF19 -> 0 | AG33: =资产预测!P111-利润表!AG19 -> 0 | AH33: =资产预测!Q111-利润表!AH19 -> 0 | ... AJ33: =资产预测!S111-利润表!AJ19 -> 0
B34: 融资活动产生的现金流量净额 | D34: =(财务基础数据!D115)*目录!$D$6 -> 0 | E34: =(财务基础数据!E115)*目录!$D$6 -> 0 | F34: =(财务基础数据!F115)*目录!$D$6 -> 0 | G34: =(财务基础数据!G115)*目录!$D$6 -> 0 | H34: =(财务基础数据!H115)*目录!$D$6 -> 0 | I34: =(财务基础数据!I115)*目录!$D$6 -> 0 | J34: =(财务基础数据!J115)*目录!$D$6 -> 0 | K34: =(财务基础数据!K115)*目录!$D$6 -> 0 | ... Z34: =(财务基础数据!Z115)*目录!$D$6 -> 0 | AA34: =IF(ISERROR(SUM(AA30:AA33)),"0",SUM(AA30:AA33)) -> 0 | AB34: =IF(ISERROR(SUM(AB30:AB33)),"0",SUM(AB30:AB33)) -> 0 | AC34: =IF(ISERROR(SUM(AC30:AC33)),"0",SUM(AC30:AC33)) -> 0 | AD34: =IF(ISERROR(SUM(AD30:AD33)),"0",SUM(AD30:AD33)) -> 0 | AE34: =IF(ISERROR(SUM(AE30:AE33)),"0",SUM(AE30:AE33)) -> 0 | AF34: =IF(ISERROR(SUM(AF30:AF33)),"0",SUM(AF30:AF33)) -> 0 | AG34: =IF(ISERROR(SUM(AG30:AG33)),"0",SUM(AG30:AG33)) -> 0 | AH34: =IF(ISERROR(SUM(AH30:AH33)),"0",SUM(AH30:AH33)) -> 0 | ... AJ34: =IF(ISERROR(SUM(AJ30:AJ33)),"0",SUM(AJ30:AJ33)) -> 0
B35: 汇率变动影响 | D35: =(财务基础数据!D116)*目录!$D$6 -> 0 | E35: =(财务基础数据!E116)*目录!$D$6 -> 0 | F35: =(财务基础数据!F116)*目录!$D$6 -> 0 | G35: =(财务基础数据!G116)*目录!$D$6 -> 0 | H35: =(财务基础数据!H116)*目录!$D$6 -> 0 | I35: =(财务基础数据!I116)*目录!$D$6 -> 0 | J35: =(财务基础数据!J116)*目录!$D$6 -> 0 | K35: =(财务基础数据!K116)*目录!$D$6 -> 0 | ... Z35: =(财务基础数据!Z116)*目录!$D$6 -> 0 | AA35: =IF(财务基础数据!W$2=0,W35,IF(财务基础数据!W$2=1,X35,IF(财务基础数据!W$2=2,Y35,Z35))) -> 0 | AB35: =AA35 -> 0 | AC35: =AB35 -> 0 | AD35: =AC35 -> 0 | AE35: =AD35 -> 0 | AF35: =AE35 -> 0 | AG35: =AF35 -> 0 | AH35: =AG35 -> 0 | AI35: =AH35 -> 0 | AJ35: =AI35 -> 0
B36: 现金及现金等价物净增加额 | D36: =(财务基础数据!D118)*目录!$D$6 -> 0 | E36: =(财务基础数据!E118)*目录!$D$6 -> 0 | F36: =(财务基础数据!F118)*目录!$D$6 -> 0 | G36: =(财务基础数据!G118)*目录!$D$6 -> 0 | H36: =(财务基础数据!H118)*目录!$D$6 -> 0 | I36: =(财务基础数据!I118)*目录!$D$6 -> 0 | J36: =(财务基础数据!J118)*目录!$D$6 -> 0 | K36: =(财务基础数据!K118)*目录!$D$6 -> 0 | ... Z36: =(财务基础数据!Z118)*目录!$D$6 -> 0 | AA36: =IF(ISERROR(AA34+AA29+AA16+AA35),"0",AA34+AA29+AA16+AA35) -> 0 | AB36: =IF(ISERROR(AB34+AB29+AB16+AB35),"0",AB34+AB29+AB16+AB35) -> 0 | AC36: =IF(ISERROR(AC34+AC29+AC16+AC35),"0",AC34+AC29+AC16+AC35) -> 0 | AD36: =IF(ISERROR(AD34+AD29+AD16+AD35),"0",AD34+AD29+AD16+AD35) -> 0 | AE36: =IF(ISERROR(AE34+AE29+AE16+AE35),"0",AE34+AE29+AE16+AE35) -> 0 | AF36: =IF(ISERROR(AF34+AF29+AF16+AF35),"0",AF34+AF29+AF16+AF35) -> 0 | AG36: =IF(ISERROR(AG34+AG29+AG16+AG35),"0",AG34+AG29+AG16+AG35) -> 0 | AH36: =IF(ISERROR(AH34+AH29+AH16+AH35),"0",AH34+AH29+AH16+AH35) -> 0 | ... AJ36: =IF(ISERROR(AJ34+AJ29+AJ16+AJ35),"0",AJ34+AJ29+AJ16+AJ35) -> 0
B37: 现金及现金等价物期初余额 | D37: =(财务基础数据!D119)*目录!$D$6 -> 0 | E37: =(财务基础数据!E119)*目录!$D$6 -> 0 | F37: =(财务基础数据!F119)*目录!$D$6 -> 0 | G37: =(财务基础数据!G119)*目录!$D$6 -> 0 | H37: =(财务基础数据!H119)*目录!$D$6 -> 0 | I37: =(财务基础数据!I119)*目录!$D$6 -> 0 | J37: =(财务基础数据!J119)*目录!$D$6 -> 0 | K37: =(财务基础数据!K119)*目录!$D$6 -> 0 | ... Z37: =(财务基础数据!Z119)*目录!$D$6 -> 0 | AA37: =资产负债表!W6 -> 0 | AB37: =资产负债表!AA6 -> 0 | AC37: =资产负债表!AB6 -> 0 | AD37: =资产负债表!AC6 -> 0 | AE37: =资产负债表!AD6 -> 0 | AF37: =资产负债表!AE6 -> 0 | AG37: =资产负债表!AF6 -> 0 | AH37: =资产负债表!AG6 -> 0 | AI37: =资产负债表!AH6 -> 0 | AJ37: =资产负债表!AI6 -> 0
B38: 现金及现金等价物期末余额 | D38: =(财务基础数据!D120)*目录!$D$6 -> 0 | E38: =(财务基础数据!E120)*目录!$D$6 -> 0 | F38: =(财务基础数据!F120)*目录!$D$6 -> 0 | G38: =(财务基础数据!G120)*目录!$D$6 -> 0 | H38: =(财务基础数据!H120)*目录!$D$6 -> 0 | I38: =(财务基础数据!I120)*目录!$D$6 -> 0 | J38: =(财务基础数据!J120)*目录!$D$6 -> 0 | K38: =(财务基础数据!K120)*目录!$D$6 -> 0 | ... Z38: =(财务基础数据!Z120)*目录!$D$6 -> 0 | AA38: =AA36+AA37 -> 0 | AB38: =AB36+AB37 -> 0 | AC38: =AC36+AC37 -> 0 | AD38: =AD36+AD37 -> 0 | AE38: =AE36+AE37 -> 0 | AF38: =AF36+AF37 -> 0 | AG38: =AG36+AG37 -> 0 | AH38: =AH36+AH37 -> 0 | ... AJ38: =AJ36+AJ37 -> 0
B40: 说明：
B41: 历史年度的期初、期末现金余额，是以上市公司公布的现金及现金等价物列示的，预测年度的期初、期末现金余额，是以货币资金金额列示的，二者计算口径略有差异，因为估值时一般无法准确预测现金及现金等价物的数值。

Sheet 估值
A1: 估值假设 | B1: 参数设置 | C1: 参数说明
A2: 预测期年数 | B2: =目录!D4 -> 3 | C2: 1.企业第一阶段增长年数（3—10）；
A3: 过渡期年数 | C3: 2.企业第二阶段增长年数（1—11）；
A4: 过渡期增长率 | C4: 3.企业第二阶段增长率（如果过度期年数为0则不填写）；
A5: 永续增长率g | C5: 4.企业长期稳定发展的增长率；
A6: 贝塔值（β） | C6: 5.根据该股票和整体市场的历史数据，经过统计得出的市场风险指标；
A7: 无风险利率Rf（%） | C7: 6.以10年期国债为参考；
A8: 市场的预期收益率Rm（%） | C8: 7.可参考第三方数据或历史指数收益率的平均值；
A9: 有效税率T（%） | B9: =销售预测!J34 -> 0 | C9: 8.企业实际所得税率；
A10: 剩余月份 | B10: =12-MONTH(TODAY()) -> 9 | C10: 9.为了更精准的估值结果，此处为剩余月份（如：当前为4月，则剩余月份为8）
A11: 资本成本 | B11: 参数设置 | C11: 预测数据参考值 | F11: 参数说明
C12: =财务基础数据!AA5&"E" -> 2022E | D12: =财务基础数据!AA5+1 -> 2023 | E12: =D12+1 -> 2024
A13: 债务资本成本Kd | B13: =C13 -> 0 | C13: =资产预测!J118 -> 0 | D13: =资产预测!K118 -> 0 | E13: =资产预测!L118 -> 0 | F13: 1.长期债务的成本
A14: 债务资本比重Wd | B14: =C14 -> 0 | C14: =IF(ISERROR(资产负债表!AA35/(资产负债表!AA35+资产负债表!AA47)),"0",资产负债表!AA35/(资产负债表!AA35+资产负债表!AA47)) -> 0 | D14: =IF(ISERROR(资产负债表!AB35/(资产负债表!AB35+资产负债表!AB47)),"0",资产负债表!AB35/(资产负债表!AB35+资产负债表!AB47)) -> 0 | E14: =IF(ISERROR(资产负债表!AC35/(资产负债表!AC35+资产负债表!AC47)),"0",资产负债表!AC35/(资产负债表!AC35+资产负债表!AC47)) -> 0 | F14: 2.长期债务/（长期债务+所有者权益）
A15: 股权资本成本Ke | B15: =C15 -> 0 | C15: =$B7+$B6*($B8-$B7) -> 0 | D15: =$B7+$B6*($B8-$B7) -> 0 | E15: =$B7+$B6*($B8-$B7) -> 0 | F15: 3.Ke=Rf+β*（Rm-Rf)
A16: 加权平均资本成本WACC | B16: =IF(ISERROR(B13*B14*(1-$B9)+B15*(1-B14)),"—",B13*B14*(1-$B9)+B15*(1-B14)) -> 0 | C16: =IF(ISERROR(C13*C14*(1-$B9)+C15*(1-C14)),"—",C13*C14*(1-$B9)+C15*(1-C14)) -> 0 | D16: =IF(ISERROR(D13*D14*(1-$B9)+D15*(1-D14)),"—",D13*D14*(1-$B9)+D15*(1-D14)) -> 0 | E16: =IF(ISERROR(E13*E14*(1-$B9)+E15*(1-E14)),"—",E13*E14*(1-$B9)+E15*(1-E14)) -> 0 | F16: 4.WACC=Kd*Wd(1-T)+Ke*(1-Wd)
A19: FCFF估值 | B19: =B42 -> — | C19: 1 | D19: 2 | E19: 3 | F19: 4 | G19: 5 | H19: 6 | I19: 7 | J19: 8 | K19: 9 | L19: 10
B20: =财务基础数据!AA5-1 -> 2021 | C20: =财务基础数据!AA5&"E" -> 2022E | D20: =财务基础数据!AA5+1 -> 2023 | E20: =D20+1 -> 2024 | F20: =E20+1 -> 2025 | G20: =F20+1 -> 2026 | H20: =G20+1 -> 2027 | I20: =H20+1 -> 2028 | J20: =I20+1 -> 2029 | K20: =J20+1 -> 2030 | L20: =K20+1 -> 2031
A21: EBIT | B21: =IF(ISERROR(利润表!W35),"—",利润表!W35) -> 0 | C21: =IF(ISERROR(利润表!AA35),"—",利润表!AA35) -> 0 | D21: =IF(ISERROR(利润表!AB35),"—",利润表!AB35) -> 0 | E21: =IF(ISERROR(利润表!AC35),"—",利润表!AC35) -> 0 | F21: =IF(ISERROR(利润表!AD35),"—",利润表!AD35) -> 0 | G21: =IF(ISERROR(利润表!AE35),"—",利润表!AE35) -> 0 | H21: =IF(ISERROR(利润表!AF35),"—",利润表!AF35) -> 0 | I21: =IF(ISERROR(利润表!AG35),"—",利润表!AG35) -> 0 | J21: =IF(ISERROR(利润表!AH35),"—",利润表!AH35) -> 0 | ... L21: =IF(ISERROR(利润表!AJ35),"—",利润表!AJ35) -> 0
A22: 所得税税率 | B22: =IF(ISERROR(利润表!W25/利润表!W24),"-",利润表!W25/利润表!W24) -> - | C22: =IF(ISERROR(利润表!AA25/利润表!AA24),"-",利润表!AA25/利润表!AA24) -> - | D22: =IF(ISERROR(利润表!AB25/利润表!AB24),"-",利润表!AB25/利润表!AB24) -> - | E22: =IF(ISERROR(利润表!AC25/利润表!AC24),"-",利润表!AC25/利润表!AC24) -> - | F22: =IF(ISERROR(利润表!AD25/利润表!AD24),"-",利润表!AD25/利润表!AD24) -> - | G22: =IF(ISERROR(利润表!AE25/利润表!AE24),"-",利润表!AE25/利润表!AE24) -> - | H22: =IF(ISERROR(利润表!AF25/利润表!AF24),"-",利润表!AF25/利润表!AF24) -> - | I22: =IF(ISERROR(利润表!AG25/利润表!AG24),"-",利润表!AG25/利润表!AG24) -> - | J22: =IF(ISERROR(利润表!AH25/利润表!AH24),"-",利润表!AH25/利润表!AH24) -> - | ... L22: =IF(ISERROR(利润表!AJ25/利润表!AJ24),"-",利润表!AJ25/利润表!AJ24) -> -
A23: 息前税后利润(NOPAT) | B23: =IF(ISERROR(B21*(1-B22)),"-",B21*(1-B22)) -> - | C23: =IF(ISERROR(C21*(1-C22)),"-",C21*(1-C22)) -> - | D23: =IF(ISERROR(D21*(1-D22)),"-",D21*(1-D22)) -> - | E23: =IF(ISERROR(E21*(1-E22)),"-",E21*(1-E22)) -> - | F23: =IF(ISERROR(F21*(1-F22)),"-",F21*(1-F22)) -> - | G23: =IF(ISERROR(G21*(1-G22)),"-",G21*(1-G22)) -> - | H23: =IF(ISERROR(H21*(1-H22)),"-",H21*(1-H22)) -> - | I23: =IF(ISERROR(I21*(1-I22)),"-",I21*(1-I22)) -> - | ... L23: =IF(ISERROR(L21*(1-L22)),"-",L21*(1-L22)) -> -
A25: 加：折旧与摊销 | B25: =现金流量表!W6 -> 0 | C25: =现金流量表!AA6 -> 0 | D25: =现金流量表!AB6 -> 0 | E25: =现金流量表!AC6 -> 0 | F25: =现金流量表!AD6 -> 0 | G25: =现金流量表!AE6 -> 0 | H25: =现金流量表!AF6 -> 0 | I25: =现金流量表!AG6 -> 0 | J25: =现金流量表!AH6 -> 0 | ... L25: =现金流量表!AJ6 -> 0
A26: 减：营运资金的增加 | B26: =资产负债表!W53-资产负债表!S53 -> 0 | C26: =资产负债表!AA53-资产负债表!W53 -> 0 | D26: =资产负债表!AB53-资产负债表!AA53 -> 0 | E26: =资产负债表!AC53-资产负债表!AB53 -> 0 | F26: =资产负债表!AD53-资产负债表!AC53 -> 0 | G26: =资产负债表!AE53-资产负债表!AD53 -> 0 | H26: =资产负债表!AF53-资产负债表!AE53 -> 0 | I26: =资产负债表!AG53-资产负债表!AF53 -> 0 | J26: =资产负债表!AH53-资产负债表!AG53 -> 0 | K26: =资产负债表!AI53-资产负债表!AH53 -> 0 | L26: =资产负债表!AJ53-资产负债表!AI53 -> 0
A27: 减：资本性投资 | B27: =现金流量表!W17 -> 0 | C27: =现金流量表!AA17 -> 0 | D27: =现金流量表!AB17 -> 0 | E27: =现金流量表!AC17 -> 0 | F27: =现金流量表!AD17 -> 0 | G27: =现金流量表!AE17 -> 0 | H27: =现金流量表!AF17 -> 0 | I27: =现金流量表!AG17 -> 0 | J27: =现金流量表!AH17 -> 0 | ... L27: =现金流量表!AJ17 -> 0
A28: 公司自由现金流量FCFF | B28: =IF(ISERROR(B23+B25-B26+B27),"0.00",B23+B25-B26+B27) -> 0.00 | C28: =IF(ISERROR(IF($B2>=C19,C23+C25-C26+C27,"")),"0.00",IF($B2>=C19,C23+C25-C26+C27,"")) -> 0.00 | D28: =IF(ISERROR(IF($B2>=D19,D23+D25-D26+D27,"")),"0.00",IF($B2>=D19,D23+D25-D26+D27,"")) -> 0.00 | E28: =IF(ISERROR(IF($B2>=E19,E23+E25-E26+E27,"")),"0.00",IF($B2>=E19,E23+E25-E26+E27,"")) -> 0.00 | F28: =IF(ISERROR(IF($B2>=F19,F23+F25-F26+F27,"")),"0.00",IF($B2>=F19,F23+F25-F26+F27,"")) | G28: =IF(ISERROR(IF($B2>=G19,G23+G25-G26+G27,"")),"0.00",IF($B2>=G19,G23+G25-G26+G27,"")) | H28: =IF(ISERROR(IF($B2>=H19,H23+H25-H26+H27,"")),"0.00",IF($B2>=H19,H23+H25-H26+H27,"")) | I28: =IF(ISERROR(IF($B2>=I19,I23+I25-I26+I27,"")),"0.00",IF($B2>=I19,I23+I25-I26+I27,"")) | J28: =IF(ISERROR(IF($B2>=J19,J23+J25-J26+J27,"")),"0.00",IF($B2>=J19,J23+J25-J26+J27,"")) | ... L28: =IF(ISERROR(IF($B2>=L19,L23+L25-L26+L27,"")),"0.00",IF($B2>=L19,L23+L25-L26+L27,""))
B30: =INDEX(C20:L20,MATCH(B2,C19:L19))+1 -> 2025 | C30: =B30+1 -> 2026 | D30: =C30+1 -> 2027 | E30: =D30+1 -> 2028 | F30: =E30+1 -> 2029 | G30: =F30+1 -> 2030 | H30: =G30+1 -> 2031 | I30: =H30+1 -> 2032 | J30: =I30+1 -> 2033 | ... L30: =K30+1 -> 2035
A31: 过渡期自由现金流 | B31: =IF($B3>0,INDEX(C28:L28,MATCH(B2,C19:L19))*(1+B4),0) -> 0 | C31: =IF(($B3-C19)>0,B31*(1+$B4),"") | D31: =IF(($B3-D19)>0,C31*(1+$B4),"") | E31: =IF(($B3-E19)>0,D31*(1+$B4),"") | F31: =IF(($B3-F19)>0,E31*(1+$B4),"") | G31: =IF(($B3-G19)>0,F31*(1+$B4),"") | H31: =IF(($B3-H19)>0,G31*(1+$B4),"") | I31: =IF(($B3-I19)>0,H31*(1+$B4),"") | J31: =IF(($B3-J19)>0,I31*(1+$B4),"") | ... L31: =IF(($B3-L19)>0,K31*(1+$B4),"")
A33: FCFF预测期现值 | B33: =IF(ISERROR((NPV(B16,D28:L28)+C28*$B$10/12)/(1+B16)^($B$10/12)),"0.00",(NPV(B16,D28:L28)+C28*$B$10/12)/(1+B16)^($B$10/12)) -> 0 | D33: 敏感性分析 | E33: 折现率变化值 | G33: 0.005
A34: FCFF过渡期现值 | B34: =IF(ISERROR(IF(B3=0,0,NPV(B16,B31:L31)/(1+B16)^(B2-1+B10/12))),"0.00",IF(B3=0,0,NPV(B16,B31:L31)/(1+B16)^(B2-1+B10/12))) -> 0 | E34: 永续增长率变化值 | G34: 0.005
A35: FCFF永续价值现值 | B35: =IF(ISERROR(INDEX(C28:L28,MATCH(B2,C19:L19))*(1+B4)^B3*(1+B5)/(B16-B5)/(POWER((1+B16),B2+B3-1+B10/12))),"—",INDEX(C28:L28,MATCH(B2,C19:L19))*(1+B4)^B3*(1+B5)/(B16-B5)/(POWER((1+B16),B2+B3-1+B10/12))) -> — | E35: =B42 -> — | F35: =IF(ISERROR(G35-$G$33),"—",G35-$G$33) -> -0.015 | G35: =IF(ISERROR(H35-$G$33),"—",H35-$G$33) -> -0.01 | H35: =IF(ISERROR(I35-$G$33),"—",I35-$G$33) -> -0.005 | I35: =B16 -> 0 | J35: =IF(ISERROR(I35+$G$33),"—",I35+$G$33) -> 0.005 | K35: =IF(ISERROR(J35+$G$33),"—",J35+$G$33) -> 0.01 | L35: =IF(ISERROR(K35+$G$33),"—",K35+$G$33) -> 0.015
A36: 企业价值 | B36: =SUM(B33:B35) -> 0 | E36: =E37-$G$34 -> -0.015 | F36: =((NPV(F$35,$D$28:$L$28)+$C$28*$B$10/12)/(1+F$35)^($B$10/12)+NPV(F$35,$B$31:$L$31)/(1+F$35)^($B$2-1+$B$10/12)+INDEX($C$28:$L$28,MATCH($B$2,$C$19:$L$19))*(1+$B$4)^$B$3*(1+$E36)/(F$35-$E36)/(POWER((1+F$35),$B$2+$B$3-1+$B$10/12))+$B$37-$B$38-$B$39)/$B$41 -> #DIV/0! | G36: =((NPV(G$35,$D$28:$L$28)+$C$28*$B$10/12)/(1+G$35)^($B$10/12)+NPV(G$35,$B$31:$L$31)/(1+G$35)^($B$2-1+$B$10/12)+INDEX($C$28:$L$28,MATCH($B$2,$C$19:$L$19))*(1+$B$4)^$B$3*(1+$E36)/(G$35-$E36)/(POWER((1+G$35),$B$2+$B$3-1+$B$10/12))+$B$37-$B$38-$B$39)/$B$41 -> #VALUE! | H36: =((NPV(H$35,$D$28:$L$28)+$C$28*$B$10/12)/(1+H$35)^($B$10/12)+NPV(H$35,$B$31:$L$31)/(1+H$35)^($B$2-1+$B$10/12)+INDEX($C$28:$L$28,MATCH($B$2,$C$19:$L$19))*(1+$B$4)^$B$3*(1+$E36)/(H$35-$E36)/(POWER((1+H$35),$B$2+$B$3-1+$B$10/12))+$B$37-$B$38-$B$39)/$B$41 -> #VALUE! | I36: =((NPV(I$35,$D$28:$L$28)+$C$28*$B$10/12)/(1+I$35)^($B$10/12)+NPV(I$35,$B$31:$L$31)/(1+I$35)^($B$2-1+$B$10/12)+INDEX($C$28:$L$28,MATCH($B$2,$C$19:$L$19))*(1+$B$4)^$B$3*(1+$E36)/(I$35-$E36)/(POWER((1+I$35),$B$2+$B$3-1+$B$10/12))+$B$37-$B$38-$B$39)/$B$41 -> #VALUE! | J36: =((NPV(J$35,$D$28:$L$28)+$C$28*$B$10/12)/(1+J$35)^($B$10/12)+NPV(J$35,$B$31:$L$31)/(1+J$35)^($B$2-1+$B$10/12)+INDEX($C$28:$L$28,MATCH($B$2,$C$19:$L$19))*(1+$B$4)^$B$3*(1+$E36)/(J$35-$E36)/(POWER((1+J$35),$B$2+$B$3-1+$B$10/12))+$B$37-$B$38-$B$39)/$B$41 -> #VALUE! | K36: =((NPV(K$35,$D$28:$L$28)+$C$28*$B$10/12)/(1+K$35)^($B$10/12)+NPV(K$35,$B$31:$L$31)/(1+K$35)^($B$2-1+$B$10/12)+INDEX($C$28:$L$28,MATCH($B$2,$C$19:$L$19))*(1+$B$4)^$B$3*(1+$E36)/(K$35-$E36)/(POWER((1+K$35),$B$2+$B$3-1+$B$10/12))+$B$37-$B$38-$B$39)/$B$41 -> #VALUE! | L36: =((NPV(L$35,$D$28:$L$28)+$C$28*$B$10/12)/(1+L$35)^($B$10/12)+NPV(L$35,$B$31:$L$31)/(1+L$35)^($B$2-1+$B$10/12)+INDEX($C$28:$L$28,MATCH($B$2,$C$19:$L$19))*(1+$B$4)^$B$3*(1+$E36)/(L$35-$E36)/(POWER((1+L$35),$B$2+$B$3-1+$B$10/12))+$B$37-$B$38-$B$39)/$B$41 -> #VALUE!
A37: 加：非核心资产价值 | B37: =IF(财务基础数据!$W$2=0,资产负债表!W57,IF(财务基础数据!$W$2=1,资产负债表!X57,IF(财务基础数据!$W$2=2,资产负债表!Y57,资产负债表!Z57))) -> 0 | E37: =E38-$G$34 -> -0.01 | F37: =((NPV(F$35,$D$28:$L$28)+$C$28*$B$10/12)/(1+F$35)^($B$10/12)+NPV(F$35,$B$31:$L$31)/(1+F$35)^($B$2-1+$B$10/12)+INDEX($C$28:$L$28,MATCH($B$2,$C$19:$L$19))*(1+$B$4)^$B$3*(1+$E37)/(F$35-$E37)/(POWER((1+F$35),$B$2+$B$3-1+$B$10/12))+$B$37-$B$38-$B$39)/$B$41 -> #VALUE! | G37: =((NPV(G$35,$D$28:$L$28)+$C$28*$B$10/12)/(1+G$35)^($B$10/12)+NPV(G$35,$B$31:$L$31)/(1+G$35)^($B$2-1+$B$10/12)+INDEX($C$28:$L$28,MATCH($B$2,$C$19:$L$19))*(1+$B$4)^$B$3*(1+$E37)/(G$35-$E37)/(POWER((1+G$35),$B$2+$B$3-1+$B$10/12))+$B$37-$B$38-$B$39)/$B$41 -> #DIV/0! | H37: =((NPV(H$35,$D$28:$L$28)+$C$28*$B$10/12)/(1+H$35)^($B$10/12)+NPV(H$35,$B$31:$L$31)/(1+H$35)^($B$2-1+$B$10/12)+INDEX($C$28:$L$28,MATCH($B$2,$C$19:$L$19))*(1+$B$4)^$B$3*(1+$E37)/(H$35-$E37)/(POWER((1+H$35),$B$2+$B$3-1+$B$10/12))+$B$37-$B$38-$B$39)/$B$41 -> #VALUE! | I37: =((NPV(I$35,$D$28:$L$28)+$C$28*$B$10/12)/(1+I$35)^($B$10/12)+NPV(I$35,$B$31:$L$31)/(1+I$35)^($B$2-1+$B$10/12)+INDEX($C$28:$L$28,MATCH($B$2,$C$19:$L$19))*(1+$B$4)^$B$3*(1+$E37)/(I$35-$E37)/(POWER((1+I$35),$B$2+$B$3-1+$B$10/12))+$B$37-$B$38-$B$39)/$B$41 -> #VALUE! | J37: =((NPV(J$35,$D$28:$L$28)+$C$28*$B$10/12)/(1+J$35)^($B$10/12)+NPV(J$35,$B$31:$L$31)/(1+J$35)^($B$2-1+$B$10/12)+INDEX($C$28:$L$28,MATCH($B$2,$C$19:$L$19))*(1+$B$4)^$B$3*(1+$E37)/(J$35-$E37)/(POWER((1+J$35),$B$2+$B$3-1+$B$10/12))+$B$37-$B$38-$B$39)/$B$41 -> #VALUE! | K37: =((NPV(K$35,$D$28:$L$28)+$C$28*$B$10/12)/(1+K$35)^($B$10/12)+NPV(K$35,$B$31:$L$31)/(1+K$35)^($B$2-1+$B$10/12)+INDEX($C$28:$L$28,MATCH($B$2,$C$19:$L$19))*(1+$B$4)^$B$3*(1+$E37)/(K$35-$E37)/(POWER((1+K$35),$B$2+$B$3-1+$B$10/12))+$B$37-$B$38-$B$39)/$B$41 -> #VALUE! | L37: =((NPV(L$35,$D$28:$L$28)+$C$28*$B$10/12)/(1+L$35)^($B$10/12)+NPV(L$35,$B$31:$L$31)/(1+L$35)^($B$2-1+$B$10/12)+INDEX($C$28:$L$28,MATCH($B$2,$C$19:$L$19))*(1+$B$4)^$B$3*(1+$E37)/(L$35-$E37)/(POWER((1+L$35),$B$2+$B$3-1+$B$10/12))+$B$37-$B$38-$B$39)/$B$41 -> #VALUE!
A38: 减：付息债务 | B38: =IF(财务基础数据!$W$2=0,资产负债表!W55,IF(财务基础数据!$W$2=1,资产负债表!X55,IF(财务基础数据!$W$2=2,资产负债表!Y55,资产负债表!Z55))) -> 0 | E38: =E39-$G$34 -> -0.005 | F38: =((NPV(F$35,$D$28:$L$28)+$C$28*$B$10/12)/(1+F$35)^($B$10/12)+NPV(F$35,$B$31:$L$31)/(1+F$35)^($B$2-1+$B$10/12)+INDEX($C$28:$L$28,MATCH($B$2,$C$19:$L$19))*(1+$B$4)^$B$3*(1+$E38)/(F$35-$E38)/(POWER((1+F$35),$B$2+$B$3-1+$B$10/12))+$B$37-$B$38-$B$39)/$B$41 -> #VALUE! | G38: =((NPV(G$35,$D$28:$L$28)+$C$28*$B$10/12)/(1+G$35)^($B$10/12)+NPV(G$35,$B$31:$L$31)/(1+G$35)^($B$2-1+$B$10/12)+INDEX($C$28:$L$28,MATCH($B$2,$C$19:$L$19))*(1+$B$4)^$B$3*(1+$E38)/(G$35-$E38)/(POWER((1+G$35),$B$2+$B$3-1+$B$10/12))+$B$37-$B$38-$B$39)/$B$41 -> #VALUE! | H38: =((NPV(H$35,$D$28:$L$28)+$C$28*$B$10/12)/(1+H$35)^($B$10/12)+NPV(H$35,$B$31:$L$31)/(1+H$35)^($B$2-1+$B$10/12)+INDEX($C$28:$L$28,MATCH($B$2,$C$19:$L$19))*(1+$B$4)^$B$3*(1+$E38)/(H$35-$E38)/(POWER((1+H$35),$B$2+$B$3-1+$B$10/12))+$B$37-$B$38-$B$39)/$B$41 -> #DIV/0! | I38: =((NPV(I$35,$D$28:$L$28)+$C$28*$B$10/12)/(1+I$35)^($B$10/12)+NPV(I$35,$B$31:$L$31)/(1+I$35)^($B$2-1+$B$10/12)+INDEX($C$28:$L$28,MATCH($B$2,$C$19:$L$19))*(1+$B$4)^$B$3*(1+$E38)/(I$35-$E38)/(POWER((1+I$35),$B$2+$B$3-1+$B$10/12))+$B$37-$B$38-$B$39)/$B$41 -> #VALUE! | J38: =((NPV(J$35,$D$28:$L$28)+$C$28*$B$10/12)/(1+J$35)^($B$10/12)+NPV(J$35,$B$31:$L$31)/(1+J$35)^($B$2-1+$B$10/12)+INDEX($C$28:$L$28,MATCH($B$2,$C$19:$L$19))*(1+$B$4)^$B$3*(1+$E38)/(J$35-$E38)/(POWER((1+J$35),$B$2+$B$3-1+$B$10/12))+$B$37-$B$38-$B$39)/$B$41 -> #VALUE! | K38: =((NPV(K$35,$D$28:$L$28)+$C$28*$B$10/12)/(1+K$35)^($B$10/12)+NPV(K$35,$B$31:$L$31)/(1+K$35)^($B$2-1+$B$10/12)+INDEX($C$28:$L$28,MATCH($B$2,$C$19:$L$19))*(1+$B$4)^$B$3*(1+$E38)/(K$35-$E38)/(POWER((1+K$35),$B$2+$B$3-1+$B$10/12))+$B$37-$B$38-$B$39)/$B$41 -> #VALUE! | L38: =((NPV(L$35,$D$28:$L$28)+$C$28*$B$10/12)/(1+L$35)^($B$10/12)+NPV(L$35,$B$31:$L$31)/(1+L$35)^($B$2-1+$B$10/12)+INDEX($C$28:$L$28,MATCH($B$2,$C$19:$L$19))*(1+$B$4)^$B$3*(1+$E38)/(L$35-$E38)/(POWER((1+L$35),$B$2+$B$3-1+$B$10/12))+$B$37-$B$38-$B$39)/$B$41 -> #VALUE!
A39: 减：少数股东权益 | B39: =IF(财务基础数据!$W$2=0,资产负债表!W46,IF(财务基础数据!$W$2=1,资产负债表!X46,IF(财务基础数据!$W$2=2,资产负债表!Y46,资产负债表!Z46))) -> 0 | E39: =B5 -> 0 | F39: =((NPV(F$35,$D$28:$L$28)+$C$28*$B$10/12)/(1+F$35)^($B$10/12)+NPV(F$35,$B$31:$L$31)/(1+F$35)^($B$2-1+$B$10/12)+INDEX($C$28:$L$28,MATCH($B$2,$C$19:$L$19))*(1+$B$4)^$B$3*(1+$E39)/(F$35-$E39)/(POWER((1+F$35),$B$2+$B$3-1+$B$10/12))+$B$37-$B$38-$B$39)/$B$41 -> #VALUE! | G39: =((NPV(G$35,$D$28:$L$28)+$C$28*$B$10/12)/(1+G$35)^($B$10/12)+NPV(G$35,$B$31:$L$31)/(1+G$35)^($B$2-1+$B$10/12)+INDEX($C$28:$L$28,MATCH($B$2,$C$19:$L$19))*(1+$B$4)^$B$3*(1+$E39)/(G$35-$E39)/(POWER((1+G$35),$B$2+$B$3-1+$B$10/12))+$B$37-$B$38-$B$39)/$B$41 -> #VALUE! | H39: =((NPV(H$35,$D$28:$L$28)+$C$28*$B$10/12)/(1+H$35)^($B$10/12)+NPV(H$35,$B$31:$L$31)/(1+H$35)^($B$2-1+$B$10/12)+INDEX($C$28:$L$28,MATCH($B$2,$C$19:$L$19))*(1+$B$4)^$B$3*(1+$E39)/(H$35-$E39)/(POWER((1+H$35),$B$2+$B$3-1+$B$10/12))+$B$37-$B$38-$B$39)/$B$41 -> #VALUE! | I39: =((NPV(I$35,$D$28:$L$28)+$C$28*$B$10/12)/(1+I$35)^($B$10/12)+NPV(I$35,$B$31:$L$31)/(1+I$35)^($B$2-1+$B$10/12)+INDEX($C$28:$L$28,MATCH($B$2,$C$19:$L$19))*(1+$B$4)^$B$3*(1+$E39)/(I$35-$E39)/(POWER((1+I$35),$B$2+$B$3-1+$B$10/12))+$B$37-$B$38-$B$39)/$B$41 -> #DIV/0! | J39: =((NPV(J$35,$D$28:$L$28)+$C$28*$B$10/12)/(1+J$35)^($B$10/12)+NPV(J$35,$B$31:$L$31)/(1+J$35)^($B$2-1+$B$10/12)+INDEX($C$28:$L$28,MATCH($B$2,$C$19:$L$19))*(1+$B$4)^$B$3*(1+$E39)/(J$35-$E39)/(POWER((1+J$35),$B$2+$B$3-1+$B$10/12))+$B$37-$B$38-$B$39)/$B$41 -> #VALUE! | K39: =((NPV(K$35,$D$28:$L$28)+$C$28*$B$10/12)/(1+K$35)^($B$10/12)+NPV(K$35,$B$31:$L$31)/(1+K$35)^($B$2-1+$B$10/12)+INDEX($C$28:$L$28,MATCH($B$2,$C$19:$L$19))*(1+$B$4)^$B$3*(1+$E39)/(K$35-$E39)/(POWER((1+K$35),$B$2+$B$3-1+$B$10/12))+$B$37-$B$38-$B$39)/$B$41 -> #VALUE! | L39: =((NPV(L$35,$D$28:$L$28)+$C$28*$B$10/12)/(1+L$35)^($B$10/12)+NPV(L$35,$B$31:$L$31)/(1+L$35)^($B$2-1+$B$10/12)+INDEX($C$28:$L$28,MATCH($B$2,$C$19:$L$19))*(1+$B$4)^$B$3*(1+$E39)/(L$35-$E39)/(POWER((1+L$35),$B$2+$B$3-1+$B$10/12))+$B$37-$B$38-$B$39)/$B$41 -> #VALUE!
A40: 股权价值 | B40: =B36+B37-B38-B39 -> 0 | E40: =E39+$G$34 -> 0.005 | F40: =((NPV(F$35,$D$28:$L$28)+$C$28*$B$10/12)/(1+F$35)^($B$10/12)+NPV(F$35,$B$31:$L$31)/(1+F$35)^($B$2-1+$B$10/12)+INDEX($C$28:$L$28,MATCH($B$2,$C$19:$L$19))*(1+$B$4)^$B$3*(1+$E40)/(F$35-$E40)/(POWER((1+F$35),$B$2+$B$3-1+$B$10/12))+$B$37-$B$38-$B$39)/$B$41 -> #VALUE! | G40: =((NPV(G$35,$D$28:$L$28)+$C$28*$B$10/12)/(1+G$35)^($B$10/12)+NPV(G$35,$B$31:$L$31)/(1+G$35)^($B$2-1+$B$10/12)+INDEX($C$28:$L$28,MATCH($B$2,$C$19:$L$19))*(1+$B$4)^$B$3*(1+$E40)/(G$35-$E40)/(POWER((1+G$35),$B$2+$B$3-1+$B$10/12))+$B$37-$B$38-$B$39)/$B$41 -> #VALUE! | H40: =((NPV(H$35,$D$28:$L$28)+$C$28*$B$10/12)/(1+H$35)^($B$10/12)+NPV(H$35,$B$31:$L$31)/(1+H$35)^($B$2-1+$B$10/12)+INDEX($C$28:$L$28,MATCH($B$2,$C$19:$L$19))*(1+$B$4)^$B$3*(1+$E40)/(H$35-$E40)/(POWER((1+H$35),$B$2+$B$3-1+$B$10/12))+$B$37-$B$38-$B$39)/$B$41 -> #VALUE! | I40: =((NPV(I$35,$D$28:$L$28)+$C$28*$B$10/12)/(1+I$35)^($B$10/12)+NPV(I$35,$B$31:$L$31)/(1+I$35)^($B$2-1+$B$10/12)+INDEX($C$28:$L$28,MATCH($B$2,$C$19:$L$19))*(1+$B$4)^$B$3*(1+$E40)/(I$35-$E40)/(POWER((1+I$35),$B$2+$B$3-1+$B$10/12))+$B$37-$B$38-$B$39)/$B$41 -> #VALUE! | J40: =((NPV(J$35,$D$28:$L$28)+$C$28*$B$10/12)/(1+J$35)^($B$10/12)+NPV(J$35,$B$31:$L$31)/(1+J$35)^($B$2-1+$B$10/12)+INDEX($C$28:$L$28,MATCH($B$2,$C$19:$L$19))*(1+$B$4)^$B$3*(1+$E40)/(J$35-$E40)/(POWER((1+J$35),$B$2+$B$3-1+$B$10/12))+$B$37-$B$38-$B$39)/$B$41 -> #DIV/0! | K40: =((NPV(K$35,$D$28:$L$28)+$C$28*$B$10/12)/(1+K$35)^($B$10/12)+NPV(K$35,$B$31:$L$31)/(1+K$35)^($B$2-1+$B$10/12)+INDEX($C$28:$L$28,MATCH($B$2,$C$19:$L$19))*(1+$B$4)^$B$3*(1+$E40)/(K$35-$E40)/(POWER((1+K$35),$B$2+$B$3-1+$B$10/12))+$B$37-$B$38-$B$39)/$B$41 -> #VALUE! | L40: =((NPV(L$35,$D$28:$L$28)+$C$28*$B$10/12)/(1+L$35)^($B$10/12)+NPV(L$35,$B$31:$L$31)/(1+L$35)^($B$2-1+$B$10/12)+INDEX($C$28:$L$28,MATCH($B$2,$C$19:$L$19))*(1+$B$4)^$B$3*(1+$E40)/(L$35-$E40)/(POWER((1+L$35),$B$2+$B$3-1+$B$10/12))+$B$37-$B$38-$B$39)/$B$41 -> #VALUE!
A41: 总股本 | B41: =IF(ISERROR(目录!F7*1000000*目录!D6),"—",目录!F7*1000000*目录!D6) -> — | E41: =E40+$G$34 -> 0.01 | F41: =((NPV(F$35,$D$28:$L$28)+$C$28*$B$10/12)/(1+F$35)^($B$10/12)+NPV(F$35,$B$31:$L$31)/(1+F$35)^($B$2-1+$B$10/12)+INDEX($C$28:$L$28,MATCH($B$2,$C$19:$L$19))*(1+$B$4)^$B$3*(1+$E41)/(F$35-$E41)/(POWER((1+F$35),$B$2+$B$3-1+$B$10/12))+$B$37-$B$38-$B$39)/$B$41 -> #VALUE! | G41: =((NPV(G$35,$D$28:$L$28)+$C$28*$B$10/12)/(1+G$35)^($B$10/12)+NPV(G$35,$B$31:$L$31)/(1+G$35)^($B$2-1+$B$10/12)+INDEX($C$28:$L$28,MATCH($B$2,$C$19:$L$19))*(1+$B$4)^$B$3*(1+$E41)/(G$35-$E41)/(POWER((1+G$35),$B$2+$B$3-1+$B$10/12))+$B$37-$B$38-$B$39)/$B$41 -> #VALUE! | H41: =((NPV(H$35,$D$28:$L$28)+$C$28*$B$10/12)/(1+H$35)^($B$10/12)+NPV(H$35,$B$31:$L$31)/(1+H$35)^($B$2-1+$B$10/12)+INDEX($C$28:$L$28,MATCH($B$2,$C$19:$L$19))*(1+$B$4)^$B$3*(1+$E41)/(H$35-$E41)/(POWER((1+H$35),$B$2+$B$3-1+$B$10/12))+$B$37-$B$38-$B$39)/$B$41 -> #VALUE! | I41: =((NPV(I$35,$D$28:$L$28)+$C$28*$B$10/12)/(1+I$35)^($B$10/12)+NPV(I$35,$B$31:$L$31)/(1+I$35)^($B$2-1+$B$10/12)+INDEX($C$28:$L$28,MATCH($B$2,$C$19:$L$19))*(1+$B$4)^$B$3*(1+$E41)/(I$35-$E41)/(POWER((1+I$35),$B$2+$B$3-1+$B$10/12))+$B$37-$B$38-$B$39)/$B$41 -> #VALUE! | J41: =((NPV(J$35,$D$28:$L$28)+$C$28*$B$10/12)/(1+J$35)^($B$10/12)+NPV(J$35,$B$31:$L$31)/(1+J$35)^($B$2-1+$B$10/12)+INDEX($C$28:$L$28,MATCH($B$2,$C$19:$L$19))*(1+$B$4)^$B$3*(1+$E41)/(J$35-$E41)/(POWER((1+J$35),$B$2+$B$3-1+$B$10/12))+$B$37-$B$38-$B$39)/$B$41 -> #VALUE! | K41: =((NPV(K$35,$D$28:$L$28)+$C$28*$B$10/12)/(1+K$35)^($B$10/12)+NPV(K$35,$B$31:$L$31)/(1+K$35)^($B$2-1+$B$10/12)+INDEX($C$28:$L$28,MATCH($B$2,$C$19:$L$19))*(1+$B$4)^$B$3*(1+$E41)/(K$35-$E41)/(POWER((1+K$35),$B$2+$B$3-1+$B$10/12))+$B$37-$B$38-$B$39)/$B$41 -> #DIV/0! | L41: =((NPV(L$35,$D$28:$L$28)+$C$28*$B$10/12)/(1+L$35)^($B$10/12)+NPV(L$35,$B$31:$L$31)/(1+L$35)^($B$2-1+$B$10/12)+INDEX($C$28:$L$28,MATCH($B$2,$C$19:$L$19))*(1+$B$4)^$B$3*(1+$E41)/(L$35-$E41)/(POWER((1+L$35),$B$2+$B$3-1+$B$10/12))+$B$37-$B$38-$B$39)/$B$41 -> #VALUE!
A42: ="每股价值("&目录!F8&")" -> 每股价值(XXXX) | B42: =IF(ISERROR(B40/B41),"—",B40/B41) -> — | E42: =E41+$G$34 -> 0.015 | F42: =((NPV(F$35,$D$28:$L$28)+$C$28*$B$10/12)/(1+F$35)^($B$10/12)+NPV(F$35,$B$31:$L$31)/(1+F$35)^($B$2-1+$B$10/12)+INDEX($C$28:$L$28,MATCH($B$2,$C$19:$L$19))*(1+$B$4)^$B$3*(1+$E42)/(F$35-$E42)/(POWER((1+F$35),$B$2+$B$3-1+$B$10/12))+$B$37-$B$38-$B$39)/$B$41 -> #VALUE! | G42: =((NPV(G$35,$D$28:$L$28)+$C$28*$B$10/12)/(1+G$35)^($B$10/12)+NPV(G$35,$B$31:$L$31)/(1+G$35)^($B$2-1+$B$10/12)+INDEX($C$28:$L$28,MATCH($B$2,$C$19:$L$19))*(1+$B$4)^$B$3*(1+$E42)/(G$35-$E42)/(POWER((1+G$35),$B$2+$B$3-1+$B$10/12))+$B$37-$B$38-$B$39)/$B$41 -> #VALUE! | H42: =((NPV(H$35,$D$28:$L$28)+$C$28*$B$10/12)/(1+H$35)^($B$10/12)+NPV(H$35,$B$31:$L$31)/(1+H$35)^($B$2-1+$B$10/12)+INDEX($C$28:$L$28,MATCH($B$2,$C$19:$L$19))*(1+$B$4)^$B$3*(1+$E42)/(H$35-$E42)/(POWER((1+H$35),$B$2+$B$3-1+$B$10/12))+$B$37-$B$38-$B$39)/$B$41 -> #VALUE! | I42: =((NPV(I$35,$D$28:$L$28)+$C$28*$B$10/12)/(1+I$35)^($B$10/12)+NPV(I$35,$B$31:$L$31)/(1+I$35)^($B$2-1+$B$10/12)+INDEX($C$28:$L$28,MATCH($B$2,$C$19:$L$19))*(1+$B$4)^$B$3*(1+$E42)/(I$35-$E42)/(POWER((1+I$35),$B$2+$B$3-1+$B$10/12))+$B$37-$B$38-$B$39)/$B$41 -> #VALUE! | J42: =((NPV(J$35,$D$28:$L$28)+$C$28*$B$10/12)/(1+J$35)^($B$10/12)+NPV(J$35,$B$31:$L$31)/(1+J$35)^($B$2-1+$B$10/12)+INDEX($C$28:$L$28,MATCH($B$2,$C$19:$L$19))*(1+$B$4)^$B$3*(1+$E42)/(J$35-$E42)/(POWER((1+J$35),$B$2+$B$3-1+$B$10/12))+$B$37-$B$38-$B$39)/$B$41 -> #VALUE! | K42: =((NPV(K$35,$D$28:$L$28)+$C$28*$B$10/12)/(1+K$35)^($B$10/12)+NPV(K$35,$B$31:$L$31)/(1+K$35)^($B$2-1+$B$10/12)+INDEX($C$28:$L$28,MATCH($B$2,$C$19:$L$19))*(1+$B$4)^$B$3*(1+$E42)/(K$35-$E42)/(POWER((1+K$35),$B$2+$B$3-1+$B$10/12))+$B$37-$B$38-$B$39)/$B$41 -> #VALUE! | L42: =((NPV(L$35,$D$28:$L$28)+$C$28*$B$10/12)/(1+L$35)^($B$10/12)+NPV(L$35,$B$31:$L$31)/(1+L$35)^($B$2-1+$B$10/12)+INDEX($C$28:$L$28,MATCH($B$2,$C$19:$L$19))*(1+$B$4)^$B$3*(1+$E42)/(L$35-$E42)/(POWER((1+L$35),$B$2+$B$3-1+$B$10/12))+$B$37-$B$38-$B$39)/$B$41 -> #DIV/0!
C44: =C20 -> 2022E | D44: =D20 -> 2023 | E44: =E20 -> 2024 | F44: =F20 -> 2025 | G44: =G20 -> 2026 | H44: =H20 -> 2027 | I44: =I20 -> 2028 | J44: =J20 -> 2029 | ... L44: =L20 -> 2031
B45: P/E | C45: =IF(ISERROR($B$40/利润表!AA29),"—",$B$40/利润表!AA29) -> — | D45: =IF(ISERROR($B$40/利润表!AB29),"—",$B$40/利润表!AB29) -> — | E45: =IF(ISERROR($B$40/利润表!AC29),"—",$B$40/利润表!AC29) -> — | F45: =IF(ISERROR($B$40/利润表!AD29),"—",$B$40/利润表!AD29) -> — | G45: =IF(ISERROR($B$40/利润表!AE29),"—",$B$40/利润表!AE29) -> — | H45: =IF(ISERROR($B$40/利润表!AF29),"—",$B$40/利润表!AF29) -> — | I45: =IF(ISERROR($B$40/利润表!AG29),"—",$B$40/利润表!AG29) -> — | J45: =IF(ISERROR($B$40/利润表!AH29),"—",$B$40/利润表!AH29) -> — | ... L45: =IF(ISERROR($B$40/利润表!AJ29),"—",$B$40/利润表!AJ29) -> —
B46: P/B | C46: =IF(ISERROR($B$40/资产负债表!AA45),"—",$B$40/资产负债表!AA45) -> — | D46: =IF(ISERROR($B$40/资产负债表!AB45),"—",$B$40/资产负债表!AB45) -> — | E46: =IF(ISERROR($B$40/资产负债表!AC45),"—",$B$40/资产负债表!AC45) -> — | F46: =IF(ISERROR($B$40/资产负债表!AD45),"—",$B$40/资产负债表!AD45) -> — | G46: =IF(ISERROR($B$40/资产负债表!AE45),"—",$B$40/资产负债表!AE45) -> — | H46: =IF(ISERROR($B$40/资产负债表!AF45),"—",$B$40/资产负债表!AF45) -> — | I46: =IF(ISERROR($B$40/资产负债表!AG45),"—",$B$40/资产负债表!AG45) -> — | J46: =IF(ISERROR($B$40/资产负债表!AH45),"—",$B$40/资产负债表!AH45) -> — | ... L46: =IF(ISERROR($B$40/资产负债表!AJ45),"—",$B$40/资产负债表!AJ45) -> —
B47: P/S | C47: =IF(ISERROR($B$40/利润表!AA6),"—",$B$40/利润表!AA6) -> — | D47: =IF(ISERROR($B$40/利润表!AB6),"—",$B$40/利润表!AB6) -> — | E47: =IF(ISERROR($B$40/利润表!AC6),"—",$B$40/利润表!AC6) -> — | F47: =IF(ISERROR($B$40/利润表!AD6),"—",$B$40/利润表!AD6) -> — | G47: =IF(ISERROR($B$40/利润表!AE6),"—",$B$40/利润表!AE6) -> — | H47: =IF(ISERROR($B$40/利润表!AF6),"—",$B$40/利润表!AF6) -> — | I47: =IF(ISERROR($B$40/利润表!AG6),"—",$B$40/利润表!AG6) -> — | J47: =IF(ISERROR($B$40/利润表!AH6),"—",$B$40/利润表!AH6) -> — | ... L47: =IF(ISERROR($B$40/利润表!AJ6),"—",$B$40/利润表!AJ6) -> —
A49: FCFE估值 | B49: =B69 -> — | C49: 1 | D49: 2 | E49: 3 | F49: 4 | G49: 5 | H49: 6 | I49: 7 | J49: 8 | K49: 9 | L49: 10
B50: =B20 -> 2021 | C50: =C20 -> 2022E | D50: =D20 -> 2023 | E50: =E20 -> 2024 | F50: =F20 -> 2025 | G50: =G20 -> 2026 | H50: =H20 -> 2027 | I50: =I20 -> 2028 | ... L50: =L20 -> 2031
A51: 净利润 | B51: =利润表!W29 -> 0 | C51: =利润表!AA29 -> 0 | D51: =利润表!AB29 -> 0 | E51: =利润表!AC29 -> 0 | F51: =利润表!AD29 -> 0 | G51: =利润表!AE29 -> 0 | H51: =利润表!AF29 -> 0 | I51: =利润表!AG29 -> 0 | J51: =利润表!AH29 -> 0 | ... L51: =利润表!AJ29 -> 0
A52: 加：折旧与摊销 | B52: =现金流量表!W6 -> 0 | C52: =现金流量表!AA6 -> 0 | D52: =现金流量表!AB6 -> 0 | E52: =现金流量表!AC6 -> 0 | F52: =现金流量表!AD6 -> 0 | G52: =现金流量表!AE6 -> 0 | H52: =现金流量表!AF6 -> 0 | I52: =现金流量表!AG6 -> 0 | J52: =现金流量表!AH6 -> 0 | ... L52: =现金流量表!AJ6 -> 0
A53: 减：营运资金的增加 | B53: =资产负债表!W53-资产负债表!S53 -> 0 | C53: =资产负债表!AA53-资产负债表!W53 -> 0 | D53: =资产负债表!AB53-资产负债表!AA53 -> 0 | E53: =资产负债表!AC53-资产负债表!AB53 -> 0 | F53: =资产负债表!AD53-资产负债表!AC53 -> 0 | G53: =资产负债表!AE53-资产负债表!AD53 -> 0 | H53: =资产负债表!AF53-资产负债表!AE53 -> 0 | I53: =资产负债表!AG53-资产负债表!AF53 -> 0 | J53: =资产负债表!AH53-资产负债表!AG53 -> 0 | K53: =资产负债表!AI53-资产负债表!AH53 -> 0 | L53: =资产负债表!AJ53-资产负债表!AI53 -> 0
A54: 减：资本性投资 | B54: =现金流量表!W17 -> 0 | C54: =现金流量表!AA17 -> 0 | D54: =现金流量表!AB17 -> 0 | E54: =现金流量表!AC17 -> 0 | F54: =现金流量表!AD17 -> 0 | G54: =现金流量表!AE17 -> 0 | H54: =现金流量表!AF17 -> 0 | I54: =现金流量表!AG17 -> 0 | J54: =现金流量表!AH17 -> 0 | ... L54: =现金流量表!AJ17 -> 0
A55: 加：新增付息债务 | B55: =资产预测!F115+资产预测!F123 -> 0 | C55: =资产预测!J115+资产预测!J116+资产预测!J123 -> 0 | D55: =资产预测!K115+资产预测!K116+资产预测!K123 -> 0 | E55: =资产预测!L115+资产预测!L116+资产预测!L123 -> 0 | F55: =资产预测!M115+资产预测!M116+资产预测!M123 -> 0 | G55: =资产预测!N115+资产预测!N116+资产预测!N123 -> 0 | H55: =资产预测!O115+资产预测!O116+资产预测!O123 -> 0 | I55: =资产预测!P115+资产预测!P116+资产预测!P123 -> 0 | J55: =资产预测!Q115+资产预测!Q116+资产预测!Q123 -> 0 | ... L55: =资产预测!S115+资产预测!S116+资产预测!S123 -> 0
A56: 加：其他非现金调整 | B56: =现金流量表!W15 -> 0 | C56: =现金流量表!AA15 -> 0 | D56: =现金流量表!AB15 -> 0 | E56: =现金流量表!AC15 -> 0 | F56: =现金流量表!AD15 -> 0 | G56: =现金流量表!AE15 -> 0 | H56: =现金流量表!AF15 -> 0 | I56: =现金流量表!AG15 -> 0 | J56: =现金流量表!AH15 -> 0 | ... L56: =现金流量表!AJ15 -> 0
A57: 股权自由现金流量FCFE | B57: =B51+B52-B53+B54+B55+B56 -> 0 | C57: =IF(ISERROR(IF($B2>=C49,C51+C52-C53+C54+C55+C56,"")),"0.00",IF($B2>=C49,C51+C52-C53+C54+C55+C56,"")) -> 0 | D57: =IF(ISERROR(IF($B2>=D49,D51+D52-D53+D54+D55+D56,"")),"0.00",IF($B2>=D49,D51+D52-D53+D54+D55+D56,"")) -> 0 | E57: =IF(ISERROR(IF($B2>=E49,E51+E52-E53+E54+E55+E56,"")),"0.00",IF($B2>=E49,E51+E52-E53+E54+E55+E56,"")) -> 0 | F57: =IF(ISERROR(IF($B2>=F49,F51+F52-F53+F54+F55+F56,"")),"0.00",IF($B2>=F49,F51+F52-F53+F54+F55+F56,"")) | G57: =IF(ISERROR(IF($B2>=G49,G51+G52-G53+G54+G55+G56,"")),"0.00",IF($B2>=G49,G51+G52-G53+G54+G55+G56,"")) | H57: =IF(ISERROR(IF($B2>=H49,H51+H52-H53+H54+H55+H56,"")),"0.00",IF($B2>=H49,H51+H52-H53+H54+H55+H56,"")) | I57: =IF(ISERROR(IF($B2>=I49,I51+I52-I53+I54+I55+I56,"")),"0.00",IF($B2>=I49,I51+I52-I53+I54+I55+I56,"")) | J57: =IF(ISERROR(IF($B2>=J49,J51+J52-J53+J54+J55+J56,"")),"0.00",IF($B2>=J49,J51+J52-J53+J54+J55+J56,"")) | ... L57: =IF(ISERROR(IF($B2>=L49,L51+L52-L53+L54+L55+L56,"")),"0.00",IF($B2>=L49,L51+L52-L53+L54+L55+L56,""))
B59: =INDEX(C50:L50,MATCH(B2,C49:K49))+1 -> 2025 | C59: =B59+1 -> 2026 | D59: =C59+1 -> 2027 | E59: =D59+1 -> 2028 | F59: =E59+1 -> 2029 | G59: =F59+1 -> 2030 | H59: =G59+1 -> 2031 | I59: =H59+1 -> 2032 | J59: =I59+1 -> 2033 | ... L59: =K59+1 -> 2035
A60: 过渡期自由现金流 | B60: =IF($B3>0,INDEX(C57:L57,MATCH(B2,C49:L49))*(1+B4),0) -> 0 | C60: =IF(($B3-C49)>0,B60*(1+$B4),"") | D60: =IF(($B3-D49)>0,C60*(1+$B4),"") | E60: =IF(($B3-E49)>0,D60*(1+$B4),"") | F60: =IF(($B3-F49)>0,E60*(1+$B4),"") | G60: =IF(($B3-G49)>0,F60*(1+$B4),"") | H60: =IF(($B3-H49)>0,G60*(1+$B4),"") | I60: =IF(($B3-I49)>0,H60*(1+$B4),"") | J60: =IF(($B3-J49)>0,I60*(1+$B4),"") | ... L60: =IF(($B3-L49)>0,K60*(1+$B4),"")
D62: 敏感性分析 | E62: 折现率变化值 | G62: 0.005
E63: 永续增长率变化值 | G63: 0.005
A64: FCFE预测期现值 | B64: =(NPV(B15,D57:L57)+C57*B10/12)/(1+B15)^(B10/12) -> 0 | E64: =B69 -> — | F64: =G64-$G$62 -> -0.015 | G64: =H64-$G$62 -> -0.01 | H64: =I64-$G$62 -> -0.005 | I64: =B15 -> 0 | J64: =I64+$G$62 -> 0.005 | K64: =J64+$G$62 -> 0.01 | L64: =K64+$G$62 -> 0.015
A65: FCFE过渡期现值 | B65: =IF(B3=0,0,NPV(B15,B60:L60)/(1+B15)^(B2-1+B10/12)) -> 0 | E65: =E66-$G$63 -> -0.015 | F65: =((NPV(F$64,$D$57:$L$57)+$C$57*$B$10/12)/(1+F$64)^($B$10/12)+NPV(F$64,$B$60:$L$60)/(1+F$64)^($B$2-1+$B$10/12)+INDEX($C$57:$L$57,MATCH($B$2,$C$49:$L$49))*(1+$B$4)^$B$3*(1+$E65)/(F$64-$E65)/(POWER((1+F$64),$B$2+$B$3-1+$B$10/12)))/$B$68 -> #DIV/0! | G65: =((NPV(G$64,$D$57:$L$57)+$C$57*$B$10/12)/(1+G$64)^($B$10/12)+NPV(G$64,$B$60:$L$60)/(1+G$64)^($B$2-1+$B$10/12)+INDEX($C$57:$L$57,MATCH($B$2,$C$49:$L$49))*(1+$B$4)^$B$3*(1+$E65)/(G$64-$E65)/(POWER((1+G$64),$B$2+$B$3-1+$B$10/12)))/$B$68 -> #VALUE! | H65: =((NPV(H$64,$D$57:$L$57)+$C$57*$B$10/12)/(1+H$64)^($B$10/12)+NPV(H$64,$B$60:$L$60)/(1+H$64)^($B$2-1+$B$10/12)+INDEX($C$57:$L$57,MATCH($B$2,$C$49:$L$49))*(1+$B$4)^$B$3*(1+$E65)/(H$64-$E65)/(POWER((1+H$64),$B$2+$B$3-1+$B$10/12)))/$B$68 -> #VALUE! | I65: =((NPV(I$64,$D$57:$L$57)+$C$57*$B$10/12)/(1+I$64)^($B$10/12)+NPV(I$64,$B$60:$L$60)/(1+I$64)^($B$2-1+$B$10/12)+INDEX($C$57:$L$57,MATCH($B$2,$C$49:$L$49))*(1+$B$4)^$B$3*(1+$E65)/(I$64-$E65)/(POWER((1+I$64),$B$2+$B$3-1+$B$10/12)))/$B$68 -> #VALUE! | J65: =((NPV(J$64,$D$57:$L$57)+$C$57*$B$10/12)/(1+J$64)^($B$10/12)+NPV(J$64,$B$60:$L$60)/(1+J$64)^($B$2-1+$B$10/12)+INDEX($C$57:$L$57,MATCH($B$2,$C$49:$L$49))*(1+$B$4)^$B$3*(1+$E65)/(J$64-$E65)/(POWER((1+J$64),$B$2+$B$3-1+$B$10/12)))/$B$68 -> #VALUE! | K65: =((NPV(K$64,$D$57:$L$57)+$C$57*$B$10/12)/(1+K$64)^($B$10/12)+NPV(K$64,$B$60:$L$60)/(1+K$64)^($B$2-1+$B$10/12)+INDEX($C$57:$L$57,MATCH($B$2,$C$49:$L$49))*(1+$B$4)^$B$3*(1+$E65)/(K$64-$E65)/(POWER((1+K$64),$B$2+$B$3-1+$B$10/12)))/$B$68 -> #VALUE! | L65: =((NPV(L$64,$D$57:$L$57)+$C$57*$B$10/12)/(1+L$64)^($B$10/12)+NPV(L$64,$B$60:$L$60)/(1+L$64)^($B$2-1+$B$10/12)+INDEX($C$57:$L$57,MATCH($B$2,$C$49:$L$49))*(1+$B$4)^$B$3*(1+$E65)/(L$64-$E65)/(POWER((1+L$64),$B$2+$B$3-1+$B$10/12)))/$B$68 -> #VALUE!
A66: FCFE永续价值现值 | B66: =INDEX(C57:L57,MATCH(B2,C49:L49))*(1+B4)^B3*(1+B5)/(B15-B5)/(POWER((1+B15),B2+B3-1+B10/12)) -> #DIV/0! | E66: =E67-$G$63 -> -0.01 | F66: =((NPV(F$64,$D$57:$L$57)+$C$57*$B$10/12)/(1+F$64)^($B$10/12)+NPV(F$64,$B$60:$L$60)/(1+F$64)^($B$2-1+$B$10/12)+INDEX($C$57:$L$57,MATCH($B$2,$C$49:$L$49))*(1+$B$4)^$B$3*(1+$E66)/(F$64-$E66)/(POWER((1+F$64),$B$2+$B$3-1+$B$10/12)))/$B$68 -> #VALUE! | G66: =((NPV(G$64,$D$57:$L$57)+$C$57*$B$10/12)/(1+G$64)^($B$10/12)+NPV(G$64,$B$60:$L$60)/(1+G$64)^($B$2-1+$B$10/12)+INDEX($C$57:$L$57,MATCH($B$2,$C$49:$L$49))*(1+$B$4)^$B$3*(1+$E66)/(G$64-$E66)/(POWER((1+G$64),$B$2+$B$3-1+$B$10/12)))/$B$68 -> #DIV/0! | H66: =((NPV(H$64,$D$57:$L$57)+$C$57*$B$10/12)/(1+H$64)^($B$10/12)+NPV(H$64,$B$60:$L$60)/(1+H$64)^($B$2-1+$B$10/12)+INDEX($C$57:$L$57,MATCH($B$2,$C$49:$L$49))*(1+$B$4)^$B$3*(1+$E66)/(H$64-$E66)/(POWER((1+H$64),$B$2+$B$3-1+$B$10/12)))/$B$68 -> #VALUE! | I66: =((NPV(I$64,$D$57:$L$57)+$C$57*$B$10/12)/(1+I$64)^($B$10/12)+NPV(I$64,$B$60:$L$60)/(1+I$64)^($B$2-1+$B$10/12)+INDEX($C$57:$L$57,MATCH($B$2,$C$49:$L$49))*(1+$B$4)^$B$3*(1+$E66)/(I$64-$E66)/(POWER((1+I$64),$B$2+$B$3-1+$B$10/12)))/$B$68 -> #VALUE! | J66: =((NPV(J$64,$D$57:$L$57)+$C$57*$B$10/12)/(1+J$64)^($B$10/12)+NPV(J$64,$B$60:$L$60)/(1+J$64)^($B$2-1+$B$10/12)+INDEX($C$57:$L$57,MATCH($B$2,$C$49:$L$49))*(1+$B$4)^$B$3*(1+$E66)/(J$64-$E66)/(POWER((1+J$64),$B$2+$B$3-1+$B$10/12)))/$B$68 -> #VALUE! | K66: =((NPV(K$64,$D$57:$L$57)+$C$57*$B$10/12)/(1+K$64)^($B$10/12)+NPV(K$64,$B$60:$L$60)/(1+K$64)^($B$2-1+$B$10/12)+INDEX($C$57:$L$57,MATCH($B$2,$C$49:$L$49))*(1+$B$4)^$B$3*(1+$E66)/(K$64-$E66)/(POWER((1+K$64),$B$2+$B$3-1+$B$10/12)))/$B$68 -> #VALUE! | L66: =((NPV(L$64,$D$57:$L$57)+$C$57*$B$10/12)/(1+L$64)^($B$10/12)+NPV(L$64,$B$60:$L$60)/(1+L$64)^($B$2-1+$B$10/12)+INDEX($C$57:$L$57,MATCH($B$2,$C$49:$L$49))*(1+$B$4)^$B$3*(1+$E66)/(L$64-$E66)/(POWER((1+L$64),$B$2+$B$3-1+$B$10/12)))/$B$68 -> #VALUE!
A67: 股权价值 | B67: =SUM(B64:B66) -> #DIV/0! | E67: =E68-$G$63 -> -0.005 | F67: =((NPV(F$64,$D$57:$L$57)+$C$57*$B$10/12)/(1+F$64)^($B$10/12)+NPV(F$64,$B$60:$L$60)/(1+F$64)^($B$2-1+$B$10/12)+INDEX($C$57:$L$57,MATCH($B$2,$C$49:$L$49))*(1+$B$4)^$B$3*(1+$E67)/(F$64-$E67)/(POWER((1+F$64),$B$2+$B$3-1+$B$10/12)))/$B$68 -> #VALUE! | G67: =((NPV(G$64,$D$57:$L$57)+$C$57*$B$10/12)/(1+G$64)^($B$10/12)+NPV(G$64,$B$60:$L$60)/(1+G$64)^($B$2-1+$B$10/12)+INDEX($C$57:$L$57,MATCH($B$2,$C$49:$L$49))*(1+$B$4)^$B$3*(1+$E67)/(G$64-$E67)/(POWER((1+G$64),$B$2+$B$3-1+$B$10/12)))/$B$68 -> #VALUE! | H67: =((NPV(H$64,$D$57:$L$57)+$C$57*$B$10/12)/(1+H$64)^($B$10/12)+NPV(H$64,$B$60:$L$60)/(1+H$64)^($B$2-1+$B$10/12)+INDEX($C$57:$L$57,MATCH($B$2,$C$49:$L$49))*(1+$B$4)^$B$3*(1+$E67)/(H$64-$E67)/(POWER((1+H$64),$B$2+$B$3-1+$B$10/12)))/$B$68 -> #DIV/0! | I67: =((NPV(I$64,$D$57:$L$57)+$C$57*$B$10/12)/(1+I$64)^($B$10/12)+NPV(I$64,$B$60:$L$60)/(1+I$64)^($B$2-1+$B$10/12)+INDEX($C$57:$L$57,MATCH($B$2,$C$49:$L$49))*(1+$B$4)^$B$3*(1+$E67)/(I$64-$E67)/(POWER((1+I$64),$B$2+$B$3-1+$B$10/12)))/$B$68 -> #VALUE! | J67: =((NPV(J$64,$D$57:$L$57)+$C$57*$B$10/12)/(1+J$64)^($B$10/12)+NPV(J$64,$B$60:$L$60)/(1+J$64)^($B$2-1+$B$10/12)+INDEX($C$57:$L$57,MATCH($B$2,$C$49:$L$49))*(1+$B$4)^$B$3*(1+$E67)/(J$64-$E67)/(POWER((1+J$64),$B$2+$B$3-1+$B$10/12)))/$B$68 -> #VALUE! | K67: =((NPV(K$64,$D$57:$L$57)+$C$57*$B$10/12)/(1+K$64)^($B$10/12)+NPV(K$64,$B$60:$L$60)/(1+K$64)^($B$2-1+$B$10/12)+INDEX($C$57:$L$57,MATCH($B$2,$C$49:$L$49))*(1+$B$4)^$B$3*(1+$E67)/(K$64-$E67)/(POWER((1+K$64),$B$2+$B$3-1+$B$10/12)))/$B$68 -> #VALUE! | L67: =((NPV(L$64,$D$57:$L$57)+$C$57*$B$10/12)/(1+L$64)^($B$10/12)+NPV(L$64,$B$60:$L$60)/(1+L$64)^($B$2-1+$B$10/12)+INDEX($C$57:$L$57,MATCH($B$2,$C$49:$L$49))*(1+$B$4)^$B$3*(1+$E67)/(L$64-$E67)/(POWER((1+L$64),$B$2+$B$3-1+$B$10/12)))/$B$68 -> #VALUE!
A68: 总股本 | B68: =IF(ISERROR(目录!F7*1000000*目录!D6),"—",目录!F7*1000000*目录!D6) -> — | E68: =B5 -> 0 | F68: =((NPV(F$64,$D$57:$L$57)+$C$57*$B$10/12)/(1+F$64)^($B$10/12)+NPV(F$64,$B$60:$L$60)/(1+F$64)^($B$2-1+$B$10/12)+INDEX($C$57:$L$57,MATCH($B$2,$C$49:$L$49))*(1+$B$4)^$B$3*(1+$E68)/(F$64-$E68)/(POWER((1+F$64),$B$2+$B$3-1+$B$10/12)))/$B$68 -> #VALUE! | G68: =((NPV(G$64,$D$57:$L$57)+$C$57*$B$10/12)/(1+G$64)^($B$10/12)+NPV(G$64,$B$60:$L$60)/(1+G$64)^($B$2-1+$B$10/12)+INDEX($C$57:$L$57,MATCH($B$2,$C$49:$L$49))*(1+$B$4)^$B$3*(1+$E68)/(G$64-$E68)/(POWER((1+G$64),$B$2+$B$3-1+$B$10/12)))/$B$68 -> #VALUE! | H68: =((NPV(H$64,$D$57:$L$57)+$C$57*$B$10/12)/(1+H$64)^($B$10/12)+NPV(H$64,$B$60:$L$60)/(1+H$64)^($B$2-1+$B$10/12)+INDEX($C$57:$L$57,MATCH($B$2,$C$49:$L$49))*(1+$B$4)^$B$3*(1+$E68)/(H$64-$E68)/(POWER((1+H$64),$B$2+$B$3-1+$B$10/12)))/$B$68 -> #VALUE! | I68: =((NPV(I$64,$D$57:$L$57)+$C$57*$B$10/12)/(1+I$64)^($B$10/12)+NPV(I$64,$B$60:$L$60)/(1+I$64)^($B$2-1+$B$10/12)+INDEX($C$57:$L$57,MATCH($B$2,$C$49:$L$49))*(1+$B$4)^$B$3*(1+$E68)/(I$64-$E68)/(POWER((1+I$64),$B$2+$B$3-1+$B$10/12)))/$B$68 -> #DIV/0! | J68: =((NPV(J$64,$D$57:$L$57)+$C$57*$B$10/12)/(1+J$64)^($B$10/12)+NPV(J$64,$B$60:$L$60)/(1+J$64)^($B$2-1+$B$10/12)+INDEX($C$57:$L$57,MATCH($B$2,$C$49:$L$49))*(1+$B$4)^$B$3*(1+$E68)/(J$64-$E68)/(POWER((1+J$64),$B$2+$B$3-1+$B$10/12)))/$B$68 -> #VALUE! | K68: =((NPV(K$64,$D$57:$L$57)+$C$57*$B$10/12)/(1+K$64)^($B$10/12)+NPV(K$64,$B$60:$L$60)/(1+K$64)^($B$2-1+$B$10/12)+INDEX($C$57:$L$57,MATCH($B$2,$C$49:$L$49))*(1+$B$4)^$B$3*(1+$E68)/(K$64-$E68)/(POWER((1+K$64),$B$2+$B$3-1+$B$10/12)))/$B$68 -> #VALUE! | L68: =((NPV(L$64,$D$57:$L$57)+$C$57*$B$10/12)/(1+L$64)^($B$10/12)+NPV(L$64,$B$60:$L$60)/(1+L$64)^($B$2-1+$B$10/12)+INDEX($C$57:$L$57,MATCH($B$2,$C$49:$L$49))*(1+$B$4)^$B$3*(1+$E68)/(L$64-$E68)/(POWER((1+L$64),$B$2+$B$3-1+$B$10/12)))/$B$68 -> #VALUE!
A69: ="每股价值("&目录!F8&")" -> 每股价值(XXXX) | B69: =IF(ISERROR(B67/B68),"—",B67/B68) -> — | E69: =E68+$G$63 -> 0.005 | F69: =((NPV(F$64,$D$57:$L$57)+$C$57*$B$10/12)/(1+F$64)^($B$10/12)+NPV(F$64,$B$60:$L$60)/(1+F$64)^($B$2-1+$B$10/12)+INDEX($C$57:$L$57,MATCH($B$2,$C$49:$L$49))*(1+$B$4)^$B$3*(1+$E69)/(F$64-$E69)/(POWER((1+F$64),$B$2+$B$3-1+$B$10/12)))/$B$68 -> #VALUE! | G69: =((NPV(G$64,$D$57:$L$57)+$C$57*$B$10/12)/(1+G$64)^($B$10/12)+NPV(G$64,$B$60:$L$60)/(1+G$64)^($B$2-1+$B$10/12)+INDEX($C$57:$L$57,MATCH($B$2,$C$49:$L$49))*(1+$B$4)^$B$3*(1+$E69)/(G$64-$E69)/(POWER((1+G$64),$B$2+$B$3-1+$B$10/12)))/$B$68 -> #VALUE! | H69: =((NPV(H$64,$D$57:$L$57)+$C$57*$B$10/12)/(1+H$64)^($B$10/12)+NPV(H$64,$B$60:$L$60)/(1+H$64)^($B$2-1+$B$10/12)+INDEX($C$57:$L$57,MATCH($B$2,$C$49:$L$49))*(1+$B$4)^$B$3*(1+$E69)/(H$64-$E69)/(POWER((1+H$64),$B$2+$B$3-1+$B$10/12)))/$B$68 -> #VALUE! | I69: =((NPV(I$64,$D$57:$L$57)+$C$57*$B$10/12)/(1+I$64)^($B$10/12)+NPV(I$64,$B$60:$L$60)/(1+I$64)^($B$2-1+$B$10/12)+INDEX($C$57:$L$57,MATCH($B$2,$C$49:$L$49))*(1+$B$4)^$B$3*(1+$E69)/(I$64-$E69)/(POWER((1+I$64),$B$2+$B$3-1+$B$10/12)))/$B$68 -> #VALUE! | J69: =((NPV(J$64,$D$57:$L$57)+$C$57*$B$10/12)/(1+J$64)^($B$10/12)+NPV(J$64,$B$60:$L$60)/(1+J$64)^($B$2-1+$B$10/12)+INDEX($C$57:$L$57,MATCH($B$2,$C$49:$L$49))*(1+$B$4)^$B$3*(1+$E69)/(J$64-$E69)/(POWER((1+J$64),$B$2+$B$3-1+$B$10/12)))/$B$68 -> #DIV/0! | K69: =((NPV(K$64,$D$57:$L$57)+$C$57*$B$10/12)/(1+K$64)^($B$10/12)+NPV(K$64,$B$60:$L$60)/(1+K$64)^($B$2-1+$B$10/12)+INDEX($C$57:$L$57,MATCH($B$2,$C$49:$L$49))*(1+$B$4)^$B$3*(1+$E69)/(K$64-$E69)/(POWER((1+K$64),$B$2+$B$3-1+$B$10/12)))/$B$68 -> #VALUE! | L69: =((NPV(L$64,$D$57:$L$57)+$C$57*$B$10/12)/(1+L$64)^($B$10/12)+NPV(L$64,$B$60:$L$60)/(1+L$64)^($B$2-1+$B$10/12)+INDEX($C$57:$L$57,MATCH($B$2,$C$49:$L$49))*(1+$B$4)^$B$3*(1+$E69)/(L$64-$E69)/(POWER((1+L$64),$B$2+$B$3-1+$B$10/12)))/$B$68 -> #VALUE!
E70: =E69+$G$63 -> 0.01 | F70: =((NPV(F$64,$D$57:$L$57)+$C$57*$B$10/12)/(1+F$64)^($B$10/12)+NPV(F$64,$B$60:$L$60)/(1+F$64)^($B$2-1+$B$10/12)+INDEX($C$57:$L$57,MATCH($B$2,$C$49:$L$49))*(1+$B$4)^$B$3*(1+$E70)/(F$64-$E70)/(POWER((1+F$64),$B$2+$B$3-1+$B$10/12)))/$B$68 -> #VALUE! | G70: =((NPV(G$64,$D$57:$L$57)+$C$57*$B$10/12)/(1+G$64)^($B$10/12)+NPV(G$64,$B$60:$L$60)/(1+G$64)^($B$2-1+$B$10/12)+INDEX($C$57:$L$57,MATCH($B$2,$C$49:$L$49))*(1+$B$4)^$B$3*(1+$E70)/(G$64-$E70)/(POWER((1+G$64),$B$2+$B$3-1+$B$10/12)))/$B$68 -> #VALUE! | H70: =((NPV(H$64,$D$57:$L$57)+$C$57*$B$10/12)/(1+H$64)^($B$10/12)+NPV(H$64,$B$60:$L$60)/(1+H$64)^($B$2-1+$B$10/12)+INDEX($C$57:$L$57,MATCH($B$2,$C$49:$L$49))*(1+$B$4)^$B$3*(1+$E70)/(H$64-$E70)/(POWER((1+H$64),$B$2+$B$3-1+$B$10/12)))/$B$68 -> #VALUE! | I70: =((NPV(I$64,$D$57:$L$57)+$C$57*$B$10/12)/(1+I$64)^($B$10/12)+NPV(I$64,$B$60:$L$60)/(1+I$64)^($B$2-1+$B$10/12)+INDEX($C$57:$L$57,MATCH($B$2,$C$49:$L$49))*(1+$B$4)^$B$3*(1+$E70)/(I$64-$E70)/(POWER((1+I$64),$B$2+$B$3-1+$B$10/12)))/$B$68 -> #VALUE! | J70: =((NPV(J$64,$D$57:$L$57)+$C$57*$B$10/12)/(1+J$64)^($B$10/12)+NPV(J$64,$B$60:$L$60)/(1+J$64)^($B$2-1+$B$10/12)+INDEX($C$57:$L$57,MATCH($B$2,$C$49:$L$49))*(1+$B$4)^$B$3*(1+$E70)/(J$64-$E70)/(POWER((1+J$64),$B$2+$B$3-1+$B$10/12)))/$B$68 -> #VALUE! | K70: =((NPV(K$64,$D$57:$L$57)+$C$57*$B$10/12)/(1+K$64)^($B$10/12)+NPV(K$64,$B$60:$L$60)/(1+K$64)^($B$2-1+$B$10/12)+INDEX($C$57:$L$57,MATCH($B$2,$C$49:$L$49))*(1+$B$4)^$B$3*(1+$E70)/(K$64-$E70)/(POWER((1+K$64),$B$2+$B$3-1+$B$10/12)))/$B$68 -> #DIV/0! | L70: =((NPV(L$64,$D$57:$L$57)+$C$57*$B$10/12)/(1+L$64)^($B$10/12)+NPV(L$64,$B$60:$L$60)/(1+L$64)^($B$2-1+$B$10/12)+INDEX($C$57:$L$57,MATCH($B$2,$C$49:$L$49))*(1+$B$4)^$B$3*(1+$E70)/(L$64-$E70)/(POWER((1+L$64),$B$2+$B$3-1+$B$10/12)))/$B$68 -> #VALUE!
E71: =E70+$G$63 -> 0.015 | F71: =((NPV(F$64,$D$57:$L$57)+$C$57*$B$10/12)/(1+F$64)^($B$10/12)+NPV(F$64,$B$60:$L$60)/(1+F$64)^($B$2-1+$B$10/12)+INDEX($C$57:$L$57,MATCH($B$2,$C$49:$L$49))*(1+$B$4)^$B$3*(1+$E71)/(F$64-$E71)/(POWER((1+F$64),$B$2+$B$3-1+$B$10/12)))/$B$68 -> #VALUE! | G71: =((NPV(G$64,$D$57:$L$57)+$C$57*$B$10/12)/(1+G$64)^($B$10/12)+NPV(G$64,$B$60:$L$60)/(1+G$64)^($B$2-1+$B$10/12)+INDEX($C$57:$L$57,MATCH($B$2,$C$49:$L$49))*(1+$B$4)^$B$3*(1+$E71)/(G$64-$E71)/(POWER((1+G$64),$B$2+$B$3-1+$B$10/12)))/$B$68 -> #VALUE! | H71: =((NPV(H$64,$D$57:$L$57)+$C$57*$B$10/12)/(1+H$64)^($B$10/12)+NPV(H$64,$B$60:$L$60)/(1+H$64)^($B$2-1+$B$10/12)+INDEX($C$57:$L$57,MATCH($B$2,$C$49:$L$49))*(1+$B$4)^$B$3*(1+$E71)/(H$64-$E71)/(POWER((1+H$64),$B$2+$B$3-1+$B$10/12)))/$B$68 -> #VALUE! | I71: =((NPV(I$64,$D$57:$L$57)+$C$57*$B$10/12)/(1+I$64)^($B$10/12)+NPV(I$64,$B$60:$L$60)/(1+I$64)^($B$2-1+$B$10/12)+INDEX($C$57:$L$57,MATCH($B$2,$C$49:$L$49))*(1+$B$4)^$B$3*(1+$E71)/(I$64-$E71)/(POWER((1+I$64),$B$2+$B$3-1+$B$10/12)))/$B$68 -> #VALUE! | J71: =((NPV(J$64,$D$57:$L$57)+$C$57*$B$10/12)/(1+J$64)^($B$10/12)+NPV(J$64,$B$60:$L$60)/(1+J$64)^($B$2-1+$B$10/12)+INDEX($C$57:$L$57,MATCH($B$2,$C$49:$L$49))*(1+$B$4)^$B$3*(1+$E71)/(J$64-$E71)/(POWER((1+J$64),$B$2+$B$3-1+$B$10/12)))/$B$68 -> #VALUE! | K71: =((NPV(K$64,$D$57:$L$57)+$C$57*$B$10/12)/(1+K$64)^($B$10/12)+NPV(K$64,$B$60:$L$60)/(1+K$64)^($B$2-1+$B$10/12)+INDEX($C$57:$L$57,MATCH($B$2,$C$49:$L$49))*(1+$B$4)^$B$3*(1+$E71)/(K$64-$E71)/(POWER((1+K$64),$B$2+$B$3-1+$B$10/12)))/$B$68 -> #VALUE! | L71: =((NPV(L$64,$D$57:$L$57)+$C$57*$B$10/12)/(1+L$64)^($B$10/12)+NPV(L$64,$B$60:$L$60)/(1+L$64)^($B$2-1+$B$10/12)+INDEX($C$57:$L$57,MATCH($B$2,$C$49:$L$49))*(1+$B$4)^$B$3*(1+$E71)/(L$64-$E71)/(POWER((1+L$64),$B$2+$B$3-1+$B$10/12)))/$B$68 -> #DIV/0!
C73: =C50 -> 2022E | D73: =D50 -> 2023 | E73: =E50 -> 2024 | F73: =F50 -> 2025 | G73: =G50 -> 2026 | H73: =H50 -> 2027 | I73: =I50 -> 2028 | J73: =J50 -> 2029 | ... L73: =L50 -> 2031
B74: P/E | C74: =IF(ISERROR($B$67/利润表!AA29),"—",$B$67/利润表!AA29) -> — | D74: =IF(ISERROR($B$67/利润表!AB29),"—",$B$67/利润表!AB29) -> — | E74: =IF(ISERROR($B$67/利润表!AC29),"—",$B$67/利润表!AC29) -> — | F74: =IF(ISERROR($B$67/利润表!AD29),"—",$B$67/利润表!AD29) -> — | G74: =IF(ISERROR($B$67/利润表!AE29),"—",$B$67/利润表!AE29) -> — | H74: =IF(ISERROR($B$67/利润表!AF29),"—",$B$67/利润表!AF29) -> — | I74: =IF(ISERROR($B$67/利润表!AG29),"—",$B$67/利润表!AG29) -> — | J74: =IF(ISERROR($B$67/利润表!AH29),"—",$B$67/利润表!AH29) -> — | ... L74: =IF(ISERROR($B$67/利润表!AJ29),"—",$B$67/利润表!AJ29) -> —
B75: P/B | C75: =IF(ISERROR($B$67/资产负债表!AA45),"—",$B$67/资产负债表!AA45) -> — | D75: =IF(ISERROR($B$67/资产负债表!AB45),"—",$B$67/资产负债表!AB45) -> — | E75: =IF(ISERROR($B$67/资产负债表!AC45),"—",$B$67/资产负债表!AC45) -> — | F75: =IF(ISERROR($B$67/资产负债表!AD45),"—",$B$67/资产负债表!AD45) -> — | G75: =IF(ISERROR($B$67/资产负债表!AE45),"—",$B$67/资产负债表!AE45) -> — | H75: =IF(ISERROR($B$67/资产负债表!AF45),"—",$B$67/资产负债表!AF45) -> — | I75: =IF(ISERROR($B$67/资产负债表!AG45),"—",$B$67/资产负债表!AG45) -> — | J75: =IF(ISERROR($B$67/资产负债表!AH45),"—",$B$67/资产负债表!AH45) -> — | ... L75: =IF(ISERROR($B$67/资产负债表!AJ45),"—",$B$67/资产负债表!AJ45) -> —
B76: P/S | C76: =IF(ISERROR($B$67/利润表!AA6),"—",$B$67/利润表!AA6) -> — | D76: =IF(ISERROR($B$67/利润表!AB6),"—",$B$67/利润表!AB6) -> — | E76: =IF(ISERROR($B$67/利润表!AC6),"—",$B$67/利润表!AC6) -> — | F76: =IF(ISERROR($B$67/利润表!AD6),"—",$B$67/利润表!AD6) -> — | G76: =IF(ISERROR($B$67/利润表!AE6),"—",$B$67/利润表!AE6) -> — | H76: =IF(ISERROR($B$67/利润表!AF6),"—",$B$67/利润表!AF6) -> — | I76: =IF(ISERROR($B$67/利润表!AG6),"—",$B$67/利润表!AG6) -> — | J76: =IF(ISERROR($B$67/利润表!AH6),"—",$B$67/利润表!AH6) -> — | ... L76: =IF(ISERROR($B$67/利润表!AJ6),"—",$B$67/利润表!AJ6) -> —
A79: DDM估值 | B79: =B93 -> — | C79: 1 | D79: 2 | E79: 3 | F79: 4 | G79: 5 | H79: 6 | I79: 7 | J79: 8 | K79: 9 | L79: 10
B80: =B20 -> 2021 | C80: =C20 -> 2022E | D80: =D20 -> 2023 | E80: =E20 -> 2024 | F80: =F20 -> 2025 | G80: =G20 -> 2026 | H80: =H20 -> 2027 | I80: =I20 -> 2028 | ... L80: =L20 -> 2031
A81: 现金红利总额 | B81: =资产预测!F98 -> 0 | C81: =IF($B$2>=C79,资产预测!J98,"") -> 0 | D81: =IF($B$2>=D79,资产预测!K98,"") -> 0 | E81: =IF($B$2>=E79,资产预测!L98,"") -> 0 | F81: =IF($B$2>=F79,资产预测!M98,"") | G81: =IF($B$2>=G79,资产预测!N98,"") | H81: =IF($B$2>=H79,资产预测!O98,"") | I81: =IF($B$2>=I79,资产预测!P98,"") | J81: =IF($B$2>=J79,资产预测!Q98,"") | ... L81: =IF($B$2>=L79,资产预测!S98,"")
B82: =INDEX(C80:L80,MATCH($B$2,C79:L79))+1 -> 2025 | C82: =B82+1 -> 2026 | D82: =C82+1 -> 2027 | E82: =D82+1 -> 2028 | F82: =E82+1 -> 2029 | G82: =F82+1 -> 2030 | H82: =G82+1 -> 2031 | I82: =H82+1 -> 2032 | J82: =I82+1 -> 2033 | ... L82: =K82+1 -> 2035
A83: 过渡期现金红利总额 | B83: =IF($B3>0,INDEX(C81:L81,MATCH(B2,C79:L79))*(1+B4),0) -> 0 | C83: =IF(($B3-C79)>0,B83*(1+$B4),"") | D83: =IF(($B3-D79)>0,C83*(1+$B4),"") | E83: =IF(($B3-E79)>0,D83*(1+$B4),"") | F83: =IF(($B3-F79)>0,E83*(1+$B4),"") | G83: =IF(($B3-G79)>0,F83*(1+$B4),"") | H83: =IF(($B3-H79)>0,G83*(1+$B4),"") | I83: =IF(($B3-I79)>0,H83*(1+$B4),"") | J83: =IF(($B3-J79)>0,I83*(1+$B4),"") | ... L83: =IF(($B3-L79)>0,K83*(1+$B4),"")
D85: 敏感性分析 | E85: 折现率变化值 | G85: 0.005
E86: 永续增长率变化值 | G86: 0.005
E87: =B93 -> — | F87: =G87-$G$85 -> -0.015 | G87: =H87-$G$85 -> -0.01 | H87: =I87-$G$85 -> -0.005 | I87: =B15 -> 0 | J87: =I87+$G$85 -> 0.005 | K87: =J87+$G$85 -> 0.01 | L87: =K87+$G$85 -> 0.015
A88: 股利预测期现值 | B88: =(C81+NPV(B15,D81:L81))/(1+B15)^(B10/12) -> 0 | E88: =E89-$G$86 -> -0.015 | F88: =(($C$81+NPV(F$87,$D$81:$L$81))/(1+F$87)^($B$10/12)+NPV(F$87,$B$83:$L$83)/(1+F$87)^($B$2-1+$B$10/12)+INDEX($C$81:$L$81,MATCH($B$2,$C$79:$L$79))*(1+$B$4)^$B$3*(1+$E88)/(F$87-$E88)/(POWER((1+F$87),$B$2+$B$3-1+$B$10/12)))/$B$92 -> #DIV/0! | G88: =(($C$81+NPV(G$87,$D$81:$L$81))/(1+G$87)^($B$10/12)+NPV(G$87,$B$83:$L$83)/(1+G$87)^($B$2-1+$B$10/12)+INDEX($C$81:$L$81,MATCH($B$2,$C$79:$L$79))*(1+$B$4)^$B$3*(1+$E88)/(G$87-$E88)/(POWER((1+G$87),$B$2+$B$3-1+$B$10/12)))/$B$92 -> #VALUE! | H88: =(($C$81+NPV(H$87,$D$81:$L$81))/(1+H$87)^($B$10/12)+NPV(H$87,$B$83:$L$83)/(1+H$87)^($B$2-1+$B$10/12)+INDEX($C$81:$L$81,MATCH($B$2,$C$79:$L$79))*(1+$B$4)^$B$3*(1+$E88)/(H$87-$E88)/(POWER((1+H$87),$B$2+$B$3-1+$B$10/12)))/$B$92 -> #VALUE! | I88: =(($C$81+NPV(I$87,$D$81:$L$81))/(1+I$87)^($B$10/12)+NPV(I$87,$B$83:$L$83)/(1+I$87)^($B$2-1+$B$10/12)+INDEX($C$81:$L$81,MATCH($B$2,$C$79:$L$79))*(1+$B$4)^$B$3*(1+$E88)/(I$87-$E88)/(POWER((1+I$87),$B$2+$B$3-1+$B$10/12)))/$B$92 -> #VALUE! | J88: =(($C$81+NPV(J$87,$D$81:$L$81))/(1+J$87)^($B$10/12)+NPV(J$87,$B$83:$L$83)/(1+J$87)^($B$2-1+$B$10/12)+INDEX($C$81:$L$81,MATCH($B$2,$C$79:$L$79))*(1+$B$4)^$B$3*(1+$E88)/(J$87-$E88)/(POWER((1+J$87),$B$2+$B$3-1+$B$10/12)))/$B$92 -> #VALUE! | K88: =(($C$81+NPV(K$87,$D$81:$L$81))/(1+K$87)^($B$10/12)+NPV(K$87,$B$83:$L$83)/(1+K$87)^($B$2-1+$B$10/12)+INDEX($C$81:$L$81,MATCH($B$2,$C$79:$L$79))*(1+$B$4)^$B$3*(1+$E88)/(K$87-$E88)/(POWER((1+K$87),$B$2+$B$3-1+$B$10/12)))/$B$92 -> #VALUE! | L88: =(($C$81+NPV(L$87,$D$81:$L$81))/(1+L$87)^($B$10/12)+NPV(L$87,$B$83:$L$83)/(1+L$87)^($B$2-1+$B$10/12)+INDEX($C$81:$L$81,MATCH($B$2,$C$79:$L$79))*(1+$B$4)^$B$3*(1+$E88)/(L$87-$E88)/(POWER((1+L$87),$B$2+$B$3-1+$B$10/12)))/$B$92 -> #VALUE!
A89: 股利过渡期现值 | B89: =IF(B3=0,0,NPV(B15,B83:L83)/(1+B15)^(B2-1+B10/12)) -> 0 | E89: =E90-$G$86 -> -0.01 | F89: =(($C$81+NPV(F$87,$D$81:$L$81))/(1+F$87)^($B$10/12)+NPV(F$87,$B$83:$L$83)/(1+F$87)^($B$2-1+$B$10/12)+INDEX($C$81:$L$81,MATCH($B$2,$C$79:$L$79))*(1+$B$4)^$B$3*(1+$E89)/(F$87-$E89)/(POWER((1+F$87),$B$2+$B$3-1+$B$10/12)))/$B$92 -> #VALUE! | G89: =(($C$81+NPV(G$87,$D$81:$L$81))/(1+G$87)^($B$10/12)+NPV(G$87,$B$83:$L$83)/(1+G$87)^($B$2-1+$B$10/12)+INDEX($C$81:$L$81,MATCH($B$2,$C$79:$L$79))*(1+$B$4)^$B$3*(1+$E89)/(G$87-$E89)/(POWER((1+G$87),$B$2+$B$3-1+$B$10/12)))/$B$92 -> #DIV/0! | H89: =(($C$81+NPV(H$87,$D$81:$L$81))/(1+H$87)^($B$10/12)+NPV(H$87,$B$83:$L$83)/(1+H$87)^($B$2-1+$B$10/12)+INDEX($C$81:$L$81,MATCH($B$2,$C$79:$L$79))*(1+$B$4)^$B$3*(1+$E89)/(H$87-$E89)/(POWER((1+H$87),$B$2+$B$3-1+$B$10/12)))/$B$92 -> #VALUE! | I89: =(($C$81+NPV(I$87,$D$81:$L$81))/(1+I$87)^($B$10/12)+NPV(I$87,$B$83:$L$83)/(1+I$87)^($B$2-1+$B$10/12)+INDEX($C$81:$L$81,MATCH($B$2,$C$79:$L$79))*(1+$B$4)^$B$3*(1+$E89)/(I$87-$E89)/(POWER((1+I$87),$B$2+$B$3-1+$B$10/12)))/$B$92 -> #VALUE! | J89: =(($C$81+NPV(J$87,$D$81:$L$81))/(1+J$87)^($B$10/12)+NPV(J$87,$B$83:$L$83)/(1+J$87)^($B$2-1+$B$10/12)+INDEX($C$81:$L$81,MATCH($B$2,$C$79:$L$79))*(1+$B$4)^$B$3*(1+$E89)/(J$87-$E89)/(POWER((1+J$87),$B$2+$B$3-1+$B$10/12)))/$B$92 -> #VALUE! | K89: =(($C$81+NPV(K$87,$D$81:$L$81))/(1+K$87)^($B$10/12)+NPV(K$87,$B$83:$L$83)/(1+K$87)^($B$2-1+$B$10/12)+INDEX($C$81:$L$81,MATCH($B$2,$C$79:$L$79))*(1+$B$4)^$B$3*(1+$E89)/(K$87-$E89)/(POWER((1+K$87),$B$2+$B$3-1+$B$10/12)))/$B$92 -> #VALUE! | L89: =(($C$81+NPV(L$87,$D$81:$L$81))/(1+L$87)^($B$10/12)+NPV(L$87,$B$83:$L$83)/(1+L$87)^($B$2-1+$B$10/12)+INDEX($C$81:$L$81,MATCH($B$2,$C$79:$L$79))*(1+$B$4)^$B$3*(1+$E89)/(L$87-$E89)/(POWER((1+L$87),$B$2+$B$3-1+$B$10/12)))/$B$92 -> #VALUE!
A90: 股利永续价值现值 | B90: =INDEX(C81:L81,MATCH(B2,C79:L79))*(1+B4)^B3*(1+B5)/(B15-B5)/(POWER((1+B15),B2+B3-1+B10/12)) -> #DIV/0! | E90: =E91-$G$86 -> -0.005 | F90: =(($C$81+NPV(F$87,$D$81:$L$81))/(1+F$87)^($B$10/12)+NPV(F$87,$B$83:$L$83)/(1+F$87)^($B$2-1+$B$10/12)+INDEX($C$81:$L$81,MATCH($B$2,$C$79:$L$79))*(1+$B$4)^$B$3*(1+$E90)/(F$87-$E90)/(POWER((1+F$87),$B$2+$B$3-1+$B$10/12)))/$B$92 -> #VALUE! | G90: =(($C$81+NPV(G$87,$D$81:$L$81))/(1+G$87)^($B$10/12)+NPV(G$87,$B$83:$L$83)/(1+G$87)^($B$2-1+$B$10/12)+INDEX($C$81:$L$81,MATCH($B$2,$C$79:$L$79))*(1+$B$4)^$B$3*(1+$E90)/(G$87-$E90)/(POWER((1+G$87),$B$2+$B$3-1+$B$10/12)))/$B$92 -> #VALUE! | H90: =(($C$81+NPV(H$87,$D$81:$L$81))/(1+H$87)^($B$10/12)+NPV(H$87,$B$83:$L$83)/(1+H$87)^($B$2-1+$B$10/12)+INDEX($C$81:$L$81,MATCH($B$2,$C$79:$L$79))*(1+$B$4)^$B$3*(1+$E90)/(H$87-$E90)/(POWER((1+H$87),$B$2+$B$3-1+$B$10/12)))/$B$92 -> #DIV/0! | I90: =(($C$81+NPV(I$87,$D$81:$L$81))/(1+I$87)^($B$10/12)+NPV(I$87,$B$83:$L$83)/(1+I$87)^($B$2-1+$B$10/12)+INDEX($C$81:$L$81,MATCH($B$2,$C$79:$L$79))*(1+$B$4)^$B$3*(1+$E90)/(I$87-$E90)/(POWER((1+I$87),$B$2+$B$3-1+$B$10/12)))/$B$92 -> #VALUE! | J90: =(($C$81+NPV(J$87,$D$81:$L$81))/(1+J$87)^($B$10/12)+NPV(J$87,$B$83:$L$83)/(1+J$87)^($B$2-1+$B$10/12)+INDEX($C$81:$L$81,MATCH($B$2,$C$79:$L$79))*(1+$B$4)^$B$3*(1+$E90)/(J$87-$E90)/(POWER((1+J$87),$B$2+$B$3-1+$B$10/12)))/$B$92 -> #VALUE! | K90: =(($C$81+NPV(K$87,$D$81:$L$81))/(1+K$87)^($B$10/12)+NPV(K$87,$B$83:$L$83)/(1+K$87)^($B$2-1+$B$10/12)+INDEX($C$81:$L$81,MATCH($B$2,$C$79:$L$79))*(1+$B$4)^$B$3*(1+$E90)/(K$87-$E90)/(POWER((1+K$87),$B$2+$B$3-1+$B$10/12)))/$B$92 -> #VALUE! | L90: =(($C$81+NPV(L$87,$D$81:$L$81))/(1+L$87)^($B$10/12)+NPV(L$87,$B$83:$L$83)/(1+L$87)^($B$2-1+$B$10/12)+INDEX($C$81:$L$81,MATCH($B$2,$C$79:$L$79))*(1+$B$4)^$B$3*(1+$E90)/(L$87-$E90)/(POWER((1+L$87),$B$2+$B$3-1+$B$10/12)))/$B$92 -> #VALUE!
A91: 股权价值 | B91: =SUM(B88:B90) -> #DIV/0! | E91: =B5 -> 0 | F91: =(($C$81+NPV(F$87,$D$81:$L$81))/(1+F$87)^($B$10/12)+NPV(F$87,$B$83:$L$83)/(1+F$87)^($B$2-1+$B$10/12)+INDEX($C$81:$L$81,MATCH($B$2,$C$79:$L$79))*(1+$B$4)^$B$3*(1+$E91)/(F$87-$E91)/(POWER((1+F$87),$B$2+$B$3-1+$B$10/12)))/$B$92 -> #VALUE! | G91: =(($C$81+NPV(G$87,$D$81:$L$81))/(1+G$87)^($B$10/12)+NPV(G$87,$B$83:$L$83)/(1+G$87)^($B$2-1+$B$10/12)+INDEX($C$81:$L$81,MATCH($B$2,$C$79:$L$79))*(1+$B$4)^$B$3*(1+$E91)/(G$87-$E91)/(POWER((1+G$87),$B$2+$B$3-1+$B$10/12)))/$B$92 -> #VALUE! | H91: =(($C$81+NPV(H$87,$D$81:$L$81))/(1+H$87)^($B$10/12)+NPV(H$87,$B$83:$L$83)/(1+H$87)^($B$2-1+$B$10/12)+INDEX($C$81:$L$81,MATCH($B$2,$C$79:$L$79))*(1+$B$4)^$B$3*(1+$E91)/(H$87-$E91)/(POWER((1+H$87),$B$2+$B$3-1+$B$10/12)))/$B$92 -> #VALUE! | I91: =(($C$81+NPV(I$87,$D$81:$L$81))/(1+I$87)^($B$10/12)+NPV(I$87,$B$83:$L$83)/(1+I$87)^($B$2-1+$B$10/12)+INDEX($C$81:$L$81,MATCH($B$2,$C$79:$L$79))*(1+$B$4)^$B$3*(1+$E91)/(I$87-$E91)/(POWER((1+I$87),$B$2+$B$3-1+$B$10/12)))/$B$92 -> #DIV/0! | J91: =(($C$81+NPV(J$87,$D$81:$L$81))/(1+J$87)^($B$10/12)+NPV(J$87,$B$83:$L$83)/(1+J$87)^($B$2-1+$B$10/12)+INDEX($C$81:$L$81,MATCH($B$2,$C$79:$L$79))*(1+$B$4)^$B$3*(1+$E91)/(J$87-$E91)/(POWER((1+J$87),$B$2+$B$3-1+$B$10/12)))/$B$92 -> #VALUE! | K91: =(($C$81+NPV(K$87,$D$81:$L$81))/(1+K$87)^($B$10/12)+NPV(K$87,$B$83:$L$83)/(1+K$87)^($B$2-1+$B$10/12)+INDEX($C$81:$L$81,MATCH($B$2,$C$79:$L$79))*(1+$B$4)^$B$3*(1+$E91)/(K$87-$E91)/(POWER((1+K$87),$B$2+$B$3-1+$B$10/12)))/$B$92 -> #VALUE! | L91: =(($C$81+NPV(L$87,$D$81:$L$81))/(1+L$87)^($B$10/12)+NPV(L$87,$B$83:$L$83)/(1+L$87)^($B$2-1+$B$10/12)+INDEX($C$81:$L$81,MATCH($B$2,$C$79:$L$79))*(1+$B$4)^$B$3*(1+$E91)/(L$87-$E91)/(POWER((1+L$87),$B$2+$B$3-1+$B$10/12)))/$B$92 -> #VALUE!
