Workbook

Sheet 目录
D2: 百万股 | E2: 股票名称 | F2: XXXX
C3: 财务估值模型V.12 | D3: 4 | E3: 最新报告期 | F3: XXXX-XX-XX
D4: 3 | E4: 最新年报报告期 | F4: XXXX-XX-XX
B5: 版权所有： 上海携宁计算机科技股份有限公司 | D5: 百万元 | E5: 估值日期 | F5: XXXX-XX-XX
B6: 联系电话： 18101638931(工作日)，18117554345(值班) | D6: 1e-06 | E6: 最新收盘价（元） | F6: XXXX
B7: E-mail ： modelsupport@sinitek.com | D7: =IF(D4>10,10,D4) -> 3 | E7: 最新总股本（百万） | F7: XXXX
B8: WebSite： www.sinitek.com | D8: =IF(LEN(D5)=1,"元",LEFT(D5,LEN(D5)-1)) -> 百万 | E8: 最新流通A股股本（百万） | F8: XXXX
B9: 下载地址： https://cloudmodel.sinitek.com | D9: 0 | E9: 最新行情日 | F9: XXXX-XX-XX
B11: 使用步骤： | E11: 重要提示：
B12: 1.使用本模型前请确保已下载并安装估值模型插件(携宁科技云估值)； | E12: 1.修改股票代码或重新选择历史数据年数后，需重新点击“提取历史数据”按钮来更新数据；
B13: 2.点击“提取历史数据”，在股票代码框中输入代码或名称，支持模糊搜索； | E13: 2.不能修改单元格内的公式，否则可能导致报表不平；
B14: 选择历史数据年数、货币单位等选项，可以设置更新范围； | E14: 3.不能增加/删除已有Sheet及已有Sheet中的行或列；
B15: 3.点击“预测数据设置”按钮可实现销售预测、资产预测的参数设置； | E15: 4.如有需要，可以自由增加Sheet，但不能修改已有Sheet名称；
B16: 4.点击“显示季度数据”可以展示/隐藏季度数据； | E16: 5.若弹窗提示"折旧摊销异常"，请前往投资与减值表填写折旧摊销数据；
B17: 5.点击“添加输出表”可进行输出表更新； | E17: 6.若弹窗提示"资本开支异常"，请前往投资与减值表填写当期资产增加值；
B18: 6.点击“导入历史模型”可实现历史预测数据迁移，支持V6-V12版本导入。 | E18: 7.若弹窗提示"资产负债表不平"，请打开空模型并通过"导入历史模型"功能将未配平模型导入。
B20: 公司经营数据 | C20: 自动生成的收入拆分数据 | E20: 参数填写说明：
B21: 销售预测 | C21: 用户填写相关假设，自动生成数据 | F21: 黄色底纹需手工填写数据
B22: 资产预测 | C22: 用户填写相关假设，自动生成数据
B23: 投资与减值 | C23: 用户填写相关假设，自动生成数据
B24: 主要财务摘要 | C24: 自动生成的财务指标计算结果 | F24: 金色边框可自由修改参数
B25: 报表摘要 | C25: 自动生成的财务指标计算结果
B26: 资产负债表 | C26: 用户填写相关假设，自动生成数据
B27: 利润表 | C27: 用户填写相关假设，自动生成数据 | F27: 蓝色底纹可以手工填写数据
B28: 现金流量表 | C28: 用户填写相关假设，自动生成数据
B29: 财务分析 | C29: 自动生成的财务指标计算结果
B30: 参数计算 | C30: 自动生成的财务指标计算结果
B31: 估值 | C31: 用户填写相关假设，自动生成数据
B32: 同业分析 | C32: 自动生成的同业分析数据
B33: 盈利敏感性分析 | C33: 用户填写相关假设，自动生成数据
B34: 单季度利润表 | C34: 自动生成的单季度利润表
B35: 财务基础数据 | C35: 自动生成的财务基础数据
B36: 财务附注数据 | C36: 自动生成的财务附注数据

Sheet 公司经营数据
A1: =目录!F2 -> XXXX | O1: 说明：1、预测年度可分项直接在黄色单元格填写各项目收入、成本金额，最后可以在第5行、第7行求和；
A2: ="单位:人民币"&目录!D5 -> 单位:人民币百万元 | O2: 2、请不要在A-AD列插入或删除列，不要更改表名，可能会影响数据提取！
O3: 3、此页数据更新可能会导致结构发生变化，可新建一个副本保存数据。
C4: 收入项目 | E4: =财务基础数据!J5 -> 2016 | F4: =财务基础数据!L5 -> 1H17 | G4: =财务基础数据!N5 -> 2017 | H4: =财务基础数据!P5 -> 1H18 | I4: =财务基础数据!R5 -> 2018 | J4: =财务基础数据!T5 -> 1H19 | K4: =财务基础数据!V5 -> 2019 | L4: =财务基础数据!X5 -> 1H20 | M4: =财务基础数据!Z5 -> 2020 | N4: =财务基础数据!AB5 -> 1H21 | O4: =财务基础数据!AD5 -> 2021 | P4: =财务基础数据!AF5 -> 1H22 | Q4: =财务基础数据!AH5 -> 2022 | R4: =财务基础数据!AJ5 -> 1H23 | S4: =财务基础数据!AL5 -> 2023 | T4: =财务基础数据!AN5 -> 1H24 | U4: =财务基础数据!AP5 -> 2024 | V4: =财务基础数据!AP5+1 -> 2025 | W4: =V4+1 -> 2026 | X4: =W4+1 -> 2027 | Y4: =X4+1 -> 2028 | Z4: =Y4+1 -> 2029 | AA4: =Z4+1 -> 2030 | AB4: =AA4+1 -> 2031 | AC4: =AB4+1 -> 2032 | AD4: =AC4+1 -> 2033
C5: 营业收入 | E5: =利润表!E8 -> 0 | F5: =利润表!G8 -> 0 | G5: =利润表!I8 -> 0 | H5: =利润表!K8 -> 0 | I5: =利润表!M8 -> 0 | J5: =利润表!O8 -> 0 | K5: =利润表!Q8 -> 0 | L5: =利润表!S8 -> 0 | M5: =利润表!U8 -> 0 | N5: =利润表!W8 -> 0 | O5: =利润表!Y8 -> 0 | P5: =利润表!AA8 -> 0 | Q5: =利润表!AC8 -> 0 | R5: =利润表!AE8 -> 0 | S5: =利润表!AG8 -> 0 | T5: =利润表!AI8 -> 0
C6: 增长率% | G6: =利润表!I9 -> — | H6: =利润表!K9 -> — | I6: =利润表!M9 -> — | J6: =利润表!O9 -> — | K6: =利润表!Q9 -> — | L6: =利润表!S9 -> — | M6: =利润表!U9 -> — | N6: =利润表!W9 -> — | O6: =利润表!Y9 -> — | P6: =利润表!AA9 -> — | Q6: =利润表!AC9 -> — | R6: =利润表!AE9 -> — | S6: =利润表!AG9 -> — | T6: =利润表!AI9 -> — | U6: =IF(ISERROR(U5/S5-1),0,U5/S5-1) -> 0 | V6: =IF(ISERROR(V5/U5-1),0,V5/U5-1) -> 0 | W6: =IF(ISERROR(W5/V5-1),0,W5/V5-1) -> 0 | X6: =IF(ISERROR(X5/W5-1),0,X5/W5-1) -> 0 | Y6: =IF(ISERROR(Y5/X5-1),0,Y5/X5-1) -> 0 | Z6: =IF(ISERROR(Z5/Y5-1),0,Z5/Y5-1) -> 0 | AA6: =IF(ISERROR(AA5/Z5-1),0,AA5/Z5-1) -> 0 | AB6: =IF(ISERROR(AB5/AA5-1),0,AB5/AA5-1) -> 0 | AC6: =IF(ISERROR(AC5/AB5-1),0,AC5/AB5-1) -> 0 | AD6: =IF(ISERROR(AD5/AC5-1),0,AD5/AC5-1) -> 0
C7: 营业成本 | E7: =利润表!E15 -> 0 | F7: =利润表!G15 -> 0 | G7: =利润表!I15 -> 0 | H7: =利润表!K15 -> 0 | I7: =利润表!M15 -> 0 | J7: =利润表!O15 -> 0 | K7: =利润表!Q15 -> 0 | L7: =利润表!S15 -> 0 | M7: =利润表!U15 -> 0 | N7: =利润表!W15 -> 0 | O7: =利润表!Y15 -> 0 | P7: =利润表!AA15 -> 0 | Q7: =利润表!AC15 -> 0 | R7: =利润表!AE15 -> 0 | S7: =利润表!AG15 -> 0 | T7: =利润表!AI15 -> 0
C8: 增长率% | G8: =利润表!I18 -> — | H8: =利润表!K18 -> — | I8: =利润表!M18 -> — | J8: =利润表!O18 -> — | K8: =利润表!Q18 -> — | L8: =利润表!S18 -> — | M8: =利润表!U18 -> — | N8: =利润表!W18 -> — | O8: =利润表!Y18 -> — | P8: =利润表!AA18 -> — | Q8: =利润表!AC18 -> — | R8: =利润表!AE18 -> — | S8: =利润表!AG18 -> — | T8: =利润表!AI18 -> — | U8: =IF(ISERROR(U7/S7-1),0,U7/S7-1) -> 0 | V8: =IF(ISERROR(V7/U7-1),0,V7/U7-1) -> 0 | W8: =IF(ISERROR(W7/V7-1),0,W7/V7-1) -> 0 | X8: =IF(ISERROR(X7/W7-1),0,X7/W7-1) -> 0 | Y8: =IF(ISERROR(Y7/X7-1),0,Y7/X7-1) -> 0 | Z8: =IF(ISERROR(Z7/Y7-1),0,Z7/Y7-1) -> 0 | AA8: =IF(ISERROR(AA7/Z7-1),0,AA7/Z7-1) -> 0 | AB8: =IF(ISERROR(AB7/AA7-1),0,AB7/AA7-1) -> 0 | AC8: =IF(ISERROR(AC7/AB7-1),0,AC7/AB7-1) -> 0 | AD8: =IF(ISERROR(AD7/AC7-1),0,AD7/AC7-1) -> 0
C9: 毛利 | E9: =E5-E7 -> 0 | F9: =F5-F7 -> 0 | G9: =G5-G7 -> 0 | H9: =H5-H7 -> 0 | I9: =I5-I7 -> 0 | J9: =J5-J7 -> 0 | K9: =K5-K7 -> 0 | L9: =L5-L7 -> 0 | ... U9: =U5-U7 -> 0 | V9: =IF(ISERROR(V5-V7),0,V5-V7) -> 0 | W9: =IF(ISERROR(W5-W7),0,W5-W7) -> 0 | X9: =IF(ISERROR(X5-X7),0,X5-X7) -> 0 | Y9: =IF(ISERROR(Y5-Y7),0,Y5-Y7) -> 0 | Z9: =IF(ISERROR(Z5-Z7),0,Z5-Z7) -> 0 | AA9: =IF(ISERROR(AA5-AA7),0,AA5-AA7) -> 0 | AB9: =IF(ISERROR(AB5-AB7),0,AB5-AB7) -> 0 | AC9: =IF(ISERROR(AC5-AC7),0,AC5-AC7) -> 0 | AD9: =IF(ISERROR(AD5-AD7),0,AD5-AD7) -> 0
C10: 毛利率 | E10: =IF(ISERROR(E9/E5),"—",E9/E5) -> — | F10: =IF(ISERROR(F9/F5),"—",F9/F5) -> — | G10: =IF(ISERROR(G9/G5),"—",G9/G5) -> — | H10: =IF(ISERROR(H9/H5),"—",H9/H5) -> — | I10: =IF(ISERROR(I9/I5),"—",I9/I5) -> — | J10: =IF(ISERROR(J9/J5),"—",J9/J5) -> — | K10: =IF(ISERROR(K9/K5),"—",K9/K5) -> — | L10: =IF(ISERROR(L9/L5),"—",L9/L5) -> — | ... T10: =IF(ISERROR(T9/T5),"—",T9/T5) -> — | U10: =IF(ISERROR(U9/U5),0,U9/U5) -> 0 | V10: =IF(ISERROR(V9/V5),0,V9/V5) -> 0 | W10: =IF(ISERROR(W9/W5),0,W9/W5) -> 0 | X10: =IF(ISERROR(X9/X5),0,X9/X5) -> 0 | Y10: =IF(ISERROR(Y9/Y5),0,Y9/Y5) -> 0 | Z10: =IF(ISERROR(Z9/Z5),0,Z9/Z5) -> 0 | AA10: =IF(ISERROR(AA9/AA5),0,AA9/AA5) -> 0 | AB10: =IF(ISERROR(AB9/AB5),0,AB9/AB5) -> 0 | ... AD10: =IF(ISERROR(AD9/AD5),0,AD9/AD5) -> 0

Sheet 销售预测
B1: 此页季度数据为单季度数据
B2: 产品收入成本 | I2: 注意：预测前三年可按照季度数据进行预测（如当前三季报已出，可直接在蓝色单元格填写第四季度数据），也可直接在黄色单元格填写年度预测数据
B3: ="单位：人民币"&目录!D5 -> 单位：人民币百万元
B4: 项 目 | I4: =利润表!Y4 -> 2021 | J4: =利润表!AC4 -> 2022 | K4: =利润表!AG4 -> 2023 | L4: =资产负债表!AK4 -> 2024E | M4: =资产负债表!AL4 -> 2025 | N4: =资产负债表!AM4 -> 2026 | O4: =资产负债表!AN4 -> 2027 | P4: =资产负债表!AO4 -> 2028 | Q4: =资产负债表!AP4 -> 2029 | R4: =资产负债表!AQ4 -> 2030 | S4: =资产负债表!AR4 -> 2031 | ... U4: =资产负债表!AT4 -> 2033 | W4: ="1Q"&利润表!Y4 -> 1Q2021 | X4: ="2Q"&利润表!Y4 -> 2Q2021 | Y4: ="3Q"&利润表!Y4 -> 3Q2021 | Z4: ="4Q"&利润表!Y4 -> 4Q2021 | AA4: ="1Q"&利润表!AC4 -> 1Q2022 | AB4: ="2Q"&利润表!AC4 -> 2Q2022 | AC4: ="3Q"&利润表!AC4 -> 3Q2022 | AD4: ="4Q"&利润表!AC4 -> 4Q2022 | AE4: ="1Q"&利润表!AG4 -> 1Q2023 | AF4: ="2Q"&利润表!AG4 -> 2Q2023 | AG4: ="3Q"&利润表!AG4 -> 3Q2023 | AH4: ="4Q"&利润表!AG4 -> 4Q2023 | AI4: ="1Q"&财务基础数据!AP5 -> 1Q2024 | AJ4: ="2Q"&财务基础数据!AP5 -> 2Q2024 | AK4: ="3Q"&财务基础数据!AP5 -> 3Q2024 | AL4: ="1Q"&财务基础数据!AP5 -> 1Q2024 | AM4: ="2Q"&财务基础数据!AP5 -> 2Q2024 | AN4: ="3Q"&财务基础数据!AP5 -> 3Q2024 | AO4: ="4Q"&财务基础数据!AP5 -> 4Q2024 | AP4: ="1Q"&财务基础数据!AP5+1 -> 1Q2025 | AQ4: ="2Q"&财务基础数据!AP5+1 -> 2Q2025 | AR4: ="3Q"&财务基础数据!AP5+1 -> 3Q2025 | AS4: ="4Q"&财务基础数据!AP5+1 -> 4Q2025 | AT4: ="1Q"&财务基础数据!AP5+2 -> 1Q2026 | AU4: ="2Q"&财务基础数据!AP5+2 -> 2Q2026 | AV4: ="3Q"&财务基础数据!AP5+2 -> 3Q2026 | AW4: ="4Q"&财务基础数据!AP5+2 -> 4Q2026
B5: 营业总收入 | I5: =利润表!Y6 -> 0 | J5: =利润表!AC6 -> 0 | K5: =利润表!AG6 -> 0 | L5: =L6+L8 -> 0 | M5: =M6+M8 -> 0 | N5: =N6+N8 -> 0 | O5: =O6+O8 -> 0 | P5: =P6+P8 -> 0 | Q5: =Q6+Q8 -> 0 | R5: =R6+R8 -> 0 | S5: =S6+S8 -> 0 | ... U5: =U6+U8 -> 0 | W5: =W6+W8 -> 0 | X5: =X6+X8 -> 0 | Y5: =Y6+Y8 -> 0 | Z5: =Z6+Z8 -> 0 | AA5: =AA6+AA8 -> 0 | AB5: =AB6+AB8 -> 0 | AC5: =AC6+AC8 -> 0 | AD5: =AD6+AD8 -> 0 | ... AK5: =AK6+AK8 -> 0 | AL5: =IF(ISERROR(AL6+AL8),"—",AL6+AL8) -> — | AM5: =IF(ISERROR(AM6+AM8),"—",AM6+AM8) -> — | AN5: =IF(ISERROR(AN6+AN8),"—",AN6+AN8) -> — | AO5: =AO6+AO8 -> 0 | AP5: =AP6+AP8 -> 0 | AQ5: =AQ6+AQ8 -> 0 | AR5: =AR6+AR8 -> 0 | AS5: =AS6+AS8 -> 0 | AT5: =AT6+AT8 -> 0 | AU5: =AU6+AU8 -> 0 | AV5: =AV6+AV8 -> 0 | AW5: =AW6+AW8 -> 0
B6: 营业收入 | I6: =利润表!Y8 -> 0 | J6: =利润表!AC8 -> 0 | K6: =利润表!AG8 -> 0 | W6: =利润表!V8 -> 0 | X6: =利润表!W8-利润表!V8 -> 0 | Y6: =利润表!X8-利润表!W8 -> 0 | Z6: =利润表!Y8-利润表!X8 -> 0 | AA6: =利润表!Z8 -> 0 | AB6: =利润表!AA8-利润表!Z8 -> 0 | AC6: =利润表!AB8-利润表!AA8 -> 0 | AD6: =利润表!AC8-利润表!AB8 -> 0 | AE6: =利润表!AD8 -> 0 | AF6: =利润表!AE8-利润表!AD8 -> 0 | AG6: =利润表!AF8-利润表!AE8 -> 0 | AH6: =利润表!AG8-利润表!AF8 -> 0 | AI6: =IF(财务基础数据!AM4=0,0,利润表!AH8) -> 0 | AJ6: =IF(财务基础数据!AM4<=1,0,利润表!AI8-利润表!AH8) -> 0 | AK6: =IF(财务基础数据!AM4<=2,0,利润表!AJ8-利润表!AI8) -> 0 | AL6: =IF(财务基础数据!AM4=0,"",AI6) | AM6: =IF(财务基础数据!AM4<=1,"",AJ6) | AN6: =IF(财务基础数据!AM4<=2,"",AK6)
B7: yoy(%) | I7: =IF(ISERROR((I6-利润表!U8)/ABS(利润表!U8)),"—",(I6-利润表!U8)/ABS(利润表!U8)) -> — | J7: =IF(ISERROR((J6-I6)/ABS(I6)),"—",(J6-I6)/ABS(I6)) -> — | K7: =IF(ISERROR((K6-J6)/ABS(J6)),"—",(K6-J6)/ABS(J6)) -> — | L7: =IF(ISERROR((L6-K6)/ABS(K6)),"—",(L6-K6)/ABS(K6)) -> — | M7: =IF(ISERROR((M6-L6)/ABS(L6)),"—",(M6-L6)/ABS(L6)) -> — | N7: =IF(ISERROR((N6-M6)/ABS(M6)),"—",(N6-M6)/ABS(M6)) -> — | O7: =IF(ISERROR((O6-N6)/ABS(N6)),"—",(O6-N6)/ABS(N6)) -> — | P7: =IF(ISERROR((P6-O6)/ABS(O6)),"—",(P6-O6)/ABS(O6)) -> — | Q7: =IF(ISERROR((Q6-P6)/ABS(P6)),"—",(Q6-P6)/ABS(P6)) -> — | ... U7: =IF(ISERROR((U6-T6)/ABS(T6)),"—",(U6-T6)/ABS(T6)) -> — | AA7: =IF(ISERROR((AA6-W6)/ABS(W6)),"—",(AA6-W6)/ABS(W6)) -> — | AB7: =IF(ISERROR((AB6-X6)/ABS(X6)),"—",(AB6-X6)/ABS(X6)) -> — | AC7: =IF(ISERROR((AC6-Y6)/ABS(Y6)),"—",(AC6-Y6)/ABS(Y6)) -> — | AD7: =IF(ISERROR((AD6-Z6)/ABS(Z6)),"—",(AD6-Z6)/ABS(Z6)) -> — | AE7: =IF(ISERROR((AE6-AA6)/ABS(AA6)),"—",(AE6-AA6)/ABS(AA6)) -> — | AF7: =IF(ISERROR((AF6-AB6)/ABS(AB6)),"—",(AF6-AB6)/ABS(AB6)) -> — | AG7: =IF(ISERROR((AG6-AC6)/ABS(AC6)),"—",(AG6-AC6)/ABS(AC6)) -> — | AH7: =IF(ISERROR((AH6-AD6)/ABS(AD6)),"—",(AH6-AD6)/ABS(AD6)) -> — | ... AK7: =IF(ISERROR((AK6-AG6)/ABS(AG6)),"—",(AK6-AG6)/ABS(AG6)) -> — | AL7: =IF(ISERROR((AL6-AE6)/ABS(AE6)),"—",(AL6-AE6)/ABS(AE6)) -> — | AM7: =IF(ISERROR((AM6-AF6)/ABS(AF6)),"—",(AM6-AF6)/ABS(AF6)) -> — | AN7: =IF(ISERROR((AN6-AG6)/ABS(AG6)),"—",(AN6-AG6)/ABS(AG6)) -> — | AO7: =IF(ISERROR((AO6-AH6)/ABS(AH6)),"—",(AO6-AH6)/ABS(AH6)) -> — | AP7: =IF(ISERROR((AP6-AL6)/ABS(AL6)),"—",(AP6-AL6)/ABS(AL6)) -> — | AQ7: =IF(ISERROR((AQ6-AM6)/ABS(AM6)),"—",(AQ6-AM6)/ABS(AM6)) -> — | AR7: =IF(ISERROR((AR6-AN6)/ABS(AN6)),"—",(AR6-AN6)/ABS(AN6)) -> — | AS7: =IF(ISERROR((AS6-AO6)/ABS(AO6)),"—",(AS6-AO6)/ABS(AO6)) -> — | AT7: =IF(ISERROR((AT6-AP6)/ABS(AP6)),"—",(AT6-AP6)/ABS(AP6)) -> — | AU7: =IF(ISERROR((AU6-AQ6)/ABS(AQ6)),"—",(AU6-AQ6)/ABS(AQ6)) -> — | AV7: =IF(ISERROR((AV6-AR6)/ABS(AR6)),"—",(AV6-AR6)/ABS(AR6)) -> — | AW7: =IF(ISERROR((AW6-AS6)/ABS(AS6)),"—",(AW6-AS6)/ABS(AS6)) -> —
B8: 其他金融类业务收入 | I8: =利润表!Y10 -> 0 | J8: =利润表!AC10 -> 0 | K8: =利润表!AG10 -> 0 | W8: =利润表!V10 -> 0 | X8: =利润表!W10-利润表!V10 -> 0 | Y8: =利润表!X10-利润表!W10 -> 0 | Z8: =利润表!Y10-利润表!X10 -> 0 | AA8: =利润表!Z10 -> 0 | AB8: =利润表!AA10-利润表!Z10 -> 0 | AC8: =利润表!AB10-利润表!AA10 -> 0 | AD8: =利润表!AC10-利润表!AB10 -> 0 | AE8: =利润表!AD10 -> 0 | AF8: =利润表!AE10-利润表!AD10 -> 0 | AG8: =利润表!AF10-利润表!AE10 -> 0 | AH8: =利润表!AG10-利润表!AF10 -> 0 | AI8: =IF(财务基础数据!AM4=0,0,利润表!AH10) -> 0 | AJ8: =IF(财务基础数据!AM4<=1,0,利润表!AI10-利润表!AH10) -> 0 | AK8: =IF(财务基础数据!AM4<=2,0,利润表!AJ10-利润表!AI10) -> 0 | AL8: =IF(财务基础数据!AM4=0,"",AI8) | AM8: =IF(财务基础数据!AM4<=1,"",AJ8) | AN8: =IF(财务基础数据!AM4<=2,"",AK8)
B9: 营业成本 | I9: =I10+I12 -> 0 | J9: =J10+J12 -> 0 | K9: =K10+K12 -> 0 | L9: =L10+L12 -> 0 | M9: =M10+M12 -> 0 | N9: =N10+N12 -> 0 | O9: =O10+O12 -> 0 | P9: =P10+P12 -> 0 | ... U9: =U10+U12 -> 0 | W9: =W10+W12 -> 0 | X9: =X10+X12 -> 0 | Y9: =Y10+Y12 -> 0 | Z9: =Z10+Z12 -> 0 | AA9: =AA10+AA12 -> 0 | AB9: =AB10+AB12 -> 0 | AC9: =AC10+AC12 -> 0 | AD9: =AD10+AD12 -> 0 | ... AK9: =AK10+AK12 -> 0 | AL9: =IF(ISERROR(AL10+AL12),"—",AL10+AL12) -> — | AM9: =IF(ISERROR(AM10+AM12),"—",AM10+AM12) -> — | AN9: =IF(ISERROR(AN10+AN12),"—",AN10+AN12) -> — | AO9: =AO10+AO12 -> 0 | AP9: =AP10+AP12 -> 0 | AQ9: =AQ10+AQ12 -> 0 | AR9: =AR10+AR12 -> 0 | AS9: =AS10+AS12 -> 0 | AT9: =AT10+AT12 -> 0 | AU9: =AU10+AU12 -> 0 | AV9: =AV10+AV12 -> 0 | AW9: =AW10+AW12 -> 0
B10: 营业成本 | I10: =利润表!Y15 -> 0 | J10: =利润表!AC15 -> 0 | K10: =利润表!AG15 -> 0 | W10: =利润表!V15 -> 0 | X10: =利润表!W15-利润表!V15 -> 0 | Y10: =利润表!X15-利润表!W15 -> 0 | Z10: =利润表!Y15-利润表!X15 -> 0 | AA10: =利润表!Z15 -> 0 | AB10: =利润表!AA15-利润表!Z15 -> 0 | AC10: =利润表!AB15-利润表!AA15 -> 0 | AD10: =利润表!AC15-利润表!AB15 -> 0 | AE10: =利润表!AD15 -> 0 | AF10: =利润表!AE15-利润表!AD15 -> 0 | AG10: =利润表!AF15-利润表!AE15 -> 0 | AH10: =利润表!AG15-利润表!AF15 -> 0 | AI10: =IF(财务基础数据!AM4=0,0,利润表!AH15) -> 0 | AJ10: =IF(财务基础数据!AM4<=1,0,利润表!AI15-利润表!AH15) -> 0 | AK10: =IF(财务基础数据!AM4<=2,0,利润表!AJ15-利润表!AI15) -> 0 | AL10: =IF(财务基础数据!AM4=0,"",AI10) | AM10: =IF(财务基础数据!AM4<=1,"",AJ10) | AN10: =IF(财务基础数据!AM4<=2,"",AK10)
B11: yoy(%) | I11: =IF(ISERROR((I10-利润表!U15)/ABS(利润表!U15)),"—",(I10-利润表!U15)/ABS(利润表!U15)) -> — | J11: =IF(ISERROR((J10-I10)/ABS(I10)),"—",(J10-I10)/ABS(I10)) -> — | K11: =IF(ISERROR((K10-J10)/ABS(J10)),"—",(K10-J10)/ABS(J10)) -> — | L11: =IF(ISERROR((L10-K10)/ABS(K10)),"—",(L10-K10)/ABS(K10)) -> — | M11: =IF(ISERROR((M10-L10)/ABS(L10)),"—",(M10-L10)/ABS(L10)) -> — | N11: =IF(ISERROR((N10-M10)/ABS(M10)),"—",(N10-M10)/ABS(M10)) -> — | O11: =IF(ISERROR((O10-N10)/ABS(N10)),"—",(O10-N10)/ABS(N10)) -> — | P11: =IF(ISERROR((P10-O10)/ABS(O10)),"—",(P10-O10)/ABS(O10)) -> — | Q11: =IF(ISERROR((Q10-P10)/ABS(P10)),"—",(Q10-P10)/ABS(P10)) -> — | ... U11: =IF(ISERROR((U10-T10)/ABS(T10)),"—",(U10-T10)/ABS(T10)) -> — | AA11: =IF(ISERROR((AA10-W10)/ABS(W10)),"—",(AA10-W10)/ABS(W10)) -> — | AB11: =IF(ISERROR((AB10-X10)/ABS(X10)),"—",(AB10-X10)/ABS(X10)) -> — | AC11: =IF(ISERROR((AC10-Y10)/ABS(Y10)),"—",(AC10-Y10)/ABS(Y10)) -> — | AD11: =IF(ISERROR((AD10-Z10)/ABS(Z10)),"—",(AD10-Z10)/ABS(Z10)) -> — | AE11: =IF(ISERROR((AE10-AA10)/ABS(AA10)),"—",(AE10-AA10)/ABS(AA10)) -> — | AF11: =IF(ISERROR((AF10-AB10)/ABS(AB10)),"—",(AF10-AB10)/ABS(AB10)) -> — | AG11: =IF(ISERROR((AG10-AC10)/ABS(AC10)),"—",(AG10-AC10)/ABS(AC10)) -> — | AH11: =IF(ISERROR((AH10-AD10)/ABS(AD10)),"—",(AH10-AD10)/ABS(AD10)) -> — | ... AK11: =IF(ISERROR((AK10-AG10)/ABS(AG10)),"—",(AK10-AG10)/ABS(AG10)) -> — | AL11: =IF(ISERROR((AL10-AE10)/ABS(AE10)),"—",(AL10-AE10)/ABS(AE10)) -> — | AM11: =IF(ISERROR((AM10-AF10)/ABS(AF10)),"—",(AM10-AF10)/ABS(AF10)) -> — | AN11: =IF(ISERROR((AN10-AG10)/ABS(AG10)),"—",(AN10-AG10)/ABS(AG10)) -> — | AO11: =IF(ISERROR((AO10-AH10)/ABS(AH10)),"—",(AO10-AH10)/ABS(AH10)) -> — | AP11: =IF(ISERROR((AP10-AL10)/ABS(AL10)),"—",(AP10-AL10)/ABS(AL10)) -> — | AQ11: =IF(ISERROR((AQ10-AM10)/ABS(AM10)),"—",(AQ10-AM10)/ABS(AM10)) -> — | AR11: =IF(ISERROR((AR10-AN10)/ABS(AN10)),"—",(AR10-AN10)/ABS(AN10)) -> — | AS11: =IF(ISERROR((AS10-AO10)/ABS(AO10)),"—",(AS10-AO10)/ABS(AO10)) -> — | AT11: =IF(ISERROR((AT10-AP10)/ABS(AP10)),"—",(AT10-AP10)/ABS(AP10)) -> — | AU11: =IF(ISERROR((AU10-AQ10)/ABS(AQ10)),"—",(AU10-AQ10)/ABS(AQ10)) -> — | AV11: =IF(ISERROR((AV10-AR10)/ABS(AR10)),"—",(AV10-AR10)/ABS(AR10)) -> — | AW11: =IF(ISERROR((AW10-AS10)/ABS(AS10)),"—",(AW10-AS10)/ABS(AS10)) -> —
B12: 其他金融类业务成本 | I12: =利润表!Y19 -> 0 | J12: =利润表!AC19 -> 0 | K12: =利润表!AG19 -> 0 | W12: =利润表!V19 -> 0 | X12: =利润表!W19-利润表!V19 -> 0 | Y12: =利润表!X19-利润表!W19 -> 0 | Z12: =利润表!Y19-利润表!X19 -> 0 | AA12: =利润表!Z19 -> 0 | AB12: =利润表!AA19-利润表!Z19 -> 0 | AC12: =利润表!AB19-利润表!AA19 -> 0 | AD12: =利润表!AC19-利润表!AB19 -> 0 | AE12: =利润表!AD19 -> 0 | AF12: =利润表!AE19-利润表!AD19 -> 0 | AG12: =利润表!AF19-利润表!AE19 -> 0 | AH12: =利润表!AG19-利润表!AF19 -> 0 | AI12: =IF(财务基础数据!AM4=0,0,利润表!AH19) -> 0 | AJ12: =IF(财务基础数据!AM4<=1,0,利润表!AI19-利润表!AH19) -> 0 | AK12: =IF(财务基础数据!AM4<=2,0,利润表!AJ19-利润表!AI19) -> 0 | AL12: =IF(财务基础数据!AM4=0,"",AI12) | AM12: =IF(财务基础数据!AM4<=1,"",AJ12) | AN12: =IF(财务基础数据!AM4<=2,"",AK12)
B14: 毛利 | I14: =I6-I10 -> 0 | J14: =J6-J10 -> 0 | K14: =K6-K10 -> 0 | L14: =L6-L10 -> 0 | M14: =M6-M10 -> 0 | N14: =N6-N10 -> 0 | O14: =O6-O10 -> 0 | P14: =P6-P10 -> 0 | ... U14: =U6-U10 -> 0 | W14: =W6-W10 -> 0 | X14: =X6-X10 -> 0 | Y14: =Y6-Y10 -> 0 | Z14: =Z6-Z10 -> 0 | AA14: =AA6-AA10 -> 0 | AB14: =AB6-AB10 -> 0 | AC14: =AC6-AC10 -> 0 | AD14: =AD6-AD10 -> 0 | ... AK14: =AK6-AK10 -> 0 | AL14: =IF(ISERROR(AL6-AL10),"—",AL6-AL10) -> — | AM14: =IF(ISERROR(AM6-AM10),"—",AM6-AM10) -> — | AN14: =IF(ISERROR(AN6-AN10),"—",AN6-AN10) -> — | AO14: =IF(ISERROR(AO6-AO10),"—",AO6-AO10) -> 0 | AP14: =AP6-AP10 -> 0 | AQ14: =AQ6-AQ10 -> 0 | AR14: =AR6-AR10 -> 0 | AS14: =AS6-AS10 -> 0 | AT14: =AT6-AT10 -> 0 | AU14: =AU6-AU10 -> 0 | AV14: =AV6-AV10 -> 0 | AW14: =AW6-AW10 -> 0
B15: 毛利率 | I15: =IF(ISERROR(I14/I6),"—",I14/I6) -> — | J15: =IF(ISERROR(J14/J6),"—",J14/J6) -> — | K15: =IF(ISERROR(K14/K6),"—",K14/K6) -> — | L15: =IF(ISERROR(L14/L6),"—",L14/L6) -> — | M15: =IF(ISERROR(M14/M6),"—",M14/M6) -> — | N15: =IF(ISERROR(N14/N6),"—",N14/N6) -> — | O15: =IF(ISERROR(O14/O6),"—",O14/O6) -> — | P15: =IF(ISERROR(P14/P6),"—",P14/P6) -> — | ... U15: =IF(ISERROR(U14/U6),"—",U14/U6) -> — | W15: =IF(ISERROR(W14/W6),"—",W14/W6) -> — | X15: =IF(ISERROR(X14/X6),"—",X14/X6) -> — | Y15: =IF(ISERROR(Y14/Y6),"—",Y14/Y6) -> — | Z15: =IF(ISERROR(Z14/Z6),"—",Z14/Z6) -> — | AA15: =IF(ISERROR(AA14/AA6),"—",AA14/AA6) -> — | AB15: =IF(ISERROR(AB14/AB6),"—",AB14/AB6) -> — | AC15: =IF(ISERROR(AC14/AC6),"—",AC14/AC6) -> — | AD15: =IF(ISERROR(AD14/AD6),"—",AD14/AD6) -> — | ... AW15: =IF(ISERROR(AW14/AW6),"—",AW14/AW6) -> —
B18: 经营收益的其他假设 | I18: 说明：季度数据预测和年度数据预测不可同时生效，只可选择其中一种预测方式
B20: 项 目 | I20: =I4 -> 2021 | J20: =J4 -> 2022 | K20: =K4 -> 2023 | W20: =W4 -> 1Q2021 | X20: =X4 -> 2Q2021 | Y20: =Y4 -> 3Q2021 | Z20: =Z4 -> 4Q2021 | AA20: =AA4 -> 1Q2022 | AB20: =AB4 -> 2Q2022 | AC20: =AC4 -> 3Q2022 | AD20: =AD4 -> 4Q2022 | ... AW20: =AW4 -> 4Q2026
B21: 税金及附加 | I21: =利润表!Y27 -> 0 | J21: =利润表!AC27 -> 0 | K21: =利润表!AG27 -> 0 | L21: =IF(COUNT(AL22:AO22)=4,SUM(AL21:AO21),L22*L6) -> 0 | M21: =IF(COUNT(AP22:AS22)=4,SUM(AP21:AS21),M22*M6) -> 0 | N21: =IF(COUNT(AT22:AW22)=4,SUM(AT21:AW21),N22*N6) -> 0 | O21: =IF(ISERROR(O22*O6),"—",O22*O6) -> 0 | P21: =IF(ISERROR(P22*P6),"—",P22*P6) -> 0 | Q21: =IF(ISERROR(Q22*Q6),"—",Q22*Q6) -> 0 | R21: =IF(ISERROR(R22*R6),"—",R22*R6) -> 0 | S21: =IF(ISERROR(S22*S6),"—",S22*S6) -> 0 | T21: =IF(ISERROR(T22*T6),"—",T22*T6) -> 0 | U21: =IF(ISERROR(U22*U6),"—",U22*U6) -> 0 | W21: =利润表!V27 -> 0 | X21: =利润表!W27-利润表!V27 -> 0 | Y21: =利润表!X27-利润表!W27 -> 0 | Z21: =利润表!Y27-利润表!X27 -> 0 | AA21: =利润表!Z27 -> 0 | AB21: =利润表!AA27-利润表!Z27 -> 0 | AC21: =利润表!AB27-利润表!AA27 -> 0 | AD21: =利润表!AC27-利润表!AB27 -> 0 | AE21: =利润表!AD27 -> 0 | AF21: =利润表!AE27-利润表!AD27 -> 0 | AG21: =利润表!AF27-利润表!AE27 -> 0 | AH21: =利润表!AG27-利润表!AF27 -> 0 | AI21: =IF(财务基础数据!AM4=0,0,利润表!AH27) -> 0 | AJ21: =IF(财务基础数据!AM4<=1,0,利润表!AI27-利润表!AH27) -> 0 | AK21: =IF(财务基础数据!AM4<=2,0,利润表!AJ27-利润表!AI27) -> 0 | AL21: =IF(ISERROR(AL22*AL6),"—",AL22*AL6) -> — | AM21: =IF(ISERROR(AM22*AM6),"—",AM22*AM6) -> — | AN21: =IF(ISERROR(AN22*AN6),"—",AN22*AN6) -> — | AO21: =IF(ISERROR(AO22*AO6),"—",AO22*AO6) -> 0 | AP21: =IF(ISERROR(AP22*AP6),"—",AP22*AP6) -> 0 | AQ21: =IF(ISERROR(AQ22*AQ6),"—",AQ22*AQ6) -> 0 | AR21: =IF(ISERROR(AR22*AR6),"—",AR22*AR6) -> 0 | AS21: =IF(ISERROR(AS22*AS6),"—",AS22*AS6) -> 0 | ... AW21: =IF(ISERROR(AW22*AW6),"—",AW22*AW6) -> 0
B22: 税金及附加/营业收入 | I22: =IF(ISERROR(I21/I6),"—",I21/I6) -> — | J22: =IF(ISERROR(J21/J6),"—",J21/J6) -> — | K22: =IF(ISERROR(K21/K6),"—",K21/K6) -> — | W22: =IF(ISERROR(W21/W6),"—",W21/W6) -> — | X22: =IF(ISERROR(X21/X6),"—",X21/X6) -> — | Y22: =IF(ISERROR(Y21/Y6),"—",Y21/Y6) -> — | Z22: =IF(ISERROR(Z21/Z6),"—",Z21/Z6) -> — | AA22: =IF(ISERROR(AA21/AA6),"—",AA21/AA6) -> — | AB22: =IF(ISERROR(AB21/AB6),"—",AB21/AB6) -> — | AC22: =IF(ISERROR(AC21/AC6),"—",AC21/AC6) -> — | AD22: =IF(ISERROR(AD21/AD6),"—",AD21/AD6) -> — | ... AK22: =IF(ISERROR(AK21/AK6),"—",AK21/AK6) -> — | AL22: =IF(财务基础数据!AM4=0,"",AI22) | AM22: =IF(财务基础数据!AM4<=1,"",AJ22) | AN22: =IF(财务基础数据!AM4<=2,"",AK22)
B24: 销售费用 | I24: =利润表!Y29 -> 0 | J24: =利润表!AC29 -> 0 | K24: =利润表!AG29 -> 0 | L24: =IF(COUNT(AL25:AO25)=4,SUM(AL24:AO24),L25*L6) -> 0 | M24: =IF(COUNT(AP25:AS25)=4,SUM(AP24:AS24),M25*M6) -> 0 | N24: =IF(COUNT(AT25:AW25)=4,SUM(AT24:AW24),N25*N6) -> 0 | O24: =IF(ISERROR(O25*O6),"—",O25*O6) -> 0 | P24: =IF(ISERROR(P25*P6),"—",P25*P6) -> 0 | Q24: =IF(ISERROR(Q25*Q6),"—",Q25*Q6) -> 0 | R24: =IF(ISERROR(R25*R6),"—",R25*R6) -> 0 | S24: =IF(ISERROR(S25*S6),"—",S25*S6) -> 0 | T24: =IF(ISERROR(T25*T6),"—",T25*T6) -> 0 | U24: =IF(ISERROR(U25*U6),"—",U25*U6) -> 0 | W24: =利润表!V29 -> 0 | X24: =利润表!W29-利润表!V29 -> 0 | Y24: =利润表!X29-利润表!W29 -> 0 | Z24: =利润表!Y29-利润表!X29 -> 0 | AA24: =利润表!Z29 -> 0 | AB24: =利润表!AA29-利润表!Z29 -> 0 | AC24: =利润表!AB29-利润表!AA29 -> 0 | AD24: =利润表!AC29-利润表!AB29 -> 0 | AE24: =利润表!AD29 -> 0 | AF24: =利润表!AE29-利润表!AD29 -> 0 | AG24: =利润表!AF29-利润表!AE29 -> 0 | AH24: =利润表!AG29-利润表!AF29 -> 0 | AI24: =IF(财务基础数据!AM4=0,0,利润表!AH29) -> 0 | AJ24: =IF(财务基础数据!AM4<=1,0,利润表!AI29-利润表!AH29) -> 0 | AK24: =IF(财务基础数据!AM4<=2,0,利润表!AJ29-利润表!AI29) -> 0 | AL24: =IF(ISERROR(AL25*AL6),"—",AL25*AL6) -> — | AM24: =IF(ISERROR(AM25*AM6),"—",AM25*AM6) -> — | AN24: =IF(ISERROR(AN25*AN6),"—",AN25*AN6) -> — | AO24: =IF(ISERROR(AO25*AO6),"—",AO25*AO6) -> 0 | AP24: =IF(ISERROR(AP25*AP6),"—",AP25*AP6) -> 0 | AQ24: =IF(ISERROR(AQ25*AQ6),"—",AQ25*AQ6) -> 0 | AR24: =IF(ISERROR(AR25*AR6),"—",AR25*AR6) -> 0 | AS24: =IF(ISERROR(AS25*AS6),"—",AS25*AS6) -> 0 | ... AW24: =IF(ISERROR(AW25*AW6),"—",AW25*AW6) -> 0
B25: 销售费用/营业收入 | I25: =IF(ISERROR(I24/I6),"—",I24/I6) -> — | J25: =IF(ISERROR(J24/J6),"—",J24/J6) -> — | K25: =IF(ISERROR(K24/K6),"—",K24/K6) -> — | W25: =IF(ISERROR(W24/W6),"—",W24/W6) -> — | X25: =IF(ISERROR(X24/X6),"—",X24/X6) -> — | Y25: =IF(ISERROR(Y24/Y6),"—",Y24/Y6) -> — | Z25: =IF(ISERROR(Z24/Z6),"—",Z24/Z6) -> — | AA25: =IF(ISERROR(AA24/AA6),"—",AA24/AA6) -> — | AB25: =IF(ISERROR(AB24/AB6),"—",AB24/AB6) -> — | AC25: =IF(ISERROR(AC24/AC6),"—",AC24/AC6) -> — | AD25: =IF(ISERROR(AD24/AD6),"—",AD24/AD6) -> — | ... AK25: =IF(ISERROR(AK24/AK6),"—",AK24/AK6) -> — | AL25: =IF(财务基础数据!AM4=0,"",AI25) | AM25: =IF(财务基础数据!AM4<=1,"",AJ25) | AN25: =IF(财务基础数据!AM4<=2,"",AK25)
B27: 管理费用 | I27: =利润表!Y31 -> 0 | J27: =利润表!AC31 -> 0 | K27: =利润表!AG31 -> 0 | L27: =IF(COUNT(AL28:AO28)=4,SUM(AL27:AO27),L28*L6) -> 0 | M27: =IF(COUNT(AP28:AS28)=4,SUM(AP27:AS27),M28*M6) -> 0 | N27: =IF(COUNT(AT28:AW28)=4,SUM(AT27:AW27),N28*N6) -> 0 | O27: =IF(ISERROR(O28*O6),"—",O28*O6) -> 0 | P27: =IF(ISERROR(P28*P6),"—",P28*P6) -> 0 | Q27: =IF(ISERROR(Q28*Q6),"—",Q28*Q6) -> 0 | R27: =IF(ISERROR(R28*R6),"—",R28*R6) -> 0 | S27: =IF(ISERROR(S28*S6),"—",S28*S6) -> 0 | T27: =IF(ISERROR(T28*T6),"—",T28*T6) -> 0 | U27: =IF(ISERROR(U28*U6),"—",U28*U6) -> 0 | W27: =利润表!V31 -> 0 | X27: =利润表!W31-利润表!V31 -> 0 | Y27: =利润表!X31-利润表!W31 -> 0 | Z27: =利润表!Y31-利润表!X31 -> 0 | AA27: =利润表!Z31 -> 0 | AB27: =利润表!AA31-利润表!Z31 -> 0 | AC27: =利润表!AB31-利润表!AA31 -> 0 | AD27: =利润表!AC31-利润表!AB31 -> 0 | AE27: =利润表!AD31 -> 0 | AF27: =利润表!AE31-利润表!AD31 -> 0 | AG27: =利润表!AF31-利润表!AE31 -> 0 | AH27: =利润表!AG31-利润表!AF31 -> 0 | AI27: =IF(财务基础数据!AM4=0,0,利润表!AH31) -> 0 | AJ27: =IF(财务基础数据!AM4<=1,0,利润表!AI31-利润表!AH31) -> 0 | AK27: =IF(财务基础数据!AM4<=2,0,利润表!AJ31-利润表!AI31) -> 0 | AL27: =IF(ISERROR(AL28*AL6),"—",AL28*AL6) -> — | AM27: =IF(ISERROR(AM28*AM6),"—",AM28*AM6) -> — | AN27: =IF(ISERROR(AN28*AN6),"—",AN28*AN6) -> — | AO27: =IF(ISERROR(AO28*AO6),"—",AO28*AO6) -> 0 | AP27: =IF(ISERROR(AP28*AP6),"—",AP28*AP6) -> 0 | AQ27: =IF(ISERROR(AQ28*AQ6),"—",AQ28*AQ6) -> 0 | AR27: =IF(ISERROR(AR28*AR6),"—",AR28*AR6) -> 0 | AS27: =IF(ISERROR(AS28*AS6),"—",AS28*AS6) -> 0 | ... AW27: =IF(ISERROR(AW28*AW6),"—",AW28*AW6) -> 0
B28: 管理费用/营业收入 | I28: =IF(ISERROR(I27/I6),"—",I27/I6) -> — | J28: =IF(ISERROR(J27/J6),"—",J27/J6) -> — | K28: =IF(ISERROR(K27/K6),"—",K27/K6) -> — | W28: =IF(ISERROR(W27/W6),"—",W27/W6) -> — | X28: =IF(ISERROR(X27/X6),"—",X27/X6) -> — | Y28: =IF(ISERROR(Y27/Y6),"—",Y27/Y6) -> — | Z28: =IF(ISERROR(Z27/Z6),"—",Z27/Z6) -> — | AA28: =IF(ISERROR(AA27/AA6),"—",AA27/AA6) -> — | AB28: =IF(ISERROR(AB27/AB6),"—",AB27/AB6) -> — | AC28: =IF(ISERROR(AC27/AC6),"—",AC27/AC6) -> — | AD28: =IF(ISERROR(AD27/AD6),"—",AD27/AD6) -> — | ... AK28: =IF(ISERROR(AK27/AK6),"—",AK27/AK6) -> — | AL28: =IF(财务基础数据!AM4=0,"",AI28) | AM28: =IF(财务基础数据!AM4<=1,"",AJ28) | AN28: =IF(财务基础数据!AM4<=2,"",AK28)
B30: 研发费用 | I30: =利润表!Y33 -> 0 | J30: =利润表!AC33 -> 0 | K30: =利润表!AG33 -> 0 | L30: =IF(COUNT(AL31:AO31)=4,SUM(AL30:AO30),L31*L6) -> 0 | M30: =IF(COUNT(AP31:AS31)=4,SUM(AP30:AS30),M31*M6) -> 0 | N30: =IF(COUNT(AT31:AW31)=4,SUM(AT30:AW30),N31*N6) -> 0 | O30: =IF(ISERROR(O31*O6),"—",O31*O6) -> 0 | P30: =IF(ISERROR(P31*P6),"—",P31*P6) -> 0 | Q30: =IF(ISERROR(Q31*Q6),"—",Q31*Q6) -> 0 | R30: =IF(ISERROR(R31*R6),"—",R31*R6) -> 0 | S30: =IF(ISERROR(S31*S6),"—",S31*S6) -> 0 | T30: =IF(ISERROR(T31*T6),"—",T31*T6) -> 0 | U30: =IF(ISERROR(U31*U6),"—",U31*U6) -> 0 | W30: =利润表!V33 -> 0 | X30: =利润表!W33-利润表!V33 -> 0 | Y30: =利润表!X33-利润表!W33 -> 0 | Z30: =利润表!Y33-利润表!X33 -> 0 | AA30: =利润表!Z33 -> 0 | AB30: =利润表!AA33-利润表!Z33 -> 0 | AC30: =利润表!AB33-利润表!AA33 -> 0 | AD30: =利润表!AC33-利润表!AB33 -> 0 | AE30: =利润表!AD33 -> 0 | AF30: =利润表!AE33-利润表!AD33 -> 0 | AG30: =利润表!AF33-利润表!AE33 -> 0 | AH30: =利润表!AG33-利润表!AF33 -> 0 | AI30: =IF(财务基础数据!AM4=0,0,利润表!AH33) -> 0 | AJ30: =IF(财务基础数据!AM4<=1,0,利润表!AI33-利润表!AH33) -> 0 | AK30: =IF(财务基础数据!AM4<=2,0,利润表!AJ33-利润表!AI33) -> 0 | AL30: =IF(ISERROR(AL31*AL6),"—",AL31*AL6) -> — | AM30: =IF(ISERROR(AM31*AM6),"—",AM31*AM6) -> — | AN30: =IF(ISERROR(AN31*AN6),"—",AN31*AN6) -> — | AO30: =IF(ISERROR(AO31*AO6),"—",AO31*AO6) -> 0 | AP30: =IF(ISERROR(AP31*AP6),"—",AP31*AP6) -> 0 | AQ30: =IF(ISERROR(AQ31*AQ6),"—",AQ31*AQ6) -> 0 | AR30: =IF(ISERROR(AR31*AR6),"—",AR31*AR6) -> 0 | AS30: =IF(ISERROR(AS31*AS6),"—",AS31*AS6) -> 0 | ... AW30: =IF(ISERROR(AW31*AW6),"—",AW31*AW6) -> 0
B31: 研发费用/营业收入 | I31: =IF(ISERROR(I30/I6),"—",I30/I6) -> — | J31: =IF(ISERROR(J30/J6),"—",J30/J6) -> — | K31: =IF(ISERROR(K30/K6),"—",K30/K6) -> — | W31: =IF(ISERROR(W30/W6),"—",W30/W6) -> — | X31: =IF(ISERROR(X30/X6),"—",X30/X6) -> — | Y31: =IF(ISERROR(Y30/Y6),"—",Y30/Y6) -> — | Z31: =IF(ISERROR(Z30/Z6),"—",Z30/Z6) -> — | AA31: =IF(ISERROR(AA30/AA6),"—",AA30/AA6) -> — | AB31: =IF(ISERROR(AB30/AB6),"—",AB30/AB6) -> — | AC31: =IF(ISERROR(AC30/AC6),"—",AC30/AC6) -> — | AD31: =IF(ISERROR(AD30/AD6),"—",AD30/AD6) -> — | ... AK31: =IF(ISERROR(AK30/AK6),"—",AK30/AK6) -> — | AL31: =IF(财务基础数据!AM4=0,"",AI31) | AM31: =IF(财务基础数据!AM4<=1,"",AJ31) | AN31: =IF(财务基础数据!AM4<=2,"",AK31)
B33: 其他收益 | I33: =利润表!Y49 -> 0 | J33: =利润表!AC49 -> 0 | K33: =利润表!AG49 -> 0 | L33: =IF(COUNT(AL34:AO34)=4,SUM(AL33:AO33),L34*L6) -> 0 | M33: =IF(COUNT(AP34:AS34)=4,SUM(AP33:AS33),M34*M6) -> 0 | N33: =IF(COUNT(AT34:AW34)=4,SUM(AT33:AW33),N34*N6) -> 0 | O33: =O34*O6 -> 0 | P33: =P34*P6 -> 0 | Q33: =Q34*Q6 -> 0 | R33: =R34*R6 -> 0 | S33: =S34*S6 -> 0 | T33: =T34*T6 -> 0 | U33: =U34*U6 -> 0 | W33: =利润表!V49 -> 0 | X33: =利润表!W49-利润表!V49 -> 0 | Y33: =利润表!X49-利润表!W49 -> 0 | Z33: =利润表!Y49-利润表!X49 -> 0 | AA33: =利润表!Z49 -> 0 | AB33: =利润表!AA49-利润表!Z49 -> 0 | AC33: =利润表!AB49-利润表!AA49 -> 0 | AD33: =利润表!AC49-利润表!AB49 -> 0 | AE33: =利润表!AD49 -> 0 | AF33: =利润表!AE49-利润表!AD49 -> 0 | AG33: =利润表!AF49-利润表!AE49 -> 0 | AH33: =利润表!AG49-利润表!AF49 -> 0 | AI33: =IF(财务基础数据!AM4=0,0,利润表!AH49) -> 0 | AJ33: =IF(财务基础数据!AM4<=1,0,利润表!AI49-利润表!AH49) -> 0 | AK33: =IF(财务基础数据!AM4<=2,0,利润表!AJ49-利润表!AI49) -> 0 | AL33: =IF(ISERROR(AL34*AL6),"—",AL34*AL6) -> — | AM33: =IF(ISERROR(AM34*AM6),"—",AM34*AM6) -> — | AN33: =IF(ISERROR(AN34*AN6),"—",AN34*AN6) -> — | AO33: =IF(ISERROR(AO34*AO6),"—",AO34*AO6) -> 0 | AP33: =IF(ISERROR(AP34*AP6),"—",AP34*AP6) -> 0 | AQ33: =IF(ISERROR(AQ34*AQ6),"—",AQ34*AQ6) -> 0 | AR33: =IF(ISERROR(AR34*AR6),"—",AR34*AR6) -> 0 | AS33: =IF(ISERROR(AS34*AS6),"—",AS34*AS6) -> 0 | ... AW33: =IF(ISERROR(AW34*AW6),"—",AW34*AW6) -> 0
B34: 其他收益/营业收入 | I34: =IF(ISERROR(I33/I6),"—",I33/I6) -> — | J34: =IF(ISERROR(J33/J6),"—",J33/J6) -> — | K34: =IF(ISERROR(K33/K6),"—",K33/K6) -> — | W34: =IF(ISERROR(W33/W6),"—",W33/W6) -> — | X34: =IF(ISERROR(X33/X6),"—",X33/X6) -> — | Y34: =IF(ISERROR(Y33/Y6),"—",Y33/Y6) -> — | Z34: =IF(ISERROR(Z33/Z6),"—",Z33/Z6) -> — | AA34: =IF(ISERROR(AA33/AA6),"—",AA33/AA6) -> — | AB34: =IF(ISERROR(AB33/AB6),"—",AB33/AB6) -> — | AC34: =IF(ISERROR(AC33/AC6),"—",AC33/AC6) -> — | AD34: =IF(ISERROR(AD33/AD6),"—",AD33/AD6) -> — | ... AK34: =IF(ISERROR(AK33/AK6),"—",AK33/AK6) -> — | AL34: =IF(财务基础数据!AM4=0,"",AI34) | AM34: =IF(财务基础数据!AM4<=1,"",AJ34) | AN34: =IF(财务基础数据!AM4<=2,"",AK34)
B36: 投资收益 | I36: =利润表!Y51 -> 0 | J36: =利润表!AC51 -> 0 | K36: =利润表!AG51 -> 0 | L36: =IF(COUNT(AL37:AO37)=4,SUM(AL36:AO36),L37*L6) -> 0 | M36: =IF(COUNT(AP37:AS37)=4,SUM(AP36:AS36),M37*M6) -> 0 | N36: =IF(COUNT(AT37:AW37)=4,SUM(AT36:AW36),N37*N6) -> 0 | O36: =O37*O6 -> 0 | P36: =P37*P6 -> 0 | Q36: =Q37*Q6 -> 0 | R36: =R37*R6 -> 0 | S36: =S37*S6 -> 0 | T36: =T37*T6 -> 0 | U36: =U37*U6 -> 0 | W36: =利润表!V51 -> 0 | X36: =利润表!W51-利润表!V51 -> 0 | Y36: =利润表!X51-利润表!W51 -> 0 | Z36: =利润表!Y51-利润表!X51 -> 0 | AA36: =利润表!Z51 -> 0 | AB36: =利润表!AA51-利润表!Z51 -> 0 | AC36: =利润表!AB51-利润表!AA51 -> 0 | AD36: =利润表!AC51-利润表!AB51 -> 0 | AE36: =利润表!AD51 -> 0 | AF36: =利润表!AE51-利润表!AD51 -> 0 | AG36: =利润表!AF51-利润表!AE51 -> 0 | AH36: =利润表!AG51-利润表!AF51 -> 0 | AI36: =IF(财务基础数据!AM4=0,0,利润表!AH51) -> 0 | AJ36: =IF(财务基础数据!AM4<=1,0,利润表!AI51-利润表!AH51) -> 0 | AK36: =IF(财务基础数据!AM4<=2,0,利润表!AJ51-利润表!AI51) -> 0 | AL36: =IF(ISERROR(AL37*AL6),"—",AL37*AL6) -> — | AM36: =IF(ISERROR(AM37*AM6),"—",AM37*AM6) -> — | AN36: =IF(ISERROR(AN37*AN6),"—",AN37*AN6) -> — | AO36: =IF(ISERROR(AO37*AO6),"—",AO37*AO6) -> 0 | AP36: =IF(ISERROR(AP37*AP6),"—",AP37*AP6) -> 0 | AQ36: =IF(ISERROR(AQ37*AQ6),"—",AQ37*AQ6) -> 0 | AR36: =IF(ISERROR(AR37*AR6),"—",AR37*AR6) -> 0 | AS36: =IF(ISERROR(AS37*AS6),"—",AS37*AS6) -> 0 | ... AW36: =IF(ISERROR(AW37*AW6),"—",AW37*AW6) -> 0
B37: 投资收益/营业收入 | I37: =IF(ISERROR(I36/I6),"—",I36/I6) -> — | J37: =IF(ISERROR(J36/J6),"—",J36/J6) -> — | K37: =IF(ISERROR(K36/K6),"—",K36/K6) -> — | W37: =IF(ISERROR(W36/W6),"—",W36/W6) -> — | X37: =IF(ISERROR(X36/X6),"—",X36/X6) -> — | Y37: =IF(ISERROR(Y36/Y6),"—",Y36/Y6) -> — | Z37: =IF(ISERROR(Z36/Z6),"—",Z36/Z6) -> — | AA37: =IF(ISERROR(AA36/AA6),"—",AA36/AA6) -> — | AB37: =IF(ISERROR(AB36/AB6),"—",AB36/AB6) -> — | AC37: =IF(ISERROR(AC36/AC6),"—",AC36/AC6) -> — | AD37: =IF(ISERROR(AD36/AD6),"—",AD36/AD6) -> — | ... AK37: =IF(ISERROR(AK36/AK6),"—",AK36/AK6) -> — | AL37: =IF(财务基础数据!AM4=0,"",AI37) | AM37: =IF(财务基础数据!AM4<=1,"",AJ37) | AN37: =IF(财务基础数据!AM4<=2,"",AK37)
B39: 资产处置收益 | I39: =利润表!Y66 -> 0 | J39: =利润表!AC66 -> 0 | K39: =利润表!AG66 -> 0 | L39: =IF(COUNT(AL40:AO40)=4,SUM(AL39:AO39),L40*L6) -> 0 | M39: =IF(COUNT(AP40:AS40)=4,SUM(AP39:AS39),M40*M6) -> 0 | N39: =IF(COUNT(AT40:AW40)=4,SUM(AT39:AW39),N40*N6) -> 0 | O39: =O40*O6 -> 0 | P39: =P40*P6 -> 0 | Q39: =Q40*Q6 -> 0 | R39: =R40*R6 -> 0 | S39: =S40*S6 -> 0 | T39: =T40*T6 -> 0 | U39: =U40*U6 -> 0 | W39: =利润表!V66 -> 0 | X39: =利润表!W66-利润表!V66 -> 0 | Y39: =利润表!X66-利润表!W66 -> 0 | Z39: =利润表!Y66-利润表!X66 -> 0 | AA39: =利润表!Z66 -> 0 | AB39: =利润表!AA66-利润表!Z66 -> 0 | AC39: =利润表!AB66-利润表!AA66 -> 0 | AD39: =利润表!AC66-利润表!AB66 -> 0 | AE39: =利润表!AD66 -> 0 | AF39: =利润表!AE66-利润表!AD66 -> 0 | AG39: =利润表!AF66-利润表!AE66 -> 0 | AH39: =利润表!AG66-利润表!AF66 -> 0 | AI39: =IF(财务基础数据!AM4=0,0,利润表!AH66) -> 0 | AJ39: =IF(财务基础数据!AM4<=1,0,利润表!AI66-利润表!AH66) -> 0 | AK39: =IF(财务基础数据!AM4<=2,0,利润表!AJ66-利润表!AI66) -> 0 | AL39: =IF(ISERROR(AL40*AL6),"—",AL40*AL6) -> — | AM39: =IF(ISERROR(AM40*AM6),"—",AM40*AM6) -> — | AN39: =IF(ISERROR(AN40*AN6),"—",AN40*AN6) -> — | AO39: =IF(ISERROR(AO40*AO6),"—",AO40*AO6) -> 0 | AP39: =IF(ISERROR(AP40*AP6),"—",AP40*AP6) -> 0 | AQ39: =IF(ISERROR(AQ40*AQ6),"—",AQ40*AQ6) -> 0 | AR39: =IF(ISERROR(AR40*AR6),"—",AR40*AR6) -> 0 | AS39: =IF(ISERROR(AS40*AS6),"—",AS40*AS6) -> 0 | ... AW39: =IF(ISERROR(AW40*AW6),"—",AW40*AW6) -> 0
B40: 资产处置收益/营业收入 | I40: =IF(ISERROR(I39/I6),"—",I39/I6) -> — | J40: =IF(ISERROR(J39/J6),"—",J39/J6) -> — | K40: =IF(ISERROR(K39/K6),"—",K39/K6) -> — | W40: =IF(ISERROR(W39/W6),"—",W39/W6) -> — | X40: =IF(ISERROR(X39/X6),"—",X39/X6) -> — | Y40: =IF(ISERROR(Y39/Y6),"—",Y39/Y6) -> — | Z40: =IF(ISERROR(Z39/Z6),"—",Z39/Z6) -> — | AA40: =IF(ISERROR(AA39/AA6),"—",AA39/AA6) -> — | AB40: =IF(ISERROR(AB39/AB6),"—",AB39/AB6) -> — | AC40: =IF(ISERROR(AC39/AC6),"—",AC39/AC6) -> — | AD40: =IF(ISERROR(AD39/AD6),"—",AD39/AD6) -> — | ... AK40: =IF(ISERROR(AK39/AK6),"—",AK39/AK6) -> — | AL40: =IF(财务基础数据!AM4=0,"",AI40) | AM40: =IF(财务基础数据!AM4<=1,"",AJ40) | AN40: =IF(财务基础数据!AM4<=2,"",AK40)
B42: 营业外收入 | I42: =利润表!Y77 -> 0 | J42: =利润表!AC77 -> 0 | K42: =利润表!AG77 -> 0 | W42: =利润表!V77 -> 0 | X42: =利润表!W77-利润表!V77 -> 0 | Y42: =利润表!X77-利润表!W77 -> 0 | Z42: =利润表!Y77-利润表!X77 -> 0 | AA42: =利润表!Z77 -> 0 | AB42: =利润表!AA77-利润表!Z77 -> 0 | AC42: =利润表!AB77-利润表!AA77 -> 0 | AD42: =利润表!AC77-利润表!AB77 -> 0 | AE42: =利润表!AD77 -> 0 | AF42: =利润表!AE77-利润表!AD77 -> 0 | AG42: =利润表!AF77-利润表!AE77 -> 0 | AH42: =利润表!AG77-利润表!AF77 -> 0 | AI42: =IF(财务基础数据!AM4=0,0,利润表!AH77) -> 0 | AJ42: =IF(财务基础数据!AM4<=1,0,利润表!AI77-利润表!AH77) -> 0 | AK42: =IF(财务基础数据!AM4<=2,0,利润表!AJ77-利润表!AI77) -> 0 | AL42: =IF(财务基础数据!AM4=0,"",AI42) | AM42: =IF(财务基础数据!AM4<=1,"",AJ42) | AN42: =IF(财务基础数据!AM4<=2,"",AK42)
B43: 营业外支出 | I43: =利润表!Y79 -> 0 | J43: =利润表!AC79 -> 0 | K43: =利润表!AG79 -> 0 | W43: =利润表!V79 -> 0 | X43: =利润表!W79-利润表!V79 -> 0 | Y43: =利润表!X79-利润表!W79 -> 0 | Z43: =利润表!Y79-利润表!X79 -> 0 | AA43: =利润表!Z79 -> 0 | AB43: =利润表!AA79-利润表!Z79 -> 0 | AC43: =利润表!AB79-利润表!AA79 -> 0 | AD43: =利润表!AC79-利润表!AB79 -> 0 | AE43: =利润表!AD79 -> 0 | AF43: =利润表!AE79-利润表!AD79 -> 0 | AG43: =利润表!AF79-利润表!AE79 -> 0 | AH43: =利润表!AG79-利润表!AF79 -> 0 | AI43: =IF(财务基础数据!AM4=0,0,利润表!AH79) -> 0 | AJ43: =IF(财务基础数据!AM4<=1,0,利润表!AI79-利润表!AH79) -> 0 | AK43: =IF(财务基础数据!AM4<=2,0,利润表!AJ79-利润表!AI79) -> 0 | AL43: =IF(财务基础数据!AM4=0,"",AI43) | AM43: =IF(财务基础数据!AM4<=1,"",AJ43) | AN43: =IF(财务基础数据!AM4<=2,"",AK43)
B44: 营业外收支 | I44: =利润表!Y81 -> 0 | J44: =利润表!AC81 -> 0 | K44: =利润表!AG81 -> 0 | L44: =IF(ISERROR(L42-L43),"—",L42-L43) -> 0 | M44: =M42-M43 -> 0 | N44: =N42-N43 -> 0 | O44: =O42-O43 -> 0 | P44: =P42-P43 -> 0 | Q44: =Q42-Q43 -> 0 | R44: =R42-R43 -> 0 | S44: =S42-S43 -> 0 | T44: =T42-T43 -> 0 | U44: =U42-U43 -> 0 | W44: =利润表!V81 -> 0 | X44: =利润表!W81-利润表!V81 -> 0 | Y44: =利润表!X81-利润表!W81 -> 0 | Z44: =利润表!Y81-利润表!X81 -> 0 | AA44: =利润表!Z81 -> 0 | AB44: =利润表!AA81-利润表!Z81 -> 0 | AC44: =利润表!AB81-利润表!AA81 -> 0 | AD44: =利润表!AC81-利润表!AB81 -> 0 | AE44: =利润表!AD81 -> 0 | AF44: =利润表!AE81-利润表!AD81 -> 0 | AG44: =利润表!AF81-利润表!AE81 -> 0 | AH44: =利润表!AG81-利润表!AF81 -> 0 | AI44: =IF(财务基础数据!AM4=0,0,利润表!AH81) -> 0 | AJ44: =IF(财务基础数据!AM4<=1,0,利润表!AI81-利润表!AH81) -> 0 | AK44: =IF(财务基础数据!AM4<=2,0,利润表!AJ81-利润表!AI81) -> 0 | AL44: =IF(ISERROR(AL42-AL43),"—",AL42-AL43) -> — | AM44: =IF(ISERROR(AM42-AM43),"—",AM42-AM43) -> — | AN44: =IF(ISERROR(AN42-AN43),"—",AN42-AN43) -> — | AO44: =IF(ISERROR(AO42-AO43),"—",AO42-AO43) -> 0 | AP44: =IF(ISERROR(AP42-AP43),"—",AP42-AP43) -> 0 | AQ44: =IF(ISERROR(AQ42-AQ43),"—",AQ42-AQ43) -> 0 | AR44: =IF(ISERROR(AR42-AR43),"—",AR42-AR43) -> 0 | AS44: =IF(ISERROR(AS42-AS43),"—",AS42-AS43) -> 0 | ... AW44: =IF(ISERROR(AW42-AW43),"—",AW42-AW43) -> 0
B45: 其中：与处置资产无关的收支
B47: 所得税费用 | I47: =利润表!Y86 -> 0 | J47: =利润表!AC86 -> 0 | K47: =利润表!AG86 -> 0 | L47: =IF(COUNT(AL47:AO47)=4,SUM(AL47:AO47),利润表!AK84*L48) -> 0 | M47: =IF(COUNT(AP47:AS47)=4,SUM(AP47:AS47),利润表!AL84*M48) -> 0 | N47: =IF(COUNT(AT47:AW47)=4,SUM(AT47:AW47),利润表!AM84*N48) -> 0 | O47: =IF(ISERROR(利润表!AN84*O48),"—",利润表!AN84*O48) -> 0 | P47: =IF(ISERROR(利润表!AO84*P48),"—",利润表!AO84*P48) -> 0 | Q47: =IF(ISERROR(利润表!AP84*Q48),"—",利润表!AP84*Q48) -> 0 | R47: =IF(ISERROR(利润表!AQ84*R48),"—",利润表!AQ84*R48) -> 0 | S47: =IF(ISERROR(利润表!AR84*S48),"—",利润表!AR84*S48) -> 0 | T47: =IF(ISERROR(利润表!AS84*T48),"—",利润表!AS84*T48) -> 0 | U47: =IF(ISERROR(利润表!AT84*U48),"—",利润表!AT84*U48) -> 0 | W47: =利润表!V86 -> 0 | X47: =利润表!W86-利润表!V86 -> 0 | Y47: =利润表!X86-利润表!W86 -> 0 | Z47: =利润表!Y86-利润表!X86 -> 0 | AA47: =利润表!Z86 -> 0 | AB47: =利润表!AA86-利润表!Z86 -> 0 | AC47: =利润表!AB86-利润表!AA86 -> 0 | AD47: =利润表!AC86-利润表!AB86 -> 0 | AE47: =利润表!AD86 -> 0 | AF47: =利润表!AE86-利润表!AD86 -> 0 | AG47: =利润表!AF86-利润表!AE86 -> 0 | AH47: =利润表!AG86-利润表!AF86 -> 0 | AI47: =IF(财务基础数据!AM4=0,0,利润表!AH86) -> 0 | AJ47: =IF(财务基础数据!AM4<=1,0,利润表!AI86-利润表!AH86) -> 0 | AK47: =IF(财务基础数据!AM4<=2,0,利润表!AJ86-利润表!AI86) -> 0 | AL47: =IF(财务基础数据!AM4=0,"",AI47) | AM47: =IF(财务基础数据!AM4<=1,"",AJ47) | AN47: =IF(财务基础数据!AM4<=2,"",AK47)
B48: 所得税税率 | I48: =利润表!Y87 -> — | J48: =利润表!AC87 -> — | K48: =利润表!AG87 -> — | W48: =利润表!V87 -> — | X48: =X47/(利润表!W84-利润表!V84) -> #DIV/0! | Y48: =Y47/(利润表!X84-利润表!W84) -> #DIV/0! | Z48: =Z47/(利润表!Y84-利润表!X84) -> #DIV/0! | AA48: =利润表!Z87 -> — | AB48: =AB47/(利润表!AA84-利润表!Z84) -> #DIV/0! | AC48: =AC47/(利润表!AB84-利润表!AA84) -> #DIV/0! | AD48: =AD47/(利润表!AC84-利润表!AB84) -> #DIV/0! | AE48: =利润表!AD87 -> — | AF48: =AF47/(利润表!AE84-利润表!AD84) -> #DIV/0! | AG48: =AG47/(利润表!AF84-利润表!AE84) -> #DIV/0! | AH48: =AH47/(利润表!AG84-利润表!AF84) -> #DIV/0!
B50: 少数股东损益 | I50: =利润表!Y91 -> 0 | J50: =利润表!AC91 -> 0 | K50: =利润表!AG91 -> 0 | L50: =IF(COUNT(AL50:AO50)=4,SUM(AL50:AO50),L51*利润表!AK88) -> 0 | M50: =IF(COUNT(AP50:AS50)=4,SUM(AP50:AS50),M51*利润表!AL88) -> 0 | N50: =IF(COUNT(AT50:AW50)=4,SUM(AT50:AW50),N51*利润表!AM88) -> 0 | O50: =IF(ISERROR(O51*利润表!AN88),"—",O51*利润表!AN88) -> 0 | P50: =IF(ISERROR(P51*利润表!AO88),"—",P51*利润表!AO88) -> 0 | Q50: =IF(ISERROR(Q51*利润表!AP88),"—",Q51*利润表!AP88) -> 0 | R50: =IF(ISERROR(R51*利润表!AQ88),"—",R51*利润表!AQ88) -> 0 | S50: =IF(ISERROR(S51*利润表!AR88),"—",S51*利润表!AR88) -> 0 | T50: =IF(ISERROR(T51*利润表!AS88),"—",T51*利润表!AS88) -> 0 | U50: =IF(ISERROR(U51*利润表!AT88),"—",U51*利润表!AT88) -> 0 | W50: =利润表!V91 -> 0 | X50: =利润表!W91-利润表!V91 -> 0 | Y50: =利润表!X91-利润表!W91 -> 0 | Z50: =利润表!Y91-利润表!X91 -> 0 | AA50: =利润表!Z91 -> 0 | AB50: =利润表!AA91-利润表!Z91 -> 0 | AC50: =利润表!AB91-利润表!AA91 -> 0 | AD50: =利润表!AC91-利润表!AB91 -> 0 | AE50: =利润表!AD91 -> 0 | AF50: =利润表!AE91-利润表!AD91 -> 0 | AG50: =利润表!AF91-利润表!AE91 -> 0 | AH50: =利润表!AG91-利润表!AF91 -> 0 | AI50: =IF(财务基础数据!AM4=0,0,利润表!AH91) -> 0 | AJ50: =IF(财务基础数据!AM4<=1,0,利润表!AI91-利润表!AH91) -> 0 | AK50: =IF(财务基础数据!AM4<=2,0,利润表!AJ91-利润表!AI91) -> 0 | AL50: =IF(财务基础数据!AM4=0,"",AI50) | AM50: =IF(财务基础数据!AM4<=1,"",AJ50) | AN50: =IF(财务基础数据!AM4<=2,"",AK50)
B51: 少数股东损益/净利润 | I51: =利润表!Y92 -> — | J51: =利润表!AC92 -> — | K51: =利润表!AG92 -> — | W51: =利润表!V92 -> — | X51: =X50/(利润表!W88-利润表!V88) -> #DIV/0! | Y51: =Y50/(利润表!X88-利润表!W88) -> #DIV/0! | Z51: =Z50/(利润表!Y88-利润表!X88) -> #DIV/0! | AA51: =利润表!Z92 -> — | AB51: =AB50/(利润表!AA88-利润表!Z88) -> #DIV/0! | AC51: =AC50/(利润表!AB88-利润表!AA88) -> #DIV/0! | AD51: =AD50/(利润表!AC88-利润表!AB88) -> #DIV/0! | AE51: =利润表!AD92 -> — | AF51: =AF50/(利润表!AE88-利润表!AD88) -> #DIV/0! | AG51: =AG50/(利润表!AF88-利润表!AE88) -> #DIV/0! | AH51: =AH50/(利润表!AG88-利润表!AF88) -> #DIV/0!
B52: 合并产生的损益（直接计入权益）

Sheet 资产预测
B2: 营运资金
B3: ="单位：人民币"&目录!D5 -> 单位：人民币百万元
B4: 会计年度截止日：12/31 | F4: =资产负债表!Y4 -> 2021 | G4: =资产负债表!AC4 -> 2022 | H4: =资产负债表!AG4 -> 2023 | I4: =资产负债表!AH4 -> 1Q24 | J4: =资产负债表!AI4 -> 1H24 | K4: =资产负债表!AJ4 -> 3Q24 | L4: =资产负债表!AK4 -> 2024E | M4: =资产负债表!AL4 -> 2025 | N4: =资产负债表!AM4 -> 2026 | O4: =资产负债表!AN4 -> 2027 | ... U4: =资产负债表!AT4 -> 2033
B5: 营业收入 | F5: =利润表!Y8 -> 0 | G5: =利润表!AC8 -> 0 | H5: =利润表!AG8 -> 0 | I5: =利润表!AH8 -> 0 | J5: =利润表!AI8 -> 0 | K5: =利润表!AJ8 -> 0 | L5: =利润表!AK8 -> 0 | M5: =利润表!AL8 -> 0 | N5: =利润表!AM8 -> 0 | O5: =利润表!AN8 -> 0 | ... U5: =利润表!AT8 -> 0
B6: 营业成本 | F6: =利润表!Y15 -> 0 | G6: =利润表!AC15 -> 0 | H6: =利润表!AG15 -> 0 | I6: =利润表!AH15 -> 0 | J6: =利润表!AI15 -> 0 | K6: =利润表!AJ15 -> 0 | L6: =利润表!AK15 -> 0 | M6: =利润表!AL15 -> 0 | N6: =利润表!AM15 -> 0 | O6: =利润表!AN15 -> 0 | ... U6: =利润表!AT15 -> 0
B8: 流动资产
B9: 以下周转天数指标按照资产/负债科目的期末值计算
B10: 应收票据 | F10: =IF(ISERROR(资产负债表!Y11),0,资产负债表!Y11) -> 0 | G10: =IF(ISERROR(资产负债表!AC11),0,资产负债表!AC11) -> 0 | H10: =IF(ISERROR(资产负债表!AG11),0,资产负债表!AG11) -> 0 | I10: =IF(ISERROR(资产负债表!AH11),0,资产负债表!AH11) -> 0 | J10: =IF(ISERROR(资产负债表!AI11),0,资产负债表!AI11) -> 0 | K10: =IF(ISERROR(资产负债表!AJ11),0,资产负债表!AJ11) -> 0 | L10: =IF(ISERROR(L5/(360/L11)),0,L5/(360/L11)) -> 0 | M10: =IF(ISERROR(M5/(360/M11)),0,M5/(360/M11)) -> 0 | N10: =IF(ISERROR(N5/(360/N11)),0,N5/(360/N11)) -> 0 | O10: =IF(ISERROR(O5/(360/O11)),0,O5/(360/O11)) -> 0 | P10: =IF(ISERROR(P5/(360/P11)),0,P5/(360/P11)) -> 0 | Q10: =IF(ISERROR(Q5/(360/Q11)),0,Q5/(360/Q11)) -> 0 | R10: =IF(ISERROR(R5/(360/R11)),0,R5/(360/R11)) -> 0 | S10: =IF(ISERROR(S5/(360/S11)),0,S5/(360/S11)) -> 0 | ... U10: =IF(ISERROR(U5/(360/U11)),0,U5/(360/U11)) -> 0
C11: 周转天数（相对于营业收入） | F11: =IF(ISERROR(360/(F5/F10)),0,360/(F5/F10)) -> 0 | G11: =IF(ISERROR(360/(G5/G10)),0,360/(G5/G10)) -> 0 | H11: =IF(ISERROR(360/(H5/H10)),0,360/(H5/H10)) -> 0 | I11: =IF(ISERROR(360/(I5/I10)),0,360/(I5/I10)) -> 0 | J11: =IF(ISERROR(360/(J5/J10)),0,360/(J5/J10)) -> 0 | K11: =IF(ISERROR(360/(K5/K10)),0,360/(K5/K10)) -> 0
C12: 应收票据/营业收入（%） | F12: =IF(ISERROR(F10/F5),0,F10/F5) -> 0 | G12: =IF(ISERROR(G10/G5),0,G10/G5) -> 0 | H12: =IF(ISERROR(H10/H5),0,H10/H5) -> 0 | I12: =IF(ISERROR(I10/I5),0,I10/I5) -> 0 | J12: =IF(ISERROR(J10/J5),0,J10/J5) -> 0 | K12: =IF(ISERROR(K10/K5),0,K10/K5) -> 0 | L12: =IF(ISERROR(L10/L5),0,L10/L5) -> 0 | M12: =IF(ISERROR(M10/M5),0,M10/M5) -> 0 | ... U12: =IF(ISERROR(U10/U5),0,U10/U5) -> 0
B14: 应收账款 | F14: =IF(ISERROR(资产负债表!Y12),0,资产负债表!Y12) -> 0 | G14: =IF(ISERROR(资产负债表!AC12),0,资产负债表!AC12) -> 0 | H14: =IF(ISERROR(资产负债表!AG12),0,资产负债表!AG12) -> 0 | I14: =IF(ISERROR(资产负债表!AH12),0,资产负债表!AH12) -> 0 | J14: =IF(ISERROR(资产负债表!AI12),0,资产负债表!AI12) -> 0 | K14: =IF(ISERROR(资产负债表!AJ12),0,资产负债表!AJ12) -> 0 | L14: =IF(ISERROR(L5/(360/L15)),0,L5/(360/L15)) -> 0 | M14: =IF(ISERROR(M5/(360/M15)),0,M5/(360/M15)) -> 0 | N14: =IF(ISERROR(N5/(360/N15)),0,N5/(360/N15)) -> 0 | O14: =IF(ISERROR(O5/(360/O15)),0,O5/(360/O15)) -> 0 | P14: =IF(ISERROR(P5/(360/P15)),0,P5/(360/P15)) -> 0 | Q14: =IF(ISERROR(Q5/(360/Q15)),0,Q5/(360/Q15)) -> 0 | R14: =IF(ISERROR(R5/(360/R15)),0,R5/(360/R15)) -> 0 | S14: =IF(ISERROR(S5/(360/S15)),0,S5/(360/S15)) -> 0 | ... U14: =IF(ISERROR(U5/(360/U15)),0,U5/(360/U15)) -> 0
C15: 周转天数（相对于营业收入） | F15: =IF(ISERROR(360/(F5/F14)),0,360/(F5/F14)) -> 0 | G15: =IF(ISERROR(360/(G5/G14)),0,360/(G5/G14)) -> 0 | H15: =IF(ISERROR(360/(H5/H14)),0,360/(H5/H14)) -> 0 | I15: =IF(ISERROR(360/(I5/I14)),0,360/(I5/I14)) -> 0 | J15: =IF(ISERROR(360/(J5/J14)),0,360/(J5/J14)) -> 0 | K15: =IF(ISERROR(360/(K5/K14)),0,360/(K5/K14)) -> 0
C16: 应收账款/营业收入（%） | F16: =IF(ISERROR(F14/F5),0,F14/F5) -> 0 | G16: =IF(ISERROR(G14/G5),0,G14/G5) -> 0 | H16: =IF(ISERROR(H14/H5),0,H14/H5) -> 0 | I16: =IF(ISERROR(I14/I5),0,I14/I5) -> 0 | J16: =IF(ISERROR(J14/J5),0,J14/J5) -> 0 | K16: =IF(ISERROR(K14/K5),0,K14/K5) -> 0 | L16: =IF(ISERROR(L14/L5),0,L14/L5) -> 0 | M16: =IF(ISERROR(M14/M5),0,M14/M5) -> 0 | ... U16: =IF(ISERROR(U14/U5),0,U14/U5) -> 0
B18: 应收款项融资 | F18: =IF(ISERROR(资产负债表!Y13),0,资产负债表!Y13) -> 0 | G18: =IF(ISERROR(资产负债表!AC13),0,资产负债表!AC13) -> 0 | H18: =IF(ISERROR(资产负债表!AG13),0,资产负债表!AG13) -> 0 | I18: =IF(ISERROR(资产负债表!AH13),0,资产负债表!AH13) -> 0 | J18: =IF(ISERROR(资产负债表!AI13),0,资产负债表!AI13) -> 0 | K18: =IF(ISERROR(资产负债表!AJ13),0,资产负债表!AJ13) -> 0 | L18: =IF(ISERROR(L5*L19),0,L5*L19) -> 0 | M18: =IF(ISERROR(M5*M19),0,M5*M19) -> 0 | N18: =IF(ISERROR(N5*N19),0,N5*N19) -> 0 | O18: =IF(ISERROR(O5*O19),0,O5*O19) -> 0 | P18: =IF(ISERROR(P5*P19),0,P5*P19) -> 0 | Q18: =IF(ISERROR(Q5*Q19),0,Q5*Q19) -> 0 | R18: =IF(ISERROR(R5*R19),0,R5*R19) -> 0 | S18: =IF(ISERROR(S5*S19),0,S5*S19) -> 0 | ... U18: =IF(ISERROR(U5*U19),0,U5*U19) -> 0
C19: 比营业收入（%） | F19: =IF(ISERROR(F18/F5),0,F18/F5) -> 0 | G19: =IF(ISERROR(G18/G5),0,G18/G5) -> 0 | H19: =IF(ISERROR(H18/H5),0,H18/H5) -> 0 | I19: =IF(ISERROR(I18/I5),0,I18/I5) -> 0 | J19: =IF(ISERROR(J18/J5),0,J18/J5) -> 0 | K19: =IF(ISERROR(K18/K5),0,K18/K5) -> 0
B21: 预付账款 | F21: =资产负债表!Y14 -> 0 | G21: =资产负债表!AC14 -> 0 | H21: =资产负债表!AG14 -> 0 | I21: =资产负债表!AH14 -> 0 | J21: =资产负债表!AI14 -> 0 | K21: =资产负债表!AJ14 -> 0 | L21: =IF(ISERROR(L6*L22),0,L6*L22) -> 0 | M21: =IF(ISERROR(M6*M22),0,M6*M22) -> 0 | N21: =IF(ISERROR(N6*N22),0,N6*N22) -> 0 | O21: =IF(ISERROR(O6*O22),0,O6*O22) -> 0 | P21: =IF(ISERROR(P6*P22),0,P6*P22) -> 0 | Q21: =IF(ISERROR(Q6*Q22),0,Q6*Q22) -> 0 | R21: =IF(ISERROR(R6*R22),0,R6*R22) -> 0 | S21: =IF(ISERROR(S6*S22),0,S6*S22) -> 0 | ... U21: =IF(ISERROR(U6*U22),0,U6*U22) -> 0
C22: 比营业成本（%） | F22: =IF(ISERROR(F21/F6),0,F21/F6) -> 0 | G22: =IF(ISERROR(G21/G6),0,G21/G6) -> 0 | H22: =IF(ISERROR(H21/H6),0,H21/H6) -> 0 | I22: =IF(ISERROR(I21/I6),0,I21/I6) -> 0 | J22: =IF(ISERROR(J21/J6),0,J21/J6) -> 0 | K22: =IF(ISERROR(K21/K6),0,K21/K6) -> 0
B24: 其他应收款 | F24: =资产负债表!Y15 -> 0 | G24: =资产负债表!AC15 -> 0 | H24: =资产负债表!AG15 -> 0 | I24: =资产负债表!AH15 -> 0 | J24: =资产负债表!AI15 -> 0 | K24: =资产负债表!AJ15 -> 0 | L24: =IF(ISERROR(L5/(360/L25)),0,L5/(360/L25)) -> 0 | M24: =IF(ISERROR(M5/(360/M25)),0,M5/(360/M25)) -> 0 | N24: =IF(ISERROR(N5/(360/N25)),0,N5/(360/N25)) -> 0 | O24: =IF(ISERROR(O5/(360/O25)),0,O5/(360/O25)) -> 0 | P24: =IF(ISERROR(P5/(360/P25)),0,P5/(360/P25)) -> 0 | Q24: =IF(ISERROR(Q5/(360/Q25)),0,Q5/(360/Q25)) -> 0 | R24: =IF(ISERROR(R5/(360/R25)),0,R5/(360/R25)) -> 0 | S24: =IF(ISERROR(S5/(360/S25)),0,S5/(360/S25)) -> 0 | ... U24: =IF(ISERROR(U5/(360/U25)),0,U5/(360/U25)) -> 0
C25: 周转天数（相对于营业收入） | F25: =IF(ISERROR(360/(F5/F24)),0,360/(F5/F24)) -> 0 | G25: =IF(ISERROR(360/(G5/G24)),0,360/(G5/G24)) -> 0 | H25: =IF(ISERROR(360/(H5/H24)),0,360/(H5/H24)) -> 0 | I25: =IF(ISERROR(360/(I5/I24)),0,360/(I5/I24)) -> 0 | J25: =IF(ISERROR(360/(J5/J24)),0,360/(J5/J24)) -> 0 | K25: =IF(ISERROR(360/(K5/K24)),0,360/(K5/K24)) -> 0
C26: 其他应收款/营业收入（%） | F26: =IF(ISERROR(F24/F5),0,F24/F5) -> 0 | G26: =IF(ISERROR(G24/G5),0,G24/G5) -> 0 | H26: =IF(ISERROR(H24/H5),0,H24/H5) -> 0 | I26: =IF(ISERROR(I24/I5),0,I24/I5) -> 0 | J26: =IF(ISERROR(J24/J5),0,J24/J5) -> 0 | K26: =IF(ISERROR(K24/K5),0,K24/K5) -> 0 | L26: =IF(ISERROR(L24/L5),0,L24/L5) -> 0 | M26: =IF(ISERROR(M24/M5),0,M24/M5) -> 0 | ... U26: =IF(ISERROR(U24/U5),0,U24/U5) -> 0
B28: 存货 | F28: =资产负债表!Y16 -> 0 | G28: =资产负债表!AC16 -> 0 | H28: =资产负债表!AG16 -> 0 | I28: =资产负债表!AH16 -> 0 | J28: =资产负债表!AI16 -> 0 | K28: =资产负债表!AJ16 -> 0 | L28: =IF(ISERROR(L6/(360/L29)),0,L6/(360/L29)) -> 0 | M28: =IF(ISERROR(M6/(360/M29)),0,M6/(360/M29)) -> 0 | N28: =IF(ISERROR(N6/(360/N29)),0,N6/(360/N29)) -> 0 | O28: =IF(ISERROR(O6/(360/O29)),0,O6/(360/O29)) -> 0 | P28: =IF(ISERROR(P6/(360/P29)),0,P6/(360/P29)) -> 0 | Q28: =IF(ISERROR(Q6/(360/Q29)),0,Q6/(360/Q29)) -> 0 | R28: =IF(ISERROR(R6/(360/R29)),0,R6/(360/R29)) -> 0 | S28: =IF(ISERROR(S6/(360/S29)),0,S6/(360/S29)) -> 0 | ... U28: =IF(ISERROR(U6/(360/U29)),0,U6/(360/U29)) -> 0
C29: 周转天数（相对于营业成本） | F29: =IF(ISERROR(360/(F6/F28)),0,360/(F6/F28)) -> 0 | G29: =IF(ISERROR(360/(G6/G28)),0,360/(G6/G28)) -> 0 | H29: =IF(ISERROR(360/(H6/H28)),0,360/(H6/H28)) -> 0 | I29: =IF(ISERROR(360/(I6/I28)),0,360/(I6/I28)) -> 0 | J29: =IF(ISERROR(360/(J6/J28)),0,360/(J6/J28)) -> 0 | K29: =IF(ISERROR(360/(K6/K28)),0,360/(K6/K28)) -> 0
C30: 存货/营业成本（%） | F30: =IF(ISERROR(F28/F6),0,F28/F6) -> 0 | G30: =IF(ISERROR(G28/G6),0,G28/G6) -> 0 | H30: =IF(ISERROR(H28/H6),0,H28/H6) -> 0 | I30: =IF(ISERROR(I28/I6),0,I28/I6) -> 0 | J30: =IF(ISERROR(J28/J6),0,J28/J6) -> 0 | K30: =IF(ISERROR(K28/K6),0,K28/K6) -> 0 | L30: =IF(ISERROR(L28/L6),0,L28/L6) -> 0 | M30: =IF(ISERROR(M28/M6),0,M28/M6) -> 0 | ... U30: =IF(ISERROR(U28/U6),0,U28/U6) -> 0
B32: 合同资产 | F32: =资产负债表!Y17 -> 0 | G32: =资产负债表!AC17 -> 0 | H32: =资产负债表!AG17 -> 0 | I32: =资产负债表!AH17 -> 0 | J32: =资产负债表!AI17 -> 0 | K32: =资产负债表!AJ17 -> 0 | L32: =IF(ISERROR(L5*L33),0,L5*L33) -> 0 | M32: =IF(ISERROR(M5*M33),0,M5*M33) -> 0 | N32: =IF(ISERROR(N5*N33),0,N5*N33) -> 0 | O32: =IF(ISERROR(O5*O33),0,O5*O33) -> 0 | P32: =IF(ISERROR(P5*P33),0,P5*P33) -> 0 | Q32: =IF(ISERROR(Q5*Q33),0,Q5*Q33) -> 0 | R32: =IF(ISERROR(R5*R33),0,R5*R33) -> 0 | S32: =IF(ISERROR(S5*S33),0,S5*S33) -> 0 | ... U32: =IF(ISERROR(U5*U33),0,U5*U33) -> 0
C33: 比营业收入（%） | F33: =IF(ISERROR(F32/F5),0,F32/F5) -> 0 | G33: =IF(ISERROR(G32/G5),0,G32/G5) -> 0 | H33: =IF(ISERROR(H32/H5),0,H32/H5) -> 0 | I33: =IF(ISERROR(I32/I5),0,I32/I5) -> 0 | J33: =IF(ISERROR(J32/J5),0,J32/J5) -> 0 | K33: =IF(ISERROR(K32/K5),0,K32/K5) -> 0
B37: 流动负债
B38: 应付票据 | F38: =资产负债表!Y52 -> 0 | G38: =资产负债表!AC52 -> 0 | H38: =资产负债表!AG52 -> 0 | I38: =资产负债表!AH52 -> 0 | J38: =资产负债表!AI52 -> 0 | K38: =资产负债表!AJ52 -> 0 | L38: =IF(ISERROR(L6/(360/L39)),0,L6/(360/L39)) -> 0 | M38: =IF(ISERROR(M6/(360/M39)),0,M6/(360/M39)) -> 0 | N38: =IF(ISERROR(N6/(360/N39)),0,N6/(360/N39)) -> 0 | O38: =IF(ISERROR(O6/(360/O39)),0,O6/(360/O39)) -> 0 | P38: =IF(ISERROR(P6/(360/P39)),0,P6/(360/P39)) -> 0 | Q38: =IF(ISERROR(Q6/(360/Q39)),0,Q6/(360/Q39)) -> 0 | R38: =IF(ISERROR(R6/(360/R39)),0,R6/(360/R39)) -> 0 | S38: =IF(ISERROR(S6/(360/S39)),0,S6/(360/S39)) -> 0 | ... U38: =IF(ISERROR(U6/(360/U39)),0,U6/(360/U39)) -> 0
C39: 周转天数（相对于营业成本） | F39: =IF(ISERROR(360/(F6/F38)),0,360/(F6/F38)) -> 0 | G39: =IF(ISERROR(360/(G6/G38)),0,360/(G6/G38)) -> 0 | H39: =IF(ISERROR(360/(H6/H38)),0,360/(H6/H38)) -> 0 | I39: =IF(ISERROR(360/(I6/I38)),0,360/(I6/I38)) -> 0 | J39: =IF(ISERROR(360/(J6/J38)),0,360/(J6/J38)) -> 0 | K39: =IF(ISERROR(360/(K6/K38)),0,360/(K6/K38)) -> 0
C40: 应付票据/营业成本（%） | F40: =IF(ISERROR(F38/F6),0,F38/F6) -> 0 | G40: =IF(ISERROR(G38/G6),0,G38/G6) -> 0 | H40: =IF(ISERROR(H38/H6),0,H38/H6) -> 0 | I40: =IF(ISERROR(I38/I6),0,I38/I6) -> 0 | J40: =IF(ISERROR(J38/J6),0,J38/J6) -> 0 | K40: =IF(ISERROR(K38/K6),0,K38/K6) -> 0 | L40: =IF(ISERROR(L38/L6),0,L38/L6) -> 0 | M40: =IF(ISERROR(M38/M6),0,M38/M6) -> 0 | ... U40: =IF(ISERROR(U38/U6),0,U38/U6) -> 0
B42: 应付账款 | F42: =资产负债表!Y53 -> 0 | G42: =资产负债表!AC53 -> 0 | H42: =资产负债表!AG53 -> 0 | I42: =资产负债表!AH53 -> 0 | J42: =资产负债表!AI53 -> 0 | K42: =资产负债表!AJ53 -> 0 | L42: =IF(ISERROR(L6/(360/L43)),0,L6/(360/L43)) -> 0 | M42: =IF(ISERROR(M6/(360/M43)),0,M6/(360/M43)) -> 0 | N42: =IF(ISERROR(N6/(360/N43)),0,N6/(360/N43)) -> 0 | O42: =IF(ISERROR(O6/(360/O43)),0,O6/(360/O43)) -> 0 | P42: =IF(ISERROR(P6/(360/P43)),0,P6/(360/P43)) -> 0 | Q42: =IF(ISERROR(Q6/(360/Q43)),0,Q6/(360/Q43)) -> 0 | R42: =IF(ISERROR(R6/(360/R43)),0,R6/(360/R43)) -> 0 | S42: =IF(ISERROR(S6/(360/S43)),0,S6/(360/S43)) -> 0 | ... U42: =IF(ISERROR(U6/(360/U43)),0,U6/(360/U43)) -> 0
C43: 周转天数（相对于营业成本） | F43: =IF(ISERROR(360/(F6/F42)),0,360/(F6/F42)) -> 0 | G43: =IF(ISERROR(360/(G6/G42)),0,360/(G6/G42)) -> 0 | H43: =IF(ISERROR(360/(H6/H42)),0,360/(H6/H42)) -> 0 | I43: =IF(ISERROR(360/(I6/I42)),0,360/(I6/I42)) -> 0 | J43: =IF(ISERROR(360/(J6/J42)),0,360/(J6/J42)) -> 0 | K43: =IF(ISERROR(360/(K6/K42)),0,360/(K6/K42)) -> 0
C44: 应付账款/营业成本（%） | F44: =IF(ISERROR(F42/F6),0,F42/F6) -> 0 | G44: =IF(ISERROR(G42/G6),0,G42/G6) -> 0 | H44: =IF(ISERROR(H42/H6),0,H42/H6) -> 0 | I44: =IF(ISERROR(I42/I6),0,I42/I6) -> 0 | J44: =IF(ISERROR(J42/J6),0,J42/J6) -> 0 | K44: =IF(ISERROR(K42/K6),0,K42/K6) -> 0 | L44: =IF(ISERROR(L42/L6),0,L42/L6) -> 0 | M44: =IF(ISERROR(M42/M6),0,M42/M6) -> 0 | ... U44: =IF(ISERROR(U42/U6),0,U42/U6) -> 0
B46: 预收账款 | F46: =资产负债表!Y54 -> 0 | G46: =资产负债表!AC54 -> 0 | H46: =资产负债表!AG54 -> 0 | I46: =资产负债表!AH54 -> 0 | J46: =资产负债表!AI54 -> 0 | K46: =资产负债表!AJ54 -> 0 | L46: =IF(ISERROR(L5*L47),0,L5*L47) -> 0 | M46: =IF(ISERROR(M5*M47),0,M5*M47) -> 0 | N46: =IF(ISERROR(N5*N47),0,N5*N47) -> 0 | O46: =IF(ISERROR(O5*O47),0,O5*O47) -> 0 | P46: =IF(ISERROR(P5*P47),0,P5*P47) -> 0 | Q46: =IF(ISERROR(Q5*Q47),0,Q5*Q47) -> 0 | R46: =IF(ISERROR(R5*R47),0,R5*R47) -> 0 | S46: =IF(ISERROR(S5*S47),0,S5*S47) -> 0 | ... U46: =IF(ISERROR(U5*U47),0,U5*U47) -> 0
C47: 比营业收入（%） | F47: =IF(ISERROR(F46/F5),0,F46/F5) -> 0 | G47: =IF(ISERROR(G46/G5),0,G46/G5) -> 0 | H47: =IF(ISERROR(H46/H5),0,H46/H5) -> 0 | I47: =IF(ISERROR(I46/I5),0,I46/I5) -> 0 | J47: =IF(ISERROR(J46/J5),0,J46/J5) -> 0 | K47: =IF(ISERROR(K46/K5),0,K46/K5) -> 0
B49: 合同负债 | F49: =资产负债表!Y55 -> 0 | G49: =资产负债表!AC55 -> 0 | H49: =资产负债表!AG55 -> 0 | I49: =资产负债表!AH55 -> 0 | J49: =资产负债表!AI55 -> 0 | K49: =资产负债表!AJ55 -> 0 | L49: =IF(ISERROR(L5*L50),0,L5*L50) -> 0 | M49: =IF(ISERROR(M5*M50),0,M5*M50) -> 0 | N49: =IF(ISERROR(N5*N50),0,N5*N50) -> 0 | O49: =IF(ISERROR(O5*O50),0,O5*O50) -> 0 | P49: =IF(ISERROR(P5*P50),0,P5*P50) -> 0 | Q49: =IF(ISERROR(Q5*Q50),0,Q5*Q50) -> 0 | R49: =IF(ISERROR(R5*R50),0,R5*R50) -> 0 | S49: =IF(ISERROR(S5*S50),0,S5*S50) -> 0 | ... U49: =IF(ISERROR(U5*U50),0,U5*U50) -> 0
C50: 比营业收入（%） | F50: =IF(ISERROR(F49/F5),0,F49/F5) -> 0 | G50: =IF(ISERROR(G49/G5),0,G49/G5) -> 0 | H50: =IF(ISERROR(H49/H5),0,H49/H5) -> 0 | I50: =IF(ISERROR(I49/I5),0,I49/I5) -> 0 | J50: =IF(ISERROR(J49/J5),0,J49/J5) -> 0 | K50: =IF(ISERROR(K49/K5),0,K49/K5) -> 0
B52: 应付职工薪酬 | F52: =资产负债表!Y56 -> 0 | G52: =资产负债表!AC56 -> 0 | H52: =资产负债表!AG56 -> 0 | I52: =资产负债表!AH56 -> 0 | J52: =资产负债表!AI56 -> 0 | K52: =资产负债表!AJ56 -> 0 | L52: =IF(ISERROR(L53*L6),0,L53*L6) -> 0 | M52: =IF(ISERROR(M53*M6),0,M53*M6) -> 0 | N52: =IF(ISERROR(N53*N6),0,N53*N6) -> 0 | O52: =IF(ISERROR(O53*O6),0,O53*O6) -> 0 | P52: =IF(ISERROR(P53*P6),0,P53*P6) -> 0 | Q52: =IF(ISERROR(Q53*Q6),0,Q53*Q6) -> 0 | R52: =IF(ISERROR(R53*R6),0,R53*R6) -> 0 | S52: =IF(ISERROR(S53*S6),0,S53*S6) -> 0 | ... U52: =IF(ISERROR(U53*U6),0,U53*U6) -> 0
C53: 比营业成本（%） | F53: =IF(ISERROR(F52/F6),0,F52/F6) -> 0 | G53: =IF(ISERROR(G52/G6),0,G52/G6) -> 0 | H53: =IF(ISERROR(H52/H6),0,H52/H6) -> 0 | I53: =IF(ISERROR(I52/I6),0,I52/I6) -> 0 | J53: =IF(ISERROR(J52/J6),0,J52/J6) -> 0 | K53: =IF(ISERROR(K52/K6),0,K52/K6) -> 0
B55: 应交税费 | F55: =资产负债表!Y57 -> 0 | G55: =资产负债表!AC57 -> 0 | H55: =资产负债表!AG57 -> 0 | I55: =资产负债表!AH57 -> 0 | J55: =资产负债表!AI57 -> 0 | K55: =资产负债表!AJ57 -> 0 | L55: =IF(ISERROR(L56*L5),0,L56*L5) -> 0 | M55: =IF(ISERROR(M56*M5),0,M56*M5) -> 0 | N55: =IF(ISERROR(N56*N5),0,N56*N5) -> 0 | O55: =IF(ISERROR(O56*O5),0,O56*O5) -> 0 | P55: =IF(ISERROR(P56*P5),0,P56*P5) -> 0 | Q55: =IF(ISERROR(Q56*Q5),0,Q56*Q5) -> 0 | R55: =IF(ISERROR(R56*R5),0,R56*R5) -> 0 | S55: =IF(ISERROR(S56*S5),0,S56*S5) -> 0 | ... U55: =IF(ISERROR(U56*U5),0,U56*U5) -> 0
C56: 比营业收入（%） | F56: =IF(ISERROR(F55/F5),0,F55/F5) -> 0 | G56: =IF(ISERROR(G55/G5),0,G55/G5) -> 0 | H56: =IF(ISERROR(H55/H5),0,H55/H5) -> 0 | I56: =IF(ISERROR(I55/I5),0,I55/I5) -> 0 | J56: =IF(ISERROR(J55/J5),0,J55/J5) -> 0 | K56: =IF(ISERROR(K55/K5),0,K55/K5) -> 0
B58: 其他应付款 | F58: =资产负债表!Y58 -> 0 | G58: =资产负债表!AC58 -> 0 | H58: =资产负债表!AG58 -> 0 | I58: =资产负债表!AH58 -> 0 | J58: =资产负债表!AI58 -> 0 | K58: =资产负债表!AJ58 -> 0 | L58: =IF(ISERROR(L59*L6),0,L59*L6) -> 0 | M58: =IF(ISERROR(M59*M6),0,M59*M6) -> 0 | N58: =IF(ISERROR(N59*N6),0,N59*N6) -> 0 | O58: =IF(ISERROR(O59*O6),0,O59*O6) -> 0 | P58: =IF(ISERROR(P59*P6),0,P59*P6) -> 0 | Q58: =IF(ISERROR(Q59*Q6),0,Q59*Q6) -> 0 | R58: =IF(ISERROR(R59*R6),0,R59*R6) -> 0 | S58: =IF(ISERROR(S59*S6),0,S59*S6) -> 0 | ... U58: =IF(ISERROR(U59*U6),0,U59*U6) -> 0
C59: 营业成本（%） | F59: =IF(ISERROR(F58/F6),0,F58/F6) -> 0 | G59: =IF(ISERROR(G58/G6),0,G58/G6) -> 0 | H59: =IF(ISERROR(H58/H6),0,H58/H6) -> 0 | I59: =IF(ISERROR(I58/I6),0,I58/I6) -> 0 | J59: =IF(ISERROR(J58/J6),0,J58/J6) -> 0 | K59: =IF(ISERROR(K58/K6),0,K58/K6) -> 0
B66: 投资预测
B67: ="单位：人民币"&目录!D5 -> 单位：人民币百万元
B68: 会计年度截止日：12/31 | F68: =F4 -> 2021 | G68: =G4 -> 2022 | H68: =H4 -> 2023 | I68: =I4 -> 1Q24 | J68: =J4 -> 1H24 | K68: =K4 -> 3Q24 | L68: =L4 -> 2024E | M68: =M4 -> 2025 | ... U68: =U4 -> 2033
B70: (一)流动金融资产/负债
B71: 交易性金融资产 | F71: =资产负债表!Y9 -> 0 | G71: =资产负债表!AC9 -> 0 | H71: =资产负债表!AG9 -> 0 | I71: =资产负债表!AH9 -> 0 | J71: =资产负债表!AI9 -> 0 | K71: =资产负债表!AJ9 -> 0 | L71: =IF(ISERROR(H71+L73+L72),0,H71+L73+L72) -> 0 | M71: =IF(ISERROR(L71+M73+M72),0,L71+M73+M72) -> 0 | N71: =IF(ISERROR(M71+N73+N72),0,M71+N73+N72) -> 0 | O71: =IF(ISERROR(N71+O73+O72),0,N71+O73+O72) -> 0 | P71: =IF(ISERROR(O71+P73+P72),0,O71+P73+P72) -> 0 | Q71: =IF(ISERROR(P71+Q73+Q72),0,P71+Q73+Q72) -> 0 | R71: =IF(ISERROR(Q71+R73+R72),0,Q71+R73+R72) -> 0 | S71: =IF(ISERROR(R71+S73+S72),0,R71+S73+S72) -> 0 | T71: =IF(ISERROR(S71+T73+T72),0,S71+T73+T72) -> 0 | U71: =IF(ISERROR(T71+U73+U72),0,T71+U73+U72) -> 0
A72: 1#1 | C72: 新增、处置 | F72: =F71-资产负债表!U9 -> 0 | G72: =G71-F71 -> 0 | H72: =H71-G71 -> 0 | I72: =IF(财务基础数据!AM4=0,0,I71-H71) -> 0 | J72: =IF(财务基础数据!AM4<=1,0,J71-I71) -> 0 | K72: =IF(财务基础数据!AM4<=2,0,K71-J71) -> 0
A73: 1#1 | C73: 公允价值变动
B75: 衍生金融资产 | F75: =资产负债表!Y10 -> 0 | G75: =资产负债表!AC10 -> 0 | H75: =资产负债表!AG10 -> 0 | I75: =资产负债表!AH10 -> 0 | J75: =资产负债表!AI10 -> 0 | K75: =资产负债表!AJ10 -> 0 | L75: =IF(ISERROR(H75+L77+L76),0,H75+L77+L76) -> 0 | M75: =IF(ISERROR(L75+M77+M76),0,L75+M77+M76) -> 0 | N75: =IF(ISERROR(M75+N77+N76),0,M75+N77+N76) -> 0 | O75: =IF(ISERROR(N75+O77+O76),0,N75+O77+O76) -> 0 | P75: =IF(ISERROR(O75+P77+P76),0,O75+P77+P76) -> 0 | Q75: =IF(ISERROR(P75+Q77+Q76),0,P75+Q77+Q76) -> 0 | R75: =IF(ISERROR(Q75+R77+R76),0,Q75+R77+R76) -> 0 | S75: =IF(ISERROR(R75+S77+S76),0,R75+S77+S76) -> 0 | T75: =IF(ISERROR(S75+T77+T76),0,S75+T77+T76) -> 0 | U75: =IF(ISERROR(T75+U77+U76),0,T75+U77+U76) -> 0
A76: 1#1 | C76: 新增、处置 | F76: =F75-资产负债表!U10 -> 0 | G76: =G75-F75 -> 0 | H76: =H75-G75 -> 0 | I76: =IF(财务基础数据!AM4=0,0,I75-H75) -> 0 | J76: =IF(财务基础数据!AM4<=1,0,J75-I75) -> 0 | K76: =IF(财务基础数据!AM4<=2,0,K75-J75) -> 0
A77: 1#1 | C77: 公允价值变动
B79: 其他流动资产 | F79: =资产负债表!Y20 -> 0 | G79: =资产负债表!AC20 -> 0 | H79: =资产负债表!AG20 -> 0 | I79: =资产负债表!AH20 -> 0 | J79: =资产负债表!AI20 -> 0 | K79: =资产负债表!AJ20 -> 0 | L79: =IF(ISERROR(H79+L80),0,H79+L80) -> 0 | M79: =IF(ISERROR(L79+M80),0,L79+M80) -> 0 | N79: =IF(ISERROR(M79+N80),0,M79+N80) -> 0 | O79: =IF(ISERROR(N79+O80),0,N79+O80) -> 0 | P79: =IF(ISERROR(O79+P80),0,O79+P80) -> 0 | Q79: =IF(ISERROR(P79+Q80),0,P79+Q80) -> 0 | R79: =IF(ISERROR(Q79+R80),0,Q79+R80) -> 0 | S79: =IF(ISERROR(R79+S80),0,R79+S80) -> 0 | T79: =IF(ISERROR(S79+T80),0,S79+T80) -> 0 | U79: =IF(ISERROR(T79+U80),0,T79+U80) -> 0
A80: 1#1 | C80: 本期增减 | F80: =F79-资产负债表!U20 -> 0 | G80: =G79-F79 -> 0 | H80: =H79-G79 -> 0 | I80: =IF(财务基础数据!AM4=0,0,I79-H79) -> 0 | J80: =IF(财务基础数据!AM4<=1,0,J79-I79) -> 0 | K80: =IF(财务基础数据!AM4<=2,0,K79-J79) -> 0
A81: 1#1 | C81: 其中：理财产品
B83: 交易性金融负债 | F83: =资产负债表!Y50 -> 0 | G83: =资产负债表!AC50 -> 0 | H83: =资产负债表!AG50 -> 0 | I83: =资产负债表!AH50 -> 0 | J83: =资产负债表!AI50 -> 0 | K83: =资产负债表!AJ50 -> 0 | L83: =IF(ISERROR(H83+L84+L85),0,H83+L84+L85) -> 0 | M83: =IF(ISERROR(L83+M84+M85),0,L83+M84+M85) -> 0 | N83: =IF(ISERROR(M83+N84+N85),0,M83+N84+N85) -> 0 | O83: =IF(ISERROR(N83+O84+O85),0,N83+O84+O85) -> 0 | P83: =IF(ISERROR(O83+P84+P85),0,O83+P84+P85) -> 0 | Q83: =IF(ISERROR(P83+Q84+Q85),0,P83+Q84+Q85) -> 0 | R83: =IF(ISERROR(Q83+R84+R85),0,Q83+R84+R85) -> 0 | S83: =IF(ISERROR(R83+S84+S85),0,R83+S84+S85) -> 0 | T83: =IF(ISERROR(S83+T84+T85),0,S83+T84+T85) -> 0 | U83: =IF(ISERROR(T83+U84+U85),0,T83+U84+U85) -> 0
A84: 1#1 | C84: 新增、处置 | F84: =F83-资产负债表!U50 -> 0 | G84: =G83-F83 -> 0 | H84: =H83-G83 -> 0 | I84: =IF(财务基础数据!AM4=0,0,I83-H83) -> 0 | J84: =IF(财务基础数据!AM4<=1,0,J83-I83) -> 0 | K84: =IF(财务基础数据!AM4<=2,0,K83-J83) -> 0
A85: 1#1 | C85: 公允价值变动
B87: 衍生金融负债 | F87: =资产负债表!Y51 -> 0 | G87: =资产负债表!AC51 -> 0 | H87: =资产负债表!AG51 -> 0 | I87: =资产负债表!AH51 -> 0 | J87: =资产负债表!AI51 -> 0 | K87: =资产负债表!AJ51 -> 0 | L87: =IF(ISERROR(H87+L88+L89),0,H87+L88+L89) -> 0 | M87: =IF(ISERROR(L87+M88+M89),0,L87+M88+M89) -> 0 | N87: =IF(ISERROR(M87+N88+N89),0,M87+N88+N89) -> 0 | O87: =IF(ISERROR(N87+O88+O89),0,N87+O88+O89) -> 0 | P87: =IF(ISERROR(O87+P88+P89),0,O87+P88+P89) -> 0 | Q87: =IF(ISERROR(P87+Q88+Q89),0,P87+Q88+Q89) -> 0 | R87: =IF(ISERROR(Q87+R88+R89),0,Q87+R88+R89) -> 0 | S87: =IF(ISERROR(R87+S88+S89),0,R87+S88+S89) -> 0 | T87: =IF(ISERROR(S87+T88+T89),0,S87+T88+T89) -> 0 | U87: =IF(ISERROR(T87+U88+U89),0,T87+U88+U89) -> 0
A88: 1#1 | C88: 新增、处置 | F88: =F87-资产负债表!U51 -> 0 | G88: =G87-F87 -> 0 | H88: =H87-G87 -> 0 | I88: =IF(财务基础数据!AM4=0,0,I87-H87) -> 0 | J88: =IF(财务基础数据!AM4<=1,0,J87-I87) -> 0 | K88: =IF(财务基础数据!AM4<=2,0,K87-J87) -> 0
A89: 1#1 | C89: 公允价值变动
B91: 其他流动负债 | F91: =资产负债表!Y61 -> 0 | G91: =资产负债表!AC61 -> 0 | H91: =资产负债表!AG61 -> 0 | I91: =资产负债表!AH61 -> 0 | J91: =资产负债表!AI61 -> 0 | K91: =资产负债表!AJ61 -> 0 | L91: =IF(ISERROR(H91+L92),0,H91+L92) -> 0 | M91: =IF(ISERROR(L91+M92),0,L91+M92) -> 0 | N91: =IF(ISERROR(M91+N92),0,M91+N92) -> 0 | O91: =IF(ISERROR(N91+O92),0,N91+O92) -> 0 | P91: =IF(ISERROR(O91+P92),0,O91+P92) -> 0 | Q91: =IF(ISERROR(P91+Q92),0,P91+Q92) -> 0 | R91: =IF(ISERROR(Q91+R92),0,Q91+R92) -> 0 | S91: =IF(ISERROR(R91+S92),0,R91+S92) -> 0 | T91: =IF(ISERROR(S91+T92),0,S91+T92) -> 0 | U91: =IF(ISERROR(T91+U92),0,T91+U92) -> 0
A92: 1#1 | C92: 本期增减 | F92: =F91-资产负债表!U61 -> 0 | G92: =G91-F91 -> 0 | H92: =H91-G91 -> 0 | I92: =IF(财务基础数据!AM4=0,0,I91-H91) -> 0 | J92: =IF(财务基础数据!AM4<=1,0,J91-I91) -> 0 | K92: =IF(财务基础数据!AM4<=2,0,K91-J91) -> 0
A93: 1#1 | C93: 其中：短期融资券
B98: （二）长期资产
B99: 债权投资 | F99: =资产负债表!Y24 -> 0 | G99: =资产负债表!AC24 -> 0 | H99: =资产负债表!AG24 -> 0 | I99: =资产负债表!AH24 -> 0 | J99: =资产负债表!AI24 -> 0 | K99: =资产负债表!AJ24 -> 0 | L99: =IF(ISERROR(H99+L100),0,H99+L100) -> 0 | M99: =IF(ISERROR(L99+M100),0,L99+M100) -> 0 | N99: =IF(ISERROR(M99+N100),0,M99+N100) -> 0 | O99: =IF(ISERROR(N99+O100),0,N99+O100) -> 0 | P99: =IF(ISERROR(O99+P100),0,O99+P100) -> 0 | Q99: =IF(ISERROR(P99+Q100),0,P99+Q100) -> 0 | R99: =IF(ISERROR(Q99+R100),0,Q99+R100) -> 0 | S99: =IF(ISERROR(R99+S100),0,R99+S100) -> 0 | T99: =IF(ISERROR(S99+T100),0,S99+T100) -> 0 | U99: =IF(ISERROR(T99+U100),0,T99+U100) -> 0
A100: 1#1 | C100: 当期增加 | F100: =F99-资产负债表!U24 -> 0 | G100: =G99-F99 -> 0 | H100: =H99-G99 -> 0 | I100: =IF(财务基础数据!AM4=0,0,I99-H99) -> 0 | J100: =IF(财务基础数据!AM4<=1,0,J99-I99) -> 0 | K100: =IF(财务基础数据!AM4<=2,0,K99-J99) -> 0
B102: 其他债权投资 | F102: =资产负债表!Y25 -> 0 | G102: =资产负债表!AC25 -> 0 | H102: =资产负债表!AG25 -> 0 | I102: =资产负债表!AH25 -> 0 | J102: =资产负债表!AI25 -> 0 | K102: =资产负债表!AJ25 -> 0 | L102: =IF(ISERROR(H102+L103),0,H102+L103) -> 0 | M102: =IF(ISERROR(L102+M103),0,L102+M103) -> 0 | N102: =IF(ISERROR(M102+N103),0,M102+N103) -> 0 | O102: =IF(ISERROR(N102+O103),0,N102+O103) -> 0 | P102: =IF(ISERROR(O102+P103),0,O102+P103) -> 0 | Q102: =IF(ISERROR(P102+Q103),0,P102+Q103) -> 0 | R102: =IF(ISERROR(Q102+R103),0,Q102+R103) -> 0 | S102: =IF(ISERROR(R102+S103),0,R102+S103) -> 0 | T102: =IF(ISERROR(S102+T103),0,S102+T103) -> 0 | U102: =IF(ISERROR(T102+U103),0,T102+U103) -> 0
A103: 1#1 | C103: 当期增加 | F103: =F102-资产负债表!U25 -> 0 | G103: =G102-F102 -> 0 | H103: =H102-G102 -> 0 | I103: =IF(财务基础数据!AM4=0,0,I102-H102) -> 0 | J103: =IF(财务基础数据!AM4<=1,0,J102-I102) -> 0 | K103: =IF(财务基础数据!AM4<=2,0,K102-J102) -> 0
B105: 长期应收款 | F105: =资产负债表!Y26 -> 0 | G105: =资产负债表!AC26 -> 0 | H105: =资产负债表!AG26 -> 0 | I105: =资产负债表!AH26 -> 0 | J105: =资产负债表!AI26 -> 0 | K105: =资产负债表!AJ26 -> 0 | L105: =IF(ISERROR(H105+L106),0,H105+L106) -> 0 | M105: =IF(ISERROR(L105+M106),0,L105+M106) -> 0 | N105: =IF(ISERROR(M105+N106),0,M105+N106) -> 0 | O105: =IF(ISERROR(N105+O106),0,N105+O106) -> 0 | P105: =IF(ISERROR(O105+P106),0,O105+P106) -> 0 | Q105: =IF(ISERROR(P105+Q106),0,P105+Q106) -> 0 | R105: =IF(ISERROR(Q105+R106),0,Q105+R106) -> 0 | S105: =IF(ISERROR(R105+S106),0,R105+S106) -> 0 | T105: =IF(ISERROR(S105+T106),0,S105+T106) -> 0 | U105: =IF(ISERROR(T105+U106),0,T105+U106) -> 0
A106: 1#1 | C106: 当期增加 | F106: =F105-资产负债表!U26 -> 0 | G106: =G105-F105 -> 0 | H106: =H105-G105 -> 0 | I106: =IF(财务基础数据!AM4=0,0,I105-H105) -> 0 | J106: =IF(财务基础数据!AM4<=1,0,J105-I105) -> 0 | K106: =IF(财务基础数据!AM4<=2,0,K105-J105) -> 0
B108: 其他权益工具投资 | F108: =资产负债表!Y28 -> 0 | G108: =资产负债表!AC28 -> 0 | H108: =资产负债表!AG28 -> 0 | I108: =资产负债表!AH28 -> 0 | J108: =资产负债表!AI28 -> 0 | K108: =资产负债表!AJ28 -> 0 | L108: =IF(ISERROR(H108+L109),0,H108+L109) -> 0 | M108: =IF(ISERROR(L108+M109),0,L108+M109) -> 0 | N108: =IF(ISERROR(M108+N109),0,M108+N109) -> 0 | O108: =IF(ISERROR(N108+O109),0,N108+O109) -> 0 | P108: =IF(ISERROR(O108+P109),0,O108+P109) -> 0 | Q108: =IF(ISERROR(P108+Q109),0,P108+Q109) -> 0 | R108: =IF(ISERROR(Q108+R109),0,Q108+R109) -> 0 | S108: =IF(ISERROR(R108+S109),0,R108+S109) -> 0 | T108: =IF(ISERROR(S108+T109),0,S108+T109) -> 0 | U108: =IF(ISERROR(T108+U109),0,T108+U109) -> 0
A109: 1#1 | C109: 当期增加 | F109: =F108-资产负债表!U28 -> 0 | G109: =G108-F108 -> 0 | H109: =H108-G108 -> 0 | I109: =IF(财务基础数据!AM4=0,0,I108-H108) -> 0 | J109: =IF(财务基础数据!AM4<=1,0,J108-I108) -> 0 | K109: =IF(财务基础数据!AM4<=2,0,K108-J108) -> 0
B111: 其他非流动金融资产 | F111: =资产负债表!Y29 -> 0 | G111: =资产负债表!AC29 -> 0 | H111: =资产负债表!AG29 -> 0 | I111: =资产负债表!AH29 -> 0 | J111: =资产负债表!AI29 -> 0 | K111: =资产负债表!AJ29 -> 0 | L111: =IF(ISERROR(H111+L112+L113),0,H111+L112+L113) -> 0 | M111: =IF(ISERROR(L111+M112+M113),0,L111+M112+M113) -> 0 | N111: =IF(ISERROR(M111+N112+N113),0,M111+N112+N113) -> 0 | O111: =IF(ISERROR(N111+O112+O113),0,N111+O112+O113) -> 0 | P111: =IF(ISERROR(O111+P112+P113),0,O111+P112+P113) -> 0 | Q111: =IF(ISERROR(P111+Q112+Q113),0,P111+Q112+Q113) -> 0 | R111: =IF(ISERROR(Q111+R112+R113),0,Q111+R112+R113) -> 0 | S111: =IF(ISERROR(R111+S112+S113),0,R111+S112+S113) -> 0 | T111: =IF(ISERROR(S111+T112+T113),0,S111+T112+T113) -> 0 | U111: =IF(ISERROR(T111+U112+U113),0,T111+U112+U113) -> 0
A112: 1#1 | C112: 当期增加 | F112: =F111-资产负债表!U29 -> 0 | G112: =G111-F111 -> 0 | H112: =H111-G111 -> 0 | I112: =IF(财务基础数据!AM4=0,0,I111-H111) -> 0 | J112: =IF(财务基础数据!AM4<=1,0,J111-I111) -> 0 | K112: =IF(财务基础数据!AM4<=2,0,K111-J111) -> 0
A113: 1#1 | C113: 公允价值变动
B115: 长期待摊费用 | F115: =资产负债表!Y39 -> 0 | G115: =资产负债表!AC39 -> 0 | H115: =资产负债表!AG39 -> 0 | I115: =资产负债表!AH39 -> 0 | J115: =资产负债表!AI39 -> 0 | K115: =资产负债表!AJ39 -> 0 | L115: =IF(ISERROR(H115+L116-L117),0,H115+L116-L117) -> 0 | M115: =IF(ISERROR(L115+M116-M117),0,L115+M116-M117) -> 0 | N115: =IF(ISERROR(M115+N116-N117),0,M115+N116-N117) -> 0 | O115: =IF(ISERROR(N115+O116-O117),0,N115+O116-O117) -> 0 | P115: =IF(ISERROR(O115+P116-P117),0,O115+P116-P117) -> 0 | Q115: =IF(ISERROR(P115+Q116-Q117),0,P115+Q116-Q117) -> 0 | R115: =IF(ISERROR(Q115+R116-R117),0,Q115+R116-R117) -> 0 | S115: =IF(ISERROR(R115+S116-S117),0,R115+S116-S117) -> 0 | T115: =IF(ISERROR(S115+T116-T117),0,S115+T116-T117) -> 0 | U115: =IF(ISERROR(T115+U116-U117),0,T115+U116-U117) -> 0
A116: 1#1 | C116: 当期增加 | F116: =F115-资产负债表!U39+F117 -> 0 | G116: =G115-F115+G117 -> 0 | H116: =H115-G115+H117 -> 0 | J116: =IF(财务基础数据!AM4<=1,0,J115-H115+J117) -> 0
A117: 1#1 | C117: 当期摊销 | F117: =现金流量表!Y14 -> 0 | G117: =现金流量表!AC14 -> 0 | H117: =现金流量表!AG14 -> 0 | J117: =IF(财务基础数据!AM4<=1,0,现金流量表!AI14) -> 0
B119: 当期公允价值变动 | L119: =IF(ISERROR(L73+L77-L85-L89+L113+投资与减值!L96+投资与减值!L139),0,(L73+L77-L85-L89+L113+投资与减值!L96+投资与减值!L139)) -> 0 | M119: =IF(ISERROR(M73+M77-M85-M89+M113+投资与减值!M96+投资与减值!M139),0,(M73+M77-M85-M89+M113+投资与减值!M96+投资与减值!M139)) -> 0 | N119: =IF(ISERROR(N73+N77-N85-N89+N113+投资与减值!N96+投资与减值!N139),0,(N73+N77-N85-N89+N113+投资与减值!N96+投资与减值!N139)) -> 0 | O119: =IF(ISERROR(O73+O77-O85-O89+O113+投资与减值!O96+投资与减值!O139),0,(O73+O77-O85-O89+O113+投资与减值!O96+投资与减值!O139)) -> 0 | P119: =IF(ISERROR(P73+P77-P85-P89+P113+投资与减值!P96+投资与减值!P139),0,(P73+P77-P85-P89+P113+投资与减值!P96+投资与减值!P139)) -> 0 | Q119: =IF(ISERROR(Q73+Q77-Q85-Q89+Q113+投资与减值!Q96+投资与减值!Q139),0,(Q73+Q77-Q85-Q89+Q113+投资与减值!Q96+投资与减值!Q139)) -> 0 | R119: =IF(ISERROR(R73+R77-R85-R89+R113+投资与减值!R96+投资与减值!R139),0,(R73+R77-R85-R89+R113+投资与减值!R96+投资与减值!R139)) -> 0 | S119: =IF(ISERROR(S73+S77-S85-S89+S113+投资与减值!S96+投资与减值!S139),0,(S73+S77-S85-S89+S113+投资与减值!S96+投资与减值!S139)) -> 0 | ... U119: =IF(ISERROR(U73+U77-U85-U89+U113+投资与减值!U96+投资与减值!U139),0,(U73+U77-U85-U89+U113+投资与减值!U96+投资与减值!U139)) -> 0 | V119: 请不要改动公允价值变动合计的公式
B121: 融资预测(股权融资、债权融资)
B122: ="单位：人民币"&目录!D5 -> 单位：人民币百万元
B123: 会计年度截止日：12/31 | F123: =F4 -> 2021 | G123: =G4 -> 2022 | H123: =H4 -> 2023 | I123: =I4 -> 1Q24 | J123: =J4 -> 1H24 | K123: =K4 -> 3Q24 | L123: =L4 -> 2024E | M123: =M4 -> 2025 | ... U123: =U4 -> 2033
B125: （一）股权融资
B126: 1、新股发行
A127: 1#1 | C127: 发行股数 | I127: =财务基础数据!AM304*目录!$D$6 -> 0 | J127: =财务基础数据!AN304*目录!$D$6 -> 0 | K127: =财务基础数据!AO304*目录!$D$6 -> 0 | L127: =SUM(I127:K127)+财务基础数据!AP304*目录!$D$6 -> 0 | M127: 0
C128: 发行价格 | I128: =财务基础数据!AM302 -> 0 | J128: =财务基础数据!AN302 -> 0 | K128: =财务基础数据!AO302 -> 0 | L128: =SUM(I128:K128)+财务基础数据!AP302 -> 0 | M128: 0
C129: 股票面值 | I129: 1 | J129: 1 | K129: 1 | L129: 1 | M129: 1 | V129: 默认股票面值为1元/股，若为特殊值，请自行在此修改
C130: 发行费用 | I130: =财务基础数据!AM305*10000*目录!$D$6 -> 0 | J130: =财务基础数据!AN305*10000*目录!$D$6 -> 0 | K130: =财务基础数据!AO305*10000*目录!$D$6 -> 0 | L130: =SUM(I130:K130)+财务基础数据!AP305*10000*目录!$D$6 -> 0 | M130: 0
C132: 当期股本增加 | I132: =I127*I129 -> 0 | J132: =J127*J129 -> 0 | K132: =K127*K129 -> 0 | L132: =L127*L129 -> 0 | M132: =M127*M129 -> 0
C133: 当期资本公积增加 | I133: =I127*I128-I130-I132 -> 0 | J133: =J127*J128-J130-J132 -> 0 | K133: =K127*K128-K130-K132 -> 0 | L133: =L127*L128-L130-L132 -> 0 | M133: =M127*M128-M130-M132 -> 0
B135: 2、增发
C136: 发行股数 | F136: =SUM(财务基础数据!AA307:AD307)*10000*目录!$D$6 -> 0 | G136: =SUM(财务基础数据!AE307:AH307)*10000*目录!$D$6 -> 0 | H136: =SUM(财务基础数据!AI307:AL307)*10000*目录!$D$6 -> 0 | I136: =财务基础数据!AM307*10000*目录!$D$6 -> 0 | J136: =财务基础数据!AN307*10000*目录!$D$6 -> 0 | K136: =财务基础数据!AO307*10000*目录!$D$6 -> 0 | L136: =SUM(I136:K136)+财务基础数据!AP307*10000*目录!$D$6 -> 0 | M136: =SUM(财务基础数据!AQ307:AR307)*10000*目录!$D$6 -> 0
C137: 发行价格 | I137: =财务基础数据!AM306 -> 0 | J137: =财务基础数据!AN306 -> 0 | K137: =财务基础数据!AO306 -> 0 | L137: =IF(ISERROR(SUM(财务基础数据!AM308:AP308)*目录!$D$6/L136),0,SUM(财务基础数据!AM308:AP308)*目录!$D$6/L136) -> 0 | M137: =IF(ISERROR(SUM(财务基础数据!AQ308:AR308)*目录!$D$6/M136),0,SUM(财务基础数据!AQ308:AR308)*目录!$D$6/M136) -> 0
C138: 发行费用 | F138: =SUM(财务基础数据!AA309:AD309)*目录!$D$6 -> 0 | G138: =SUM(财务基础数据!AE309:AH309)*目录!$D$6 -> 0 | H138: =SUM(财务基础数据!AI309:AL309)*目录!$D$6 -> 0 | I138: =财务基础数据!AM309*目录!$D$6 -> 0 | J138: =财务基础数据!AN309*目录!$D$6 -> 0 | K138: =财务基础数据!AO309*目录!$D$6 -> 0 | L138: =SUM(I138:K138)+财务基础数据!AP309*目录!$D$6 -> 0 | M138: =SUM(财务基础数据!AQ309:AR309)*目录!$D$6 -> 0
C140: 当期股本增加 | I140: =I136*$L$129 -> 0 | J140: =J136*$L$129 -> 0 | K140: =K136*$L$129 -> 0 | L140: =L136*$L$129 -> 0 | M140: =M136*$L$129 -> 0 | N140: =N136*$L$129 -> 0 | O140: =O136*$L$129 -> 0 | P140: =P136*$L$129 -> 0 | ... U140: =U136*$L$129 -> 0
C141: 当期资本公积增加 | I141: =I136*I137-I138-I140 -> 0 | J141: =J136*J137-J138-J140 -> 0 | K141: =K136*K137-K138-K140 -> 0 | L141: =L136*L137-L138-L140 -> 0 | M141: =M136*M137-M138-M140 -> 0 | N141: =N136*N137-N138-N140 -> 0 | O141: =O136*O137-O138-O140 -> 0 | P141: =P136*P137-P138-P140 -> 0 | ... U141: =U136*U137-U138-U140 -> 0
B143: 3、回购股份
C144: 回购股数 | F144: =SUM(财务基础数据!AA310:AD310)*目录!$D$6 -> 0 | G144: =SUM(财务基础数据!AE310:AH310)*目录!$D$6 -> 0 | H144: =SUM(财务基础数据!AI310:AL310)*目录!$D$6 -> 0 | I144: =财务基础数据!AM310*目录!$D$6 -> 0 | J144: =财务基础数据!AN310*目录!$D$6 -> 0 | K144: =财务基础数据!AO310*目录!$D$6 -> 0 | L144: =SUM(I144:K144)+财务基础数据!AP310*目录!$D$6 -> 0 | M144: =SUM(财务基础数据!AQ310:AR310)*目录!$D$6 -> 0 | V144: 1.默认回购股份未注销，只影响库存股； 2.若当期回购且注销股份，影响股本和资本公积，请在147、148行填写数据（参考单元格批注），同时清空149行数据； 3.若当期仅注销股份，所有者权益内部增减变动不影响现金流，请同时调整147、148、149行数据。
C145: 回购总金额 | F145: =SUM(财务基础数据!AA311:AD311)*目录!$D$6 -> 0 | G145: =SUM(财务基础数据!AE311:AH311)*目录!$D$6 -> 0 | H145: =SUM(财务基础数据!AI311:AL311)*目录!$D$6 -> 0 | I145: =财务基础数据!AM311*目录!$D$6 -> 0 | J145: =财务基础数据!AN311*目录!$D$6 -> 0 | K145: =财务基础数据!AO311*目录!$D$6 -> 0 | L145: =SUM(I145:K145)+财务基础数据!AP311*目录!$D$6 -> 0 | M145: =SUM(财务基础数据!AQ311:AR311)*目录!$D$6 -> 0
...

Sheet 投资与减值
B2: 投资支出
B3: ="单位：人民币"&目录!D5 -> 单位：人民币百万元
B4: 会计年度截止日：12/31 | F4: =资产预测!F4 -> 2021 | G4: =资产预测!G4 -> 2022 | H4: =资产预测!H4 -> 2023 | I4: =资产预测!I4 -> 1Q24 | J4: =资产预测!J4 -> 1H24 | K4: =资产预测!K4 -> 3Q24 | L4: =资产预测!L4 -> 2024E | M4: =资产预测!M4 -> 2025 | ... U4: =资产预测!U4 -> 2033
B6: 一、固定资产
B7: 假设： | C7: 预计使用寿命 | D7: 10
C8: 预计净残值 | D8: 0.05
B10: 原值： | C10: 期初 | F10: =财务附注数据!Z6*目录!$D$6 -> 0 | G10: =财务附注数据!AD6*目录!$D$6 -> 0 | H10: =财务附注数据!AH6*目录!$D$6 -> 0 | J10: =H13 -> 0 | L10: =H13 -> 0 | M10: =L13 -> 0 | N10: =M13 -> 0 | O10: =N13 -> 0 | P10: =O13 -> 0 | Q10: =P13 -> 0 | R10: =Q13 -> 0 | S10: =R13 -> 0 | T10: =S13 -> 0 | U10: =T13 -> 0
C11: 本期增加(外购） | F11: =F13-F10 -> 0 | G11: =G13-G10 -> 0 | H11: =H13-H10 -> 0 | J11: =IF(财务基础数据!AM4<=1,0,J13-J10) -> 0
C12: 本期在建工程转固 | L12: =L44 -> 0 | M12: =M44 -> 0 | N12: =N44 -> 0 | O12: =O44 -> 0 | P12: =P44 -> 0 | Q12: =Q44 -> 0 | R12: =R44 -> 0 | S12: =S44 -> 0 | ... U12: =U44 -> 0 | V12: 在建工程转固金额请在下方填写预测参数，不要修改此处公式！
C13: 期末 | F13: =财务附注数据!AD6*目录!$D$6 -> 0 | G13: =财务附注数据!AH6*目录!$D$6 -> 0 | H13: =财务附注数据!AL6*目录!$D$6 -> 0 | J13: =财务附注数据!AN6*目录!$D$6 -> 0 | L13: =L10+L11+L12 -> 0 | M13: =M10+M11+M12 -> 0 | N13: =N10+N11+N12 -> 0 | O13: =O10+O11+O12 -> 0 | P13: =P10+P11+P12 -> 0 | Q13: =Q10+Q11+Q12 -> 0 | R13: =R10+R11+R12 -> 0 | S13: =S10+S11+S12 -> 0 | ... U13: =U10+U11+U12 -> 0
B15: 本期计提折旧： | F15: =IF(财务基础数据!AD282=0,财务基础数据!AD281*目录!$D$6-F99-F142-F151-F110,财务基础数据!AD281*目录!$D$6-F99-F142-F151) -> 0 | G15: =IF(财务基础数据!AH282=0,财务基础数据!AH281*目录!$D$6-G99-G142-G151-G110,财务基础数据!AH281*目录!$D$6-G99-G142-G151) -> 0 | H15: =IF(财务基础数据!AL282=0,财务基础数据!AL281*目录!$D$6-H99-H142-H151-H110,财务基础数据!AL281*目录!$D$6-H99-H142-H151) -> 0 | J15: =IF(财务基础数据!AN282=0,财务基础数据!AN281*目录!$D$6-J99-J142-J151-J110,财务基础数据!AN281*目录!$D$6-J99-J142-J151) -> 0 | L15: =L39 -> 0 | M15: =M39 -> 0 | N15: =N39 -> 0 | O15: =O39 -> 0 | P15: =P39 -> 0 | Q15: =Q39 -> 0 | R15: =R39 -> 0 | S15: =S39 -> 0 | ... U15: =U39 -> 0
C16: 折旧率% | D16: 0 | F16: =IF(ISERROR(F15/F10),0,F15/F10) -> 0 | G16: =IF(ISERROR(G15/G10),0,G15/G10) -> 0 | H16: =IF(ISERROR(H15/H10),0,H15/H10) -> 0 | J16: =IF(ISERROR(J15/J10*2),0,J15/J10*2) -> 0 | L16: =$D$16 -> 0 | M16: =$D$16 -> 0 | N16: =$D$16 -> 0 | O16: =$D$16 -> 0 | P16: =$D$16 -> 0 | Q16: =$D$16 -> 0 | R16: =$D$16 -> 0 | S16: =$D$16 -> 0 | ... U16: =$D$16 -> 0
B18: 减值： | C18: 期初 | F18: =财务附注数据!Z8*目录!$D$6 -> 0 | G18: =财务附注数据!AD8*目录!$D$6 -> 0 | H18: =财务附注数据!AH8*目录!$D$6 -> 0 | J18: =H20 -> 0 | L18: =H20 -> 0 | M18: =L20 -> 0 | N18: =M20 -> 0 | O18: =N20 -> 0 | P18: =O20 -> 0 | Q18: =P20 -> 0 | R18: =Q20 -> 0 | S18: =R20 -> 0 | T18: =S20 -> 0 | U18: =T20 -> 0
C19: 本期增加 | F19: =F20-F18 -> 0 | G19: =G20-G18 -> 0 | H19: =H20-H18 -> 0 | J19: =IF(财务基础数据!AM4<=1,0,J20-J18) -> 0
C20: 期末 | F20: =财务附注数据!AD8*目录!$D$6 -> 0 | G20: =财务附注数据!AH8*目录!$D$6 -> 0 | H20: =财务附注数据!AL8*目录!$D$6 -> 0 | J20: =财务附注数据!AN8*目录!$D$6 -> 0 | L20: =L18+L19 -> 0 | M20: =M18+M19 -> 0 | N20: =N18+N19 -> 0 | O20: =O18+O19 -> 0 | P20: =P18+P19 -> 0 | Q20: =Q18+Q19 -> 0 | R20: =R18+R19 -> 0 | S20: =S18+S19 -> 0 | ... U20: =U18+U19 -> 0
C22: 其他增减
B23: 期初固定资产净额 | F23: =资产负债表!U31 -> 0 | G23: =资产负债表!Y31 -> 0 | H23: =资产负债表!AC31 -> 0 | L23: =H24 -> 0 | M23: =L24 -> 0 | N23: =M24 -> 0 | O23: =N24 -> 0 | P23: =O24 -> 0 | Q23: =P24 -> 0 | R23: =Q24 -> 0 | S23: =R24 -> 0 | T23: =S24 -> 0 | U23: =T24 -> 0
B24: 期末固定资产净额 | F24: =资产负债表!Y31 -> 0 | G24: =资产负债表!AC31 -> 0 | H24: =资产负债表!AG31 -> 0 | I24: =资产负债表!AH31 -> 0 | J24: =资产负债表!AI31 -> 0 | K24: =资产负债表!AJ31 -> 0 | L24: =H24+L11+L12-L15-L19+L22 -> 0 | M24: =L24+M11+M12-M15-M19+M22 -> 0 | N24: =M24+N11+N12-N15-N19+N22 -> 0 | O24: =N24+O11+O12-O15-O19+O22 -> 0 | P24: =O24+P11+P12-P15-P19+P22 -> 0 | Q24: =P24+Q11+Q12-Q15-Q19+Q22 -> 0 | R24: =Q24+R11+R12-R15-R19+R22 -> 0 | S24: =R24+S11+S12-S15-S19+S22 -> 0 | T24: =S24+T11+T12-T15-T19+T22 -> 0 | U24: =T24+U11+U12-U15-U19+U22 -> 0
F26: 原有资产 | G26: 期末净额 | H26: 期末原值 | L26: =L4 -> 2024E | M26: =M4 -> 2025 | N26: =N4 -> 2026 | O26: =O4 -> 2027 | P26: =P4 -> 2028 | Q26: =Q4 -> 2029 | R26: =R4 -> 2030 | S26: =S4 -> 2031 | ... U26: =U4 -> 2033
G27: =H24 -> 0 | H27: =H13 -> 0 | L27: =IF(SUM($K$27:K27)=$G$27,0,IF($G$27-SUM($K$27:K27)<$H$27*L16,$G$27-SUM($K$27:K27),$H$27*L16)) -> 0 | M27: =IF(SUM($K$27:L27)=$G$27,0,IF($G$27-SUM($K$27:L27)<$H$27*M16,$G$27-SUM($K$27:L27),$H$27*M16)) -> 0 | N27: =IF(SUM($K$27:M27)=$G$27,0,IF($G$27-SUM($K$27:M27)<$H$27*N16,$G$27-SUM($K$27:M27),$H$27*N16)) -> 0 | O27: =IF(SUM($K$27:N27)=$G$27,0,IF($G$27-SUM($K$27:N27)<$H$27*O16,$G$27-SUM($K$27:N27),$H$27*O16)) -> 0 | P27: =IF(SUM($K$27:O27)=$G$27,0,IF($G$27-SUM($K$27:O27)<$H$27*P16,$G$27-SUM($K$27:O27),$H$27*P16)) -> 0 | Q27: =IF(SUM($K$27:P27)=$G$27,0,IF($G$27-SUM($K$27:P27)<$H$27*Q16,$G$27-SUM($K$27:P27),$H$27*Q16)) -> 0 | R27: =IF(SUM($K$27:Q27)=$G$27,0,IF($G$27-SUM($K$27:Q27)<$H$27*R16,$G$27-SUM($K$27:Q27),$H$27*R16)) -> 0 | S27: =IF(SUM($K$27:R27)=$G$27,0,IF($G$27-SUM($K$27:R27)<$H$27*S16,$G$27-SUM($K$27:R27),$H$27*S16)) -> 0 | ... U27: =IF(SUM($K$27:T27)=$G$27,0,IF($G$27-SUM($K$27:T27)<$H$27*U16,$G$27-SUM($K$27:T27),$H$27*U16)) -> 0
G28: 新增资产 | H28: 使用年限
F29: {=TRANSPOSE(L4:U4)} -> 2024E | G29: =L11+L12 -> 0 | H29: =$D$7 -> 10 | L29: =IF($H29>=1,$G29*(1-$D$8)/$H29,"") -> 0 | M29: =IF($H29>=2,$G29*(1-$D$8)/$H29,"") -> 0 | N29: =IF($H29>=3,$G29*(1-$D$8)/$H29,"") -> 0 | O29: =IF($H29>=4,$G29*(1-$D$8)/$H29,"") -> 0 | P29: =IF($H29>=5,$G29*(1-$D$8)/$H29,"") -> 0 | Q29: =IF($H29>=6,$G29*(1-$D$8)/$H29,"") -> 0 | R29: =IF($H29>=7,$G29*(1-$D$8)/$H29,"") -> 0 | S29: =IF($H29>=8,$G29*(1-$D$8)/$H29,"") -> 0 | T29: =IF($H29>=9,$G29*(1-$D$8)/$H29,"") -> 0 | U29: =IF($H29>=10,$G29*(1-$D$8)/$H29,"") -> 0
F30: 2025 | G30: =M11+M12 -> 0 | H30: =$D$7 -> 10 | M30: =IF($H30>=1,$G30*(1-$D$8)/$H30,"") -> 0 | N30: =IF($H30>=2,$G30*(1-$D$8)/$H30,"") -> 0 | O30: =IF($H30>=3,$G30*(1-$D$8)/$H30,"") -> 0 | P30: =IF($H30>=4,$G30*(1-$D$8)/$H30,"") -> 0 | Q30: =IF($H30>=5,$G30*(1-$D$8)/$H30,"") -> 0 | R30: =IF($H30>=6,$G30*(1-$D$8)/$H30,"") -> 0 | S30: =IF($H30>=7,$G30*(1-$D$8)/$H30,"") -> 0 | T30: =IF($H30>=8,$G30*(1-$D$8)/$H30,"") -> 0 | U30: =IF($H30>=9,$G30*(1-$D$8)/$H30,"") -> 0
F31: 2026 | G31: =N11+N12 -> 0 | H31: =$D$7 -> 10 | N31: =IF($H31>=1,$G31*(1-$D$8)/$H31,"") -> 0 | O31: =IF($H31>=2,$G31*(1-$D$8)/$H31,"") -> 0 | P31: =IF($H31>=3,$G31*(1-$D$8)/$H31,"") -> 0 | Q31: =IF($H31>=4,$G31*(1-$D$8)/$H31,"") -> 0 | R31: =IF($H31>=5,$G31*(1-$D$8)/$H31,"") -> 0 | S31: =IF($H31>=6,$G31*(1-$D$8)/$H31,"") -> 0 | T31: =IF($H31>=7,$G31*(1-$D$8)/$H31,"") -> 0 | U31: =IF($H31>=8,$G31*(1-$D$8)/$H31,"") -> 0
F32: 2027 | G32: =O11+O12 -> 0 | H32: =$D$7 -> 10 | O32: =IF($H32>=1,$G32*(1-$D$8)/$H32,"") -> 0 | P32: =IF($H32>=2,$G32*(1-$D$8)/$H32,"") -> 0 | Q32: =IF($H32>=3,$G32*(1-$D$8)/$H32,"") -> 0 | R32: =IF($H32>=4,$G32*(1-$D$8)/$H32,"") -> 0 | S32: =IF($H32>=5,$G32*(1-$D$8)/$H32,"") -> 0 | T32: =IF($H32>=6,$G32*(1-$D$8)/$H32,"") -> 0 | U32: =IF($H32>=7,$G32*(1-$D$8)/$H32,"") -> 0
F33: 2028 | G33: =P11+P12 -> 0 | H33: =$D$7 -> 10 | P33: =IF($H33>=1,$G33*(1-$D$8)/$H33,"") -> 0 | Q33: =IF($H33>=2,$G33*(1-$D$8)/$H33,"") -> 0 | R33: =IF($H33>=3,$G33*(1-$D$8)/$H33,"") -> 0 | S33: =IF($H33>=4,$G33*(1-$D$8)/$H33,"") -> 0 | T33: =IF($H33>=5,$G33*(1-$D$8)/$H33,"") -> 0 | U33: =IF($H33>=6,$G33*(1-$D$8)/$H33,"") -> 0
F34: 2029 | G34: =Q11+Q12 -> 0 | H34: =$D$7 -> 10 | Q34: =IF($H34>=1,$G34*(1-$D$8)/$H34,"") -> 0 | R34: =IF($H34>=2,$G34*(1-$D$8)/$H34,"") -> 0 | S34: =IF($H34>=3,$G34*(1-$D$8)/$H34,"") -> 0 | T34: =IF($H34>=4,$G34*(1-$D$8)/$H34,"") -> 0 | U34: =IF($H34>=5,$G34*(1-$D$8)/$H34,"") -> 0
F35: 2030 | G35: =R11+R12 -> 0 | H35: =$D$7 -> 10 | R35: =IF($H35>=1,$G35*(1-$D$8)/$H35,"") -> 0 | S35: =IF($H35>=2,$G35*(1-$D$8)/$H35,"") -> 0 | T35: =IF($H35>=3,$G35*(1-$D$8)/$H35,"") -> 0 | U35: =IF($H35>=4,$G35*(1-$D$8)/$H35,"") -> 0
F36: 2031 | G36: =S11+S12 -> 0 | H36: =$D$7 -> 10 | S36: =IF($H36>=1,$G36*(1-$D$8)/$H36,"") -> 0 | T36: =IF($H36>=2,$G36*(1-$D$8)/$H36,"") -> 0 | U36: =IF($H36>=3,$G36*(1-$D$8)/$H36,"") -> 0
F37: 2032 | G37: =T11+T12 -> 0 | H37: =$D$7 -> 10 | T37: =IF($H37>=1,$G37*(1-$D$8)/$H37,"") -> 0 | U37: =IF($H37>=2,$G37*(1-$D$8)/$H37,"") -> 0
F38: 2033 | G38: =U11+U12 -> 0 | H38: =$D$7 -> 10 | U38: =IF($H38>=1,$G38*(1-$D$8)/$H38,"") -> 0
F39: 折旧总额 | L39: =SUM(L27:L38) -> 0 | M39: =SUM(M27:M38) -> 0 | N39: =SUM(N27:N38) -> 0 | O39: =SUM(O27:O38) -> 0 | P39: =SUM(P27:P38) -> 0 | Q39: =SUM(Q27:Q38) -> 0 | R39: =SUM(R27:R38) -> 0 | S39: =SUM(S27:S38) -> 0 | ... U39: =SUM(U27:U38) -> 0
B41: 二、在建工程
B42: 期初在建工程净额 | F42: =资产负债表!U32 -> 0 | G42: =资产负债表!Y32 -> 0 | H42: =资产负债表!AC32 -> 0 | I42: =资产负债表!AG32 -> 0 | J42: =资产负债表!AH32 -> 0 | K42: =资产负债表!AI32 -> 0 | L42: =H46 -> 0 | M42: =L46 -> 0 | N42: =M46 -> 0 | O42: =N46 -> 0 | P42: =O46 -> 0 | Q42: =P46 -> 0 | R42: =Q46 -> 0 | S42: =R46 -> 0 | T42: =S46 -> 0 | U42: =T46 -> 0
C43: 本期增加 | F43: =F46-F42 -> 0 | G43: =G46-G42 -> 0 | H43: =H46-H42 -> 0 | I43: =IF(财务基础数据!AM4=0,0,I46-I42) -> 0 | J43: =IF(财务基础数据!AM4<=1,0,J46-J42) -> 0 | K43: =IF(财务基础数据!AM4<=2,0,K46-K42) -> 0
C44: 在建工程转固 | D44: 0 | L44: =$D$44*(L42+L43) -> 0 | M44: =$D$44*(M42+M43) -> 0 | N44: =$D$44*(N42+N43) -> 0 | O44: =$D$44*(O42+O43) -> 0 | P44: =$D$44*(P42+P43) -> 0 | Q44: =$D$44*(Q42+Q43) -> 0 | R44: =$D$44*(R42+R43) -> 0 | S44: =$D$44*(S42+S43) -> 0 | ... U44: =$D$44*(U42+U43) -> 0
C45: 本期减值准备
B46: 期末在建工程净额 | F46: =资产负债表!Y32 -> 0 | G46: =资产负债表!AC32 -> 0 | H46: =资产负债表!AG32 -> 0 | I46: =资产负债表!AH32 -> 0 | J46: =资产负债表!AI32 -> 0 | K46: =资产负债表!AJ32 -> 0 | L46: =L42+L43-L44-L45 -> 0 | M46: =M42+M43-M44-M45 -> 0 | N46: =N42+N43-N44-N45 -> 0 | O46: =O42+O43-O44-O45 -> 0 | P46: =P42+P43-P44-P45 -> 0 | Q46: =Q42+Q43-Q44-Q45 -> 0 | R46: =R42+R43-R44-R45 -> 0 | S46: =S42+S43-S44-S45 -> 0 | ... U46: =U42+U43-U44-U45 -> 0
B48: 三、无形资产
B49: 假设： | C49: 预计使用寿命 | D49: 20
B51: 原值： | C51: 期初 | F51: =财务附注数据!Z14*目录!$D$6 -> 0 | G51: =财务附注数据!AD14*目录!$D$6 -> 0 | H51: =财务附注数据!AH14*目录!$D$6 -> 0 | J51: =H53 -> 0 | L51: =H53 -> 0 | M51: =L53 -> 0 | N51: =M53 -> 0 | O51: =N53 -> 0 | P51: =O53 -> 0 | Q51: =P53 -> 0 | R51: =Q53 -> 0 | S51: =R53 -> 0 | T51: =S53 -> 0 | U51: =T53 -> 0
C52: 本期增加 | F52: =F53-F51 -> 0 | G52: =G53-G51 -> 0 | H52: =H53-H51 -> 0 | J52: =IF(财务基础数据!AM4<=1,0,J53-J51) -> 0
C53: 期末 | F53: =财务附注数据!AD14*目录!$D$6 -> 0 | G53: =财务附注数据!AH14*目录!$D$6 -> 0 | H53: =财务附注数据!AL14*目录!$D$6 -> 0 | J53: =财务附注数据!AN14*目录!$D$6 -> 0 | L53: =L51+L52 -> 0 | M53: =M51+M52 -> 0 | N53: =N51+N52 -> 0 | O53: =O51+O52 -> 0 | P53: =P51+P52 -> 0 | Q53: =Q51+Q52 -> 0 | R53: =R51+R52 -> 0 | S53: =S51+S52 -> 0 | ... U53: =U51+U52 -> 0
B55: 本期计提摊销： | F55: =财务基础数据!AD255*目录!$D$6 -> 0 | G55: =财务基础数据!AH255*目录!$D$6 -> 0 | H55: =财务基础数据!AL255*目录!$D$6 -> 0 | J55: =财务基础数据!AN255*目录!$D$6 -> 0 | L55: =L78 -> 0 | M55: =M78 -> 0 | N55: =N78 -> 0 | O55: =O78 -> 0 | P55: =P78 -> 0 | Q55: =Q78 -> 0 | R55: =R78 -> 0 | S55: =S78 -> 0 | ... U55: =U78 -> 0
C56: 摊销率 | D56: 0 | F56: =IF(ISERROR(F55/F51),0,F55/F51) -> 0 | G56: =IF(ISERROR(G55/G51),0,G55/G51) -> 0 | H56: =IF(ISERROR(H55/H51),0,H55/H51) -> 0 | J56: =IF(ISERROR(J55/J51*2),0,J55/J51*2) -> 0 | L56: =$D$56 -> 0 | M56: =$D$56 -> 0 | N56: =$D$56 -> 0 | O56: =$D$56 -> 0 | P56: =$D$56 -> 0 | Q56: =$D$56 -> 0 | R56: =$D$56 -> 0 | S56: =$D$56 -> 0 | ... U56: =$D$56 -> 0
B58: 减值： | C58: 期初 | F58: =财务附注数据!Z16*目录!$D$6 -> 0 | G58: =财务附注数据!AD16*目录!$D$6 -> 0 | H58: =财务附注数据!AH16*目录!$D$6 -> 0 | J58: =H60 -> 0 | L58: =H60 -> 0 | M58: =L60 -> 0 | N58: =M60 -> 0 | O58: =N60 -> 0 | P58: =O60 -> 0 | Q58: =P60 -> 0 | R58: =Q60 -> 0 | S58: =R60 -> 0 | T58: =S60 -> 0 | U58: =T60 -> 0
C59: 本期增加 | F59: =F60-F58 -> 0 | G59: =G60-G58 -> 0 | H59: =H60-H58 -> 0 | J59: =IF(财务基础数据!AM4<=1,0,J60-J58) -> 0
C60: 期末 | F60: =财务附注数据!AD16*目录!$D$6 -> 0 | G60: =财务附注数据!AH16*目录!$D$6 -> 0 | H60: =财务附注数据!AL16*目录!$D$6 -> 0 | J60: =财务附注数据!AN16*目录!$D$6 -> 0 | L60: =L58+L59 -> 0 | M60: =M58+M59 -> 0 | N60: =N58+N59 -> 0 | O60: =O58+O59 -> 0 | P60: =P58+P59 -> 0 | Q60: =Q58+Q59 -> 0 | R60: =R58+R59 -> 0 | S60: =S58+S59 -> 0 | ... U60: =U58+U59 -> 0
B62: 期初无形资产净额 | F62: =资产负债表!U36 -> 0 | G62: =资产负债表!Y36 -> 0 | H62: =资产负债表!AC36 -> 0 | L62: =H63 -> 0 | M62: =L63 -> 0 | N62: =M63 -> 0 | O62: =N63 -> 0 | P62: =O63 -> 0 | Q62: =P63 -> 0 | R62: =Q63 -> 0 | S62: =R63 -> 0 | T62: =S63 -> 0 | U62: =T63 -> 0
B63: 期末无形资产净额 | F63: =资产负债表!Y36 -> 0 | G63: =资产负债表!AC36 -> 0 | H63: =资产负债表!AG36 -> 0 | I63: =资产负债表!AH36 -> 0 | J63: =资产负债表!AI36 -> 0 | K63: =资产负债表!AJ36 -> 0 | L63: =H63+L52-L55-L59 -> 0 | M63: =L63+M52-M55-M59 -> 0 | N63: =M63+N52-N55-N59 -> 0 | O63: =N63+O52-O55-O59 -> 0 | P63: =O63+P52-P55-P59 -> 0 | Q63: =P63+Q52-Q55-Q59 -> 0 | R63: =Q63+R52-R55-R59 -> 0 | S63: =R63+S52-S55-S59 -> 0 | T63: =S63+T52-T55-T59 -> 0 | U63: =T63+U52-U55-U59 -> 0
F65: 原有资产 | G65: 期末净额 | H65: 期末原值 | L65: =L4 -> 2024E | M65: =M4 -> 2025 | N65: =N4 -> 2026 | O65: =O4 -> 2027 | P65: =P4 -> 2028 | Q65: =Q4 -> 2029 | R65: =R4 -> 2030 | S65: =S4 -> 2031 | ... U65: =U4 -> 2033
G66: =H63 -> 0 | H66: =H53 -> 0 | L66: =IF(SUM($K$66:K66)=$G$66,0,IF($G$66-SUM($K$66:K66)<$H$66*L56,$G$66-SUM($K$66:K66),$H$66*L56)) -> 0 | M66: =IF(SUM($K$66:L66)=$G$66,0,IF($G$66-SUM($K$66:L66)<$H$66*M56,$G$66-SUM($K$66:L66),$H$66*M56)) -> 0 | N66: =IF(SUM($K$66:M66)=$G$66,0,IF($G$66-SUM($K$66:M66)<$H$66*N56,$G$66-SUM($K$66:M66),$H$66*N56)) -> 0 | O66: =IF(SUM($K$66:N66)=$G$66,0,IF($G$66-SUM($K$66:N66)<$H$66*O56,$G$66-SUM($K$66:N66),$H$66*O56)) -> 0 | P66: =IF(SUM($K$66:O66)=$G$66,0,IF($G$66-SUM($K$66:O66)<$H$66*P56,$G$66-SUM($K$66:O66),$H$66*P56)) -> 0 | Q66: =IF(SUM($K$66:P66)=$G$66,0,IF($G$66-SUM($K$66:P66)<$H$66*Q56,$G$66-SUM($K$66:P66),$H$66*Q56)) -> 0 | R66: =IF(SUM($K$66:Q66)=$G$66,0,IF($G$66-SUM($K$66:Q66)<$H$66*R56,$G$66-SUM($K$66:Q66),$H$66*R56)) -> 0 | S66: =IF(SUM($K$66:R66)=$G$66,0,IF($G$66-SUM($K$66:R66)<$H$66*S56,$G$66-SUM($K$66:R66),$H$66*S56)) -> 0 | ... U66: =IF(SUM($K$66:T66)=$G$66,0,IF($G$66-SUM($K$66:T66)<$H$66*U56,$G$66-SUM($K$66:T66),$H$66*U56)) -> 0
G67: 新增资产 | H67: 使用年限
F68: {=TRANSPOSE(L4:U4)} -> 2024E | G68: {=TRANSPOSE(L52:U52)} -> 0 | H68: =$D$49 -> 20 | L68: =IF($H68>=1,$G68/$H68,"") -> 0 | M68: =IF($H68>=2,$G68/$H68,"") -> 0 | N68: =IF($H68>=3,$G68/$H68,"") -> 0 | O68: =IF($H68>=4,$G68/$H68,"") -> 0 | P68: =IF($H68>=5,$G68/$H68,"") -> 0 | Q68: =IF($H68>=6,$G68/$H68,"") -> 0 | R68: =IF($H68>=7,$G68/$H68,"") -> 0 | S68: =IF($H68>=8,$G68/$H68,"") -> 0 | T68: =IF($H68>=9,$G68/$H68,"") -> 0 | U68: =IF($H68>=10,$G68/$H68,"") -> 0
F69: 2025 | G69: 0 | H69: =$D$49 -> 20 | M69: =IF($H69>=1,$G69/$H69,"") -> 0 | N69: =IF($H69>=2,$G69/$H69,"") -> 0 | O69: =IF($H69>=3,$G69/$H69,"") -> 0 | P69: =IF($H69>=4,$G69/$H69,"") -> 0 | Q69: =IF($H69>=5,$G69/$H69,"") -> 0 | R69: =IF($H69>=6,$G69/$H69,"") -> 0 | S69: =IF($H69>=7,$G69/$H69,"") -> 0 | T69: =IF($H69>=8,$G69/$H69,"") -> 0 | U69: =IF($H69>=9,$G69/$H69,"") -> 0
F70: 2026 | G70: 0 | H70: =$D$49 -> 20 | N70: =IF($H70>=1,$G70/$H70,"") -> 0 | O70: =IF($H70>=2,$G70/$H70,"") -> 0 | P70: =IF($H70>=3,$G70/$H70,"") -> 0 | Q70: =IF($H70>=4,$G70/$H70,"") -> 0 | R70: =IF($H70>=5,$G70/$H70,"") -> 0 | S70: =IF($H70>=6,$G70/$H70,"") -> 0 | T70: =IF($H70>=7,$G70/$H70,"") -> 0 | U70: =IF($H70>=8,$G70/$H70,"") -> 0
F71: 2027 | G71: 0 | H71: =$D$49 -> 20 | O71: =IF($H71>=1,$G71/$H71,"") -> 0 | P71: =IF($H71>=2,$G71/$H71,"") -> 0 | Q71: =IF($H71>=3,$G71/$H71,"") -> 0 | R71: =IF($H71>=4,$G71/$H71,"") -> 0 | S71: =IF($H71>=5,$G71/$H71,"") -> 0 | T71: =IF($H71>=6,$G71/$H71,"") -> 0 | U71: =IF($H71>=7,$G71/$H71,"") -> 0
F72: 2028 | G72: 0 | H72: =$D$49 -> 20 | P72: =IF($H72>=1,$G72/$H72,"") -> 0 | Q72: =IF($H72>=2,$G72/$H72,"") -> 0 | R72: =IF($H72>=3,$G72/$H72,"") -> 0 | S72: =IF($H72>=4,$G72/$H72,"") -> 0 | T72: =IF($H72>=5,$G72/$H72,"") -> 0 | U72: =IF($H72>=6,$G72/$H72,"") -> 0
F73: 2029 | G73: 0 | H73: =$D$49 -> 20 | Q73: =IF($H73>=1,$G73/$H73,"") -> 0 | R73: =IF($H73>=2,$G73/$H73,"") -> 0 | S73: =IF($H73>=3,$G73/$H73,"") -> 0 | T73: =IF($H73>=4,$G73/$H73,"") -> 0 | U73: =IF($H73>=5,$G73/$H73,"") -> 0
F74: 2030 | G74: 0 | H74: =$D$49 -> 20 | R74: =IF($H74>=1,$G74/$H74,"") -> 0 | S74: =IF($H74>=2,$G74/$H74,"") -> 0 | T74: =IF($H74>=3,$G74/$H74,"") -> 0 | U74: =IF($H74>=4,$G74/$H74,"") -> 0
F75: 2031 | G75: 0 | H75: =$D$49 -> 20 | S75: =IF($H75>=1,$G75/$H75,"") -> 0 | T75: =IF($H75>=2,$G75/$H75,"") -> 0 | U75: =IF($H75>=3,$G75/$H75,"") -> 0
F76: 2032 | G76: 0 | H76: =$D$49 -> 20 | T76: =IF($H76>=1,$G76/$H76,"") -> 0 | U76: =IF($H76>=2,$G76/$H76,"") -> 0
F77: 2033 | G77: 0 | H77: =$D$49 -> 20 | U77: =IF($H77>=1,$G77/$H77,"") -> 0
F78: 折旧总额 | L78: =SUM(L66:L77) -> 0 | M78: =SUM(M66:M77) -> 0 | N78: =SUM(N66:N77) -> 0 | O78: =SUM(O66:O77) -> 0 | P78: =SUM(P66:P77) -> 0 | Q78: =SUM(Q66:Q77) -> 0 | R78: =SUM(R66:R77) -> 0 | S78: =SUM(S66:S77) -> 0 | ... U78: =SUM(U66:U77) -> 0
B79: 四、商誉
B80: 期初商誉净额 | F80: =资产负债表!U38 -> 0 | G80: =资产负债表!Y38 -> 0 | H80: =资产负债表!AC38 -> 0 | I80: =资产负债表!AG38 -> 0 | J80: =资产负债表!AH38 -> 0 | K80: =资产负债表!AI38 -> 0 | L80: =H83 -> 0 | M80: =L83 -> 0 | N80: =M83 -> 0 | O80: =N83 -> 0 | P80: =O83 -> 0 | Q80: =P83 -> 0 | R80: =Q83 -> 0 | S80: =R83 -> 0 | T80: =S83 -> 0 | U80: =T83 -> 0
C81: 本期增加 | F81: =F83-F80 -> 0 | G81: =G83-G80 -> 0 | H81: =H83-H80 -> 0 | I81: =IF(财务基础数据!AM4=0,0,I83-I80) -> 0 | J81: =IF(财务基础数据!AM4<=1,0,J83-J80) -> 0 | K81: =IF(财务基础数据!AM4<=2,0,K83-K80) -> 0
C82: 本期减值准备
B83: 期末商誉净额 | F83: =资产负债表!Y38 -> 0 | G83: =资产负债表!AC38 -> 0 | H83: =资产负债表!AG38 -> 0 | I83: =资产负债表!AH38 -> 0 | J83: =资产负债表!AI38 -> 0 | K83: =资产负债表!AJ38 -> 0 | L83: =L80+L81-L82 -> 0 | M83: =M80+M81-M82 -> 0 | N83: =N80+N81-N82 -> 0 | O83: =O80+O81-O82 -> 0 | P83: =P80+P81-P82 -> 0 | Q83: =Q80+Q81-Q82 -> 0 | R83: =R80+R81-R82 -> 0 | S83: =S80+S81-S82 -> 0 | ... U83: =U80+U81-U82 -> 0
B85: 五、长期股权投资
B86: 期初长期股权投资 | F86: =资产负债表!U27 -> 0 | G86: =资产负债表!Y27 -> 0 | H86: =资产负债表!AC27 -> 0 | I86: =资产负债表!AG27 -> 0 | J86: =资产负债表!AH27 -> 0 | K86: =资产负债表!AI27 -> 0 | L86: =H90 -> 0 | M86: =L90 -> 0 | N86: =M90 -> 0 | O86: =N90 -> 0 | P86: =O90 -> 0 | Q86: =P90 -> 0 | R86: =Q90 -> 0 | S86: =R90 -> 0 | T86: =S90 -> 0 | U86: =T90 -> 0
C87: 权益法下确认的投资收益 | V87: 假设此处投资收益不影响现金流
C88: 增加/减少投资 | F88: =F90-F86 -> 0 | G88: =G90-G86 -> 0 | H88: =H90-H86 -> 0 | I88: =IF(财务基础数据!AM4=0,0,I90-I86) -> 0 | J88: =IF(财务基础数据!AM4<=1,0,J90-J86) -> 0 | K88: =IF(财务基础数据!AM4<=2,0,K90-K86) -> 0
C89: 本期减值准备
B90: 期末长期股权投资 | F90: =资产负债表!Y27 -> 0 | G90: =资产负债表!AC27 -> 0 | H90: =资产负债表!AG27 -> 0 | I90: =资产负债表!AH27 -> 0 | J90: =资产负债表!AI27 -> 0 | K90: =资产负债表!AJ27 -> 0 | L90: =L86+L87+L88-L89 -> 0 | M90: =M86+M87+M88-M89 -> 0 | N90: =N86+N87+N88-N89 -> 0 | O90: =O86+O87+O88-O89 -> 0 | P90: =P86+P87+P88-P89 -> 0 | Q90: =Q86+Q87+Q88-Q89 -> 0 | R90: =R86+R87+R88-R89 -> 0 | S90: =S86+S87+S88-S89 -> 0 | ... U90: =U86+U87+U88-U89 -> 0
B92: 六、投资性房地产
B93: 期初投资性房地产 | F93: =资产负债表!U30 -> 0 | G93: =资产负债表!Y30 -> 0 | H93: =资产负债表!AC30 -> 0 | J93: =H101 -> 0 | L93: =H101 -> 0 | M93: =L101 -> 0 | N93: =M101 -> 0 | O93: =N101 -> 0 | P93: =O101 -> 0 | Q93: =P101 -> 0 | R93: =Q101 -> 0 | S93: =R101 -> 0 | T93: =S101 -> 0 | U93: =T101 -> 0
B94: 1.公允价值模式计量
C95: 本期增加
C96: 本期公允价值变动
B97: 2.成本模式计量
C98: 本期增加 | F98: =F101-F93+F99+F100 -> 0 | G98: =G101-G93+G99+G100 -> 0 | H98: =H101-H93+H99+H100 -> 0 | J98: =J101-J93+J99+J100 -> 0
C99: 本期折旧/摊销 | F99: =(财务附注数据!AD11-财务附注数据!Z11)*目录!$D$6 -> 0 | G99: =(财务附注数据!AH11-财务附注数据!AD11)*目录!$D$6 -> 0 | H99: =(财务附注数据!AL11-财务附注数据!AH11)*目录!$D$6 -> 0 | J99: =IF(财务基础数据!AM4<=1,0,(财务附注数据!AN11-财务附注数据!AL11)*目录!$D$6) -> 0
C100: 本期减值准备 | F100: =(财务附注数据!AD12-财务附注数据!Z12)*目录!$D$6 -> 0 | G100: =(财务附注数据!AH12-财务附注数据!AD12)*目录!$D$6 -> 0 | H100: =(财务附注数据!AL12-财务附注数据!AH12)*目录!$D$6 -> 0 | J100: =IF(财务基础数据!AM4<=1,0,(财务附注数据!AN12-财务附注数据!AL12)*目录!$D$6) -> 0
B101: 期末投资性房地产 | F101: =资产负债表!Y30 -> 0 | G101: =资产负债表!AC30 -> 0 | H101: =资产负债表!AG30 -> 0 | I101: =资产负债表!AH30 -> 0 | J101: =资产负债表!AI30 -> 0 | K101: =资产负债表!AJ30 -> 0 | L101: =L93+L95+L96+L98-L99-L100 -> 0 | M101: =M93+M95+M96+M98-M99-M100 -> 0 | N101: =N93+N95+N96+N98-N99-N100 -> 0 | O101: =O93+O95+O96+O98-O99-O100 -> 0 | P101: =P93+P95+P96+P98-P99-P100 -> 0 | Q101: =Q93+Q95+Q96+Q98-Q99-Q100 -> 0 | R101: =R93+R95+R96+R98-R99-R100 -> 0 | S101: =S93+S95+S96+S98-S99-S100 -> 0 | ... U101: =U93+U95+U96+U98-U99-U100 -> 0
B103: 七、使用权资产
B104: 假设： | C104: 预计使用寿命 | D104: 5
B106: 原值： | C106: 期初 | F106: =财务附注数据!Z18*目录!$D$6 -> 0 | G106: =财务附注数据!AD18*目录!$D$6 -> 0 | H106: =财务附注数据!AH18*目录!$D$6 -> 0 | J106: =H108 -> 0 | L106: =H108 -> 0 | M106: =L108 -> 0 | N106: =M108 -> 0 | O106: =N108 -> 0 | P106: =O108 -> 0 | Q106: =P108 -> 0 | R106: =Q108 -> 0 | S106: =R108 -> 0 | T106: =S108 -> 0 | U106: =T108 -> 0
C107: 本期增加 | F107: =F108-F106 -> 0 | G107: =G108-G106 -> 0 | H107: =H108-H106 -> 0 | J107: =IF(财务基础数据!AM4<=1,0,J108-J106) -> 0
C108: 期末 | F108: =财务附注数据!AD18*目录!$D$6 -> 0 | G108: =财务附注数据!AH18*目录!$D$6 -> 0 | H108: =财务附注数据!AL18*目录!$D$6 -> 0 | J108: =财务附注数据!AN18*目录!$D$6 -> 0 | L108: =L106+L107 -> 0 | M108: =M106+M107 -> 0 | N108: =N106+N107 -> 0 | O108: =O106+O107 -> 0 | P108: =P106+P107 -> 0 | Q108: =Q106+Q107 -> 0 | R108: =R106+R107 -> 0 | S108: =S106+S107 -> 0 | ... U108: =U106+U107 -> 0
B110: 本期计提折旧： | F110: =IF(财务基础数据!AD282=0,财务附注数据!AD19*目录!$D$6-财务附注数据!Z19*目录!$D$6,财务基础数据!AD282*目录!$D$6) -> 0 | G110: =IF(财务基础数据!AH282=0,财务附注数据!AH19*目录!$D$6-财务附注数据!AD19*目录!$D$6,财务基础数据!AH282*目录!$D$6) -> 0 | H110: =IF(财务基础数据!AL282=0,财务附注数据!AL19*目录!$D$6-财务附注数据!AH19*目录!$D$6,财务基础数据!AL282*目录!$D$6) -> 0 | J110: =IF(财务基础数据!AN282=0,财务附注数据!AN19*目录!$D$6-财务附注数据!AL19*目录!$D$6,财务基础数据!AN282*目录!$D$6) -> 0 | L110: =L133 -> 0 | M110: =M133 -> 0 | N110: =N133 -> 0 | O110: =O133 -> 0 | P110: =P133 -> 0 | Q110: =Q133 -> 0 | R110: =R133 -> 0 | S110: =S133 -> 0 | ... U110: =U133 -> 0
C111: 折旧率% | D111: 0 | F111: =IF(ISERROR(F110/F106),0,F110/F106) -> 0 | G111: =IF(ISERROR(G110/G106),0,G110/G106) -> 0 | H111: =IF(ISERROR(H110/H106),0,H110/H106) -> 0 | J111: =IF(ISERROR(J110/J106*2),0,J110/J106*2) -> 0 | L111: =$D$111 -> 0 | M111: =$D$111 -> 0 | N111: =$D$111 -> 0 | O111: =$D$111 -> 0 | P111: =$D$111 -> 0 | Q111: =$D$111 -> 0 | R111: =$D$111 -> 0 | S111: =$D$111 -> 0 | ... U111: =$D$111 -> 0
B113: 减值： | C113: 期初 | F113: =财务附注数据!Z20*目录!$D$6 -> 0 | G113: =财务附注数据!AD20*目录!$D$6 -> 0 | H113: =财务附注数据!AH20*目录!$D$6 -> 0 | J113: =H115 -> 0 | L113: =H115 -> 0 | M113: =L115 -> 0 | N113: =M115 -> 0 | O113: =N115 -> 0 | P113: =O115 -> 0 | Q113: =P115 -> 0 | R113: =Q115 -> 0 | S113: =R115 -> 0 | T113: =S115 -> 0 | U113: =T115 -> 0
C114: 本期增加 | F114: =F115-F113 -> 0 | G114: =G115-G113 -> 0 | H114: =H115-H113 -> 0 | J114: =IF(财务基础数据!AM4<=1,0,J115-J113) -> 0
C115: 期末 | F115: =财务附注数据!AD20*目录!$D$6 -> 0 | G115: =财务附注数据!AH20*目录!$D$6 -> 0 | H115: =财务附注数据!AL20*目录!$D$6 -> 0 | J115: =财务附注数据!AN20*目录!$D$6 -> 0 | L115: =L113+L114 -> 0 | M115: =M113+M114 -> 0 | N115: =N113+N114 -> 0 | O115: =O113+O114 -> 0 | P115: =P113+P114 -> 0 | Q115: =Q113+Q114 -> 0 | R115: =R113+R114 -> 0 | S115: =S113+S114 -> 0 | ... U115: =U113+U114 -> 0
B117: 期初使用权资产净额 | F117: =资产负债表!U35 -> 0 | G117: =资产负债表!Y35 -> 0 | H117: =资产负债表!AC35 -> 0 | L117: =H118 -> 0 | M117: =L118 -> 0 | N117: =M118 -> 0 | O117: =N118 -> 0 | P117: =O118 -> 0 | Q117: =P118 -> 0 | R117: =Q118 -> 0 | S117: =R118 -> 0 | T117: =S118 -> 0 | U117: =T118 -> 0
B118: 期末使用权资产净额 | F118: =资产负债表!Y35 -> 0 | G118: =资产负债表!AC35 -> 0 | H118: =资产负债表!AG35 -> 0 | I118: =资产负债表!AH35 -> 0 | J118: =资产负债表!AI35 -> 0 | K118: =资产负债表!AJ35 -> 0 | L118: =H118+L107-L110-L114 -> 0 | M118: =L118+M107-M110-M114 -> 0 | N118: =M118+N107-N110-N114 -> 0 | O118: =N118+O107-O110-O114 -> 0 | P118: =O118+P107-P110-P114 -> 0 | Q118: =P118+Q107-Q110-Q114 -> 0 | R118: =Q118+R107-R110-R114 -> 0 | S118: =R118+S107-S110-S114 -> 0 | T118: =S118+T107-T110-T114 -> 0 | U118: =T118+U107-U110-U114 -> 0
F120: 原有资产 | G120: 期末净额 | H120: 期末原值 | L120: =L4 -> 2024E | M120: =M4 -> 2025 | N120: =N4 -> 2026 | O120: =O4 -> 2027 | P120: =P4 -> 2028 | Q120: =Q4 -> 2029 | R120: =R4 -> 2030 | S120: =S4 -> 2031 | ... U120: =U4 -> 2033
G121: =H118 -> 0 | H121: =H108 -> 0 | L121: =IF(SUM($K$121:K121)=$G$121,0,IF($G$121-SUM($K$121:K121)<$H$121*L111,$G$121-SUM($K$121:K121),$H$121*L111)) -> 0 | M121: =IF(SUM($K$121:L121)=$G$121,0,IF($G$121-SUM($K$121:L121)<$H$121*M111,$G$121-SUM($K$121:L121),$H$121*M111)) -> 0 | N121: =IF(SUM($K$121:M121)=$G$121,0,IF($G$121-SUM($K$121:M121)<$H$121*N111,$G$121-SUM($K$121:M121),$H$121*N111)) -> 0 | O121: =IF(SUM($K$121:N121)=$G$121,0,IF($G$121-SUM($K$121:N121)<$H$121*O111,$G$121-SUM($K$121:N121),$H$121*O111)) -> 0 | P121: =IF(SUM($K$121:O121)=$G$121,0,IF($G$121-SUM($K$121:O121)<$H$121*P111,$G$121-SUM($K$121:O121),$H$121*P111)) -> 0 | Q121: =IF(SUM($K$121:P121)=$G$121,0,IF($G$121-SUM($K$121:P121)<$H$121*Q111,$G$121-SUM($K$121:P121),$H$121*Q111)) -> 0 | R121: =IF(SUM($K$121:Q121)=$G$121,0,IF($G$121-SUM($K$121:Q121)<$H$121*R111,$G$121-SUM($K$121:Q121),$H$121*R111)) -> 0 | S121: =IF(SUM($K$121:R121)=$G$121,0,IF($G$121-SUM($K$121:R121)<$H$121*S111,$G$121-SUM($K$121:R121),$H$121*S111)) -> 0 | ... U121: =IF(SUM($K$121:T121)=$G$121,0,IF($G$121-SUM($K$121:T121)<$H$121*U111,$G$121-SUM($K$121:T121),$H$121*U111)) -> 0
G122: 新增资产 | H122: 使用年限
...

Sheet 主要财务摘要
B1: =财务基础数据!C4 -> XXXX | C1: =财务基础数据!A4 -> XXXX | G1: 每股转换比例： | H1: 1
B2: 公司基本情况
B3: 项 目 | C3: =资产负债表!Y4 -> 2021 | D3: =资产负债表!AC4 -> 2022 | E3: =资产负债表!AG4 -> 2023 | F3: =资产负债表!AK4 -> 2024E | G3: =资产负债表!AL4&"E" -> 2025E | H3: =资产负债表!AM4&"E" -> 2026E
B4: ="股本（"&目录!$D$8&"）" -> 股本（百万） | C4: =IF(ISERROR(财务基础数据!AD290*目录!D6),目录!F7*1000000*目录!D6,财务基础数据!AD290*目录!D6) -> 0 | D4: =IF(ISERROR(财务基础数据!AH290*目录!D6),目录!F7*1000000*目录!D6,财务基础数据!AH290*目录!D6) -> 0 | E4: =IF(ISERROR(财务基础数据!AL290*目录!D6),目录!F7*1000000*目录!D6,财务基础数据!AL290*目录!D6) -> 0 | F4: =IF(ISERROR(目录!F7*1000000*目录!D6),"—",目录!F7*1000000*目录!D6) -> — | G4: =F4 -> — | H4: =G4 -> —
B5: 收盘价 | F5: =目录!F6 -> XXXX | G5: =F5 -> XXXX | H5: =G5 -> XXXX
B6: EV/EBITDA | C6: =IF(ISERROR(((C4*C5)+资产负债表!$Y$103-资产负债表!$Y$8)/利润表!Y42),"—",((C4*C5)+资产负债表!$Y$103-资产负债表!$Y$8)/利润表!Y42) -> — | D6: =IF(ISERROR(((D4*D5)+资产负债表!$AC$103-资产负债表!$AC$8)/利润表!AC42),"—",((D4*D5)+资产负债表!$AC$103-资产负债表!$AC$8)/利润表!AC42) -> — | E6: =IF(ISERROR(((E4*E5)+资产负债表!$AG$103-资产负债表!$AG$8)/利润表!AG42),"—",((E4*E5)+资产负债表!$AG$103-资产负债表!$AG$8)/利润表!AG42) -> — | F6: =IF(ISERROR(((F4*F5)+资产负债表!$AK$103-资产负债表!$AK$8)/利润表!AK42),"—",((F4*F5)+资产负债表!$AK$103-资产负债表!$AK$8)/利润表!AK42) -> — | G6: =IF(ISERROR(((G4*G5)+资产负债表!$AL$103-资产负债表!$AL$8)/利润表!AL42),"—",((G4*G5)+资产负债表!$AL$103-资产负债表!$AL$8)/利润表!AL42) -> — | H6: =IF(ISERROR(((H4*H5)+资产负债表!$AM$103-资产负债表!$AM$8)/利润表!AM42),"—",((H4*H5)+资产负债表!$AM$103-资产负债表!$AM$8)/利润表!AM42) -> —
B7: EV/销售收入 | C7: =IF(ISERROR(((C4*C5)+资产负债表!$Y$103-资产负债表!$Y$8)/利润表!Y8),"—",((C4*C5)+资产负债表!$Y$103-资产负债表!$Y$8)/利润表!Y8) -> — | D7: =IF(ISERROR(((D4*D5)+资产负债表!$AC$103-资产负债表!$AC$8)/利润表!AC8),"—",((D4*D5)+资产负债表!$AC$103-资产负债表!$AC$8)/利润表!AC8) -> — | E7: =IF(ISERROR(((E4*E5)+资产负债表!$AG$103-资产负债表!$AG$8)/利润表!AG8),"—",((E4*E5)+资产负债表!$AG$103-资产负债表!$AG$8)/利润表!AG8) -> — | F7: =IF(ISERROR(((F4*F5)+资产负债表!$AK$103-资产负债表!$AK$8)/利润表!AK8),"—",((F4*F5)+资产负债表!$AK$103-资产负债表!$AK$8)/利润表!AK8) -> — | G7: =IF(ISERROR(((G4*G5)+资产负债表!$AL$103-资产负债表!$AL$8)/利润表!AL8),"—",((G4*G5)+资产负债表!$AL$103-资产负债表!$AL$8)/利润表!AL8) -> — | H7: =IF(ISERROR(((H4*H5)+资产负债表!$AM$103-资产负债表!$AM$8)/利润表!AM8),"—",((H4*H5)+资产负债表!$AM$103-资产负债表!$AM$8)/利润表!AM8) -> —
B8: 营业总收入增长率 | C8: =利润表!Y7 -> — | D8: =利润表!AC7 -> — | E8: =利润表!AG7 -> — | F8: =利润表!AK7 -> — | G8: =利润表!AL7 -> — | H8: =利润表!AM7 -> —
B9: 归母净利润增长率 | C9: =利润表!Y96 -> — | D9: =利润表!AC96 -> — | E9: =利润表!AG96 -> — | F9: =利润表!AK96 -> — | G9: =利润表!AL96 -> — | H9: =利润表!AM96 -> —
B10: 净资产收益率ROE | C10: =财务分析!E5 -> — | D10: =财务分析!F5 -> — | E10: =财务分析!G5 -> — | F10: =财务分析!H5 -> — | G10: =财务分析!I5 -> — | H10: =财务分析!J5 -> —
B11: 总资产收益率ROA | C11: =财务分析!E7 -> — | D11: =财务分析!F7 -> — | E11: =财务分析!G7 -> — | F11: =财务分析!H7 -> — | G11: =财务分析!I7 -> — | H11: =财务分析!J7 -> —
B13: 每股指标（历史）
B14: 每股收益EPS | C14: =IF(ISERROR(财务基础数据!AD41),"—",财务基础数据!AD41) -> 0 | D14: =IF(ISERROR(财务基础数据!AH41),"—",财务基础数据!AH41) -> 0 | E14: =IF(ISERROR(财务基础数据!AL41),"—",财务基础数据!AL41) -> 0 | F14: =IF(ISERROR(利润表!AK94/F4),"—",利润表!AK94/F4) -> — | G14: =IF(ISERROR(利润表!AL94/G4),"—",利润表!AL94/G4) -> — | H14: =IF(ISERROR(利润表!AM94/H4),"—",利润表!AM94/H4) -> —
B15: 每股净资产 | C15: =IF(ISERROR(资产负债表!Y89/C4),"—",资产负债表!Y89/C4) -> — | D15: =IF(ISERROR(资产负债表!AC89/D4),"—",资产负债表!AC89/D4) -> — | E15: =IF(ISERROR(资产负债表!AG89/E4),"—",资产负债表!AG89/E4) -> — | F15: =IF(ISERROR(资产负债表!AK89/F4),"—",资产负债表!AK89/F4) -> — | G15: =IF(ISERROR(资产负债表!AL89/G4),"—",资产负债表!AL89/G4) -> — | H15: =IF(ISERROR(资产负债表!AM89/H4),"—",资产负债表!AM89/H4) -> —
B16: 市盈率PE | C16: =IF(OR(ISERROR(C5/C14*$H$1),C14<0),"—",C5/C14*$H$1) -> — | D16: =IF(OR(ISERROR(D5/D14*$H$1),D14<0),"—",D5/D14*$H$1) -> — | E16: =IF(OR(ISERROR(E5/E14*$H$1),E14<0),"—",E5/E14*$H$1) -> — | F16: =IF(OR(ISERROR(F5/F14*$H$1),F14<0),"—",F5/F14*$H$1) -> — | G16: =IF(OR(ISERROR(G5/G14*$H$1),G14<0),"—",G5/G14*$H$1) -> — | H16: =IF(OR(ISERROR(H5/H14*$H$1),H14<0),"—",H5/H14*$H$1) -> —
B17: 市净率PB | C17: =IF(ISERROR(C5/C15*$H$1),"—",C5/C15*$H$1) -> — | D17: =IF(ISERROR(D5/D15*$H$1),"—",D5/D15*$H$1) -> — | E17: =IF(ISERROR(E5/E15*$H$1),"—",E5/E15*$H$1) -> — | F17: =IF(ISERROR(F5/F15*$H$1),"—",F5/F15*$H$1) -> — | G17: =IF(ISERROR(G5/G15*$H$1),"—",G5/G15*$H$1) -> — | H17: =IF(ISERROR(H5/H15*$H$1),"—",H5/H15*$H$1) -> —
B18: PE/G | C18: =IF(OR(ISERROR(C16/(C9*100)),C9<0),"—",C16/(C9*100)) -> — | D18: =IF(OR(ISERROR(D16/(D9*100)),D9<0),"—",D16/(D9*100)) -> — | E18: =IF(OR(ISERROR(E16/(E9*100)),E9<0),"—",E16/(E9*100)) -> — | F18: =IF(OR(ISERROR(F16/(F9*100)),F9<0),"—",F16/(F9*100)) -> — | G18: =IF(OR(ISERROR(G16/(G9*100)),G9<0),"—",G16/(G9*100)) -> — | H18: =IF(OR(ISERROR(H16/(H9*100)),H9<0),"—",H16/(H9*100)) -> —
B19: 每股经营性现金流 | C19: =IF(ISERROR(现金流量表!Y36/C4),"—",现金流量表!Y36/C4) -> — | D19: =IF(ISERROR(现金流量表!AC36/D4),"—",现金流量表!AC36/D4) -> — | E19: =IF(ISERROR(现金流量表!AG36/E4),"—",现金流量表!AG36/E4) -> — | F19: =IF(ISERROR(现金流量表!AK36/F4),"—",现金流量表!AK36/F4) -> — | G19: =IF(ISERROR(现金流量表!AL36/G4),"—",现金流量表!AL36/G4) -> — | H19: =IF(ISERROR(现金流量表!AM36/H4),"—",现金流量表!AM36/H4) -> —
B20: 市销率PS | C20: =IF(ISERROR(C4*C5/利润表!Y8*$H$1),"—",C4*C5/利润表!Y8*$H$1) -> — | D20: =IF(ISERROR(D4*D5/利润表!AC8*$H$1),"—",D4*D5/利润表!AC8*$H$1) -> — | E20: =IF(ISERROR(E4*E5/利润表!AG8*$H$1),"—",E4*E5/利润表!AG8*$H$1) -> — | F20: =IF(ISERROR(F4*F5/利润表!AK8*$H$1),"—",F4*F5/利润表!AK8*$H$1) -> — | G20: =IF(ISERROR(G4*G5/利润表!AL8*$H$1),"—",G4*G5/利润表!AL8*$H$1) -> — | H20: =IF(ISERROR(H4*H5/利润表!AM8*$H$1),"—",H4*H5/利润表!AM8*$H$1) -> —
B22: 每股指标（摊薄）
B23: 每股收益EPS | C23: =IF(ISERROR(利润表!Y94/F4),"—",利润表!Y94/F4) -> — | D23: =IF(ISERROR(利润表!AC94/F4),"—",利润表!AC94/F4) -> — | E23: =IF(ISERROR(利润表!AG94/F4),"—",利润表!AG94/F4) -> — | F23: =IF(ISERROR(利润表!AK94/F4),"—",利润表!AK94/F4) -> — | G23: =IF(ISERROR(利润表!AL94/G4),"—",利润表!AL94/G4) -> — | H23: =IF(ISERROR(利润表!AM94/H4),"—",利润表!AM94/H4) -> —
B24: 每股净资产 | C24: =IF(ISERROR(资产负债表!Y89/F4),"—",资产负债表!Y89/F4) -> — | D24: =IF(ISERROR(资产负债表!AC89/F4),"—",资产负债表!AC89/F4) -> — | E24: =IF(ISERROR(资产负债表!AG89/F4),"—",资产负债表!AG89/F4) -> — | F24: =IF(ISERROR(资产负债表!AK89/F4),"—",资产负债表!AK89/F4) -> — | G24: =IF(ISERROR(资产负债表!AL89/G4),"—",资产负债表!AL89/G4) -> — | H24: =IF(ISERROR(资产负债表!AM89/H4),"—",资产负债表!AM89/H4) -> —
B25: 市盈率PE | C25: =IF(OR(ISERROR(目录!$F$6/C23*$H$1),C23<0),"—",目录!$F$6/C23*$H$1) -> — | D25: =IF(OR(ISERROR(目录!$F$6/D23*$H$1),D23<0),"—",目录!$F$6/D23*$H$1) -> — | E25: =IF(OR(ISERROR(目录!$F$6/E23*$H$1),E23<0),"—",目录!$F$6/E23*$H$1) -> — | F25: =IF(OR(ISERROR(目录!$F$6/F23*$H$1),F23<0),"—",目录!$F$6/F23*$H$1) -> — | G25: =IF(OR(ISERROR(目录!$F$6/G23*$H$1),G23<0),"—",目录!$F$6/G23*$H$1) -> — | H25: =IF(OR(ISERROR(目录!$F$6/H23*$H$1),H23<0),"—",目录!$F$6/H23*$H$1) -> —
B26: 市净率PB | C26: =IF(ISERROR(目录!$F$6/C24*$H$1),"—",目录!$F$6/C24*$H$1) -> — | D26: =IF(ISERROR(目录!$F$6/D24*$H$1),"—",目录!$F$6/D24*$H$1) -> — | E26: =IF(ISERROR(目录!$F$6/E24*$H$1),"—",目录!$F$6/E24*$H$1) -> — | F26: =IF(ISERROR(目录!$F$6/F24*$H$1),"—",目录!$F$6/F24*$H$1) -> — | G26: =IF(ISERROR(目录!$F$6/G24*$H$1),"—",目录!$F$6/G24*$H$1) -> — | H26: =IF(ISERROR(目录!$F$6/H24*$H$1),"—",目录!$F$6/H24*$H$1) -> —
B27: PE/G | C27: =IF(OR(ISERROR(C25/(C9*100)),C9<0),"—",C25/(C9*100)) -> — | D27: =IF(OR(ISERROR(D25/(D9*100)),D9<0),"—",D25/(D9*100)) -> — | E27: =IF(OR(ISERROR(E25/(E9*100)),E9<0),"—",E25/(E9*100)) -> — | F27: =IF(OR(ISERROR(F25/(F9*100)),F9<0),"—",F25/(F9*100)) -> — | G27: =IF(OR(ISERROR(G25/(G9*100)),G9<0),"—",G25/(G9*100)) -> — | H27: =IF(OR(ISERROR(H25/(H9*100)),H9<0),"—",H25/(H9*100)) -> —
B28: 每股经营性现金流 | C28: =IF(ISERROR(现金流量表!Y36/F4),"—",现金流量表!Y36/F4) -> — | D28: =IF(ISERROR(现金流量表!AC36/F4),"—",现金流量表!AC36/F4) -> — | E28: =IF(ISERROR(现金流量表!AG36/F4),"—",现金流量表!AG36/F4) -> — | F28: =IF(ISERROR(现金流量表!AK36/F4),"—",现金流量表!AK36/F4) -> — | G28: =IF(ISERROR(现金流量表!AL36/G4),"—",现金流量表!AL36/G4) -> — | H28: =IF(ISERROR(现金流量表!AM36/H4),"—",现金流量表!AM36/H4) -> —
B29: 市销率PS | C29: =IF(ISERROR($F$4*$F$5/利润表!Y8*$H$1),"—",$F$4*$F$5/利润表!Y8*$H$1) -> — | D29: =IF(ISERROR($F$4*$F$5/利润表!AC8*$H$1),"—",$F$4*$F$5/利润表!AC8*$H$1) -> — | E29: =IF(ISERROR($F$4*$F$5/利润表!AG8*$H$1),"—",$F$4*$F$5/利润表!AG8*$H$1) -> — | F29: =IF(ISERROR($F$4*$F$5/利润表!AK8*$H$1),"—",$F$4*$F$5/利润表!AK8*$H$1) -> — | G29: =IF(ISERROR($F$4*$F$5/利润表!AL8*$H$1),"—",$F$4*$F$5/利润表!AL8*$H$1) -> — | H29: =IF(ISERROR($F$4*$F$5/利润表!AM8*$H$1),"—",$F$4*$F$5/利润表!AM8*$H$1) -> —

Sheet 报表摘要
B2: ="利润表(人民币"&目录!$D$5&")" -> 利润表(人民币百万元) | C2: =资产负债表!Y4 -> 2021 | D2: =资产负债表!AC4 -> 2022 | E2: =资产负债表!AG4 -> 2023 | F2: =资产负债表!AK4 -> 2024E | G2: =资产负债表!AL4 -> 2025 | H2: =资产负债表!AM4 -> 2026 | J2: ="资产负债表(人民币"&目录!$D$5&")" -> 资产负债表(人民币百万元) | K2: =C2 -> 2021 | L2: =D2 -> 2022 | M2: =E2 -> 2023 | N2: =F2 -> 2024E | O2: =G2 -> 2025 | P2: =H2 -> 2026
B3: 营业总收入 | C3: =IF(ISERROR(利润表!Y6),"—",利润表!Y6) -> 0 | D3: =IF(ISERROR(利润表!AC6),"—",利润表!AC6) -> 0 | E3: =IF(ISERROR(利润表!AG6),"—",利润表!AG6) -> 0 | F3: =IF(ISERROR(利润表!AK6),"—",利润表!AK6) -> 0 | G3: =IF(ISERROR(利润表!AL6),"—",利润表!AL6) -> 0 | H3: =IF(ISERROR(利润表!AM6),"—",利润表!AM6) -> 0 | J3: 货币资金 | K3: =IF(ISERROR(资产负债表!Y8),"—",资产负债表!Y8) -> 0 | L3: =IF(ISERROR(资产负债表!AC8),"—",资产负债表!AC8) -> 0 | M3: =IF(ISERROR(资产负债表!AG8),"—",资产负债表!AG8) -> 0 | N3: =IF(ISERROR(资产负债表!AK8),"—",资产负债表!AK8) -> 0 | O3: =IF(ISERROR(资产负债表!AL8),"—",资产负债表!AL8) -> 0 | P3: =IF(ISERROR(资产负债表!AM8),"—",资产负债表!AM8) -> 0
B4: %增长率 | C4: =IF(ISERROR(利润表!Y7),"—",利润表!Y7) -> — | D4: =IF(ISERROR(利润表!AC7),"—",利润表!AC7) -> — | E4: =IF(ISERROR(利润表!AG7),"—",利润表!AG7) -> — | F4: =IF(ISERROR(利润表!AK7),"—",利润表!AK7) -> — | G4: =IF(ISERROR(利润表!AL7),"—",利润表!AL7) -> — | H4: =IF(ISERROR(利润表!AM7),"—",利润表!AM7) -> — | J4: 应收票据 | K4: =IF(ISERROR(资产负债表!Y11),"—",资产负债表!Y11) -> 0 | L4: =IF(ISERROR(资产负债表!AC11),"—",资产负债表!AC11) -> 0 | M4: =IF(ISERROR(资产负债表!AG11),"—",资产负债表!AG11) -> 0 | N4: =IF(ISERROR(资产负债表!AK11),"—",资产负债表!AK11) -> 0 | O4: =IF(ISERROR(资产负债表!AL11),"—",资产负债表!AL11) -> 0 | P4: =IF(ISERROR(资产负债表!AM11),"—",资产负债表!AM11) -> 0
B5: 营业成本 | C5: =IF(ISERROR(利润表!Y15+利润表!Y19),"—",利润表!Y15+利润表!Y19) -> 0 | D5: =IF(ISERROR(利润表!AC15+利润表!AC19),"—",利润表!AC15+利润表!AC19) -> 0 | E5: =IF(ISERROR(利润表!AG15+利润表!AG19),"—",利润表!AG15+利润表!AG19) -> 0 | F5: =IF(ISERROR(利润表!AK15+利润表!AK19),"—",利润表!AK15+利润表!AK19) -> 0 | G5: =IF(ISERROR(利润表!AL15+利润表!AL19),"—",利润表!AL15+利润表!AL19) -> 0 | H5: =IF(ISERROR(利润表!AM15+利润表!AM19),"—",利润表!AM15+利润表!AM19) -> 0 | J5: 应收账款 | K5: =IF(ISERROR(资产负债表!Y12),"—",资产负债表!Y12) -> 0 | L5: =IF(ISERROR(资产负债表!AC12),"—",资产负债表!AC12) -> 0 | M5: =IF(ISERROR(资产负债表!AG12),"—",资产负债表!AG12) -> 0 | N5: =IF(ISERROR(资产负债表!AK12),"—",资产负债表!AK12) -> 0 | O5: =IF(ISERROR(资产负债表!AL12),"—",资产负债表!AL12) -> 0 | P5: =IF(ISERROR(资产负债表!AM12),"—",资产负债表!AM12) -> 0
B6: %营业收入 | C6: =IF(ISERROR(利润表!Y17+利润表!Y20),"—",利润表!Y17+利润表!Y20) -> — | D6: =IF(ISERROR(利润表!AC17+利润表!AC20),"—",利润表!AC17+利润表!AC20) -> — | E6: =IF(ISERROR(利润表!AG17+利润表!AG20),"—",利润表!AG17+利润表!AG20) -> — | F6: =IF(ISERROR(利润表!AK17+利润表!AK20),"—",利润表!AK17+利润表!AK20) -> — | G6: =IF(ISERROR(利润表!AL17+利润表!AL20),"—",利润表!AL17+利润表!AL20) -> — | H6: =IF(ISERROR(利润表!AM17+利润表!AM20),"—",利润表!AM17+利润表!AM20) -> — | J6: 其他应收款 | K6: =IF(ISERROR(资产负债表!Y15),"—",资产负债表!Y15) -> 0 | L6: =IF(ISERROR(资产负债表!AC15),"—",资产负债表!AC15) -> 0 | M6: =IF(ISERROR(资产负债表!AG15),"—",资产负债表!AG15) -> 0 | N6: =IF(ISERROR(资产负债表!AK15),"—",资产负债表!AK15) -> 0 | O6: =IF(ISERROR(资产负债表!AL15),"—",资产负债表!AL15) -> 0 | P6: =IF(ISERROR(资产负债表!AM15),"—",资产负债表!AM15) -> 0
B7: 毛利 | C7: =IF(ISERROR(利润表!Y22),"—",利润表!Y22) -> 0 | D7: =IF(ISERROR(利润表!AC22),"—",利润表!AC22) -> 0 | E7: =IF(ISERROR(利润表!AG22),"—",利润表!AG22) -> 0 | F7: =IF(ISERROR(利润表!AK22),"—",利润表!AK22) -> 0 | G7: =IF(ISERROR(利润表!AL22),"—",利润表!AL22) -> 0 | H7: =IF(ISERROR(利润表!AM22),"—",利润表!AM22) -> 0 | J7: 存货 | K7: =IF(ISERROR(资产负债表!Y16),"—",资产负债表!Y16) -> 0 | L7: =IF(ISERROR(资产负债表!AC16),"—",资产负债表!AC16) -> 0 | M7: =IF(ISERROR(资产负债表!AG16),"—",资产负债表!AG16) -> 0 | N7: =IF(ISERROR(资产负债表!AK16),"—",资产负债表!AK16) -> 0 | O7: =IF(ISERROR(资产负债表!AL16),"—",资产负债表!AL16) -> 0 | P7: =IF(ISERROR(资产负债表!AM16),"—",资产负债表!AM16) -> 0
B8: %营业收入 | C8: =IF(ISERROR(利润表!Y23),"—",利润表!Y23) -> — | D8: =IF(ISERROR(利润表!AC23),"—",利润表!AC23) -> — | E8: =IF(ISERROR(利润表!AG23),"—",利润表!AG23) -> — | F8: =IF(ISERROR(利润表!AK23),"—",利润表!AK23) -> — | G8: =IF(ISERROR(利润表!AL23),"—",利润表!AL23) -> — | H8: =IF(ISERROR(利润表!AM23),"—",利润表!AM23) -> — | J8: 其他流动资产 | K8: =IF(ISERROR(K9-K3-K4-K5-K6-K7),"—",K9-K3-K4-K5-K6-K7) -> 0 | L8: =IF(ISERROR(L9-L3-L4-L5-L6-L7),"—",L9-L3-L4-L5-L6-L7) -> 0 | M8: =IF(ISERROR(M9-M3-M4-M5-M6-M7),"—",M9-M3-M4-M5-M6-M7) -> 0 | N8: =IF(ISERROR(N9-N3-N4-N5-N6-N7),"—",N9-N3-N4-N5-N6-N7) -> 0 | O8: =IF(ISERROR(O9-O3-O4-O5-O6-O7),"—",O9-O3-O4-O5-O6-O7) -> 0 | P8: =IF(ISERROR(P9-P3-P4-P5-P6-P7),"—",P9-P3-P4-P5-P6-P7) -> 0
B9: 税金及附加 | C9: =IF(ISERROR(利润表!Y27),"—",利润表!Y27) -> 0 | D9: =IF(ISERROR(利润表!AC27),"—",利润表!AC27) -> 0 | E9: =IF(ISERROR(利润表!AG27),"—",利润表!AG27) -> 0 | F9: =IF(ISERROR(利润表!AK27),"—",利润表!AK27) -> 0 | G9: =IF(ISERROR(利润表!AL27),"—",利润表!AL27) -> 0 | H9: =IF(ISERROR(利润表!AM27),"—",利润表!AM27) -> 0 | J9: 流动资产 | K9: =IF(ISERROR(资产负债表!Y21),"—",资产负债表!Y21) -> 0 | L9: =IF(ISERROR(资产负债表!AC21),"—",资产负债表!AC21) -> 0 | M9: =IF(ISERROR(资产负债表!AG21),"—",资产负债表!AG21) -> 0 | N9: =IF(ISERROR(资产负债表!AK21),"—",资产负债表!AK21) -> 0 | O9: =IF(ISERROR(资产负债表!AL21),"—",资产负债表!AL21) -> 0 | P9: =IF(ISERROR(资产负债表!AM21),"—",资产负债表!AM21) -> 0
B10: %营业收入 | C10: =IF(ISERROR(利润表!Y28),"—",利润表!Y28) -> — | D10: =IF(ISERROR(利润表!AC28),"—",利润表!AC28) -> — | E10: =IF(ISERROR(利润表!AG28),"—",利润表!AG28) -> — | F10: =IF(ISERROR(利润表!AK28),"—",利润表!AK28) -> — | G10: =IF(ISERROR(利润表!AL28),"—",利润表!AL28) -> — | H10: =IF(ISERROR(利润表!AM28),"—",利润表!AM28) -> — | J10: 长期股权投资 | K10: =IF(ISERROR(资产负债表!Y27),"—",资产负债表!Y27) -> 0 | L10: =IF(ISERROR(资产负债表!AC27),"—",资产负债表!AC27) -> 0 | M10: =IF(ISERROR(资产负债表!AG27),"—",资产负债表!AG27) -> 0 | N10: =IF(ISERROR(资产负债表!AK27),"—",资产负债表!AK27) -> 0 | O10: =IF(ISERROR(资产负债表!AL27),"—",资产负债表!AL27) -> 0 | P10: =IF(ISERROR(资产负债表!AM27),"—",资产负债表!AM27) -> 0
B11: 销售费用 | C11: =IF(ISERROR(利润表!Y29),"—",利润表!Y29) -> 0 | D11: =IF(ISERROR(利润表!AC29),"—",利润表!AC29) -> 0 | E11: =IF(ISERROR(利润表!AG29),"—",利润表!AG29) -> 0 | F11: =IF(ISERROR(利润表!AK29),"—",利润表!AK29) -> 0 | G11: =IF(ISERROR(利润表!AL29),"—",利润表!AL29) -> 0 | H11: =IF(ISERROR(利润表!AM29),"—",利润表!AM29) -> 0 | J11: 固定资产 | K11: =IF(ISERROR(资产负债表!Y31),"—",资产负债表!Y31) -> 0 | L11: =IF(ISERROR(资产负债表!AC31),"—",资产负债表!AC31) -> 0 | M11: =IF(ISERROR(资产负债表!AG31),"—",资产负债表!AG31) -> 0 | N11: =IF(ISERROR(资产负债表!AK31),"—",资产负债表!AK31) -> 0 | O11: =IF(ISERROR(资产负债表!AL31),"—",资产负债表!AL31) -> 0 | P11: =IF(ISERROR(资产负债表!AM31),"—",资产负债表!AM31) -> 0
B12: %营业收入 | C12: =IF(ISERROR(利润表!Y30),"—",利润表!Y30) -> — | D12: =IF(ISERROR(利润表!AC30),"—",利润表!AC30) -> — | E12: =IF(ISERROR(利润表!AG30),"—",利润表!AG30) -> — | F12: =IF(ISERROR(利润表!AK30),"—",利润表!AK30) -> — | G12: =IF(ISERROR(利润表!AL30),"—",利润表!AL30) -> — | H12: =IF(ISERROR(利润表!AM30),"—",利润表!AM30) -> — | J12: 在建工程 | K12: =IF(ISERROR(资产负债表!Y32),"—",资产负债表!Y32) -> 0 | L12: =IF(ISERROR(资产负债表!AC32),"—",资产负债表!AC32) -> 0 | M12: =IF(ISERROR(资产负债表!AG32),"—",资产负债表!AG32) -> 0 | N12: =IF(ISERROR(资产负债表!AK32),"—",资产负债表!AK32) -> 0 | O12: =IF(ISERROR(资产负债表!AL32),"—",资产负债表!AL32) -> 0 | P12: =IF(ISERROR(资产负债表!AM32),"—",资产负债表!AM32) -> 0
B13: 管理费用 | C13: =IF(ISERROR(利润表!Y31),"—",利润表!Y31) -> 0 | D13: =IF(ISERROR(利润表!AC31),"—",利润表!AC31) -> 0 | E13: =IF(ISERROR(利润表!AG31),"—",利润表!AG31) -> 0 | F13: =IF(ISERROR(利润表!AK31),"—",利润表!AK31) -> 0 | G13: =IF(ISERROR(利润表!AL31),"—",利润表!AL31) -> 0 | H13: =IF(ISERROR(利润表!AM31),"—",利润表!AM31) -> 0 | J13: 无形资产 | K13: =IF(ISERROR(资产负债表!Y36),"—",资产负债表!Y36) -> 0 | L13: =IF(ISERROR(资产负债表!AC36),"—",资产负债表!AC36) -> 0 | M13: =IF(ISERROR(资产负债表!AG36),"—",资产负债表!AG36) -> 0 | N13: =IF(ISERROR(资产负债表!AK36),"—",资产负债表!AK36) -> 0 | O13: =IF(ISERROR(资产负债表!AL36),"—",资产负债表!AL36) -> 0 | P13: =IF(ISERROR(资产负债表!AM36),"—",资产负债表!AM36) -> 0
B14: %营业收入 | C14: =IF(ISERROR(利润表!Y32),"—",利润表!Y32) -> — | D14: =IF(ISERROR(利润表!AC32),"—",利润表!AC32) -> — | E14: =IF(ISERROR(利润表!AG32),"—",利润表!AG32) -> — | F14: =IF(ISERROR(利润表!AK32),"—",利润表!AK32) -> — | G14: =IF(ISERROR(利润表!AL32),"—",利润表!AL32) -> — | H14: =IF(ISERROR(利润表!AM32),"—",利润表!AM32) -> — | J14: 商誉 | K14: =IF(ISERROR(资产负债表!Y38),"—",资产负债表!Y38) -> 0 | L14: =IF(ISERROR(资产负债表!AC38),"—",资产负债表!AC38) -> 0 | M14: =IF(ISERROR(资产负债表!AG38),"—",资产负债表!AG38) -> 0 | N14: =IF(ISERROR(资产负债表!AK38),"—",资产负债表!AK38) -> 0 | O14: =IF(ISERROR(资产负债表!AL38),"—",资产负债表!AL38) -> 0 | P14: =IF(ISERROR(资产负债表!AM38),"—",资产负债表!AM38) -> 0
B15: 研发费用 | C15: =IF(ISERROR(利润表!Y33),"—",利润表!Y33) -> 0 | D15: =IF(ISERROR(利润表!AC33),"—",利润表!AC33) -> 0 | E15: =IF(ISERROR(利润表!AG33),"—",利润表!AG33) -> 0 | F15: =IF(ISERROR(利润表!AK33),"—",利润表!AK33) -> 0 | G15: =IF(ISERROR(利润表!AL33),"—",利润表!AL33) -> 0 | H15: =IF(ISERROR(利润表!AM33),"—",利润表!AM33) -> 0 | J15: 其他非流动资产 | K15: =IF(ISERROR(K16-K10-K11-K12-K13-K14),"—",K16-K10-K11-K12-K13-K14) -> 0 | L15: =IF(ISERROR(L16-L10-L11-L12-L13-L14),"—",L16-L10-L11-L12-L13-L14) -> 0 | M15: =IF(ISERROR(M16-M10-M11-M12-M13-M14),"—",M16-M10-M11-M12-M13-M14) -> 0 | N15: =IF(ISERROR(N16-N10-N11-N12-N13-N14),"—",N16-N10-N11-N12-N13-N14) -> 0 | O15: =IF(ISERROR(O16-O10-O11-O12-O13-O14),"—",O16-O10-O11-O12-O13-O14) -> 0 | P15: =IF(ISERROR(P16-P10-P11-P12-P13-P14),"—",P16-P10-P11-P12-P13-P14) -> 0
B16: %营业收入 | C16: =IF(ISERROR(利润表!Y34),"—",利润表!Y34) -> — | D16: =IF(ISERROR(利润表!AC34),"—",利润表!AC34) -> — | E16: =IF(ISERROR(利润表!AG34),"—",利润表!AG34) -> — | F16: =IF(ISERROR(利润表!AK34),"—",利润表!AK34) -> — | G16: =IF(ISERROR(利润表!AL34),"—",利润表!AL34) -> — | H16: =IF(ISERROR(利润表!AM34),"—",利润表!AM34) -> — | J16: 非流动资产 | K16: =IF(ISERROR(资产负债表!Y42),"—",资产负债表!Y42) -> 0 | L16: =IF(ISERROR(资产负债表!AC42),"—",资产负债表!AC42) -> 0 | M16: =IF(ISERROR((资产负债表!AG42)),"—",(资产负债表!AG42)) -> 0 | N16: =IF(ISERROR((资产负债表!AK42)),"—",(资产负债表!AK42)) -> 0 | O16: =IF(ISERROR((资产负债表!AL42)),"—",(资产负债表!AL42)) -> 0 | P16: =IF(ISERROR((资产负债表!AM42)),"—",(资产负债表!AM42)) -> 0
B17: 财务费用 | C17: =IF(ISERROR(利润表!Y36),"—",利润表!Y36) -> 0 | D17: =IF(ISERROR(利润表!AC36),"—",利润表!AC36) -> 0 | E17: =IF(ISERROR(利润表!AG36),"—",利润表!AG36) -> 0 | F17: =IF(ISERROR(利润表!AK36),"—",利润表!AK36) -> 0 | G17: =IF(ISERROR(利润表!AL36),"—",利润表!AL36) -> 0 | H17: =IF(ISERROR(利润表!AM36),"—",利润表!AM36) -> 0 | J17: 资产总计 | K17: =IF(ISERROR(资产负债表!Y45),"—",资产负债表!Y45) -> 0 | L17: =IF(ISERROR(资产负债表!AC45),"—",资产负债表!AC45) -> 0 | M17: =IF(ISERROR(资产负债表!AG45),"—",资产负债表!AG45) -> 0 | N17: =IF(ISERROR(资产负债表!AK45),"—",资产负债表!AK45) -> 0 | O17: =IF(ISERROR(资产负债表!AL45),"—",资产负债表!AL45) -> 0 | P17: =IF(ISERROR(资产负债表!AM45),"—",资产负债表!AM45) -> 0
B18: %营业收入 | C18: =IF(ISERROR(利润表!Y37),"—",利润表!Y37) -> — | D18: =IF(ISERROR(利润表!AC37),"—",利润表!AC37) -> — | E18: =IF(ISERROR(利润表!AG37),"—",利润表!AG37) -> — | F18: =IF(ISERROR(利润表!AK37),"—",利润表!AK37) -> — | G18: =IF(ISERROR(利润表!AL37),"—",利润表!AL37) -> — | H18: =IF(ISERROR(利润表!AM37),"—",利润表!AM37) -> — | J18: 短期借款 | K18: =IF(ISERROR((资产负债表!Y49)),"—",(资产负债表!Y49)) -> 0 | L18: =IF(ISERROR((资产负债表!AC49)),"—",(资产负债表!AC49)) -> 0 | M18: =IF(ISERROR((资产负债表!AG49)),"—",(资产负债表!AG49)) -> 0 | N18: =IF(ISERROR((资产负债表!AK49)),"—",(资产负债表!AK49)) -> 0 | O18: =IF(ISERROR((资产负债表!AL49)),"—",(资产负债表!AL49)) -> 0 | P18: =IF(ISERROR((资产负债表!AM49)),"—",(资产负债表!AM49)) -> 0
B19: 息税前利润（EBIT） | C19: =IF(ISERROR(利润表!Y45),"—",利润表!Y45) -> 0 | D19: =IF(ISERROR(利润表!AC45),"—",利润表!AC45) -> 0 | E19: =IF(ISERROR(利润表!AG45),"—",利润表!AG45) -> 0 | F19: =IF(ISERROR(利润表!AK45),"—",利润表!AK45) -> 0 | G19: =IF(ISERROR(利润表!AL45),"—",利润表!AL45) -> 0 | H19: =IF(ISERROR(利润表!AM45),"—",利润表!AM45) -> 0 | J19: 应付票据 | K19: =IF(ISERROR(资产负债表!Y52),"—",资产负债表!Y52) -> 0 | L19: =IF(ISERROR(资产负债表!AC52),"—",资产负债表!AC52) -> 0 | M19: =IF(ISERROR((资产负债表!AG52)),"—",(资产负债表!AG52)) -> 0 | N19: =IF(ISERROR((资产负债表!AK52)),"—",(资产负债表!AK52)) -> 0 | O19: =IF(ISERROR((资产负债表!AL52)),"—",(资产负债表!AL52)) -> 0 | P19: =IF(ISERROR((资产负债表!AM52)),"—",(资产负债表!AM52)) -> 0
B20: %营业收入 | C20: =IF(ISERROR(利润表!Y46),"—",利润表!Y46) -> — | D20: =IF(ISERROR(利润表!AC46),"—",利润表!AC46) -> — | E20: =IF(ISERROR(利润表!AG46),"—",利润表!AG46) -> — | F20: =IF(ISERROR(利润表!AK46),"—",利润表!AK46) -> — | G20: =IF(ISERROR(利润表!AL46),"—",利润表!AL46) -> — | H20: =IF(ISERROR(利润表!AM46),"—",利润表!AM46) -> — | J20: 应付账款 | K20: =IF(ISERROR(资产负债表!Y53),"—",资产负债表!Y53) -> 0 | L20: =IF(ISERROR(资产负债表!AC53),"—",资产负债表!AC53) -> 0 | M20: =IF(ISERROR((资产负债表!AG53)),"—",(资产负债表!AG53)) -> 0 | N20: =IF(ISERROR((资产负债表!AK53)),"—",(资产负债表!AK53)) -> 0 | O20: =IF(ISERROR((资产负债表!AL53)),"—",(资产负债表!AL53)) -> 0 | P20: =IF(ISERROR((资产负债表!AM53)),"—",(资产负债表!AM53)) -> 0
B21: 其他收益 | C21: =IF(ISERROR(利润表!Y49),"—",利润表!Y49) -> 0 | D21: =IF(ISERROR(利润表!AC49),"—",利润表!AC49) -> 0 | E21: =IF(ISERROR(利润表!AG49),"—",利润表!AG49) -> 0 | F21: =IF(ISERROR(利润表!AK49),"—",利润表!AK49) -> 0 | G21: =IF(ISERROR(利润表!AL49),"—",利润表!AL49) -> 0 | H21: =IF(ISERROR(利润表!AM49),"—",利润表!AM49) -> 0 | J21: 其他应付款 | K21: =IF(ISERROR(资产负债表!Y58),"—",资产负债表!Y58) -> 0 | L21: =IF(ISERROR(资产负债表!AC58),"—",资产负债表!AC58) -> 0 | M21: =IF(ISERROR((资产负债表!AG58)),"—",(资产负债表!AG58)) -> 0 | N21: =IF(ISERROR((资产负债表!AK58)),"—",(资产负债表!AK58)) -> 0 | O21: =IF(ISERROR((资产负债表!AL58)),"—",(资产负债表!AL58)) -> 0 | P21: =IF(ISERROR((资产负债表!AM58)),"—",(资产负债表!AM58)) -> 0
B22: 投资收益 | C22: =IF(ISERROR(利润表!Y51),"—",利润表!Y51) -> 0 | D22: =IF(ISERROR(利润表!AC51),"—",利润表!AC51) -> 0 | E22: =IF(ISERROR(利润表!AG51),"—",利润表!AG51) -> 0 | F22: =IF(ISERROR(利润表!AK51),"—",利润表!AK51) -> 0 | G22: =IF(ISERROR(利润表!AL51),"—",利润表!AL51) -> 0 | H22: =IF(ISERROR(利润表!AM51),"—",利润表!AM51) -> 0 | J22: 其他流动负债 | K22: =IF(ISERROR(K23-K18-K19-K20-K21),"—",K23-K18-K19-K20-K21) -> 0 | L22: =IF(ISERROR(L23-L18-L19-L20-L21),"—",L23-L18-L19-L20-L21) -> 0 | M22: =IF(ISERROR(M23-M18-M19-M20-M21),"—",M23-M18-M19-M20-M21) -> 0 | N22: =IF(ISERROR(N23-N18-N19-N20-N21),"—",N23-N18-N19-N20-N21) -> 0 | O22: =IF(ISERROR(O23-O18-O19-O20-O21),"—",O23-O18-O19-O20-O21) -> 0 | P22: =IF(ISERROR(P23-P18-P19-P20-P21),"—",P23-P18-P19-P20-P21) -> 0
B23: 净敞口套期收益 | C23: =IF(ISERROR(利润表!Y54),"—",利润表!Y54) -> 0 | D23: =IF(ISERROR(利润表!AC54),"—",利润表!AC54) -> 0 | E23: =IF(ISERROR(利润表!AG54),"—",利润表!AG54) -> 0 | F23: =IF(ISERROR(利润表!AK54),"—",利润表!AK54) -> 0 | G23: =IF(ISERROR(利润表!AL54),"—",利润表!AL54) -> 0 | H23: =IF(ISERROR(利润表!AM54),"—",利润表!AM54) -> 0 | J23: 流动负债 | K23: =IF(ISERROR(资产负债表!Y62),"—",资产负债表!Y62) -> 0 | L23: =IF(ISERROR(资产负债表!AC62),"—",资产负债表!AC62) -> 0 | M23: =IF(ISERROR((资产负债表!AG62)),"—",(资产负债表!AG62)) -> 0 | N23: =IF(ISERROR((资产负债表!AK62)),"—",(资产负债表!AK62)) -> 0 | O23: =IF(ISERROR((资产负债表!AL62)),"—",(资产负债表!AL62)) -> 0 | P23: =IF(ISERROR((资产负债表!AM62)),"—",(资产负债表!AM62)) -> 0
B24: 公允价值变动收益 | C24: =IF(ISERROR(利润表!Y57),"—",利润表!Y57) -> 0 | D24: =IF(ISERROR(利润表!AC57),"—",利润表!AC57) -> 0 | E24: =IF(ISERROR(利润表!AG57),"—",利润表!AG57) -> 0 | F24: =IF(ISERROR(利润表!AK57),"—",利润表!AK57) -> 0 | G24: =IF(ISERROR(利润表!AL57),"—",利润表!AL57) -> 0 | H24: =IF(ISERROR(利润表!AM57),"—",利润表!AM57) -> 0 | J24: 长期借款 | K24: =IF(ISERROR(资产负债表!Y65),"—",资产负债表!Y65) -> 0 | L24: =IF(ISERROR(资产负债表!AC65),"—",资产负债表!AC65) -> 0 | M24: =IF(ISERROR(资产负债表!AG65),"—",资产负债表!AG65) -> 0 | N24: =IF(ISERROR(资产负债表!AK65),"—",资产负债表!AK65) -> 0 | O24: =IF(ISERROR(资产负债表!AL65),"—",资产负债表!AL65) -> 0 | P24: =IF(ISERROR(资产负债表!AM65),"—",资产负债表!AM65) -> 0
B25: 信用减值损失 | C25: =IF(ISERROR(利润表!Y60),"—",利润表!Y60) -> 0 | D25: =IF(ISERROR(利润表!AC60),"—",利润表!AC60) -> 0 | E25: =IF(ISERROR(利润表!AG60),"—",利润表!AG60) -> 0 | F25: =IF(ISERROR(利润表!AK60),"—",利润表!AK60) -> 0 | G25: =IF(ISERROR(利润表!AL60),"—",利润表!AL60) -> 0 | H25: =IF(ISERROR(利润表!AM60),"—",利润表!AM60) -> 0 | J25: 应付债券 | K25: =IF(ISERROR(资产负债表!Y66),"—",资产负债表!Y66) -> 0 | L25: =IF(ISERROR(资产负债表!AC66),"—",资产负债表!AC66) -> 0 | M25: =IF(ISERROR(资产负债表!AG66),"—",资产负债表!AG66) -> 0 | N25: =IF(ISERROR(资产负债表!AK66),"—",资产负债表!AK66) -> 0 | O25: =IF(ISERROR(资产负债表!AL66),"—",资产负债表!AL66) -> 0 | P25: =IF(ISERROR(资产负债表!AM66),"—",资产负债表!AM66) -> 0
B26: 资产减值损失 | C26: =IF(ISERROR(利润表!Y63),"—",利润表!Y63) -> 0 | D26: =IF(ISERROR(利润表!AC63),"—",利润表!AC63) -> 0 | E26: =IF(ISERROR(利润表!AG63),"—",利润表!AG63) -> 0 | F26: =IF(ISERROR(利润表!AK63),"—",利润表!AK63) -> 0 | G26: =IF(ISERROR(利润表!AL63),"—",利润表!AL63) -> 0 | H26: =IF(ISERROR(利润表!AM63),"—",利润表!AM63) -> 0 | J26: 长期应付款 | K26: =IF(ISERROR(资产负债表!Y68),"—",资产负债表!Y68) -> 0 | L26: =IF(ISERROR(资产负债表!AC68),"—",资产负债表!AC68) -> 0 | M26: =IF(ISERROR(资产负债表!AG68),"—",资产负债表!AG68) -> 0 | N26: =IF(ISERROR(资产负债表!AK68),"—",资产负债表!AK68) -> 0 | O26: =IF(ISERROR(资产负债表!AL68),"—",资产负债表!AL68) -> 0 | P26: =IF(ISERROR(资产负债表!AM68),"—",资产负债表!AM68) -> 0
B27: 资产处置收益 | C27: =IF(ISERROR(利润表!Y66),"—",利润表!Y66) -> 0 | D27: =IF(ISERROR(利润表!AC66),"—",利润表!AC66) -> 0 | E27: =IF(ISERROR(利润表!AG66),"—",利润表!AG66) -> 0 | F27: =IF(ISERROR(利润表!AK66),"—",利润表!AK66) -> 0 | G27: =IF(ISERROR(利润表!AL66),"—",利润表!AL66) -> 0 | H27: =IF(ISERROR(利润表!AM66),"—",利润表!AM66) -> 0 | J27: 其他长期负债 | K27: =IF(ISERROR(K28-K24-K25-K26),"—",K28-K24-K25-K26) -> 0 | L27: =IF(ISERROR(L28-L24-L25-L26),"—",L28-L24-L25-L26) -> 0 | M27: =IF(ISERROR(M28-M24-M25-M26),"—",M28-M24-M25-M26) -> 0 | N27: =IF(ISERROR(N28-N24-N25-N26),"—",N28-N24-N25-N26) -> 0 | O27: =IF(ISERROR(O28-O24-O25-O26),"—",O28-O24-O25-O26) -> 0 | P27: =IF(ISERROR(P28-P24-P25-P26),"—",P28-P24-P25-P26) -> 0
B28: 汇兑净收益 | C28: =IF(ISERROR(利润表!Y69),"—",利润表!Y69) -> 0 | D28: =IF(ISERROR(利润表!AC69),"—",利润表!AC69) -> 0 | E28: =IF(ISERROR(利润表!AG69),"—",利润表!AG69) -> 0 | F28: =IF(ISERROR(利润表!AK69),"—",利润表!AK69) -> 0 | G28: =IF(ISERROR(利润表!AL69),"—",利润表!AL69) -> 0 | H28: =IF(ISERROR(利润表!AM69),"—",利润表!AM69) -> 0 | J28: 非流动负债 | K28: =IF(ISERROR(资产负债表!Y73),"—",资产负债表!Y73) -> 0 | L28: =IF(ISERROR(资产负债表!AC73),"—",资产负债表!AC73) -> 0 | M28: =IF(ISERROR(资产负债表!AG73),"—",资产负债表!AG73) -> 0 | N28: =IF(ISERROR(资产负债表!AK73),"—",资产负债表!AK73) -> 0 | O28: =IF(ISERROR(资产负债表!AL73),"—",资产负债表!AL73) -> 0 | P28: =IF(ISERROR(资产负债表!AM73),"—",资产负债表!AM73) -> 0
B29: 营业利润 | C29: =IF(ISERROR(利润表!Y73),"—",利润表!Y73) -> 0 | D29: =IF(ISERROR(利润表!AC73),"—",利润表!AC73) -> 0 | E29: =IF(ISERROR(利润表!AG73),"—",利润表!AG73) -> 0 | F29: =IF(ISERROR(利润表!AK73),"—",利润表!AK73) -> 0 | G29: =IF(ISERROR(利润表!AL73),"—",利润表!AL73) -> 0 | H29: =IF(ISERROR(利润表!AM73),"—",利润表!AM73) -> 0 | J29: 负债总计 | K29: =IF(ISERROR(资产负债表!Y76),"—",资产负债表!Y76) -> 0 | L29: =IF(ISERROR(资产负债表!AC76),"—",资产负债表!AC76) -> 0 | M29: =IF(ISERROR(资产负债表!AG76),"—",资产负债表!AG76) -> 0 | N29: =IF(ISERROR(资产负债表!AK76),"—",资产负债表!AK76) -> 0 | O29: =IF(ISERROR(资产负债表!AL76),"—",资产负债表!AL76) -> 0 | P29: =IF(ISERROR(资产负债表!AM76),"—",资产负债表!AM76) -> 0
B30: %增长率 | C30: =IF(ISERROR(利润表!Y75),"—",利润表!Y75) -> — | D30: =IF(ISERROR(利润表!AC75),"—",利润表!AC75) -> — | E30: =IF(ISERROR(利润表!AG75),"—",利润表!AG75) -> — | F30: =IF(ISERROR(利润表!AK75),"—",利润表!AK75) -> — | G30: =IF(ISERROR(利润表!AL75),"—",利润表!AL75) -> — | H30: =IF(ISERROR(利润表!AM75),"—",利润表!AM75) -> — | J30: 股本 | K30: =IF(ISERROR(资产负债表!Y78),"—",资产负债表!Y78) -> 0 | L30: =IF(ISERROR(资产负债表!AC78),"—",资产负债表!AC78) -> 0 | M30: =IF(ISERROR(资产负债表!AG78),"—",资产负债表!AG78) -> 0 | N30: =IF(ISERROR(资产负债表!AK78),"—",资产负债表!AK78) -> 0 | O30: =IF(ISERROR(资产负债表!AL78),"—",资产负债表!AL78) -> 0 | P30: =IF(ISERROR(资产负债表!AM78),"—",资产负债表!AM78) -> 0
B31: 营业外收支 | C31: =IF(ISERROR(利润表!Y81),"—",利润表!Y81) -> 0 | D31: =IF(ISERROR(利润表!AC81),"—",利润表!AC81) -> 0 | E31: =IF(ISERROR((利润表!AG81)),"—",(利润表!AG81)) -> 0 | F31: =IF(ISERROR(利润表!AK81),"—",利润表!AK81) -> 0 | G31: =IF(ISERROR(利润表!AL81),"—",利润表!AL81) -> 0 | H31: =IF(ISERROR(利润表!AM81),"—",利润表!AM81) -> 0 | J31: 资本公积 | K31: =IF(ISERROR(资产负债表!Y82),"—",资产负债表!Y82) -> 0 | L31: =IF(ISERROR(资产负债表!AC82),"—",资产负债表!AC82) -> 0 | M31: =IF(ISERROR(资产负债表!AG82),"—",资产负债表!AG82) -> 0 | N31: =IF(ISERROR(资产负债表!AK82),"—",资产负债表!AK82) -> 0 | O31: =IF(ISERROR(资产负债表!AL82),"—",资产负债表!AL82) -> 0 | P31: =IF(ISERROR(资产负债表!AM82),"—",资产负债表!AM82) -> 0
B32: 利润总额 | C32: =IF(ISERROR(利润表!Y84),"—",利润表!Y84) -> 0 | D32: =IF(ISERROR(利润表!AC84),"—",利润表!AC84) -> 0 | E32: =IF(ISERROR((利润表!AG84)),"—",(利润表!AG84)) -> 0 | F32: =IF(ISERROR(利润表!AK84),"—",利润表!AK84) -> 0 | G32: =IF(ISERROR(利润表!AL84),"—",利润表!AL84) -> 0 | H32: =IF(ISERROR(利润表!AM84),"—",利润表!AM84) -> 0 | J32: 归母所有者权益 | K32: =IF(ISERROR(资产负债表!Y89),"—",资产负债表!Y89) -> 0 | L32: =IF(ISERROR(资产负债表!AC89),"—",资产负债表!AC89) -> 0 | M32: =IF(ISERROR(资产负债表!AG89),"—",资产负债表!AG89) -> 0 | N32: =IF(ISERROR(资产负债表!AK89),"—",资产负债表!AK89) -> 0 | O32: =IF(ISERROR(资产负债表!AL89),"—",资产负债表!AL89) -> 0 | P32: =IF(ISERROR(资产负债表!AM89),"—",资产负债表!AM89) -> 0
B33: %增长率 | C33: =IF(ISERROR((利润表!Y84-利润表!U84)/ABS(利润表!U84)),"—",(利润表!Y84-利润表!U84)/ABS(利润表!U84)) -> — | D33: =IF(ISERROR((D32-C32)/ABS(C32)),"—",(D32-C32)/ABS(C32)) -> — | E33: =IF(ISERROR((E32-D32)/ABS(D32)),"—",(E32-D32)/ABS(D32)) -> — | F33: =IF(ISERROR((F32-E32)/ABS(E32)),"—",(F32-E32)/ABS(E32)) -> — | G33: =IF(ISERROR((G32-F32)/ABS(F32)),"—",(G32-F32)/ABS(F32)) -> — | H33: =IF(ISERROR((H32-G32)/ABS(G32)),"—",(H32-G32)/ABS(G32)) -> — | J33: 少数股东权益 | K33: =IF(ISERROR(资产负债表!Y91),"—",资产负债表!Y91) -> 0 | L33: =IF(ISERROR(资产负债表!AC91),"—",资产负债表!AC91) -> 0 | M33: =IF(ISERROR(资产负债表!AG91),"—",资产负债表!AG91) -> 0 | N33: =IF(ISERROR(资产负债表!AK91),"—",资产负债表!AK91) -> 0 | O33: =IF(ISERROR(资产负债表!AL91),"—",资产负债表!AL91) -> 0 | P33: =IF(ISERROR(资产负债表!AM91),"—",资产负债表!AM91) -> 0
B34: 所得税 | C34: =IF(ISERROR(利润表!Y86),"—",利润表!Y86) -> 0 | D34: =IF(ISERROR(利润表!AC86),"—",利润表!AC86) -> 0 | E34: =IF(ISERROR(利润表!AG86),"—",利润表!AG86) -> 0 | F34: =IF(ISERROR(利润表!AK86),"—",利润表!AK86) -> 0 | G34: =IF(ISERROR(利润表!AL86),"—",利润表!AL86) -> 0 | H34: =IF(ISERROR(利润表!AM86),"—",利润表!AM86) -> 0 | J34: 所有者权益合计 | K34: =IF(ISERROR(资产负债表!Y93),"—",资产负债表!Y93) -> 0 | L34: =IF(ISERROR(资产负债表!AC93),"—",资产负债表!AC93) -> 0 | M34: =IF(ISERROR(资产负债表!AG93),"—",资产负债表!AG93) -> 0 | N34: =IF(ISERROR(资产负债表!AK93),"—",资产负债表!AK93) -> 0 | O34: =IF(ISERROR(资产负债表!AL93),"—",资产负债表!AL93) -> 0 | P34: =IF(ISERROR(资产负债表!AM93),"—",资产负债表!AM93) -> 0
B35: 所得税率 | C35: =IF(ISERROR(利润表!Y87),"—",利润表!Y87) -> — | D35: =IF(ISERROR(利润表!AC87),"—",利润表!AC87) -> — | E35: =IF(ISERROR(利润表!AG87),"—",利润表!AG87) -> — | F35: =IF(ISERROR(利润表!AK87),"—",利润表!AK87) -> — | G35: =IF(ISERROR(利润表!AL87),"—",利润表!AL87) -> — | H35: =IF(ISERROR(利润表!AM87),"—",利润表!AM87) -> — | J35: 负债股东权益合计 | K35: =IF(ISERROR(资产负债表!Y95),"—",资产负债表!Y95) -> 0 | L35: =IF(ISERROR(资产负债表!AC95),"—",资产负债表!AC95) -> 0 | M35: =IF(ISERROR(资产负债表!AG95),"—",资产负债表!AG95) -> 0 | N35: =IF(ISERROR(资产负债表!AK95),"—",资产负债表!AK95) -> 0 | O35: =IF(ISERROR(资产负债表!AL95),"—",资产负债表!AL95) -> 0 | P35: =IF(ISERROR(资产负债表!AM95),"—",资产负债表!AM95) -> 0
B36: 合并报表的净利润 | C36: =IF(ISERROR(利润表!Y88),"—",利润表!Y88) -> 0 | D36: =IF(ISERROR(利润表!AC88),"—",利润表!AC88) -> 0 | E36: =IF(ISERROR(利润表!AG88),"—",利润表!AG88) -> 0 | F36: =IF(ISERROR(利润表!AK88),"—",利润表!AK88) -> 0 | G36: =IF(ISERROR(利润表!AL88),"—",利润表!AL88) -> 0 | H36: =IF(ISERROR(利润表!AM88),"—",利润表!AM88) -> 0
B37: 少数股东损益 | C37: =IF(ISERROR(利润表!Y91),"—",利润表!Y91) -> 0 | D37: =IF(ISERROR(利润表!AC91),"—",利润表!AC91) -> 0 | E37: =IF(ISERROR(利润表!AG91),"—",利润表!AG91) -> 0 | F37: =IF(ISERROR(利润表!AK91),"—",利润表!AK91) -> 0 | G37: =IF(ISERROR(利润表!AL91),"—",利润表!AL91) -> 0 | H37: =IF(ISERROR(利润表!AM91),"—",利润表!AM91) -> 0
B38: 归属于母公司股东的净利润 | C38: =IF(ISERROR(利润表!Y94),"—",利润表!Y94) -> 0 | D38: =IF(ISERROR(利润表!AC94),"—",利润表!AC94) -> 0 | E38: =IF(ISERROR(利润表!AG94),"—",利润表!AG94) -> 0 | F38: =IF(ISERROR(利润表!AK94),"—",利润表!AK94) -> 0 | G38: =IF(ISERROR(利润表!AL94),"—",利润表!AL94) -> 0 | H38: =IF(ISERROR(利润表!AM94),"—",利润表!AM94) -> 0 | J38: 比率分析 | K38: =C2 -> 2021 | L38: =D2 -> 2022 | M38: =E2 -> 2023 | N38: =F2 -> 2024E | O38: =G2 -> 2025 | P38: =H2 -> 2026
B39: %增长率 | C39: =IF(ISERROR(利润表!Y96),"—",利润表!Y96) -> — | D39: =IF(ISERROR(利润表!AC96),"—",利润表!AC96) -> — | E39: =IF(ISERROR(利润表!AG96),"—",利润表!AG96) -> — | F39: =IF(ISERROR(利润表!AK96),"—",利润表!AK96) -> — | G39: =IF(ISERROR(利润表!AL96),"—",利润表!AL96) -> — | H39: =IF(ISERROR(利润表!AM96),"—",利润表!AM96) -> — | J39: 盈利能力
B40: 净利率 | C40: =IF(ISERROR(利润表!Y95),"—",利润表!Y95) -> — | D40: =IF(ISERROR(利润表!AC95),"—",利润表!AC95) -> — | E40: =IF(ISERROR(利润表!AG95),"—",利润表!AG95) -> — | F40: =IF(ISERROR(利润表!AK95),"—",利润表!AK95) -> — | G40: =IF(ISERROR(利润表!AL95),"—",利润表!AL95) -> — | H40: =IF(ISERROR(利润表!AM95),"—",利润表!AM95) -> — | J40: 净资产收益率 | K40: =IF(ISERROR(利润表!Y94/资产负债表!Y89),"—",利润表!Y94/资产负债表!Y89) -> — | L40: =IF(ISERROR(利润表!AC94/资产负债表!AC89),"—",利润表!AC94/资产负债表!AC89) -> — | M40: =IF(ISERROR(利润表!AG94/资产负债表!AG89),"—",利润表!AG94/资产负债表!AG89) -> — | N40: =IF(ISERROR(利润表!AK94/资产负债表!AK89),"—",利润表!AK94/资产负债表!AK89) -> — | O40: =IF(ISERROR(利润表!AL94/资产负债表!AL89),"—",利润表!AL94/资产负债表!AL89) -> — | P40: =IF(ISERROR(利润表!AM94/资产负债表!AM89),"—",利润表!AM94/资产负债表!AM89) -> —
J41: 总资产收益率 | K41: =IF(ISERROR(利润表!Y88*2/(资产负债表!U45+资产负债表!Y45)),"—",利润表!Y88*2/(资产负债表!U45+资产负债表!Y45)) -> — | L41: =IF(ISERROR(利润表!AC88*2/(资产负债表!Y45+资产负债表!AC45)),"—",利润表!AC88*2/(资产负债表!Y45+资产负债表!AC45)) -> — | M41: =IF(ISERROR(利润表!AG88*2/(资产负债表!AC45+资产负债表!AG45)),"—",利润表!AG88*2/(资产负债表!AC45+资产负债表!AG45)) -> — | N41: =IF(ISERROR(利润表!AK88*2/(资产负债表!AG45+资产负债表!AK45)),"—",利润表!AK88*2/(资产负债表!AG45+资产负债表!AK45)) -> — | O41: =IF(ISERROR(利润表!AL88*2/(资产负债表!AK45+资产负债表!AL45)),"—",利润表!AL88*2/(资产负债表!AK45+资产负债表!AL45)) -> — | P41: =IF(ISERROR(利润表!AM88*2/(资产负债表!AL45+资产负债表!AM45)),"—",利润表!AM88*2/(资产负债表!AL45+资产负债表!AM45)) -> —
J42: 投入资本收益率 | K42: =IF(ISERROR(利润表!Y45*(1-利润表!Y87)/资产负债表!Y105),"—",利润表!Y45*(1-利润表!Y87)/资产负债表!Y105) -> — | L42: =IF(ISERROR(利润表!AC45*(1-利润表!AC87)/资产负债表!AC105),"—",利润表!AC45*(1-利润表!AC87)/资产负债表!AC105) -> — | M42: =IF(ISERROR(利润表!AG45*(1-利润表!AG87)/资产负债表!AG105),"—",利润表!AG45*(1-利润表!AG87)/资产负债表!AG105) -> — | N42: =IF(ISERROR(利润表!AK45*(1-利润表!AK87)/资产负债表!AK105),"—",利润表!AK45*(1-利润表!AK87)/资产负债表!AK105) -> — | O42: =IF(ISERROR(利润表!AL45*(1-利润表!AL87)/资产负债表!AL105),"—",利润表!AL45*(1-利润表!AL87)/资产负债表!AL105) -> — | P42: =IF(ISERROR(利润表!AM45*(1-利润表!AM87)/资产负债表!AM105),"—",利润表!AM45*(1-利润表!AM87)/资产负债表!AM105) -> —
B43: ="现金流量表(人民币"&目录!$D$5&")" -> 现金流量表(人民币百万元) | C43: =C2 -> 2021 | D43: =D2 -> 2022 | E43: =E2 -> 2023 | F43: =F2 -> 2024E | G43: =G2 -> 2025 | H43: =H2 -> 2026 | J43: 合并报表净利率 | K43: =IF(ISERROR(利润表!Y89),"—",利润表!Y89) -> — | L43: =IF(ISERROR(利润表!AC89),"—",利润表!AC89) -> — | M43: =IF(ISERROR(利润表!AG89),"—",利润表!AG89) -> — | N43: =IF(ISERROR(利润表!AK89),"—",利润表!AK89) -> — | O43: =IF(ISERROR(利润表!AL89),"—",利润表!AL89) -> — | P43: =IF(ISERROR(利润表!AM89),"—",利润表!AM89) -> —
B44: 净利润 | C44: =C38 -> 0 | D44: =D38 -> 0 | E44: =E38 -> 0 | F44: =F38 -> 0 | G44: =G38 -> 0 | H44: =H38 -> 0 | J44: 毛利率 | K44: =IF(ISERROR(利润表!Y23),"—",利润表!Y23) -> — | L44: =IF(ISERROR(利润表!AC23),"—",利润表!AC23) -> — | M44: =IF(ISERROR(利润表!AG23),"—",利润表!AG23) -> — | N44: =IF(ISERROR(利润表!AK23),"—",利润表!AK23) -> — | O44: =IF(ISERROR(利润表!AL23),"—",利润表!AL23) -> — | P44: =IF(ISERROR(利润表!AM23),"—",利润表!AM23) -> —
B45: 少数股东损益 | C45: =C37 -> 0 | D45: =D37 -> 0 | E45: =E37 -> 0 | F45: =F37 -> 0 | G45: =G37 -> 0 | H45: =H37 -> 0 | J45: 成长能力
B46: 非现金支出 | C46: =IF(ISERROR(现金流量表!Y9),"—",现金流量表!Y9) -> 0 | D46: =IF(ISERROR(现金流量表!AC9),"—",现金流量表!AC9) -> 0 | E46: =IF(ISERROR(现金流量表!AG9),"—",现金流量表!AG9) -> 0 | F46: =IF(ISERROR(现金流量表!AK9),"—",现金流量表!AK9) -> 0 | G46: =IF(ISERROR(现金流量表!AL9),"—",现金流量表!AL9) -> 0 | H46: =IF(ISERROR(现金流量表!AM9),"—",现金流量表!AM9) -> 0 | J46: 营业总收入增长率 | K46: =IF(ISERROR(利润表!Y7),"—",利润表!Y7) -> — | L46: =IF(ISERROR(利润表!AC7),"—",利润表!AC7) -> — | M46: =IF(ISERROR(利润表!AG7),"—",利润表!AG7) -> — | N46: =IF(ISERROR(利润表!AK7),"—",利润表!AK7) -> — | O46: =IF(ISERROR(利润表!AL7),"—",利润表!AL7) -> — | P46: =IF(ISERROR(利润表!AM7),"—",利润表!AM7) -> —
B47: 非经营收益 | C47: =IF(ISERROR(现金流量表!Y16),"—",现金流量表!Y16) -> 0 | D47: =IF(ISERROR(现金流量表!AC16),"—",现金流量表!AC16) -> 0 | E47: =IF(ISERROR(现金流量表!AG16),"—",现金流量表!AG16) -> 0 | F47: =IF(ISERROR(现金流量表!AK16),"—",现金流量表!AK16) -> 0 | G47: =IF(ISERROR(现金流量表!AL16),"—",现金流量表!AL16) -> 0 | H47: =IF(ISERROR(现金流量表!AM16),"—",现金流量表!AM16) -> 0 | J47: EBIT增长率 | K47: =IF(ISERROR(利润表!Y47),"—",利润表!Y47) -> — | L47: =IF(ISERROR(利润表!AC47),"—",利润表!AC47) -> — | M47: =IF(ISERROR(利润表!AG47),"—",利润表!AG47) -> — | N47: =IF(ISERROR(利润表!AK47),"—",利润表!AK47) -> — | O47: =IF(ISERROR(利润表!AL47),"—",利润表!AL47) -> — | P47: =IF(ISERROR(利润表!AM47),"—",利润表!AM47) -> —
B48: 营运资金变动 | C48: =IF(ISERROR(现金流量表!Y23),"—",现金流量表!Y23) -> 0 | D48: =IF(ISERROR(现金流量表!AC23),"—",现金流量表!AC23) -> 0 | E48: =IF(ISERROR(现金流量表!AG23),"—",现金流量表!AG23) -> 0 | F48: =IF(ISERROR(现金流量表!AK23),"—",现金流量表!AK23) -> 0 | G48: =IF(ISERROR(现金流量表!AL23),"—",现金流量表!AL23) -> 0 | H48: =IF(ISERROR(现金流量表!AM23),"—",现金流量表!AM23) -> 0 | J48: 归母净利润增长率 | K48: =IF(ISERROR(利润表!Y96),"—",利润表!Y96) -> — | L48: =IF(ISERROR(利润表!AC96),"—",利润表!AC96) -> — | M48: =IF(ISERROR(利润表!AG96),"—",利润表!AG96) -> — | N48: =IF(ISERROR(利润表!AK96),"—",利润表!AK96) -> — | O48: =IF(ISERROR(利润表!AL96),"—",利润表!AL96) -> — | P48: =IF(ISERROR(利润表!AM96),"—",利润表!AM96) -> —
B49: 经营活动现金净流 | C49: =IF(ISERROR(现金流量表!Y36),"—",现金流量表!Y36) -> 0 | D49: =IF(ISERROR(现金流量表!AC36),"—",现金流量表!AC36) -> 0 | E49: =IF(ISERROR(现金流量表!AG36),"—",现金流量表!AG36) -> 0 | F49: =IF(ISERROR(现金流量表!AK36),"—",现金流量表!AK36) -> 0 | G49: =IF(ISERROR(现金流量表!AL36),"—",现金流量表!AL36) -> 0 | H49: =IF(ISERROR(现金流量表!AM36),"—",现金流量表!AM36) -> 0 | J49: 总资产增长率 | K49: =IF(ISERROR((资产负债表!Y45-资产负债表!U45)/ABS(资产负债表!U45)),"—",(资产负债表!Y45-资产负债表!U45)/ABS(资产负债表!U45)) -> — | L49: =IF(ISERROR((资产负债表!AC45-资产负债表!Y45)/ABS(资产负债表!Y45)),"—",(资产负债表!AC45-资产负债表!Y45)/ABS(资产负债表!Y45)) -> — | M49: =IF(ISERROR((资产负债表!AG45-资产负债表!AC45)/ABS(资产负债表!AC45)),"—",(资产负债表!AG45-资产负债表!AC45)/ABS(资产负债表!AC45)) -> — | N49: =IF(ISERROR((资产负债表!AK45-资产负债表!AG45)/ABS(资产负债表!AG45)),"—",(资产负债表!AK45-资产负债表!AG45)/ABS(资产负债表!AG45)) -> — | O49: =IF(ISERROR((资产负债表!AL45-资产负债表!AK45)/ABS(资产负债表!AK45)),"—",(资产负债表!AL45-资产负债表!AK45)/ABS(资产负债表!AK45)) -> — | P49: =IF(ISERROR((资产负债表!AM45-资产负债表!AL45)/ABS(资产负债表!AL45)),"—",(资产负债表!AM45-资产负债表!AL45)/ABS(资产负债表!AL45)) -> —
B50: 资本开支 | C50: =IF(ISERROR(现金流量表!Y47),"—",现金流量表!Y47) -> 0 | D50: =IF(ISERROR(现金流量表!AC47),"—",现金流量表!AC47) -> 0 | E50: =IF(ISERROR(现金流量表!AG47),"—",现金流量表!AG47) -> 0 | F50: =IF(ISERROR(现金流量表!AK47),"—",现金流量表!AK47) -> 0 | G50: =IF(ISERROR(现金流量表!AL47),"—",现金流量表!AL47) -> 0 | H50: =IF(ISERROR(现金流量表!AM47),"—",现金流量表!AM47) -> 0 | J50: 资产管理能力
B51: 投资 | C51: =IF(ISERROR(现金流量表!Y39),"—",现金流量表!Y39) -> 0 | D51: =IF(ISERROR(现金流量表!AC39),"—",现金流量表!AC39) -> 0 | E51: =IF(ISERROR(现金流量表!AG39),"—",现金流量表!AG39) -> 0 | F51: =IF(ISERROR(现金流量表!AK39),"—",现金流量表!AK39) -> 0 | G51: =IF(ISERROR(现金流量表!AL39),"—",现金流量表!AL39) -> 0 | H51: =IF(ISERROR(现金流量表!AM39),"—",现金流量表!AM39) -> 0 | J51: 应收账款周转天数 | K51: =IF(ISERROR(360/(利润表!Y8*2/(资产负债表!U12+资产负债表!Y12))),"—",360/(利润表!Y8*2/(资产负债表!U12+资产负债表!Y12))) -> — | L51: =IF(ISERROR(360/(利润表!AC8*2/(资产负债表!Y12+资产负债表!AC12))),"—",360/(利润表!AC8*2/(资产负债表!Y12+资产负债表!AC12))) -> — | M51: =IF(ISERROR(360/(利润表!AG8*2/(资产负债表!AC12+资产负债表!AG12))),"—",360/(利润表!AG8*2/(资产负债表!AC12+资产负债表!AG12))) -> — | N51: =IF(ISERROR(360/(利润表!AK8*2/(资产负债表!AG12+资产负债表!AK12))),"—",360/(利润表!AK8*2/(资产负债表!AG12+资产负债表!AK12))) -> — | O51: =IF(ISERROR(360/(利润表!AL8*2/(资产负债表!AK12+资产负债表!AL12))),"—",360/(利润表!AL8*2/(资产负债表!AK12+资产负债表!AL12))) -> — | P51: =IF(ISERROR(360/(利润表!AM8*2/(资产负债表!AL12+资产负债表!AM12))),"—",360/(利润表!AM8*2/(资产负债表!AL12+资产负债表!AM12))) -> — | Q51: 此处周转天数按照期初期末平均值计算
B52: 其他 | C52: =IF(ISERROR(现金流量表!Y56+现金流量表!Y57),"—",现金流量表!Y56+现金流量表!Y57) -> 0 | D52: =IF(ISERROR(现金流量表!AC56+现金流量表!AC57),"—",现金流量表!AC56+现金流量表!AC57) -> 0 | E52: =IF(ISERROR(现金流量表!AG56+现金流量表!AG57),"—",现金流量表!AG56+现金流量表!AG57) -> 0 | F52: =IF(ISERROR(现金流量表!AK56+现金流量表!AK57),"—",现金流量表!AK56+现金流量表!AK57) -> 0 | G52: =IF(ISERROR(现金流量表!AL56+现金流量表!AL57),"—",现金流量表!AL56+现金流量表!AL57) -> 0 | H52: =IF(ISERROR(现金流量表!AM56+现金流量表!AM57),"—",现金流量表!AM56+现金流量表!AM57) -> 0 | J52: 存货周转天数 | K52: =IF(ISERROR(360/(利润表!Y15*2/(资产负债表!U16+资产负债表!Y16))),"—",360/(利润表!Y15*2/(资产负债表!U16+资产负债表!Y16))) -> — | L52: =IF(ISERROR(360/(利润表!AC15*2/(资产负债表!Y16+资产负债表!AC16))),"—",360/(利润表!AC15*2/(资产负债表!Y16+资产负债表!AC16))) -> — | M52: =IF(ISERROR(360/(利润表!AG15*2/(资产负债表!AC16+资产负债表!AG16))),"—",360/(利润表!AG15*2/(资产负债表!AC16+资产负债表!AG16))) -> — | N52: =IF(ISERROR(360/(利润表!AK15*2/(资产负债表!AG16+资产负债表!AK16))),"—",360/(利润表!AK15*2/(资产负债表!AG16+资产负债表!AK16))) -> — | O52: =IF(ISERROR(360/(利润表!AL15*2/(资产负债表!AK16+资产负债表!AL16))),"—",360/(利润表!AL15*2/(资产负债表!AK16+资产负债表!AL16))) -> — | P52: =IF(ISERROR(360/(利润表!AM15*2/(资产负债表!AL16+资产负债表!AM16))),"—",360/(利润表!AM15*2/(资产负债表!AL16+资产负债表!AM16))) -> —
B53: 投资活动现金净流 | C53: =IF(ISERROR(现金流量表!Y58),"—",现金流量表!Y58) -> 0 | D53: =IF(ISERROR(现金流量表!AC58),"—",现金流量表!AC58) -> 0 | E53: =IF(ISERROR(现金流量表!AG58),"—",现金流量表!AG58) -> 0 | F53: =IF(ISERROR(现金流量表!AK58),"—",现金流量表!AK58) -> 0 | G53: =IF(ISERROR(现金流量表!AL58),"—",现金流量表!AL58) -> 0 | H53: =IF(ISERROR(现金流量表!AM58),"—",现金流量表!AM58) -> 0 | J53: 应付账款周转天数 | K53: =IF(ISERROR(360/(利润表!Y15*2/(资产负债表!U53+资产负债表!Y53))),"—",360/(利润表!Y15*2/(资产负债表!U53+资产负债表!Y53))) -> — | L53: =IF(ISERROR(360/(利润表!AC15*2/(资产负债表!Y53+资产负债表!AC53))),"—",360/(利润表!AC15*2/(资产负债表!Y53+资产负债表!AC53))) -> — | M53: =IF(ISERROR(360/(利润表!AG15*2/(资产负债表!AC53+资产负债表!AG53))),"—",360/(利润表!AG15*2/(资产负债表!AC53+资产负债表!AG53))) -> — | N53: =IF(ISERROR(360/(利润表!AK15*2/(资产负债表!AG53+资产负债表!AK53))),"—",360/(利润表!AK15*2/(资产负债表!AG53+资产负债表!AK53))) -> — | O53: =IF(ISERROR(360/(利润表!AL15*2/(资产负债表!AK53+资产负债表!AL53))),"—",360/(利润表!AL15*2/(资产负债表!AK53+资产负债表!AL53))) -> — | P53: =IF(ISERROR(360/(利润表!AM15*2/(资产负债表!AL53+资产负债表!AM53))),"—",360/(利润表!AM15*2/(资产负债表!AL53+资产负债表!AM53))) -> —
B54: 股权融资 | C54: =IF(ISERROR(现金流量表!Y61),"—",现金流量表!Y61) -> 0 | D54: =IF(ISERROR(现金流量表!AC61),"—",现金流量表!AC61) -> 0 | E54: =IF(ISERROR(现金流量表!AG61),"—",现金流量表!AG61) -> 0 | F54: =IF(ISERROR(现金流量表!AK61),"—",现金流量表!AK61) -> 0 | G54: =IF(ISERROR(现金流量表!AL61),"—",现金流量表!AL61) -> 0 | H54: =IF(ISERROR(现金流量表!AM61),"—",现金流量表!AM61) -> 0 | J54: 固定资产周转天数 | K54: =IF(ISERROR(360/(利润表!Y6*2/(资产负债表!U31+资产负债表!Y31))),"—",360/(利润表!Y6*2/(资产负债表!U31+资产负债表!Y31))) -> — | L54: =IF(ISERROR(360/(利润表!AC6*2/(资产负债表!Y31+资产负债表!AC31))),"—",360/(利润表!AC6*2/(资产负债表!Y31+资产负债表!AC31))) -> — | M54: =IF(ISERROR(360/(利润表!AG6*2/(资产负债表!AC31+资产负债表!AG31))),"—",360/(利润表!AG6*2/(资产负债表!AC31+资产负债表!AG31))) -> — | N54: =IF(ISERROR(360/(利润表!AK6*2/(资产负债表!AG31+资产负债表!AK31))),"—",360/(利润表!AK6*2/(资产负债表!AG31+资产负债表!AK31))) -> — | O54: =IF(ISERROR(360/(利润表!AL6*2/(资产负债表!AK31+资产负债表!AL31))),"—",360/(利润表!AL6*2/(资产负债表!AK31+资产负债表!AL31))) -> — | P54: =IF(ISERROR(360/(利润表!AM6*2/(资产负债表!AL31+资产负债表!AM31))),"—",360/(利润表!AM6*2/(资产负债表!AL31+资产负债表!AM31))) -> —
B55: 债权融资 | C55: =IF(ISERROR(现金流量表!Y62),"—",现金流量表!Y62) -> 0 | D55: =IF(ISERROR(现金流量表!AC62),"—",现金流量表!AC62) -> 0 | E55: =IF(ISERROR((现金流量表!AG62)),"—",(现金流量表!AG62)) -> 0 | F55: =IF(ISERROR((现金流量表!AK62)),"—",(现金流量表!AK62)) -> 0 | G55: =IF(ISERROR((现金流量表!AL62)),"—",(现金流量表!AL62)) -> 0 | H55: =IF(ISERROR((现金流量表!AM62)),"—",(现金流量表!AM62)) -> 0 | J55: 总资产周转天数 | K55: =IF(ISERROR(360/(利润表!Y6*2/(资产负债表!U45+资产负债表!Y45))),"—",360/(利润表!Y6*2/(资产负债表!U45+资产负债表!Y45))) -> — | L55: =IF(ISERROR(360/(利润表!AC6*2/(资产负债表!Y45+资产负债表!AC45))),"—",360/(利润表!AC6*2/(资产负债表!Y45+资产负债表!AC45))) -> — | M55: =IF(ISERROR(360/(利润表!AG6*2/(资产负债表!AC45+资产负债表!AG45))),"—",360/(利润表!AG6*2/(资产负债表!AC45+资产负债表!AG45))) -> — | N55: =IF(ISERROR(360/(利润表!AK6*2/(资产负债表!AG45+资产负债表!AK45))),"—",360/(利润表!AK6*2/(资产负债表!AG45+资产负债表!AK45))) -> — | O55: =IF(ISERROR(360/(利润表!AL6*2/(资产负债表!AK45+资产负债表!AL45))),"—",360/(利润表!AL6*2/(资产负债表!AK45+资产负债表!AL45))) -> — | P55: =IF(ISERROR(360/(利润表!AM6*2/(资产负债表!AL45+资产负债表!AM45))),"—",360/(利润表!AM6*2/(资产负债表!AL45+资产负债表!AM45))) -> —
B56: 其中:长期借款 | C56: =IF(ISERROR(资产负债表!Y65-资产负债表!U65),"—",资产负债表!Y65-资产负债表!U65) -> 0 | D56: =IF(ISERROR(资产负债表!AC65-资产负债表!Y65),"—",资产负债表!AC65-资产负债表!Y65) -> 0 | E56: =IF(ISERROR(资产负债表!AG65-资产负债表!AC65),"—",资产负债表!AG65-资产负债表!AC65) -> 0 | F56: =IF(ISERROR(资产负债表!AK65-资产负债表!AG65),"—",资产负债表!AK65-资产负债表!AG65) -> 0 | G56: =IF(ISERROR(资产负债表!AL65-资产负债表!AK65),"—",资产负债表!AL65-资产负债表!AK65) -> 0 | H56: =IF(ISERROR(资产负债表!AM65-资产负债表!AL65),"—",资产负债表!AM65-资产负债表!AL65) -> 0 | J56: 偿债能力
B57: 短期借款 | C57: =IF(ISERROR(资产负债表!Y49-资产负债表!U49),"—",资产负债表!Y49-资产负债表!U49) -> 0 | D57: =IF(ISERROR(资产负债表!AC49-资产负债表!Y49),"—",资产负债表!AC49-资产负债表!Y49) -> 0 | E57: =IF(ISERROR(资产负债表!AG49-资产负债表!AC49),"—",资产负债表!AG49-资产负债表!AC49) -> 0 | F57: =IF(ISERROR(资产负债表!AK49-资产负债表!AG49),"—",资产负债表!AK49-资产负债表!AG49) -> 0 | G57: =IF(ISERROR(资产负债表!AL49-资产负债表!AK49),"—",资产负债表!AL49-资产负债表!AK49) -> 0 | H57: =IF(ISERROR(资产负债表!AM49-资产负债表!AL49),"—",资产负债表!AM49-资产负债表!AL49) -> 0 | J57: 资产负债率 | K57: =财务分析!E49 -> — | L57: =财务分析!F49 -> — | M57: =财务分析!G49 -> — | N57: =财务分析!H49 -> — | O57: =财务分析!I49 -> — | P57: =财务分析!J49 -> —
B58: 股利分配与偿付利息 | C58: =IF(ISERROR(现金流量表!Y70),"—",现金流量表!Y70) -> 0 | D58: =IF(ISERROR(现金流量表!AC70),"—",现金流量表!AC70) -> 0 | E58: =IF(ISERROR((现金流量表!AG70)),"—",(现金流量表!AG70)) -> 0 | F58: =IF(ISERROR((现金流量表!AK70)),"—",(现金流量表!AK70)) -> 0 | G58: =IF(ISERROR((现金流量表!AL70)),"—",(现金流量表!AL70)) -> 0 | H58: =IF(ISERROR((现金流量表!AM70)),"—",(现金流量表!AM70)) -> 0 | J58: 净资产负债率 | K58: =财务分析!E48 -> — | L58: =财务分析!F48 -> — | M58: =财务分析!G48 -> — | N58: =财务分析!H48 -> — | O58: =财务分析!I48 -> — | P58: =财务分析!J48 -> —
B59: 其他 | C59: =IF(ISERROR(现金流量表!Y71),"—",现金流量表!Y71) -> 0 | D59: =IF(ISERROR(现金流量表!AC71),"—",现金流量表!AC71) -> 0 | E59: =IF(ISERROR((现金流量表!AG71)),"—",(现金流量表!AG71)) -> 0 | F59: =IF(ISERROR((现金流量表!AK71)),"—",(现金流量表!AK71)) -> 0 | G59: =IF(ISERROR((现金流量表!AL71)),"—",(现金流量表!AL71)) -> 0 | H59: =IF(ISERROR((现金流量表!AM71)),"—",(现金流量表!AM71)) -> 0 | J59: 流动比率 | K59: =财务分析!E43 -> — | L59: =财务分析!F43 -> — | M59: =财务分析!G43 -> — | N59: =财务分析!H43 -> — | O59: =财务分析!I43 -> — | P59: =财务分析!J43 -> —
B60: 筹资活动现金净流 | C60: =IF(ISERROR(现金流量表!Y72),"—",现金流量表!Y72) -> 0 | D60: =IF(ISERROR(现金流量表!AC72),"—",现金流量表!AC72) -> 0 | E60: =IF(ISERROR(现金流量表!AG72),"—",现金流量表!AG72) -> 0 | F60: =IF(ISERROR(现金流量表!AK72),"—",现金流量表!AK72) -> 0 | G60: =IF(ISERROR(现金流量表!AL72),"—",现金流量表!AL72) -> 0 | H60: =IF(ISERROR(现金流量表!AM72),"—",现金流量表!AM72) -> 0 | J60: 速动比率 | K60: =财务分析!E44 -> — | L60: =财务分析!F44 -> — | M60: =财务分析!G44 -> — | N60: =财务分析!H44 -> — | O60: =财务分析!I44 -> — | P60: =财务分析!J44 -> —
B61: 现金净流量 | C61: =IF(ISERROR(现金流量表!Y76),"—",现金流量表!Y76) -> 0 | D61: =IF(ISERROR(现金流量表!AC76),"—",现金流量表!AC76) -> 0 | E61: =IF(ISERROR(现金流量表!AG76),"—",现金流量表!AG76) -> 0 | F61: =IF(ISERROR(现金流量表!AK76),"—",现金流量表!AK76) -> 0 | G61: =IF(ISERROR(现金流量表!AL76),"—",现金流量表!AL76) -> 0 | H61: =IF(ISERROR(现金流量表!AM76),"—",现金流量表!AM76) -> 0 | J61: EBIT利息保障倍数 | K61: =财务分析!E46 -> — | L61: =财务分析!F46 -> — | M61: =财务分析!G46 -> — | N61: =财务分析!H46 -> — | O61: =财务分析!I46 -> — | P61: =财务分析!J46 -> —

Sheet 资产负债表
B2: 资产负债表
B3: =财务基础数据!C4 -> XXXX
B4: 会计年度截止日：12/31 | E4: =财务基础数据!J5 -> 2016 | F4: =财务基础数据!K5 -> 1Q17 | G4: =财务基础数据!L5 -> 1H17 | H4: =财务基础数据!M5 -> 3Q17 | I4: =财务基础数据!N5 -> 2017 | J4: =财务基础数据!O5 -> 1Q18 | K4: =财务基础数据!P5 -> 1H18 | L4: =财务基础数据!Q5 -> 3Q18 | ... AJ4: =财务基础数据!AO5 -> 3Q24 | AK4: =财务基础数据!AP5&"E" -> 2024E | AL4: =财务基础数据!AP5+1 -> 2025 | AM4: =AL4+1 -> 2026 | AN4: =AM4+1 -> 2027 | AO4: =AN4+1 -> 2028 | AP4: =AO4+1 -> 2029 | AQ4: =AP4+1 -> 2030 | AR4: =AQ4+1 -> 2031 | AS4: =AR4+1 -> 2032 | AT4: =AS4+1 -> 2033
B5: ="单位：人民币"&目录!$D$5 -> 单位：人民币百万元
B6: 资产
B8: 货币资金 | E8: =财务基础数据!J63*目录!$D$6 -> 0 | F8: =财务基础数据!K63*目录!$D$6 -> 0 | G8: =财务基础数据!L63*目录!$D$6 -> 0 | H8: =财务基础数据!M63*目录!$D$6 -> 0 | I8: =财务基础数据!N63*目录!$D$6 -> 0 | J8: =财务基础数据!O63*目录!$D$6 -> 0 | K8: =财务基础数据!P63*目录!$D$6 -> 0 | L8: =财务基础数据!Q63*目录!$D$6 -> 0 | ... AJ8: =财务基础数据!AO63*目录!$D$6 -> 0 | AK8: =IF(ISERROR(资产预测!L230),0,资产预测!L230) -> 0 | AL8: =IF(ISERROR(资产预测!M230),0,资产预测!M230) -> 0 | AM8: =IF(ISERROR(资产预测!N230),0,资产预测!N230) -> 0 | AN8: =IF(ISERROR(资产预测!O230),0,资产预测!O230) -> 0 | AO8: =IF(ISERROR(资产预测!P230),0,资产预测!P230) -> 0 | AP8: =IF(ISERROR(资产预测!Q230),0,资产预测!Q230) -> 0 | AQ8: =IF(ISERROR(资产预测!R230),0,资产预测!R230) -> 0 | AR8: =IF(ISERROR(资产预测!S230),0,资产预测!S230) -> 0 | ... AT8: =IF(ISERROR(资产预测!U230),0,资产预测!U230) -> 0
B9: 交易性金融资产 | E9: =(财务基础数据!J64+财务基础数据!J65)*目录!$D$6 -> 0 | F9: =(财务基础数据!K64+财务基础数据!K65)*目录!$D$6 -> 0 | G9: =(财务基础数据!L64+财务基础数据!L65)*目录!$D$6 -> 0 | H9: =(财务基础数据!M64+财务基础数据!M65)*目录!$D$6 -> 0 | I9: =(财务基础数据!N64+财务基础数据!N65)*目录!$D$6 -> 0 | J9: =(财务基础数据!O64+财务基础数据!O65)*目录!$D$6 -> 0 | K9: =(财务基础数据!P64+财务基础数据!P65)*目录!$D$6 -> 0 | L9: =(财务基础数据!Q64+财务基础数据!Q65)*目录!$D$6 -> 0 | ... AJ9: =(财务基础数据!AO64+财务基础数据!AO65)*目录!$D$6 -> 0 | AK9: =IF(ISERROR(资产预测!L71),0,资产预测!L71) -> 0 | AL9: =IF(ISERROR(资产预测!M71),0,资产预测!M71) -> 0 | AM9: =IF(ISERROR(资产预测!N71),0,资产预测!N71) -> 0 | AN9: =IF(ISERROR(资产预测!O71),0,资产预测!O71) -> 0 | AO9: =IF(ISERROR(资产预测!P71),0,资产预测!P71) -> 0 | AP9: =IF(ISERROR(资产预测!Q71),0,资产预测!Q71) -> 0 | AQ9: =IF(ISERROR(资产预测!R71),0,资产预测!R71) -> 0 | AR9: =IF(ISERROR(资产预测!S71),0,资产预测!S71) -> 0 | ... AT9: =IF(ISERROR(资产预测!U71),0,资产预测!U71) -> 0
B10: 衍生金融资产 | E10: =财务基础数据!J150*目录!$D$6 -> 0 | F10: =财务基础数据!K150*目录!$D$6 -> 0 | G10: =财务基础数据!L150*目录!$D$6 -> 0 | H10: =财务基础数据!M150*目录!$D$6 -> 0 | I10: =财务基础数据!N150*目录!$D$6 -> 0 | J10: =财务基础数据!O150*目录!$D$6 -> 0 | K10: =财务基础数据!P150*目录!$D$6 -> 0 | L10: =财务基础数据!Q150*目录!$D$6 -> 0 | ... AJ10: =财务基础数据!AO150*目录!$D$6 -> 0 | AK10: =IF(ISERROR(资产预测!L75),0,资产预测!L75) -> 0 | AL10: =IF(ISERROR(资产预测!M75),0,资产预测!M75) -> 0 | AM10: =IF(ISERROR(资产预测!N75),0,资产预测!N75) -> 0 | AN10: =IF(ISERROR(资产预测!O75),0,资产预测!O75) -> 0 | AO10: =IF(ISERROR(资产预测!P75),0,资产预测!P75) -> 0 | AP10: =IF(ISERROR(资产预测!Q75),0,资产预测!Q75) -> 0 | AQ10: =IF(ISERROR(资产预测!R75),0,资产预测!R75) -> 0 | AR10: =IF(ISERROR(资产预测!S75),0,资产预测!S75) -> 0 | ... AT10: =IF(ISERROR(资产预测!U75),0,资产预测!U75) -> 0
B11: 应收票据 | E11: =(财务基础数据!J66)*目录!$D$6 -> 0 | F11: =(财务基础数据!K66)*目录!$D$6 -> 0 | G11: =(财务基础数据!L66)*目录!$D$6 -> 0 | H11: =(财务基础数据!M66)*目录!$D$6 -> 0 | I11: =(财务基础数据!N66)*目录!$D$6 -> 0 | J11: =(财务基础数据!O66)*目录!$D$6 -> 0 | K11: =(财务基础数据!P66)*目录!$D$6 -> 0 | L11: =(财务基础数据!Q66)*目录!$D$6 -> 0 | ... AD11: =(财务基础数据!AI66)*目录!$D$6 -> 0 | AE11: =IF(财务基础数据!AJ147=0,财务基础数据!AJ66*目录!$D$6,0) -> 0 | AF11: =(财务基础数据!AK66)*目录!$D$6 -> 0 | AG11: =(财务基础数据!AL66)*目录!$D$6 -> 0 | AH11: =(财务基础数据!AM66)*目录!$D$6 -> 0 | AI11: =(财务基础数据!AN66)*目录!$D$6 -> 0 | AJ11: =(财务基础数据!AO66)*目录!$D$6 -> 0 | AK11: =IF(ISERROR(资产预测!L10+投资与减值!L178),0,资产预测!L10+投资与减值!L178) -> 0 | AL11: =IF(ISERROR(资产预测!M10+投资与减值!M178),0,资产预测!M10+投资与减值!M178)+投资与减值!L178 -> 0 | AM11: =IF(ISERROR(资产预测!N10+投资与减值!N178),0,资产预测!N10+投资与减值!N178)+SUM(投资与减值!$L178:M178) -> 0 | AN11: =IF(ISERROR(资产预测!O10+投资与减值!O178),0,资产预测!O10+投资与减值!O178)+SUM(投资与减值!$L178:N178) -> 0 | AO11: =IF(ISERROR(资产预测!P10+投资与减值!P178),0,资产预测!P10+投资与减值!P178)+SUM(投资与减值!$L178:O178) -> 0 | AP11: =IF(ISERROR(资产预测!Q10+投资与减值!Q178),0,资产预测!Q10+投资与减值!Q178)+SUM(投资与减值!$L178:P178) -> 0 | AQ11: =IF(ISERROR(资产预测!R10+投资与减值!R178),0,资产预测!R10+投资与减值!R178)+SUM(投资与减值!$L178:Q178) -> 0 | AR11: =IF(ISERROR(资产预测!S10+投资与减值!S178),0,资产预测!S10+投资与减值!S178)+SUM(投资与减值!$L178:R178) -> 0 | AS11: =IF(ISERROR(资产预测!T10+投资与减值!T178),0,资产预测!T10+投资与减值!T178)+SUM(投资与减值!$L178:S178) -> 0 | AT11: =IF(ISERROR(资产预测!U10+投资与减值!U178),0,资产预测!U10+投资与减值!U178)+SUM(投资与减值!$L178:T178) -> 0
B12: 应收账款 | E12: =(财务基础数据!J67)*目录!$D$6 -> 0 | F12: =(财务基础数据!K67)*目录!$D$6 -> 0 | G12: =(财务基础数据!L67)*目录!$D$6 -> 0 | H12: =(财务基础数据!M67)*目录!$D$6 -> 0 | I12: =(财务基础数据!N67)*目录!$D$6 -> 0 | J12: =(财务基础数据!O67)*目录!$D$6 -> 0 | K12: =(财务基础数据!P67)*目录!$D$6 -> 0 | L12: =(财务基础数据!Q67)*目录!$D$6 -> 0 | ... AD12: =(财务基础数据!AI67)*目录!$D$6 -> 0 | AE12: =(财务基础数据!AJ147)*目录!$D$6 -> 0 | AF12: =(财务基础数据!AK67)*目录!$D$6 -> 0 | AG12: =(财务基础数据!AL67)*目录!$D$6 -> 0 | AH12: =(财务基础数据!AM67)*目录!$D$6 -> 0 | AI12: =(财务基础数据!AN67)*目录!$D$6 -> 0 | AJ12: =(财务基础数据!AO67)*目录!$D$6 -> 0 | AK12: =IF(ISERROR(资产预测!L14+投资与减值!L177),0,资产预测!L14+投资与减值!L177) -> 0 | AL12: =IF(ISERROR(资产预测!M14+投资与减值!M177),0,资产预测!M14+投资与减值!M177)+投资与减值!L177 -> 0 | AM12: =IF(ISERROR(资产预测!N14+投资与减值!N177),0,资产预测!N14+投资与减值!N177)+SUM(投资与减值!$L177:M177) -> 0 | AN12: =IF(ISERROR(资产预测!O14+投资与减值!O177),0,资产预测!O14+投资与减值!O177)+SUM(投资与减值!$L177:N177) -> 0 | AO12: =IF(ISERROR(资产预测!P14+投资与减值!P177),0,资产预测!P14+投资与减值!P177)+SUM(投资与减值!$L177:O177) -> 0 | AP12: =IF(ISERROR(资产预测!Q14+投资与减值!Q177),0,资产预测!Q14+投资与减值!Q177)+SUM(投资与减值!$L177:P177) -> 0 | AQ12: =IF(ISERROR(资产预测!R14+投资与减值!R177),0,资产预测!R14+投资与减值!R177)+SUM(投资与减值!$L177:Q177) -> 0 | AR12: =IF(ISERROR(资产预测!S14+投资与减值!S177),0,资产预测!S14+投资与减值!S177)+SUM(投资与减值!$L177:R177) -> 0 | AS12: =IF(ISERROR(资产预测!T14+投资与减值!T177),0,资产预测!T14+投资与减值!T177)+SUM(投资与减值!$L177:S177) -> 0 | AT12: =IF(ISERROR(资产预测!U14+投资与减值!U177),0,资产预测!U14+投资与减值!U177)+SUM(投资与减值!$L177:T177) -> 0
B13: 应收款项融资 | E13: =(财务基础数据!J163)*目录!$D$6 -> 0 | F13: =(财务基础数据!K163)*目录!$D$6 -> 0 | G13: =(财务基础数据!L163)*目录!$D$6 -> 0 | H13: =(财务基础数据!M163)*目录!$D$6 -> 0 | I13: =(财务基础数据!N163)*目录!$D$6 -> 0 | J13: =(财务基础数据!O163)*目录!$D$6 -> 0 | K13: =(财务基础数据!P163)*目录!$D$6 -> 0 | L13: =(财务基础数据!Q163)*目录!$D$6 -> 0 | ... AJ13: =(财务基础数据!AO163)*目录!$D$6 -> 0 | AK13: =IF(ISERROR(资产预测!L18),0,资产预测!L18) -> 0 | AL13: =IF(ISERROR(资产预测!M18),0,资产预测!M18) -> 0 | AM13: =IF(ISERROR(资产预测!N18),0,资产预测!N18) -> 0 | AN13: =IF(ISERROR(资产预测!O18),0,资产预测!O18) -> 0 | AO13: =IF(ISERROR(资产预测!P18),0,资产预测!P18) -> 0 | AP13: =IF(ISERROR(资产预测!Q18),0,资产预测!Q18) -> 0 | AQ13: =IF(ISERROR(资产预测!R18),0,资产预测!R18) -> 0 | AR13: =IF(ISERROR(资产预测!S18),0,资产预测!S18) -> 0 | ... AT13: =IF(ISERROR(资产预测!U18),0,资产预测!U18) -> 0
B14: 预付款项 | E14: =财务基础数据!J69*目录!$D$6 -> 0 | F14: =财务基础数据!K69*目录!$D$6 -> 0 | G14: =财务基础数据!L69*目录!$D$6 -> 0 | H14: =财务基础数据!M69*目录!$D$6 -> 0 | I14: =财务基础数据!N69*目录!$D$6 -> 0 | J14: =财务基础数据!O69*目录!$D$6 -> 0 | K14: =财务基础数据!P69*目录!$D$6 -> 0 | L14: =财务基础数据!Q69*目录!$D$6 -> 0 | ... AJ14: =财务基础数据!AO69*目录!$D$6 -> 0 | AK14: =IF(ISERROR(资产预测!L21),0,资产预测!L21) -> 0 | AL14: =IF(ISERROR(资产预测!M21),0,资产预测!M21) -> 0 | AM14: =IF(ISERROR(资产预测!N21),0,资产预测!N21) -> 0 | AN14: =IF(ISERROR(资产预测!O21),0,资产预测!O21) -> 0 | AO14: =IF(ISERROR(资产预测!P21),0,资产预测!P21) -> 0 | AP14: =IF(ISERROR(资产预测!Q21),0,资产预测!Q21) -> 0 | AQ14: =IF(ISERROR(资产预测!R21),0,资产预测!R21) -> 0 | AR14: =IF(ISERROR(资产预测!S21),0,资产预测!S21) -> 0 | ... AT14: =IF(ISERROR(资产预测!U21),0,资产预测!U21) -> 0
B15: 其他应收款 | E15: =(财务基础数据!J153)*目录!$D$6 -> 0 | F15: =(财务基础数据!K153)*目录!$D$6 -> 0 | G15: =(财务基础数据!L153)*目录!$D$6 -> 0 | H15: =(财务基础数据!M153)*目录!$D$6 -> 0 | I15: =(财务基础数据!N153)*目录!$D$6 -> 0 | J15: =(财务基础数据!O153)*目录!$D$6 -> 0 | K15: =(财务基础数据!P153)*目录!$D$6 -> 0 | L15: =(财务基础数据!Q153)*目录!$D$6 -> 0 | ... AJ15: =(财务基础数据!AO153)*目录!$D$6 -> 0 | AK15: =IF(ISERROR(资产预测!L24+投资与减值!L179),0,资产预测!L24+投资与减值!L179) -> 0 | AL15: =IF(ISERROR(资产预测!M24+投资与减值!M179),0,资产预测!M24+投资与减值!M179)+投资与减值!L179 -> 0 | AM15: =IF(ISERROR(资产预测!N24+投资与减值!N179),0,资产预测!N24+投资与减值!N179)+SUM(投资与减值!$L179:M179) -> 0 | AN15: =IF(ISERROR(资产预测!O24+投资与减值!O179),0,资产预测!O24+投资与减值!O179)+SUM(投资与减值!$L179:N179) -> 0 | AO15: =IF(ISERROR(资产预测!P24+投资与减值!P179),0,资产预测!P24+投资与减值!P179)+SUM(投资与减值!$L179:O179) -> 0 | AP15: =IF(ISERROR(资产预测!Q24+投资与减值!Q179),0,资产预测!Q24+投资与减值!Q179)+SUM(投资与减值!$L179:P179) -> 0 | AQ15: =IF(ISERROR(资产预测!R24+投资与减值!R179),0,资产预测!R24+投资与减值!R179)+SUM(投资与减值!$L179:Q179) -> 0 | AR15: =IF(ISERROR(资产预测!S24+投资与减值!S179),0,资产预测!S24+投资与减值!S179)+SUM(投资与减值!$L179:R179) -> 0 | AS15: =IF(ISERROR(资产预测!T24+投资与减值!T179),0,资产预测!T24+投资与减值!T179)+SUM(投资与减值!$L179:S179) -> 0 | AT15: =IF(ISERROR(资产预测!U24+投资与减值!U179),0,资产预测!U24+投资与减值!U179)+SUM(投资与减值!$L179:T179) -> 0
B16: 存货 | E16: =财务基础数据!J70*目录!$D$6 -> 0 | F16: =财务基础数据!K70*目录!$D$6 -> 0 | G16: =财务基础数据!L70*目录!$D$6 -> 0 | H16: =财务基础数据!M70*目录!$D$6 -> 0 | I16: =财务基础数据!N70*目录!$D$6 -> 0 | J16: =财务基础数据!O70*目录!$D$6 -> 0 | K16: =财务基础数据!P70*目录!$D$6 -> 0 | L16: =财务基础数据!Q70*目录!$D$6 -> 0 | ... AJ16: =财务基础数据!AO70*目录!$D$6 -> 0 | AK16: =IF(ISERROR(资产预测!L28+投资与减值!L171),0,资产预测!L28+投资与减值!L171) -> 0 | AL16: =IF(ISERROR(资产预测!M28+投资与减值!M171),0,资产预测!M28+投资与减值!M171)+投资与减值!L171 -> 0 | AM16: =IF(ISERROR(资产预测!N28+投资与减值!N171),0,资产预测!N28+投资与减值!N171)+SUM(投资与减值!$L171:M171) -> 0 | AN16: =IF(ISERROR(资产预测!O28+投资与减值!O171),0,资产预测!O28+投资与减值!O171)+SUM(投资与减值!$L171:N171) -> 0 | AO16: =IF(ISERROR(资产预测!P28+投资与减值!P171),0,资产预测!P28+投资与减值!P171)+SUM(投资与减值!$L171:O171) -> 0 | AP16: =IF(ISERROR(资产预测!Q28+投资与减值!Q171),0,资产预测!Q28+投资与减值!Q171)+SUM(投资与减值!$L171:P171) -> 0 | AQ16: =IF(ISERROR(资产预测!R28+投资与减值!R171),0,资产预测!R28+投资与减值!R171)+SUM(投资与减值!$L171:Q171) -> 0 | AR16: =IF(ISERROR(资产预测!S28+投资与减值!S171),0,资产预测!S28+投资与减值!S171)+SUM(投资与减值!$L171:R171) -> 0 | AS16: =IF(ISERROR(资产预测!T28+投资与减值!T171),0,资产预测!T28+投资与减值!T171)+SUM(投资与减值!$L171:S171) -> 0 | AT16: =IF(ISERROR(资产预测!U28+投资与减值!U171),0,资产预测!U28+投资与减值!U171)+SUM(投资与减值!$L171:T171) -> 0
B17: 合同资产 | E17: =财务基础数据!J145*目录!$D$6 -> 0 | F17: =财务基础数据!K145*目录!$D$6 -> 0 | G17: =财务基础数据!L145*目录!$D$6 -> 0 | H17: =财务基础数据!M145*目录!$D$6 -> 0 | I17: =财务基础数据!N145*目录!$D$6 -> 0 | J17: =财务基础数据!O145*目录!$D$6 -> 0 | K17: =财务基础数据!P145*目录!$D$6 -> 0 | L17: =财务基础数据!Q145*目录!$D$6 -> 0 | ... AJ17: =财务基础数据!AO145*目录!$D$6 -> 0 | AK17: =IF(ISERROR(资产预测!L32+投资与减值!L172),"—",资产预测!L32+投资与减值!L172) -> 0 | AL17: =IF(ISERROR(资产预测!M32+投资与减值!M172),"—",资产预测!M32+投资与减值!M172)+投资与减值!L172 -> 0 | AM17: =IF(ISERROR(资产预测!N32+投资与减值!N172),"—",资产预测!N32+投资与减值!N172)+SUM(投资与减值!$L172:M172) -> 0 | AN17: =IF(ISERROR(资产预测!O32+投资与减值!O172),"—",资产预测!O32+投资与减值!O172)+SUM(投资与减值!$L172:N172) -> 0 | AO17: =IF(ISERROR(资产预测!P32+投资与减值!P172),"—",资产预测!P32+投资与减值!P172)+SUM(投资与减值!$L172:O172) -> 0 | AP17: =IF(ISERROR(资产预测!Q32+投资与减值!Q172),"—",资产预测!Q32+投资与减值!Q172)+SUM(投资与减值!$L172:P172) -> 0 | AQ17: =IF(ISERROR(资产预测!R32+投资与减值!R172),"—",资产预测!R32+投资与减值!R172)+SUM(投资与减值!$L172:Q172) -> 0 | AR17: =IF(ISERROR(资产预测!S32+投资与减值!S172),"—",资产预测!S32+投资与减值!S172)+SUM(投资与减值!$L172:R172) -> 0 | AS17: =IF(ISERROR(资产预测!T32+投资与减值!T172),"—",资产预测!T32+投资与减值!T172)+SUM(投资与减值!$L172:S172) -> 0 | AT17: =IF(ISERROR(资产预测!U32+投资与减值!U172),"—",资产预测!U32+投资与减值!U172)+SUM(投资与减值!$L172:T172) -> 0
B18: 持有待售资产 | E18: =(财务基础数据!J141+财务基础数据!J137)*目录!$D$6 -> 0 | F18: =(财务基础数据!K141+财务基础数据!K137)*目录!$D$6 -> 0 | G18: =(财务基础数据!L141+财务基础数据!L137)*目录!$D$6 -> 0 | H18: =(财务基础数据!M141+财务基础数据!M137)*目录!$D$6 -> 0 | I18: =(财务基础数据!N141+财务基础数据!N137)*目录!$D$6 -> 0 | J18: =(财务基础数据!O141+财务基础数据!O137)*目录!$D$6 -> 0 | K18: =(财务基础数据!P141+财务基础数据!P137)*目录!$D$6 -> 0 | L18: =(财务基础数据!Q141+财务基础数据!Q137)*目录!$D$6 -> 0 | ... AJ18: =(财务基础数据!AO141+财务基础数据!AO137)*目录!$D$6 -> 0 | AK18: =IF(财务基础数据!$AM$4=0,AG18,IF(财务基础数据!$AM$4=1,AH18,IF(财务基础数据!$AM$4=2,AI18,AJ18))) -> 0 | AL18: =AK18 -> 0 | AM18: =AL18 -> 0 | AN18: =AM18 -> 0 | AO18: =AN18 -> 0 | AP18: =AO18 -> 0 | AQ18: =AP18 -> 0 | AR18: =AQ18 -> 0 | AS18: =AR18 -> 0 | AT18: =AS18 -> 0
B19: 一年内到期的非流动资产 | E19: =(财务基础数据!J71+财务基础数据!J72)*目录!$D$6 -> 0 | F19: =(财务基础数据!K71+财务基础数据!K72)*目录!$D$6 -> 0 | G19: =(财务基础数据!L71+财务基础数据!L72)*目录!$D$6 -> 0 | H19: =(财务基础数据!M71+财务基础数据!M72)*目录!$D$6 -> 0 | I19: =(财务基础数据!N71+财务基础数据!N72)*目录!$D$6 -> 0 | J19: =(财务基础数据!O71+财务基础数据!O72)*目录!$D$6 -> 0 | K19: =(财务基础数据!P71+财务基础数据!P72)*目录!$D$6 -> 0 | L19: =(财务基础数据!Q71+财务基础数据!Q72)*目录!$D$6 -> 0 | ... AJ19: =(财务基础数据!AO71+财务基础数据!AO72)*目录!$D$6 -> 0 | AK19: =IF(财务基础数据!$AM$4=0,AG19,IF(财务基础数据!$AM$4=1,AH19,IF(财务基础数据!$AM$4=2,AI19,AJ19))) -> 0 | AL19: =AK19 -> 0 | AM19: =AL19 -> 0 | AN19: =AM19 -> 0 | AO19: =AN19 -> 0 | AP19: =AO19 -> 0 | AQ19: =AP19 -> 0 | AR19: =AQ19 -> 0 | AS19: =AR19 -> 0 | AT19: =AS19 -> 0
B20: 其他流动资产 | E20: =E21-SUM(E8:E19) -> 0 | F20: =F21-SUM(F8:F19) -> 0 | G20: =G21-SUM(G8:G19) -> 0 | H20: =H21-SUM(H8:H19) -> 0 | I20: =I21-SUM(I8:I19) -> 0 | J20: =J21-SUM(J8:J19) -> 0 | K20: =K21-SUM(K8:K19) -> 0 | L20: =L21-SUM(L8:L19) -> 0 | ... AJ20: =AJ21-SUM(AJ8:AJ19) -> 0 | AK20: =IF(ISERROR(资产预测!L79),0,资产预测!L79) -> 0 | AL20: =IF(ISERROR(资产预测!M79),0,资产预测!M79) -> 0 | AM20: =IF(ISERROR(资产预测!N79),0,资产预测!N79) -> 0 | AN20: =IF(ISERROR(资产预测!O79),0,资产预测!O79) -> 0 | AO20: =IF(ISERROR(资产预测!P79),0,资产预测!P79) -> 0 | AP20: =IF(ISERROR(资产预测!Q79),0,资产预测!Q79) -> 0 | AQ20: =IF(ISERROR(资产预测!R79),0,资产预测!R79) -> 0 | AR20: =IF(ISERROR(资产预测!S79),0,资产预测!S79) -> 0 | ... AT20: =IF(ISERROR(资产预测!U79),0,资产预测!U79) -> 0
B21: 流动资产总额 | E21: =财务基础数据!J74*目录!$D$6 -> 0 | F21: =财务基础数据!K74*目录!$D$6 -> 0 | G21: =财务基础数据!L74*目录!$D$6 -> 0 | H21: =财务基础数据!M74*目录!$D$6 -> 0 | I21: =财务基础数据!N74*目录!$D$6 -> 0 | J21: =财务基础数据!O74*目录!$D$6 -> 0 | K21: =财务基础数据!P74*目录!$D$6 -> 0 | L21: =财务基础数据!Q74*目录!$D$6 -> 0 | ... AJ21: =财务基础数据!AO74*目录!$D$6 -> 0 | AK21: =SUM(AK8:AK20) -> 0 | AL21: =SUM(AL8:AL20) -> 0 | AM21: =SUM(AM8:AM20) -> 0 | AN21: =SUM(AN8:AN20) -> 0 | AO21: =SUM(AO8:AO20) -> 0 | AP21: =SUM(AP8:AP20) -> 0 | AQ21: =SUM(AQ8:AQ20) -> 0 | AR21: =SUM(AR8:AR20) -> 0 | ... AT21: =SUM(AT8:AT20) -> 0
B24: 债权投资 | E24: =财务基础数据!J158*目录!$D$6 -> 0 | F24: =财务基础数据!K158*目录!$D$6 -> 0 | G24: =财务基础数据!L158*目录!$D$6 -> 0 | H24: =财务基础数据!M158*目录!$D$6 -> 0 | I24: =财务基础数据!N158*目录!$D$6 -> 0 | J24: =财务基础数据!O158*目录!$D$6 -> 0 | K24: =财务基础数据!P158*目录!$D$6 -> 0 | L24: =财务基础数据!Q158*目录!$D$6 -> 0 | ... AJ24: =财务基础数据!AO158*目录!$D$6 -> 0 | AK24: =IF(ISERROR(资产预测!L99+投资与减值!L181),"—",资产预测!L99+投资与减值!L181) -> 0 | AL24: =IF(ISERROR(资产预测!M99+投资与减值!M181),"—",资产预测!M99+投资与减值!M181)+投资与减值!L181 -> 0 | AM24: =IF(ISERROR(资产预测!N99+投资与减值!N181),"—",资产预测!N99+投资与减值!N181)+SUM(投资与减值!$L181:M181) -> 0 | AN24: =IF(ISERROR(资产预测!O99+投资与减值!O181),"—",资产预测!O99+投资与减值!O181)+SUM(投资与减值!$L181:N181) -> 0 | AO24: =IF(ISERROR(资产预测!P99+投资与减值!P181),"—",资产预测!P99+投资与减值!P181)+SUM(投资与减值!$L181:O181) -> 0 | AP24: =IF(ISERROR(资产预测!Q99+投资与减值!Q181),"—",资产预测!Q99+投资与减值!Q181)+SUM(投资与减值!$L181:P181) -> 0 | AQ24: =IF(ISERROR(资产预测!R99+投资与减值!R181),"—",资产预测!R99+投资与减值!R181)+SUM(投资与减值!$L181:Q181) -> 0 | AR24: =IF(ISERROR(资产预测!S99+投资与减值!S181),"—",资产预测!S99+投资与减值!S181)+SUM(投资与减值!$L181:R181) -> 0 | AS24: =IF(ISERROR(资产预测!T99+投资与减值!T181),"—",资产预测!T99+投资与减值!T181)+SUM(投资与减值!$L181:S181) -> 0 | AT24: =IF(ISERROR(资产预测!U99+投资与减值!U181),"—",资产预测!U99+投资与减值!U181)+SUM(投资与减值!$L181:T181) -> 0
B25: 其他债权投资 | E25: =财务基础数据!J159*目录!$D$6 -> 0 | F25: =财务基础数据!K159*目录!$D$6 -> 0 | G25: =财务基础数据!L159*目录!$D$6 -> 0 | H25: =财务基础数据!M159*目录!$D$6 -> 0 | I25: =财务基础数据!N159*目录!$D$6 -> 0 | J25: =财务基础数据!O159*目录!$D$6 -> 0 | K25: =财务基础数据!P159*目录!$D$6 -> 0 | L25: =财务基础数据!Q159*目录!$D$6 -> 0 | ... AJ25: =财务基础数据!AO159*目录!$D$6 -> 0 | AK25: =IF(ISERROR(资产预测!L102+投资与减值!L182),"—",资产预测!L102+投资与减值!L182) -> 0 | AL25: =IF(ISERROR(资产预测!M102+投资与减值!M182),"—",资产预测!M102+投资与减值!M182)+投资与减值!L182 -> 0 | AM25: =IF(ISERROR(资产预测!N102+投资与减值!N182),"—",资产预测!N102+投资与减值!N182)+SUM(投资与减值!$L182:M182) -> 0 | AN25: =IF(ISERROR(资产预测!O102+投资与减值!O182),"—",资产预测!O102+投资与减值!O182)+SUM(投资与减值!$L182:N182) -> 0 | AO25: =IF(ISERROR(资产预测!P102+投资与减值!P182),"—",资产预测!P102+投资与减值!P182)+SUM(投资与减值!$L182:O182) -> 0 | AP25: =IF(ISERROR(资产预测!Q102+投资与减值!Q182),"—",资产预测!Q102+投资与减值!Q182)+SUM(投资与减值!$L182:P182) -> 0 | AQ25: =IF(ISERROR(资产预测!R102+投资与减值!R182),"—",资产预测!R102+投资与减值!R182)+SUM(投资与减值!$L182:Q182) -> 0 | AR25: =IF(ISERROR(资产预测!S102+投资与减值!S182),"—",资产预测!S102+投资与减值!S182)+SUM(投资与减值!$L182:R182) -> 0 | AS25: =IF(ISERROR(资产预测!T102+投资与减值!T182),"—",资产预测!T102+投资与减值!T182)+SUM(投资与减值!$L182:S182) -> 0 | AT25: =IF(ISERROR(资产预测!U102+投资与减值!U182),"—",资产预测!U102+投资与减值!U182)+SUM(投资与减值!$L182:T182) -> 0
B26: 长期应收款 | E26: =财务基础数据!J77*目录!$D$6 -> 0 | F26: =财务基础数据!K77*目录!$D$6 -> 0 | G26: =财务基础数据!L77*目录!$D$6 -> 0 | H26: =财务基础数据!M77*目录!$D$6 -> 0 | I26: =财务基础数据!N77*目录!$D$6 -> 0 | J26: =财务基础数据!O77*目录!$D$6 -> 0 | K26: =财务基础数据!P77*目录!$D$6 -> 0 | L26: =财务基础数据!Q77*目录!$D$6 -> 0 | ... AJ26: =财务基础数据!AO77*目录!$D$6 -> 0 | AK26: =IF(ISERROR(资产预测!L105+投资与减值!L180),"—",资产预测!L105+投资与减值!L180) -> 0 | AL26: =IF(ISERROR(资产预测!M105+投资与减值!M180),"—",资产预测!M105+投资与减值!M180)+投资与减值!L180 -> 0 | AM26: =IF(ISERROR(资产预测!N105+投资与减值!N180),"—",资产预测!N105+投资与减值!N180)+SUM(投资与减值!$L180:M180) -> 0 | AN26: =IF(ISERROR(资产预测!O105+投资与减值!O180),"—",资产预测!O105+投资与减值!O180)+SUM(投资与减值!$L180:N180) -> 0 | AO26: =IF(ISERROR(资产预测!P105+投资与减值!P180),"—",资产预测!P105+投资与减值!P180)+SUM(投资与减值!$L180:O180) -> 0 | AP26: =IF(ISERROR(资产预测!Q105+投资与减值!Q180),"—",资产预测!Q105+投资与减值!Q180)+SUM(投资与减值!$L180:P180) -> 0 | AQ26: =IF(ISERROR(资产预测!R105+投资与减值!R180),"—",资产预测!R105+投资与减值!R180)+SUM(投资与减值!$L180:Q180) -> 0 | AR26: =IF(ISERROR(资产预测!S105+投资与减值!S180),"—",资产预测!S105+投资与减值!S180)+SUM(投资与减值!$L180:R180) -> 0 | AS26: =IF(ISERROR(资产预测!T105+投资与减值!T180),"—",资产预测!T105+投资与减值!T180)+SUM(投资与减值!$L180:S180) -> 0 | AT26: =IF(ISERROR(资产预测!U105+投资与减值!U180),"—",资产预测!U105+投资与减值!U180)+SUM(投资与减值!$L180:T180) -> 0
B27: 长期股权投资 | E27: =财务基础数据!J78*目录!$D$6 -> 0 | F27: =财务基础数据!K78*目录!$D$6 -> 0 | G27: =财务基础数据!L78*目录!$D$6 -> 0 | H27: =财务基础数据!M78*目录!$D$6 -> 0 | I27: =财务基础数据!N78*目录!$D$6 -> 0 | J27: =财务基础数据!O78*目录!$D$6 -> 0 | K27: =财务基础数据!P78*目录!$D$6 -> 0 | L27: =财务基础数据!Q78*目录!$D$6 -> 0 | ... AJ27: =财务基础数据!AO78*目录!$D$6 -> 0 | AK27: =IF(ISERROR(投资与减值!L90),"—",投资与减值!L90) -> 0 | AL27: =IF(ISERROR(投资与减值!M90),"—",投资与减值!M90) -> 0 | AM27: =IF(ISERROR(投资与减值!N90),"—",投资与减值!N90) -> 0 | AN27: =IF(ISERROR(投资与减值!O90),"—",投资与减值!O90) -> 0 | AO27: =IF(ISERROR(投资与减值!P90),"—",投资与减值!P90) -> 0 | AP27: =IF(ISERROR(投资与减值!Q90),"—",投资与减值!Q90) -> 0 | AQ27: =IF(ISERROR(投资与减值!R90),"—",投资与减值!R90) -> 0 | AR27: =IF(ISERROR(投资与减值!S90),"—",投资与减值!S90) -> 0 | ... AT27: =IF(ISERROR(投资与减值!U90),"—",投资与减值!U90) -> 0
B28: 其他权益工具投资 | E28: =财务基础数据!J160*目录!$D$6 -> 0 | F28: =财务基础数据!K160*目录!$D$6 -> 0 | G28: =财务基础数据!L160*目录!$D$6 -> 0 | H28: =财务基础数据!M160*目录!$D$6 -> 0 | I28: =财务基础数据!N160*目录!$D$6 -> 0 | J28: =财务基础数据!O160*目录!$D$6 -> 0 | K28: =财务基础数据!P160*目录!$D$6 -> 0 | L28: =财务基础数据!Q160*目录!$D$6 -> 0 | ... AJ28: =财务基础数据!AO160*目录!$D$6 -> 0 | AK28: =IF(ISERROR(资产预测!L108),"—",资产预测!L108) -> 0 | AL28: =IF(ISERROR(资产预测!M108),"—",资产预测!M108) -> 0 | AM28: =IF(ISERROR(资产预测!N108),"—",资产预测!N108) -> 0 | AN28: =IF(ISERROR(资产预测!O108),"—",资产预测!O108) -> 0 | AO28: =IF(ISERROR(资产预测!P108),"—",资产预测!P108) -> 0 | AP28: =IF(ISERROR(资产预测!Q108),"—",资产预测!Q108) -> 0 | AQ28: =IF(ISERROR(资产预测!R108),"—",资产预测!R108) -> 0 | AR28: =IF(ISERROR(资产预测!S108),"—",资产预测!S108) -> 0 | ... AT28: =IF(ISERROR(资产预测!U108),"—",资产预测!U108) -> 0
B29: 其他非流动金融资产 | E29: =(财务基础数据!J143+财务基础数据!J144+财务基础数据!J161)*目录!$D$6 -> 0 | F29: =(财务基础数据!K143+财务基础数据!K144+财务基础数据!K161)*目录!$D$6 -> 0 | G29: =(财务基础数据!L143+财务基础数据!L144+财务基础数据!L161)*目录!$D$6 -> 0 | H29: =(财务基础数据!M143+财务基础数据!M144+财务基础数据!M161)*目录!$D$6 -> 0 | I29: =(财务基础数据!N143+财务基础数据!N144+财务基础数据!N161)*目录!$D$6 -> 0 | J29: =(财务基础数据!O143+财务基础数据!O144+财务基础数据!O161)*目录!$D$6 -> 0 | K29: =(财务基础数据!P143+财务基础数据!P144+财务基础数据!P161)*目录!$D$6 -> 0 | L29: =(财务基础数据!Q143+财务基础数据!Q144+财务基础数据!Q161)*目录!$D$6 -> 0 | ... AJ29: =(财务基础数据!AO143+财务基础数据!AO144+财务基础数据!AO161)*目录!$D$6 -> 0 | AK29: =IF(ISERROR(资产预测!L111),"—",资产预测!L111) -> 0 | AL29: =IF(ISERROR(资产预测!M111),"—",资产预测!M111) -> 0 | AM29: =IF(ISERROR(资产预测!N111),"—",资产预测!N111) -> 0 | AN29: =IF(ISERROR(资产预测!O111),"—",资产预测!O111) -> 0 | AO29: =IF(ISERROR(资产预测!P111),"—",资产预测!P111) -> 0 | AP29: =IF(ISERROR(资产预测!Q111),"—",资产预测!Q111) -> 0 | AQ29: =IF(ISERROR(资产预测!R111),"—",资产预测!R111) -> 0 | AR29: =IF(ISERROR(资产预测!S111),"—",资产预测!S111) -> 0 | ... AT29: =IF(ISERROR(资产预测!U111),"—",资产预测!U111) -> 0
B30: 投资性房地产 | E30: =财务基础数据!J82*目录!$D$6 -> 0 | F30: =财务基础数据!K82*目录!$D$6 -> 0 | G30: =财务基础数据!L82*目录!$D$6 -> 0 | H30: =财务基础数据!M82*目录!$D$6 -> 0 | I30: =财务基础数据!N82*目录!$D$6 -> 0 | J30: =财务基础数据!O82*目录!$D$6 -> 0 | K30: =财务基础数据!P82*目录!$D$6 -> 0 | L30: =财务基础数据!Q82*目录!$D$6 -> 0 | ... AJ30: =财务基础数据!AO82*目录!$D$6 -> 0 | AK30: =IF(ISERROR(投资与减值!L101),"—",投资与减值!L101) -> 0 | AL30: =IF(ISERROR(投资与减值!M101),"—",投资与减值!M101) -> 0 | AM30: =IF(ISERROR(投资与减值!N101),"—",投资与减值!N101) -> 0 | AN30: =IF(ISERROR(投资与减值!O101),"—",投资与减值!O101) -> 0 | AO30: =IF(ISERROR(投资与减值!P101),"—",投资与减值!P101) -> 0 | AP30: =IF(ISERROR(投资与减值!Q101),"—",投资与减值!Q101) -> 0 | AQ30: =IF(ISERROR(投资与减值!R101),"—",投资与减值!R101) -> 0 | AR30: =IF(ISERROR(投资与减值!S101),"—",投资与减值!S101) -> 0 | ... AT30: =IF(ISERROR(投资与减值!U101),"—",投资与减值!U101) -> 0
B31: 固定资产 | E31: =(财务基础数据!J154)*目录!$D$6 -> 0 | F31: =(财务基础数据!K154)*目录!$D$6 -> 0 | G31: =(财务基础数据!L154)*目录!$D$6 -> 0 | H31: =(财务基础数据!M154)*目录!$D$6 -> 0 | I31: =(财务基础数据!N154)*目录!$D$6 -> 0 | J31: =(财务基础数据!O154)*目录!$D$6 -> 0 | K31: =(财务基础数据!P154)*目录!$D$6 -> 0 | L31: =(财务基础数据!Q154)*目录!$D$6 -> 0 | ... AJ31: =(财务基础数据!AO154)*目录!$D$6 -> 0 | AK31: =IF(ISERROR(投资与减值!L24),"—",投资与减值!L24) -> 0 | AL31: =IF(ISERROR(投资与减值!M24),"—",投资与减值!M24) -> 0 | AM31: =IF(ISERROR(投资与减值!N24),"—",投资与减值!N24) -> 0 | AN31: =IF(ISERROR(投资与减值!O24),"—",投资与减值!O24) -> 0 | AO31: =IF(ISERROR(投资与减值!P24),"—",投资与减值!P24) -> 0 | AP31: =IF(ISERROR(投资与减值!Q24),"—",投资与减值!Q24) -> 0 | AQ31: =IF(ISERROR(投资与减值!R24),"—",投资与减值!R24) -> 0 | AR31: =IF(ISERROR(投资与减值!S24),"—",投资与减值!S24) -> 0 | ... AT31: =IF(ISERROR(投资与减值!U24),"—",投资与减值!U24) -> 0
B32: 在建工程 | E32: =(财务基础数据!J155)*目录!$D$6 -> 0 | F32: =(财务基础数据!K155)*目录!$D$6 -> 0 | G32: =(财务基础数据!L155)*目录!$D$6 -> 0 | H32: =(财务基础数据!M155)*目录!$D$6 -> 0 | I32: =(财务基础数据!N155)*目录!$D$6 -> 0 | J32: =(财务基础数据!O155)*目录!$D$6 -> 0 | K32: =(财务基础数据!P155)*目录!$D$6 -> 0 | L32: =(财务基础数据!Q155)*目录!$D$6 -> 0 | ... AJ32: =(财务基础数据!AO155)*目录!$D$6 -> 0 | AK32: =IF(ISERROR(投资与减值!L46),"—",投资与减值!L46) -> 0 | AL32: =IF(ISERROR(投资与减值!M46),"—",投资与减值!M46) -> 0 | AM32: =IF(ISERROR(投资与减值!N46),"—",投资与减值!N46) -> 0 | AN32: =IF(ISERROR(投资与减值!O46),"—",投资与减值!O46) -> 0 | AO32: =IF(ISERROR(投资与减值!P46),"—",投资与减值!P46) -> 0 | AP32: =IF(ISERROR(投资与减值!Q46),"—",投资与减值!Q46) -> 0 | AQ32: =IF(ISERROR(投资与减值!R46),"—",投资与减值!R46) -> 0 | AR32: =IF(ISERROR(投资与减值!S46),"—",投资与减值!S46) -> 0 | ... AT32: =IF(ISERROR(投资与减值!U46),"—",投资与减值!U46) -> 0
B33: 生产性生物资产 | E33: =财务基础数据!J85*目录!$D$6 -> 0 | F33: =财务基础数据!K85*目录!$D$6 -> 0 | G33: =财务基础数据!L85*目录!$D$6 -> 0 | H33: =财务基础数据!M85*目录!$D$6 -> 0 | I33: =财务基础数据!N85*目录!$D$6 -> 0 | J33: =财务基础数据!O85*目录!$D$6 -> 0 | K33: =财务基础数据!P85*目录!$D$6 -> 0 | L33: =财务基础数据!Q85*目录!$D$6 -> 0 | ... AJ33: =财务基础数据!AO85*目录!$D$6 -> 0 | AK33: =IF(ISERROR(投资与减值!L144),"—",投资与减值!L144) -> 0 | AL33: =IF(ISERROR(投资与减值!M144),"—",投资与减值!M144) -> 0 | AM33: =IF(ISERROR(投资与减值!N144),"—",投资与减值!N144) -> 0 | AN33: =IF(ISERROR(投资与减值!O144),"—",投资与减值!O144) -> 0 | AO33: =IF(ISERROR(投资与减值!P144),"—",投资与减值!P144) -> 0 | AP33: =IF(ISERROR(投资与减值!Q144),"—",投资与减值!Q144) -> 0 | AQ33: =IF(ISERROR(投资与减值!R144),"—",投资与减值!R144) -> 0 | AR33: =IF(ISERROR(投资与减值!S144),"—",投资与减值!S144) -> 0 | ... AT33: =IF(ISERROR(投资与减值!U144),"—",投资与减值!U144) -> 0
B34: 油气资产 | E34: =财务基础数据!J86*目录!$D$6 -> 0 | F34: =财务基础数据!K86*目录!$D$6 -> 0 | G34: =财务基础数据!L86*目录!$D$6 -> 0 | H34: =财务基础数据!M86*目录!$D$6 -> 0 | I34: =财务基础数据!N86*目录!$D$6 -> 0 | J34: =财务基础数据!O86*目录!$D$6 -> 0 | K34: =财务基础数据!P86*目录!$D$6 -> 0 | L34: =财务基础数据!Q86*目录!$D$6 -> 0 | ... AJ34: =财务基础数据!AO86*目录!$D$6 -> 0 | AK34: =IF(ISERROR(投资与减值!L158),"—",投资与减值!L158) -> 0 | AL34: =IF(ISERROR(投资与减值!M158),"—",投资与减值!M158) -> 0 | AM34: =IF(ISERROR(投资与减值!N158),"—",投资与减值!N158) -> 0 | AN34: =IF(ISERROR(投资与减值!O158),"—",投资与减值!O158) -> 0 | AO34: =IF(ISERROR(投资与减值!P158),"—",投资与减值!P158) -> 0 | AP34: =IF(ISERROR(投资与减值!Q158),"—",投资与减值!Q158) -> 0 | AQ34: =IF(ISERROR(投资与减值!R158),"—",投资与减值!R158) -> 0 | AR34: =IF(ISERROR(投资与减值!S158),"—",投资与减值!S158) -> 0 | ... AT34: =IF(ISERROR(投资与减值!U158),"—",投资与减值!U158) -> 0
B35: 使用权资产 | E35: =财务基础数据!J164*目录!$D$6 -> 0 | F35: =财务基础数据!K164*目录!$D$6 -> 0 | G35: =财务基础数据!L164*目录!$D$6 -> 0 | H35: =财务基础数据!M164*目录!$D$6 -> 0 | I35: =财务基础数据!N164*目录!$D$6 -> 0 | J35: =财务基础数据!O164*目录!$D$6 -> 0 | K35: =财务基础数据!P164*目录!$D$6 -> 0 | L35: =财务基础数据!Q164*目录!$D$6 -> 0 | ... AJ35: =财务基础数据!AO164*目录!$D$6 -> 0 | AK35: =IF(ISERROR(投资与减值!L118),"—",投资与减值!L118) -> 0 | AL35: =IF(ISERROR(投资与减值!M118),"—",投资与减值!M118) -> 0 | AM35: =IF(ISERROR(投资与减值!N118),"—",投资与减值!N118) -> 0 | AN35: =IF(ISERROR(投资与减值!O118),"—",投资与减值!O118) -> 0 | AO35: =IF(ISERROR(投资与减值!P118),"—",投资与减值!P118) -> 0 | AP35: =IF(ISERROR(投资与减值!Q118),"—",投资与减值!Q118) -> 0 | AQ35: =IF(ISERROR(投资与减值!R118),"—",投资与减值!R118) -> 0 | AR35: =IF(ISERROR(投资与减值!S118),"—",投资与减值!S118) -> 0 | ... AT35: =IF(ISERROR(投资与减值!U118),"—",投资与减值!U118) -> 0
B36: 无形资产 | E36: =财务基础数据!J87*目录!$D$6 -> 0 | F36: =财务基础数据!K87*目录!$D$6 -> 0 | G36: =财务基础数据!L87*目录!$D$6 -> 0 | H36: =财务基础数据!M87*目录!$D$6 -> 0 | I36: =财务基础数据!N87*目录!$D$6 -> 0 | J36: =财务基础数据!O87*目录!$D$6 -> 0 | K36: =财务基础数据!P87*目录!$D$6 -> 0 | L36: =财务基础数据!Q87*目录!$D$6 -> 0 | ... AJ36: =财务基础数据!AO87*目录!$D$6 -> 0 | AK36: =IF(ISERROR(投资与减值!L63),"—",投资与减值!L63) -> 0 | AL36: =IF(ISERROR(投资与减值!M63),"—",投资与减值!M63) -> 0 | AM36: =IF(ISERROR(投资与减值!N63),"—",投资与减值!N63) -> 0 | AN36: =IF(ISERROR(投资与减值!O63),"—",投资与减值!O63) -> 0 | AO36: =IF(ISERROR(投资与减值!P63),"—",投资与减值!P63) -> 0 | AP36: =IF(ISERROR(投资与减值!Q63),"—",投资与减值!Q63) -> 0 | AQ36: =IF(ISERROR(投资与减值!R63),"—",投资与减值!R63) -> 0 | AR36: =IF(ISERROR(投资与减值!S63),"—",投资与减值!S63) -> 0 | ... AT36: =IF(ISERROR(投资与减值!U63),"—",投资与减值!U63) -> 0
B37: 开发支出 | E37: =财务基础数据!J88*目录!$D$6 -> 0 | F37: =财务基础数据!K88*目录!$D$6 -> 0 | G37: =财务基础数据!L88*目录!$D$6 -> 0 | H37: =财务基础数据!M88*目录!$D$6 -> 0 | I37: =财务基础数据!N88*目录!$D$6 -> 0 | J37: =财务基础数据!O88*目录!$D$6 -> 0 | K37: =财务基础数据!P88*目录!$D$6 -> 0 | L37: =财务基础数据!Q88*目录!$D$6 -> 0 | ... AJ37: =财务基础数据!AO88*目录!$D$6 -> 0 | AK37: =IF(财务基础数据!$AM$4=0,AG37,IF(财务基础数据!$AM$4=1,AH37,IF(财务基础数据!$AM$4=2,AI37,AJ37))) -> 0 | AL37: =AK37 -> 0 | AM37: =AL37 -> 0 | AN37: =AM37 -> 0 | AO37: =AN37 -> 0 | AP37: =AO37 -> 0 | AQ37: =AP37 -> 0 | AR37: =AQ37 -> 0 | AS37: =AR37 -> 0 | AT37: =AS37 -> 0
B38: 商誉 | E38: =财务基础数据!J89*目录!$D$6 -> 0 | F38: =财务基础数据!K89*目录!$D$6 -> 0 | G38: =财务基础数据!L89*目录!$D$6 -> 0 | H38: =财务基础数据!M89*目录!$D$6 -> 0 | I38: =财务基础数据!N89*目录!$D$6 -> 0 | J38: =财务基础数据!O89*目录!$D$6 -> 0 | K38: =财务基础数据!P89*目录!$D$6 -> 0 | L38: =财务基础数据!Q89*目录!$D$6 -> 0 | ... AJ38: =财务基础数据!AO89*目录!$D$6 -> 0 | AK38: =IF(ISERROR(投资与减值!L83),"—",投资与减值!L83) -> 0 | AL38: =IF(ISERROR(投资与减值!M83),"—",投资与减值!M83) -> 0 | AM38: =IF(ISERROR(投资与减值!N83),"—",投资与减值!N83) -> 0 | AN38: =IF(ISERROR(投资与减值!O83),"—",投资与减值!O83) -> 0 | AO38: =IF(ISERROR(投资与减值!P83),"—",投资与减值!P83) -> 0 | AP38: =IF(ISERROR(投资与减值!Q83),"—",投资与减值!Q83) -> 0 | AQ38: =IF(ISERROR(投资与减值!R83),"—",投资与减值!R83) -> 0 | AR38: =IF(ISERROR(投资与减值!S83),"—",投资与减值!S83) -> 0 | ... AT38: =IF(ISERROR(投资与减值!U83),"—",投资与减值!U83) -> 0
B39: 长期待摊费用 | E39: =财务基础数据!J90*目录!$D$6 -> 0 | F39: =财务基础数据!K90*目录!$D$6 -> 0 | G39: =财务基础数据!L90*目录!$D$6 -> 0 | H39: =财务基础数据!M90*目录!$D$6 -> 0 | I39: =财务基础数据!N90*目录!$D$6 -> 0 | J39: =财务基础数据!O90*目录!$D$6 -> 0 | K39: =财务基础数据!P90*目录!$D$6 -> 0 | L39: =财务基础数据!Q90*目录!$D$6 -> 0 | ... AJ39: =财务基础数据!AO90*目录!$D$6 -> 0 | AK39: =IF(ISERROR(资产预测!L115),"—",资产预测!L115) -> 0 | AL39: =IF(ISERROR(资产预测!M115),"—",资产预测!M115) -> 0 | AM39: =IF(ISERROR(资产预测!N115),"—",资产预测!N115) -> 0 | AN39: =IF(ISERROR(资产预测!O115),"—",资产预测!O115) -> 0 | AO39: =IF(ISERROR(资产预测!P115),"—",资产预测!P115) -> 0 | AP39: =IF(ISERROR(资产预测!Q115),"—",资产预测!Q115) -> 0 | AQ39: =IF(ISERROR(资产预测!R115),"—",资产预测!R115) -> 0 | AR39: =IF(ISERROR(资产预测!S115),"—",资产预测!S115) -> 0 | ... AT39: =IF(ISERROR(资产预测!U115),"—",资产预测!U115) -> 0
B40: 递延所得税资产 | E40: =财务基础数据!J92*目录!$D$6 -> 0 | F40: =(财务基础数据!K92)*目录!$D$6 -> 0 | G40: =(财务基础数据!L92)*目录!$D$6 -> 0 | H40: =(财务基础数据!M92)*目录!$D$6 -> 0 | I40: =(财务基础数据!N92)*目录!$D$6 -> 0 | J40: =(财务基础数据!O92)*目录!$D$6 -> 0 | K40: =(财务基础数据!P92)*目录!$D$6 -> 0 | L40: =(财务基础数据!Q92)*目录!$D$6 -> 0 | M40: =(财务基础数据!R92)*目录!$D$6 -> 0 | ... AJ40: =(财务基础数据!AO92)*目录!$D$6 -> 0 | AK40: =IF(财务基础数据!$AM$4=0,AG40,IF(财务基础数据!$AM$4=1,AH40,IF(财务基础数据!$AM$4=2,AI40,AJ40))) -> 0 | AL40: =AK40 -> 0 | AM40: =AL40 -> 0 | AN40: =AM40 -> 0 | AO40: =AN40 -> 0 | AP40: =AO40 -> 0 | AQ40: =AP40 -> 0 | AR40: =AQ40 -> 0 | AS40: =AR40 -> 0 | AT40: =AS40 -> 0
B41: 其他非流动资产 | E41: =E42-SUM(E24:E40) -> 0 | F41: =F42-SUM(F24:F40) -> 0 | G41: =G42-SUM(G24:G40) -> 0 | H41: =H42-SUM(H24:H40) -> 0 | I41: =I42-SUM(I24:I40) -> 0 | J41: =J42-SUM(J24:J40) -> 0 | K41: =K42-SUM(K24:K40) -> 0 | L41: =L42-SUM(L24:L40) -> 0 | ... AJ41: =AJ42-SUM(AJ24:AJ40) -> 0 | AK41: =IF(财务基础数据!$AM$4=0,AG41,IF(财务基础数据!$AM$4=1,AH41,IF(财务基础数据!$AM$4=2,AI41,AJ41))) -> 0 | AL41: =AK41 -> 0 | AM41: =AL41 -> 0 | AN41: =AM41 -> 0 | AO41: =AN41 -> 0 | AP41: =AO41 -> 0 | AQ41: =AP41 -> 0 | AR41: =AQ41 -> 0 | AS41: =AR41 -> 0 | AT41: =AS41 -> 0
B42: 非流动资产总额 | E42: =财务基础数据!J94*目录!$D$6 -> 0 | F42: =财务基础数据!K94*目录!$D$6 -> 0 | G42: =财务基础数据!L94*目录!$D$6 -> 0 | H42: =财务基础数据!M94*目录!$D$6 -> 0 | I42: =财务基础数据!N94*目录!$D$6 -> 0 | J42: =财务基础数据!O94*目录!$D$6 -> 0 | K42: =财务基础数据!P94*目录!$D$6 -> 0 | L42: =财务基础数据!Q94*目录!$D$6 -> 0 | ... AJ42: =财务基础数据!AO94*目录!$D$6 -> 0 | AK42: =SUM(AK24:AK41) -> 0 | AL42: =SUM(AL24:AL41) -> 0 | AM42: =SUM(AM24:AM41) -> 0 | AN42: =SUM(AN24:AN41) -> 0 | AO42: =SUM(AO24:AO41) -> 0 | AP42: =SUM(AP24:AP41) -> 0 | AQ42: =SUM(AQ24:AQ41) -> 0 | AR42: =SUM(AR24:AR41) -> 0 | ... AT42: =SUM(AT24:AT41) -> 0
B45: 资产总额 | E45: =IF(ISERROR(E21+E42),"—",E21+E42) -> 0 | F45: =IF(ISERROR(F21+F42),"—",F21+F42) -> 0 | G45: =IF(ISERROR(G21+G42),"—",G21+G42) -> 0 | H45: =IF(ISERROR(H21+H42),"—",H21+H42) -> 0 | I45: =IF(ISERROR(I21+I42),"—",I21+I42) -> 0 | J45: =IF(ISERROR(J21+J42),"—",J21+J42) -> 0 | K45: =IF(ISERROR(K21+K42),"—",K21+K42) -> 0 | L45: =IF(ISERROR(L21+L42),"—",L21+L42) -> 0 | ... AT45: =IF(ISERROR(AT21+AT42),"—",AT21+AT42) -> 0
B47: 负债和股东权益
B49: 短期借款 | E49: =财务基础数据!J97*目录!$D$6 -> 0 | F49: =财务基础数据!K97*目录!$D$6 -> 0 | G49: =财务基础数据!L97*目录!$D$6 -> 0 | H49: =财务基础数据!M97*目录!$D$6 -> 0 | I49: =财务基础数据!N97*目录!$D$6 -> 0 | J49: =财务基础数据!O97*目录!$D$6 -> 0 | K49: =财务基础数据!P97*目录!$D$6 -> 0 | L49: =财务基础数据!Q97*目录!$D$6 -> 0 | ... AJ49: =财务基础数据!AO97*目录!$D$6 -> 0 | AK49: =IF(ISERROR(资产预测!L204),"—",资产预测!L204) -> 0 | AL49: =IF(ISERROR(资产预测!M204),"—",资产预测!M204) -> 0 | AM49: =IF(ISERROR(资产预测!N204),"—",资产预测!N204) -> 0 | AN49: =IF(ISERROR(资产预测!O204),"—",资产预测!O204) -> 0 | AO49: =IF(ISERROR(资产预测!P204),"—",资产预测!P204) -> 0 | AP49: =IF(ISERROR(资产预测!Q204),"—",资产预测!Q204) -> 0 | AQ49: =IF(ISERROR(资产预测!R204),"—",资产预测!R204) -> 0 | AR49: =IF(ISERROR(资产预测!S204),"—",资产预测!S204) -> 0 | ... AT49: =IF(ISERROR(资产预测!U204),"—",资产预测!U204) -> 0
B50: 交易性金融负债 | E50: =财务基础数据!J98*目录!$D$6 -> 0 | F50: =财务基础数据!K98*目录!$D$6 -> 0 | G50: =财务基础数据!L98*目录!$D$6 -> 0 | H50: =财务基础数据!M98*目录!$D$6 -> 0 | I50: =财务基础数据!N98*目录!$D$6 -> 0 | J50: =财务基础数据!O98*目录!$D$6 -> 0 | K50: =财务基础数据!P98*目录!$D$6 -> 0 | L50: =财务基础数据!Q98*目录!$D$6 -> 0 | ... AJ50: =财务基础数据!AO98*目录!$D$6 -> 0 | AK50: =IF(ISERROR(资产预测!L83),"—",资产预测!L83) -> 0 | AL50: =IF(ISERROR(资产预测!M83),"—",资产预测!M83) -> 0 | AM50: =IF(ISERROR(资产预测!N83),"—",资产预测!N83) -> 0 | AN50: =IF(ISERROR(资产预测!O83),"—",资产预测!O83) -> 0 | AO50: =IF(ISERROR(资产预测!P83),"—",资产预测!P83) -> 0 | AP50: =IF(ISERROR(资产预测!Q83),"—",资产预测!Q83) -> 0 | AQ50: =IF(ISERROR(资产预测!R83),"—",资产预测!R83) -> 0 | AR50: =IF(ISERROR(资产预测!S83),"—",资产预测!S83) -> 0 | ... AT50: =IF(ISERROR(资产预测!U83),"—",资产预测!U83) -> 0
B51: 衍生金融负债 | E51: =财务基础数据!J152*目录!$D$6 -> 0 | F51: =财务基础数据!K152*目录!$D$6 -> 0 | G51: =财务基础数据!L152*目录!$D$6 -> 0 | H51: =财务基础数据!M152*目录!$D$6 -> 0 | I51: =财务基础数据!N152*目录!$D$6 -> 0 | J51: =财务基础数据!O152*目录!$D$6 -> 0 | K51: =财务基础数据!P152*目录!$D$6 -> 0 | L51: =财务基础数据!Q152*目录!$D$6 -> 0 | ... AJ51: =财务基础数据!AO152*目录!$D$6 -> 0 | AK51: =IF(ISERROR(资产预测!L87),"—",资产预测!L87) -> 0 | AL51: =IF(ISERROR(资产预测!M87),"—",资产预测!M87) -> 0 | AM51: =IF(ISERROR(资产预测!N87),"—",资产预测!N87) -> 0 | AN51: =IF(ISERROR(资产预测!O87),"—",资产预测!O87) -> 0 | AO51: =IF(ISERROR(资产预测!P87),"—",资产预测!P87) -> 0 | AP51: =IF(ISERROR(资产预测!Q87),"—",资产预测!Q87) -> 0 | AQ51: =IF(ISERROR(资产预测!R87),"—",资产预测!R87) -> 0 | AR51: =IF(ISERROR(资产预测!S87),"—",资产预测!S87) -> 0 | ... AT51: =IF(ISERROR(资产预测!U87),"—",资产预测!U87) -> 0
B52: 应付票据 | E52: =(财务基础数据!J99)*目录!$D$6 -> 0 | F52: =(财务基础数据!K99)*目录!$D$6 -> 0 | G52: =(财务基础数据!L99)*目录!$D$6 -> 0 | H52: =(财务基础数据!M99)*目录!$D$6 -> 0 | I52: =(财务基础数据!N99)*目录!$D$6 -> 0 | J52: =(财务基础数据!O99)*目录!$D$6 -> 0 | K52: =(财务基础数据!P99)*目录!$D$6 -> 0 | L52: =(财务基础数据!Q99)*目录!$D$6 -> 0 | ... AJ52: =(财务基础数据!AO99)*目录!$D$6 -> 0 | AK52: =IF(ISERROR(资产预测!L38),"—",资产预测!L38) -> 0 | AL52: =IF(ISERROR(资产预测!M38),"—",资产预测!M38) -> 0 | AM52: =IF(ISERROR(资产预测!N38),"—",资产预测!N38) -> 0 | AN52: =IF(ISERROR(资产预测!O38),"—",资产预测!O38) -> 0 | AO52: =IF(ISERROR(资产预测!P38),"—",资产预测!P38) -> 0 | AP52: =IF(ISERROR(资产预测!Q38),"—",资产预测!Q38) -> 0 | AQ52: =IF(ISERROR(资产预测!R38),"—",资产预测!R38) -> 0 | AR52: =IF(ISERROR(资产预测!S38),"—",资产预测!S38) -> 0 | ... AT52: =IF(ISERROR(资产预测!U38),"—",资产预测!U38) -> 0
B53: 应付账款 | E53: =(财务基础数据!J100)*目录!$D$6 -> 0 | F53: =(财务基础数据!K100)*目录!$D$6 -> 0 | G53: =(财务基础数据!L100)*目录!$D$6 -> 0 | H53: =(财务基础数据!M100)*目录!$D$6 -> 0 | I53: =(财务基础数据!N100)*目录!$D$6 -> 0 | J53: =(财务基础数据!O100)*目录!$D$6 -> 0 | K53: =(财务基础数据!P100)*目录!$D$6 -> 0 | L53: =(财务基础数据!Q100)*目录!$D$6 -> 0 | ... AJ53: =(财务基础数据!AO100)*目录!$D$6 -> 0 | AK53: =IF(ISERROR(资产预测!L42),"—",资产预测!L42) -> 0 | AL53: =IF(ISERROR(资产预测!M42),"—",资产预测!M42) -> 0 | AM53: =IF(ISERROR(资产预测!N42),"—",资产预测!N42) -> 0 | AN53: =IF(ISERROR(资产预测!O42),"—",资产预测!O42) -> 0 | AO53: =IF(ISERROR(资产预测!P42),"—",资产预测!P42) -> 0 | AP53: =IF(ISERROR(资产预测!Q42),"—",资产预测!Q42) -> 0 | AQ53: =IF(ISERROR(资产预测!R42),"—",资产预测!R42) -> 0 | AR53: =IF(ISERROR(资产预测!S42),"—",资产预测!S42) -> 0 | ... AT53: =IF(ISERROR(资产预测!U42),"—",资产预测!U42) -> 0
B54: 预收款项 | E54: =财务基础数据!J101*目录!$D$6 -> 0 | F54: =财务基础数据!K101*目录!$D$6 -> 0 | G54: =财务基础数据!L101*目录!$D$6 -> 0 | H54: =财务基础数据!M101*目录!$D$6 -> 0 | I54: =财务基础数据!N101*目录!$D$6 -> 0 | J54: =财务基础数据!O101*目录!$D$6 -> 0 | K54: =财务基础数据!P101*目录!$D$6 -> 0 | L54: =财务基础数据!Q101*目录!$D$6 -> 0 | ... AJ54: =财务基础数据!AO101*目录!$D$6 -> 0 | AK54: =IF(ISERROR(资产预测!L46),"—",资产预测!L46) -> 0 | AL54: =IF(ISERROR(资产预测!M46),"—",资产预测!M46) -> 0 | AM54: =IF(ISERROR(资产预测!N46),"—",资产预测!N46) -> 0 | AN54: =IF(ISERROR(资产预测!O46),"—",资产预测!O46) -> 0 | AO54: =IF(ISERROR(资产预测!P46),"—",资产预测!P46) -> 0 | AP54: =IF(ISERROR(资产预测!Q46),"—",资产预测!Q46) -> 0 | AQ54: =IF(ISERROR(资产预测!R46),"—",资产预测!R46) -> 0 | AR54: =IF(ISERROR(资产预测!S46),"—",资产预测!S46) -> 0 | ... AT54: =IF(ISERROR(资产预测!U46),"—",资产预测!U46) -> 0
B55: 合同负债 | E55: =财务基础数据!J146*目录!$D$6 -> 0 | F55: =财务基础数据!K146*目录!$D$6 -> 0 | G55: =财务基础数据!L146*目录!$D$6 -> 0 | H55: =财务基础数据!M146*目录!$D$6 -> 0 | I55: =财务基础数据!N146*目录!$D$6 -> 0 | J55: =财务基础数据!O146*目录!$D$6 -> 0 | K55: =财务基础数据!P146*目录!$D$6 -> 0 | L55: =财务基础数据!Q146*目录!$D$6 -> 0 | ... AJ55: =财务基础数据!AO146*目录!$D$6 -> 0 | AK55: =IF(ISERROR(资产预测!L49),"—",资产预测!L49) -> 0 | AL55: =IF(ISERROR(资产预测!M49),"—",资产预测!M49) -> 0 | AM55: =IF(ISERROR(资产预测!N49),"—",资产预测!N49) -> 0 | AN55: =IF(ISERROR(资产预测!O49),"—",资产预测!O49) -> 0 | AO55: =IF(ISERROR(资产预测!P49),"—",资产预测!P49) -> 0 | AP55: =IF(ISERROR(资产预测!Q49),"—",资产预测!Q49) -> 0 | AQ55: =IF(ISERROR(资产预测!R49),"—",资产预测!R49) -> 0 | AR55: =IF(ISERROR(资产预测!S49),"—",资产预测!S49) -> 0 | ... AT55: =IF(ISERROR(资产预测!U49),"—",资产预测!U49) -> 0
B56: 应付职工薪酬 | E56: =(财务基础数据!J102+财务基础数据!J103)*目录!$D$6 -> 0 | F56: =(财务基础数据!K102+财务基础数据!K103)*目录!$D$6 -> 0 | G56: =(财务基础数据!L102+财务基础数据!L103)*目录!$D$6 -> 0 | H56: =(财务基础数据!M102+财务基础数据!M103)*目录!$D$6 -> 0 | I56: =(财务基础数据!N102+财务基础数据!N103)*目录!$D$6 -> 0 | J56: =(财务基础数据!O102+财务基础数据!O103)*目录!$D$6 -> 0 | K56: =(财务基础数据!P102+财务基础数据!P103)*目录!$D$6 -> 0 | L56: =(财务基础数据!Q102+财务基础数据!Q103)*目录!$D$6 -> 0 | ... AJ56: =(财务基础数据!AO102+财务基础数据!AO103)*目录!$D$6 -> 0 | AK56: =IF(ISERROR(资产预测!L52),"—",资产预测!L52) -> 0 | AL56: =IF(ISERROR(资产预测!M52),"—",资产预测!M52) -> 0 | AM56: =IF(ISERROR(资产预测!N52),"—",资产预测!N52) -> 0 | AN56: =IF(ISERROR(资产预测!O52),"—",资产预测!O52) -> 0 | AO56: =IF(ISERROR(资产预测!P52),"—",资产预测!P52) -> 0 | AP56: =IF(ISERROR(资产预测!Q52),"—",资产预测!Q52) -> 0 | AQ56: =IF(ISERROR(资产预测!R52),"—",资产预测!R52) -> 0 | AR56: =IF(ISERROR(资产预测!S52),"—",资产预测!S52) -> 0 | ... AT56: =IF(ISERROR(资产预测!U52),"—",资产预测!U52) -> 0
B57: 应交税费 | E57: =(财务基础数据!J104)*目录!$D$6 -> 0 | F57: =(财务基础数据!K104)*目录!$D$6 -> 0 | G57: =(财务基础数据!L104)*目录!$D$6 -> 0 | H57: =(财务基础数据!M104)*目录!$D$6 -> 0 | I57: =(财务基础数据!N104)*目录!$D$6 -> 0 | J57: =(财务基础数据!O104)*目录!$D$6 -> 0 | K57: =(财务基础数据!P104)*目录!$D$6 -> 0 | L57: =(财务基础数据!Q104)*目录!$D$6 -> 0 | ... AJ57: =(财务基础数据!AO104)*目录!$D$6 -> 0 | AK57: =IF(ISERROR(资产预测!L55),"—",资产预测!L55) -> 0 | AL57: =IF(ISERROR(资产预测!M55),"—",资产预测!M55) -> 0 | AM57: =IF(ISERROR(资产预测!N55),"—",资产预测!N55) -> 0 | AN57: =IF(ISERROR(资产预测!O55),"—",资产预测!O55) -> 0 | AO57: =IF(ISERROR(资产预测!P55),"—",资产预测!P55) -> 0 | AP57: =IF(ISERROR(资产预测!Q55),"—",资产预测!Q55) -> 0 | AQ57: =IF(ISERROR(资产预测!R55),"—",资产预测!R55) -> 0 | AR57: =IF(ISERROR(资产预测!S55),"—",资产预测!S55) -> 0 | ... AT57: =IF(ISERROR(资产预测!U55),"—",资产预测!U55) -> 0
B58: 其他应付款 | E58: =(财务基础数据!J156)*目录!$D$6 -> 0 | F58: =(财务基础数据!K156)*目录!$D$6 -> 0 | G58: =(财务基础数据!L156)*目录!$D$6 -> 0 | H58: =(财务基础数据!M156)*目录!$D$6 -> 0 | I58: =(财务基础数据!N156)*目录!$D$6 -> 0 | J58: =(财务基础数据!O156)*目录!$D$6 -> 0 | K58: =(财务基础数据!P156)*目录!$D$6 -> 0 | L58: =(财务基础数据!Q156)*目录!$D$6 -> 0 | ... AJ58: =(财务基础数据!AO156)*目录!$D$6 -> 0 | AK58: =IF(ISERROR(资产预测!L58),"—",资产预测!L58) -> 0 | AL58: =IF(ISERROR(资产预测!M58),"—",资产预测!M58) -> 0 | AM58: =IF(ISERROR(资产预测!N58),"—",资产预测!N58) -> 0 | AN58: =IF(ISERROR(资产预测!O58),"—",资产预测!O58) -> 0 | AO58: =IF(ISERROR(资产预测!P58),"—",资产预测!P58) -> 0 | AP58: =IF(ISERROR(资产预测!Q58),"—",资产预测!Q58) -> 0 | AQ58: =IF(ISERROR(资产预测!R58),"—",资产预测!R58) -> 0 | AR58: =IF(ISERROR(资产预测!S58),"—",资产预测!S58) -> 0 | ... AT58: =IF(ISERROR(资产预测!U58),"—",资产预测!U58) -> 0
B59: 持有待售负债 | E59: =财务基础数据!J142*目录!$D$6 -> 0 | F59: =财务基础数据!K142*目录!$D$6 -> 0 | G59: =财务基础数据!L142*目录!$D$6 -> 0 | H59: =财务基础数据!M142*目录!$D$6 -> 0 | I59: =财务基础数据!N142*目录!$D$6 -> 0 | J59: =财务基础数据!O142*目录!$D$6 -> 0 | K59: =财务基础数据!P142*目录!$D$6 -> 0 | L59: =财务基础数据!Q142*目录!$D$6 -> 0 | ... AJ59: =财务基础数据!AO142*目录!$D$6 -> 0 | AK59: =IF(财务基础数据!$AM$4=0,AG59,IF(财务基础数据!$AM$4=1,AH59,IF(财务基础数据!$AM$4=2,AI59,AJ59))) -> 0 | AL59: =AK59 -> 0 | AM59: =AL59 -> 0 | AN59: =AM59 -> 0 | AO59: =AN59 -> 0 | AP59: =AO59 -> 0 | AQ59: =AP59 -> 0 | AR59: =AQ59 -> 0 | AS59: =AR59 -> 0 | AT59: =AS59 -> 0
B60: 一年内到期的非流动负债 | E60: =(财务基础数据!J107+财务基础数据!J108)*目录!$D$6 -> 0 | F60: =(财务基础数据!K107+财务基础数据!K108)*目录!$D$6 -> 0 | G60: =(财务基础数据!L107+财务基础数据!L108)*目录!$D$6 -> 0 | H60: =(财务基础数据!M107+财务基础数据!M108)*目录!$D$6 -> 0 | I60: =(财务基础数据!N107+财务基础数据!N108)*目录!$D$6 -> 0 | J60: =(财务基础数据!O107+财务基础数据!O108)*目录!$D$6 -> 0 | K60: =(财务基础数据!P107+财务基础数据!P108)*目录!$D$6 -> 0 | L60: =(财务基础数据!Q107+财务基础数据!Q108)*目录!$D$6 -> 0 | ... AJ60: =(财务基础数据!AO107+财务基础数据!AO108)*目录!$D$6 -> 0 | AK60: =IF(财务基础数据!$AM$4=0,AG60,IF(财务基础数据!$AM$4=1,AH60,IF(财务基础数据!$AM$4=2,AI60,AJ60))) -> 0 | AL60: =AK60 -> 0 | AM60: =AL60 -> 0 | AN60: =AM60 -> 0 | AO60: =AN60 -> 0 | AP60: =AO60 -> 0 | AQ60: =AP60 -> 0 | AR60: =AQ60 -> 0 | AS60: =AR60 -> 0 | AT60: =AS60 -> 0
B61: 其他流动负债 | E61: =E62-SUM(E49:E60) -> 0 | F61: =F62-SUM(F49:F60) -> 0 | G61: =G62-SUM(G49:G60) -> 0 | H61: =H62-SUM(H49:H60) -> 0 | I61: =I62-SUM(I49:I60) -> 0 | J61: =J62-SUM(J49:J60) -> 0 | K61: =K62-SUM(K49:K60) -> 0 | L61: =L62-SUM(L49:L60) -> 0 | ... AJ61: =AJ62-SUM(AJ49:AJ60) -> 0 | AK61: =IF(ISERROR(资产预测!L91),"—",资产预测!L91) -> 0 | AL61: =IF(ISERROR(资产预测!M91),"—",资产预测!M91) -> 0 | AM61: =IF(ISERROR(资产预测!N91),"—",资产预测!N91) -> 0 | AN61: =IF(ISERROR(资产预测!O91),"—",资产预测!O91) -> 0 | AO61: =IF(ISERROR(资产预测!P91),"—",资产预测!P91) -> 0 | AP61: =IF(ISERROR(资产预测!Q91),"—",资产预测!Q91) -> 0 | AQ61: =IF(ISERROR(资产预测!R91),"—",资产预测!R91) -> 0 | AR61: =IF(ISERROR(资产预测!S91),"—",资产预测!S91) -> 0 | ... AT61: =IF(ISERROR(资产预测!U91),"—",资产预测!U91) -> 0
B62: 流动负债总额 | E62: =财务基础数据!J110*目录!$D$6 -> 0 | F62: =财务基础数据!K110*目录!$D$6 -> 0 | G62: =财务基础数据!L110*目录!$D$6 -> 0 | H62: =财务基础数据!M110*目录!$D$6 -> 0 | I62: =财务基础数据!N110*目录!$D$6 -> 0 | J62: =财务基础数据!O110*目录!$D$6 -> 0 | K62: =财务基础数据!P110*目录!$D$6 -> 0 | L62: =财务基础数据!Q110*目录!$D$6 -> 0 | ... AJ62: =财务基础数据!AO110*目录!$D$6 -> 0 | AK62: =SUM(AK49:AK61) -> 0 | AL62: =SUM(AL49:AL61) -> 0 | AM62: =SUM(AM49:AM61) -> 0 | AN62: =SUM(AN49:AN61) -> 0 | AO62: =SUM(AO49:AO61) -> 0 | AP62: =SUM(AP49:AP61) -> 0 | AQ62: =SUM(AQ49:AQ61) -> 0 | AR62: =SUM(AR49:AR61) -> 0 | ... AT62: =SUM(AT49:AT61) -> 0
B65: 长期借款 | E65: =财务基础数据!J111*目录!$D$6 -> 0 | F65: =财务基础数据!K111*目录!$D$6 -> 0 | G65: =财务基础数据!L111*目录!$D$6 -> 0 | H65: =财务基础数据!M111*目录!$D$6 -> 0 | I65: =财务基础数据!N111*目录!$D$6 -> 0 | J65: =财务基础数据!O111*目录!$D$6 -> 0 | K65: =财务基础数据!P111*目录!$D$6 -> 0 | L65: =财务基础数据!Q111*目录!$D$6 -> 0 | ... AJ65: =财务基础数据!AO111*目录!$D$6 -> 0 | AK65: =IF(ISERROR(资产预测!L197),"—",资产预测!L197) -> 0 | AL65: =IF(ISERROR(资产预测!M197),"—",资产预测!M197) -> 0 | AM65: =IF(ISERROR(资产预测!N197),"—",资产预测!N197) -> 0 | AN65: =IF(ISERROR(资产预测!O197),"—",资产预测!O197) -> 0 | AO65: =IF(ISERROR(资产预测!P197),"—",资产预测!P197) -> 0 | AP65: =IF(ISERROR(资产预测!Q197),"—",资产预测!Q197) -> 0 | AQ65: =IF(ISERROR(资产预测!R197),"—",资产预测!R197) -> 0 | AR65: =IF(ISERROR(资产预测!S197),"—",资产预测!S197) -> 0 | ... AT65: =IF(ISERROR(资产预测!U197),"—",资产预测!U197) -> 0
B66: 应付债券 | E66: =财务基础数据!J112*目录!$D$6 -> 0 | F66: =财务基础数据!K112*目录!$D$6 -> 0 | G66: =财务基础数据!L112*目录!$D$6 -> 0 | H66: =财务基础数据!M112*目录!$D$6 -> 0 | I66: =财务基础数据!N112*目录!$D$6 -> 0 | J66: =财务基础数据!O112*目录!$D$6 -> 0 | K66: =财务基础数据!P112*目录!$D$6 -> 0 | L66: =财务基础数据!Q112*目录!$D$6 -> 0 | ... AJ66: =财务基础数据!AO112*目录!$D$6 -> 0 | AK66: =IF(ISERROR(资产预测!L185),"—",资产预测!L185) -> 0 | AL66: =IF(ISERROR(资产预测!M185),"—",资产预测!M185) -> 0 | AM66: =IF(ISERROR(资产预测!N185),"—",资产预测!N185) -> 0 | AN66: =IF(ISERROR(资产预测!O185),"—",资产预测!O185) -> 0 | AO66: =IF(ISERROR(资产预测!P185),"—",资产预测!P185) -> 0 | AP66: =IF(ISERROR(资产预测!Q185),"—",资产预测!Q185) -> 0 | AQ66: =IF(ISERROR(资产预测!R185),"—",资产预测!R185) -> 0 | AR66: =IF(ISERROR(资产预测!S185),"—",资产预测!S185) -> 0 | ... AT66: =IF(ISERROR(资产预测!U185),"—",资产预测!U185) -> 0
B67: 租赁负债 | E67: =财务基础数据!J165*目录!$D$6 -> 0 | F67: =财务基础数据!K165*目录!$D$6 -> 0 | G67: =财务基础数据!L165*目录!$D$6 -> 0 | H67: =财务基础数据!M165*目录!$D$6 -> 0 | I67: =财务基础数据!N165*目录!$D$6 -> 0 | J67: =财务基础数据!O165*目录!$D$6 -> 0 | K67: =财务基础数据!P165*目录!$D$6 -> 0 | L67: =财务基础数据!Q165*目录!$D$6 -> 0 | ... AJ67: =财务基础数据!AO165*目录!$D$6 -> 0 | AK67: =IF(ISERROR(资产预测!L191),"—",资产预测!L191) -> 0 | AL67: =IF(ISERROR(资产预测!M191),"—",资产预测!M191) -> 0 | AM67: =IF(ISERROR(资产预测!N191),"—",资产预测!N191) -> 0 | AN67: =IF(ISERROR(资产预测!O191),"—",资产预测!O191) -> 0 | AO67: =IF(ISERROR(资产预测!P191),"—",资产预测!P191) -> 0 | AP67: =IF(ISERROR(资产预测!Q191),"—",资产预测!Q191) -> 0 | AQ67: =IF(ISERROR(资产预测!R191),"—",资产预测!R191) -> 0 | AR67: =IF(ISERROR(资产预测!S191),"—",资产预测!S191) -> 0 | ... AT67: =IF(ISERROR(资产预测!U191),"—",资产预测!U191) -> 0
B68: 长期应付款 | E68: =(财务基础数据!J157)*目录!$D$6 -> 0 | F68: =(财务基础数据!K157+财务基础数据!K138)*目录!$D$6 -> 0 | G68: =(财务基础数据!L157+财务基础数据!L138)*目录!$D$6 -> 0 | H68: =(财务基础数据!M157+财务基础数据!M138)*目录!$D$6 -> 0 | I68: =(财务基础数据!N157+财务基础数据!N138)*目录!$D$6 -> 0 | J68: =(财务基础数据!O157+财务基础数据!O138)*目录!$D$6 -> 0 | K68: =(财务基础数据!P157+财务基础数据!P138)*目录!$D$6 -> 0 | L68: =(财务基础数据!Q157+财务基础数据!Q138)*目录!$D$6 -> 0 | M68: =(财务基础数据!R157+财务基础数据!R138)*目录!$D$6 -> 0 | ... AJ68: =(财务基础数据!AO157+财务基础数据!AO138)*目录!$D$6 -> 0 | AK68: =IF(财务基础数据!$AM$4=0,AG68,IF(财务基础数据!$AM$4=1,AH68,IF(财务基础数据!$AM$4=2,AI68,AJ68))) -> 0 | AL68: =AK68 -> 0 | AM68: =AL68 -> 0 | AN68: =AM68 -> 0 | AO68: =AN68 -> 0 | AP68: =AO68 -> 0 | AQ68: =AP68 -> 0 | AR68: =AQ68 -> 0 | AS68: =AR68 -> 0 | AT68: =AS68 -> 0
B69: 预计负债 | E69: =财务基础数据!J106*目录!$D$6 -> 0 | F69: =(财务基础数据!K106+财务基础数据!K114)*目录!$D$6 -> 0 | G69: =(财务基础数据!L106+财务基础数据!L114)*目录!$D$6 -> 0 | H69: =(财务基础数据!M106+财务基础数据!M114)*目录!$D$6 -> 0 | I69: =(财务基础数据!N106+财务基础数据!N114)*目录!$D$6 -> 0 | J69: =(财务基础数据!O106+财务基础数据!O114)*目录!$D$6 -> 0 | K69: =(财务基础数据!P106+财务基础数据!P114)*目录!$D$6 -> 0 | L69: =(财务基础数据!Q106+财务基础数据!Q114)*目录!$D$6 -> 0 | M69: =(财务基础数据!R106+财务基础数据!R114)*目录!$D$6 -> 0 | ... AJ69: =(财务基础数据!AO106+财务基础数据!AO114)*目录!$D$6 -> 0 | AK69: =IF(财务基础数据!$AM$4=0,AG69,IF(财务基础数据!$AM$4=1,AH69,IF(财务基础数据!$AM$4=2,AI69,AJ69))) -> 0 | AL69: =AK69 -> 0 | AM69: =AL69 -> 0 | AN69: =AM69 -> 0 | AO69: =AN69 -> 0 | AP69: =AO69 -> 0 | AQ69: =AP69 -> 0 | AR69: =AQ69 -> 0 | AS69: =AR69 -> 0 | AT69: =AS69 -> 0
B70: 递延收益 | E70: =(财务基础数据!J149+财务基础数据!J151)*目录!$D$6 -> 0 | F70: =(财务基础数据!K149+财务基础数据!K151)*目录!$D$6 -> 0 | G70: =(财务基础数据!L149+财务基础数据!L151)*目录!$D$6 -> 0 | H70: =(财务基础数据!M149+财务基础数据!M151)*目录!$D$6 -> 0 | I70: =(财务基础数据!N149+财务基础数据!N151)*目录!$D$6 -> 0 | J70: =(财务基础数据!O149+财务基础数据!O151)*目录!$D$6 -> 0 | K70: =(财务基础数据!P149+财务基础数据!P151)*目录!$D$6 -> 0 | L70: =(财务基础数据!Q149+财务基础数据!Q151)*目录!$D$6 -> 0 | ... AJ70: =(财务基础数据!AO149+财务基础数据!AO151)*目录!$D$6 -> 0 | AK70: =IF(财务基础数据!$AM$4=0,AG70,IF(财务基础数据!$AM$4=1,AH70,IF(财务基础数据!$AM$4=2,AI70,AJ70))) -> 0 | AL70: =AK70 -> 0 | AM70: =AL70 -> 0 | AN70: =AM70 -> 0 | AO70: =AN70 -> 0 | AP70: =AO70 -> 0 | AQ70: =AP70 -> 0 | AR70: =AQ70 -> 0 | AS70: =AR70 -> 0 | AT70: =AS70 -> 0
B71: 递延所得税负债 | E71: =(财务基础数据!J117)*目录!$D$6 -> 0 | F71: =(财务基础数据!K117)*目录!$D$6 -> 0 | G71: =(财务基础数据!L117)*目录!$D$6 -> 0 | H71: =(财务基础数据!M117)*目录!$D$6 -> 0 | I71: =(财务基础数据!N117)*目录!$D$6 -> 0 | J71: =(财务基础数据!O117)*目录!$D$6 -> 0 | K71: =(财务基础数据!P117)*目录!$D$6 -> 0 | L71: =(财务基础数据!Q117)*目录!$D$6 -> 0 | ... AJ71: =(财务基础数据!AO117)*目录!$D$6 -> 0 | AK71: =IF(财务基础数据!$AM$4=0,AG71,IF(财务基础数据!$AM$4=1,AH71,IF(财务基础数据!$AM$4=2,AI71,AJ71))) -> 0 | AL71: =AK71 -> 0 | AM71: =AL71 -> 0 | AN71: =AM71 -> 0 | AO71: =AN71 -> 0 | AP71: =AO71 -> 0 | AQ71: =AP71 -> 0 | AR71: =AQ71 -> 0 | AS71: =AR71 -> 0 | AT71: =AS71 -> 0
B72: 其他非流动负债 | E72: =E73-SUM(E65:E71) -> 0 | F72: =F73-SUM(F65:F71) -> 0 | G72: =G73-SUM(G65:G71) -> 0 | H72: =H73-SUM(H65:H71) -> 0 | I72: =I73-SUM(I65:I71) -> 0 | J72: =J73-SUM(J65:J71) -> 0 | K72: =K73-SUM(K65:K71) -> 0 | L72: =L73-SUM(L65:L71) -> 0 | ... AJ72: =AJ73-SUM(AJ65:AJ71) -> 0 | AK72: =IF(财务基础数据!$AM$4=0,AG72,IF(财务基础数据!$AM$4=1,AH72,IF(财务基础数据!$AM$4=2,AI72,AJ72))) -> 0 | AL72: =AK72 -> 0 | AM72: =AL72 -> 0 | AN72: =AM72 -> 0 | AO72: =AN72 -> 0 | AP72: =AO72 -> 0 | AQ72: =AP72 -> 0 | AR72: =AQ72 -> 0 | AS72: =AR72 -> 0 | AT72: =AS72 -> 0
B73: 非流动负债合计 | E73: =(财务基础数据!J118)*目录!$D$6 -> 0 | F73: =(财务基础数据!K118)*目录!$D$6 -> 0 | G73: =(财务基础数据!L118)*目录!$D$6 -> 0 | H73: =(财务基础数据!M118)*目录!$D$6 -> 0 | I73: =(财务基础数据!N118)*目录!$D$6 -> 0 | J73: =(财务基础数据!O118)*目录!$D$6 -> 0 | K73: =(财务基础数据!P118)*目录!$D$6 -> 0 | L73: =(财务基础数据!Q118)*目录!$D$6 -> 0 | ... AJ73: =(财务基础数据!AO118)*目录!$D$6 -> 0 | AK73: =SUM(AK65:AK72) -> 0 | AL73: =SUM(AL65:AL72) -> 0 | AM73: =SUM(AM65:AM72) -> 0 | AN73: =SUM(AN65:AN72) -> 0 | AO73: =SUM(AO65:AO72) -> 0 | AP73: =SUM(AP65:AP72) -> 0 | AQ73: =SUM(AQ65:AQ72) -> 0 | AR73: =SUM(AR65:AR72) -> 0 | ... AT73: =SUM(AT65:AT72) -> 0
B76: 负债合计 | E76: =(财务基础数据!J120)*目录!$D$6 -> 0 | F76: =(财务基础数据!K120)*目录!$D$6 -> 0 | G76: =(财务基础数据!L120)*目录!$D$6 -> 0 | H76: =(财务基础数据!M120)*目录!$D$6 -> 0 | I76: =(财务基础数据!N120)*目录!$D$6 -> 0 | J76: =(财务基础数据!O120)*目录!$D$6 -> 0 | K76: =(财务基础数据!P120)*目录!$D$6 -> 0 | L76: =(财务基础数据!Q120)*目录!$D$6 -> 0 | ... AJ76: =(财务基础数据!AO120)*目录!$D$6 -> 0 | AK76: =AK62+AK73 -> 0 | AL76: =AL62+AL73 -> 0 | AM76: =AM62+AM73 -> 0 | AN76: =AN62+AN73 -> 0 | AO76: =AO62+AO73 -> 0 | AP76: =AP62+AP73 -> 0 | AQ76: =AQ62+AQ73 -> 0 | AR76: =AR62+AR73 -> 0 | ... AT76: =AT62+AT73 -> 0
B78: 实收资本（或股本） | E78: =财务基础数据!J121*目录!$D$6 -> 0 | F78: =财务基础数据!K121*目录!$D$6 -> 0 | G78: =财务基础数据!L121*目录!$D$6 -> 0 | H78: =财务基础数据!M121*目录!$D$6 -> 0 | I78: =财务基础数据!N121*目录!$D$6 -> 0 | J78: =财务基础数据!O121*目录!$D$6 -> 0 | K78: =财务基础数据!P121*目录!$D$6 -> 0 | L78: =财务基础数据!Q121*目录!$D$6 -> 0 | ... AJ78: =财务基础数据!AO121*目录!$D$6 -> 0 | AK78: =AG78+资产预测!L132+资产预测!L140-资产预测!L147+资产预测!L152+资产预测!L168 -> 0 | AL78: =IF(ISERROR(AK78+资产预测!M132+资产预测!M140-资产预测!M147+资产预测!M152+资产预测!M168),0,AK78+资产预测!M132+资产预测!M140-资产预测!M147+资产预测!M152+资产预测!M168) -> 0 | AM78: =IF(ISERROR(AL78+资产预测!N140-资产预测!N147+资产预测!N152+资产预测!N168),0,AL78+资产预测!N140-资产预测!N147+资产预测!N152+资产预测!N168) -> 0 | AN78: =IF(ISERROR(AM78+资产预测!O140-资产预测!O147+资产预测!O152+资产预测!O168),0,AM78+资产预测!O140-资产预测!O147+资产预测!O152+资产预测!O168) -> 0 | AO78: =IF(ISERROR(AN78+资产预测!P140-资产预测!P147+资产预测!P152+资产预测!P168),0,AN78+资产预测!P140-资产预测!P147+资产预测!P152+资产预测!P168) -> 0 | AP78: =IF(ISERROR(AO78+资产预测!Q140-资产预测!Q147+资产预测!Q152+资产预测!Q168),0,AO78+资产预测!Q140-资产预测!Q147+资产预测!Q152+资产预测!Q168) -> 0 | AQ78: =IF(ISERROR(AP78+资产预测!R140-资产预测!R147+资产预测!R152+资产预测!R168),0,AP78+资产预测!R140-资产预测!R147+资产预测!R152+资产预测!R168) -> 0 | AR78: =IF(ISERROR(AQ78+资产预测!S140-资产预测!S147+资产预测!S152+资产预测!S168),0,AQ78+资产预测!S140-资产预测!S147+资产预测!S152+资产预测!S168) -> 0 | AS78: =IF(ISERROR(AR78+资产预测!T140-资产预测!T147+资产预测!T152+资产预测!T168),0,AR78+资产预测!T140-资产预测!T147+资产预测!T152+资产预测!T168) -> 0 | AT78: =IF(ISERROR(AS78+资产预测!U140-资产预测!U147+资产预测!U152+资产预测!U168),0,AS78+资产预测!U140-资产预测!U147+资产预测!U152+资产预测!U168) -> 0
B79: 其他权益工具 | E79: =财务基础数据!J140*目录!$D$6 -> 0 | F79: =财务基础数据!K140*目录!$D$6 -> 0 | G79: =财务基础数据!L140*目录!$D$6 -> 0 | H79: =财务基础数据!M140*目录!$D$6 -> 0 | I79: =财务基础数据!N140*目录!$D$6 -> 0 | J79: =财务基础数据!O140*目录!$D$6 -> 0 | K79: =财务基础数据!P140*目录!$D$6 -> 0 | L79: =财务基础数据!Q140*目录!$D$6 -> 0 | ... AJ79: =财务基础数据!AO140*目录!$D$6 -> 0 | AK79: =IF(财务基础数据!$AM$4=0,AG79,IF(财务基础数据!$AM$4=1,AH79,IF(财务基础数据!$AM$4=2,AI79,AJ79))) -> 0 | AL79: =AK79 -> 0 | AM79: =AL79 -> 0 | AN79: =AM79 -> 0 | AO79: =AN79 -> 0 | AP79: =AO79 -> 0 | AQ79: =AP79 -> 0 | AR79: =AQ79 -> 0 | AS79: =AR79 -> 0 | AT79: =AS79 -> 0
B80: 其中：优先股 | E80: =E79-E81 -> 0 | F80: =F79-F81 -> 0 | G80: =G79-G81 -> 0 | H80: =H79-H81 -> 0 | I80: =I79-I81 -> 0 | J80: =J79-J81 -> 0 | K80: =K79-K81 -> 0 | L80: =L79-L81 -> 0 | ... AJ80: =AJ79-AJ81 -> 0
B81: 永续债 | E81: =财务基础数据!J162*目录!$D$6 -> 0 | F81: =财务基础数据!K162*目录!$D$6 -> 0 | G81: =财务基础数据!L162*目录!$D$6 -> 0 | H81: =财务基础数据!M162*目录!$D$6 -> 0 | I81: =财务基础数据!N162*目录!$D$6 -> 0 | J81: =财务基础数据!O162*目录!$D$6 -> 0 | K81: =财务基础数据!P162*目录!$D$6 -> 0 | L81: =财务基础数据!Q162*目录!$D$6 -> 0 | ... AJ81: =财务基础数据!AO162*目录!$D$6 -> 0
B82: 资本公积 | E82: =财务基础数据!J122*目录!$D$6 -> 0 | F82: =财务基础数据!K122*目录!$D$6 -> 0 | G82: =财务基础数据!L122*目录!$D$6 -> 0 | H82: =财务基础数据!M122*目录!$D$6 -> 0 | I82: =财务基础数据!N122*目录!$D$6 -> 0 | J82: =财务基础数据!O122*目录!$D$6 -> 0 | K82: =财务基础数据!P122*目录!$D$6 -> 0 | L82: =财务基础数据!Q122*目录!$D$6 -> 0 | ... AJ82: =财务基础数据!AO122*目录!$D$6 -> 0 | AK82: =AG82+资产预测!L133+资产预测!L141-资产预测!L148+资产预测!L158+资产预测!L160+资产预测!L171 -> 0 | AL82: =IF(ISERROR(AK82+资产预测!M133+资产预测!M141-资产预测!M148+资产预测!M158+资产预测!M160+资产预测!M171),"—",AK82+资产预测!M133+资产预测!M141-资产预测!M148+资产预测!M158+资产预测!M160+资产预测!M171) -> 0 | AM82: =IF(ISERROR(AL82+资产预测!N141-资产预测!N148+资产预测!N158+资产预测!N160+资产预测!N171),"—",AL82+资产预测!N141-资产预测!N148+资产预测!N158+资产预测!N160+资产预测!N171) -> 0 | AN82: =IF(ISERROR(AM82+资产预测!O141-资产预测!O148+资产预测!O158+资产预测!O160+资产预测!O171),"—",AM82+资产预测!O141-资产预测!O148+资产预测!O158+资产预测!O160+资产预测!O171) -> 0 | AO82: =IF(ISERROR(AN82+资产预测!P141-资产预测!P148+资产预测!P158+资产预测!P160+资产预测!P171),"—",AN82+资产预测!P141-资产预测!P148+资产预测!P158+资产预测!P160+资产预测!P171) -> 0 | AP82: =IF(ISERROR(AO82+资产预测!Q141-资产预测!Q148+资产预测!Q158+资产预测!Q160+资产预测!Q171),"—",AO82+资产预测!Q141-资产预测!Q148+资产预测!Q158+资产预测!Q160+资产预测!Q171) -> 0 | AQ82: =IF(ISERROR(AP82+资产预测!R141-资产预测!R148+资产预测!R158+资产预测!R160+资产预测!R171),"—",AP82+资产预测!R141-资产预测!R148+资产预测!R158+资产预测!R160+资产预测!R171) -> 0 | AR82: =IF(ISERROR(AQ82+资产预测!S141-资产预测!S148+资产预测!S158+资产预测!S160+资产预测!S171),"—",AQ82+资产预测!S141-资产预测!S148+资产预测!S158+资产预测!S160+资产预测!S171) -> 0 | AS82: =IF(ISERROR(AR82+资产预测!T141-资产预测!T148+资产预测!T158+资产预测!T160+资产预测!T171),"—",AR82+资产预测!T141-资产预测!T148+资产预测!T158+资产预测!T160+资产预测!T171) -> 0 | AT82: =IF(ISERROR(AS82+资产预测!U141-资产预测!U148+资产预测!U158+资产预测!U160+资产预测!U171),"—",AS82+资产预测!U141-资产预测!U148+资产预测!U158+资产预测!U160+资产预测!U171) -> 0
B83: 减：库存股 | E83: =财务基础数据!J123*目录!$D$6 -> 0 | F83: =财务基础数据!K123*目录!$D$6 -> 0 | G83: =财务基础数据!L123*目录!$D$6 -> 0 | H83: =财务基础数据!M123*目录!$D$6 -> 0 | I83: =财务基础数据!N123*目录!$D$6 -> 0 | J83: =财务基础数据!O123*目录!$D$6 -> 0 | K83: =财务基础数据!P123*目录!$D$6 -> 0 | L83: =财务基础数据!Q123*目录!$D$6 -> 0 | ... AJ83: =财务基础数据!AO123*目录!$D$6 -> 0 | AK83: =IF(ISERROR(AG83+资产预测!L149),"—",AG83+资产预测!L149) -> 0 | AL83: =IF(ISERROR(AK83+资产预测!M149),"—",AK83+资产预测!M149) -> 0 | AM83: =IF(ISERROR(AL83+资产预测!N149),"—",AL83+资产预测!N149) -> 0 | AN83: =IF(ISERROR(AM83+资产预测!O149),"—",AM83+资产预测!O149) -> 0 | AO83: =IF(ISERROR(AN83+资产预测!P149),"—",AN83+资产预测!P149) -> 0 | AP83: =IF(ISERROR(AO83+资产预测!Q149),"—",AO83+资产预测!Q149) -> 0 | AQ83: =IF(ISERROR(AP83+资产预测!R149),"—",AP83+资产预测!R149) -> 0 | AR83: =IF(ISERROR(AQ83+资产预测!S149),"—",AQ83+资产预测!S149) -> 0 | AS83: =IF(ISERROR(AR83+资产预测!T149),"—",AR83+资产预测!T149) -> 0 | AT83: =IF(ISERROR(AS83+资产预测!U149),"—",AS83+资产预测!U149) -> 0
B84: 其他综合收益 | E84: =财务基础数据!J139*目录!$D$6 -> 0 | F84: =财务基础数据!K139*目录!$D$6 -> 0 | G84: =财务基础数据!L139*目录!$D$6 -> 0 | H84: =财务基础数据!M139*目录!$D$6 -> 0 | I84: =财务基础数据!N139*目录!$D$6 -> 0 | J84: =财务基础数据!O139*目录!$D$6 -> 0 | K84: =财务基础数据!P139*目录!$D$6 -> 0 | L84: =财务基础数据!Q139*目录!$D$6 -> 0 | ... AJ84: =财务基础数据!AO139*目录!$D$6 -> 0 | AK84: =IF(财务基础数据!$AM$4=0,AG84,IF(财务基础数据!$AM$4=1,AH84,IF(财务基础数据!$AM$4=2,AI84,AJ84))) -> 0 | AL84: =AK84 -> 0 | AM84: =AL84 -> 0 | AN84: =AM84 -> 0 | AO84: =AN84 -> 0 | AP84: =AO84 -> 0 | AQ84: =AP84 -> 0 | AR84: =AQ84 -> 0 | AS84: =AR84 -> 0 | AT84: =AS84 -> 0
B85: 专项储备 | E85: =财务基础数据!J136*目录!$D$6 -> 0 | F85: =财务基础数据!K136*目录!$D$6 -> 0 | G85: =财务基础数据!L136*目录!$D$6 -> 0 | H85: =财务基础数据!M136*目录!$D$6 -> 0 | I85: =财务基础数据!N136*目录!$D$6 -> 0 | J85: =财务基础数据!O136*目录!$D$6 -> 0 | K85: =财务基础数据!P136*目录!$D$6 -> 0 | L85: =财务基础数据!Q136*目录!$D$6 -> 0 | ... AJ85: =财务基础数据!AO136*目录!$D$6 -> 0 | AK85: =IF(财务基础数据!$AM$4=0,AG85,IF(财务基础数据!$AM$4=1,AH85,IF(财务基础数据!$AM$4=2,AI85,AJ85))) -> 0 | AL85: =AK85 -> 0 | AM85: =AL85 -> 0 | AN85: =AM85 -> 0 | AO85: =AN85 -> 0 | AP85: =AO85 -> 0 | AQ85: =AP85 -> 0 | AR85: =AQ85 -> 0 | AS85: =AR85 -> 0 | AT85: =AS85 -> 0
B86: 盈余公积 | E86: =财务基础数据!J124*目录!$D$6 -> 0 | F86: =财务基础数据!K124*目录!$D$6 -> 0 | G86: =财务基础数据!L124*目录!$D$6 -> 0 | H86: =财务基础数据!M124*目录!$D$6 -> 0 | I86: =财务基础数据!N124*目录!$D$6 -> 0 | J86: =财务基础数据!O124*目录!$D$6 -> 0 | K86: =财务基础数据!P124*目录!$D$6 -> 0 | L86: =财务基础数据!Q124*目录!$D$6 -> 0 | ... AJ86: =财务基础数据!AO124*目录!$D$6 -> 0 | AK86: =IF(利润表!AK94>=0,利润表!AK94*15%+资产负债表!AG86,资产负债表!AG86) -> 0 | AL86: =IF(利润表!AL94>=0,利润表!AL94*15%+资产负债表!AK86,资产负债表!AK86) -> 0 | AM86: =IF(利润表!AM94>=0,利润表!AM94*15%+资产负债表!AL86,资产负债表!AL86) -> 0 | AN86: =IF(利润表!AN94>=0,利润表!AN94*15%+资产负债表!AM86,资产负债表!AM86) -> 0 | AO86: =IF(利润表!AO94>=0,利润表!AO94*15%+资产负债表!AN86,资产负债表!AN86) -> 0 | AP86: =IF(利润表!AP94>=0,利润表!AP94*15%+资产负债表!AO86,资产负债表!AO86) -> 0 | AQ86: =IF(利润表!AQ94>=0,利润表!AQ94*15%+资产负债表!AP86,资产负债表!AP86) -> 0 | AR86: =IF(利润表!AR94>=0,利润表!AR94*15%+资产负债表!AQ86,资产负债表!AQ86) -> 0 | AS86: =IF(利润表!AS94>=0,利润表!AS94*15%+资产负债表!AR86,资产负债表!AR86) -> 0 | AT86: =IF(利润表!AT94>=0,利润表!AT94*15%+资产负债表!AS86,资产负债表!AS86) -> 0
B87: 未分配利润 | E87: =财务基础数据!J126*目录!$D$6 -> 0 | F87: =(财务基础数据!K126+财务基础数据!K128)*目录!$D$6 -> 0 | G87: =(财务基础数据!L126+财务基础数据!L128)*目录!$D$6 -> 0 | H87: =(财务基础数据!M126+财务基础数据!M128)*目录!$D$6 -> 0 | I87: =(财务基础数据!N126+财务基础数据!N128)*目录!$D$6 -> 0 | J87: =(财务基础数据!O126+财务基础数据!O128)*目录!$D$6 -> 0 | K87: =(财务基础数据!P126+财务基础数据!P128)*目录!$D$6 -> 0 | L87: =(财务基础数据!Q126+财务基础数据!Q128)*目录!$D$6 -> 0 | M87: =(财务基础数据!R126+财务基础数据!R128)*目录!$D$6 -> 0 | ... AJ87: =(财务基础数据!AO126+财务基础数据!AO128)*目录!$D$6 -> 0 | AK87: =IF(利润表!AK94>=0,AG87+利润表!AK94*0.85-资产预测!L163+现金流量表!AK74-销售预测!L52-投资与减值!L173+投资与减值!L22-投资与减值!L183+资产预测!L159+资产预测!L232-资产预测!H232,AG87+利润表!AK94-资产预测!L163+现金流量表!AK74-销售预测!L52-投资与减值!L173+投资与减值!L22-投资与减值!L183+资产预测!L159+资产预测!L232-资产预测!H232) -> 0 | AL87: =IF(利润表!AL94>=0,AK87+利润表!AL94*0.85-资产预测!M163+现金流量表!AL74-销售预测!M52-投资与减值!M173+投资与减值!M22-投资与减值!M183+资产预测!M159+资产预测!M232-资产预测!L232,AK87+利润表!AL94-资产预测!M163+现金流量表!AL74-销售预测!M52-投资与减值!M173+投资与减值!M22-投资与减值!M183+资产预测!M159+资产预测!M232-资产预测!L232) -> 0 | AM87: =IF(利润表!AM94>=0,AL87+利润表!AM94*0.85-资产预测!N163+现金流量表!AM74-销售预测!N52-投资与减值!N173+投资与减值!N22-投资与减值!N183+资产预测!N159+资产预测!N232-资产预测!M232,AL87+利润表!AM94-资产预测!N163+现金流量表!AM74-销售预测!N52-投资与减值!N173+投资与减值!N22-投资与减值!N183+资产预测!N159+资产预测!N232-资产预测!M232) -> 0 | AN87: =IF(利润表!AN94>=0,AM87+利润表!AN94*0.85-资产预测!O163+现金流量表!AN74-销售预测!O52-投资与减值!O173+投资与减值!O22-投资与减值!O183+资产预测!O159+资产预测!O232-资产预测!N232,AM87+利润表!AN94-资产预测!O163+现金流量表!AN74-销售预测!O52-投资与减值!O173+投资与减值!O22-投资与减值!O183+资产预测!O159+资产预测!O232-资产预测!N232) -> 0 | AO87: =IF(利润表!AO94>=0,AN87+利润表!AO94*0.85-资产预测!P163+现金流量表!AO74-销售预测!P52-投资与减值!P173+投资与减值!P22-投资与减值!P183+资产预测!P159+资产预测!P232-资产预测!O232,AN87+利润表!AO94-资产预测!P163+现金流量表!AO74-销售预测!P52-投资与减值!P173+投资与减值!P22-投资与减值!P183+资产预测!P159+资产预测!P232-资产预测!O232) -> 0 | AP87: =IF(利润表!AP94>=0,AO87+利润表!AP94*0.85-资产预测!Q163+现金流量表!AP74-销售预测!Q52-投资与减值!Q173+投资与减值!Q22-投资与减值!Q183+资产预测!Q159+资产预测!Q232-资产预测!P232,AO87+利润表!AP94-资产预测!Q163+现金流量表!AP74-销售预测!Q52-投资与减值!Q173+投资与减值!Q22-投资与减值!Q183+资产预测!Q159+资产预测!Q232-资产预测!P232) -> 0 | AQ87: =IF(利润表!AQ94>=0,AP87+利润表!AQ94*0.85-资产预测!R163+现金流量表!AQ74-销售预测!R52-投资与减值!R173+投资与减值!R22-投资与减值!R183+资产预测!R159+资产预测!R232-资产预测!Q232,AP87+利润表!AQ94-资产预测!R163+现金流量表!AQ74-销售预测!R52-投资与减值!R173+投资与减值!R22-投资与减值!R183+资产预测!R159+资产预测!R232-资产预测!Q232) -> 0 | AR87: =IF(利润表!AR94>=0,AQ87+利润表!AR94*0.85-资产预测!S163+现金流量表!AR74-销售预测!S52-投资与减值!S173+投资与减值!S22-投资与减值!S183+资产预测!S159+资产预测!S232-资产预测!R232,AQ87+利润表!AR94-资产预测!S163+现金流量表!AR74-销售预测!S52-投资与减值!S173+投资与减值!S22-投资与减值!S183+资产预测!S159+资产预测!S232-资产预测!R232) -> 0 | AS87: =IF(利润表!AS94>=0,AR87+利润表!AS94*0.85-资产预测!T163+现金流量表!AS74-销售预测!T52-投资与减值!T173+投资与减值!T22-投资与减值!T183+资产预测!T159+资产预测!T232-资产预测!S232,AR87+利润表!AS94-资产预测!T163+现金流量表!AS74-销售预测!T52-投资与减值!T173+投资与减值!T22-投资与减值!T183+资产预测!T159+资产预测!T232-资产预测!S232) -> 0 | AT87: =IF(利润表!AT94>=0,AS87+利润表!AT94*0.85-资产预测!U163+现金流量表!AT74-销售预测!U52-投资与减值!U173+投资与减值!U22-投资与减值!U183+资产预测!U159+资产预测!U232-资产预测!T232,AS87+利润表!AT94-资产预测!U163+现金流量表!AT74-销售预测!U52-投资与减值!U173+投资与减值!U22-投资与减值!U183+资产预测!U159+资产预测!U232-资产预测!T232) -> 0
B88: 外币报表折算差额 | E88: =财务基础数据!J127*目录!$D$6 -> 0 | F88: =财务基础数据!K127*目录!$D$6 -> 0 | G88: =财务基础数据!L127*目录!$D$6 -> 0 | H88: =财务基础数据!M127*目录!$D$6 -> 0 | I88: =财务基础数据!N127*目录!$D$6 -> 0 | J88: =财务基础数据!O127*目录!$D$6 -> 0 | K88: =财务基础数据!P127*目录!$D$6 -> 0 | L88: =财务基础数据!Q127*目录!$D$6 -> 0 | ... AJ88: =财务基础数据!AO127*目录!$D$6 -> 0 | AK88: =IF(财务基础数据!$AM$4=0,AG88,IF(财务基础数据!$AM$4=1,AH88,IF(财务基础数据!$AM$4=2,AI88,AJ88))) -> 0 | AL88: =AK88 -> 0 | AM88: =AL88 -> 0 | AN88: =AM88 -> 0 | AO88: =AN88 -> 0 | AP88: =AO88 -> 0 | AQ88: =AP88 -> 0 | AR88: =AQ88 -> 0 | AS88: =AR88 -> 0 | AT88: =AS88 -> 0
B89: 归属于母公司所有者权益合计 | E89: =财务基础数据!J129*目录!$D$6 -> 0 | F89: =财务基础数据!K129*目录!$D$6 -> 0 | G89: =财务基础数据!L129*目录!$D$6 -> 0 | H89: =财务基础数据!M129*目录!$D$6 -> 0 | I89: =财务基础数据!N129*目录!$D$6 -> 0 | J89: =财务基础数据!O129*目录!$D$6 -> 0 | K89: =财务基础数据!P129*目录!$D$6 -> 0 | L89: =财务基础数据!Q129*目录!$D$6 -> 0 | ... AJ89: =财务基础数据!AO129*目录!$D$6 -> 0 | AK89: =SUM(AK78:AK79)+AK82-AK83+AK84+AK85+AK86+AK87+AK88 -> 0 | AL89: =SUM(AL78:AL79)+AL82-AL83+AL84+AL85+AL86+AL87+AL88 -> 0 | AM89: =SUM(AM78:AM79)+AM82-AM83+AM84+AM85+AM86+AM87+AM88 -> 0 | AN89: =SUM(AN78:AN79)+AN82-AN83+AN84+AN85+AN86+AN87+AN88 -> 0 | AO89: =SUM(AO78:AO79)+AO82-AO83+AO84+AO85+AO86+AO87+AO88 -> 0 | AP89: =SUM(AP78:AP79)+AP82-AP83+AP84+AP85+AP86+AP87+AP88 -> 0 | AQ89: =SUM(AQ78:AQ79)+AQ82-AQ83+AQ84+AQ85+AQ86+AQ87+AQ88 -> 0 | AR89: =SUM(AR78:AR79)+AR82-AR83+AR84+AR85+AR86+AR87+AR88 -> 0 | ... AT89: =SUM(AT78:AT79)+AT82-AT83+AT84+AT85+AT86+AT87+AT88 -> 0
